Workbook

Sheet 6月调整栏
A1: 调整时间 | B1: 商品名称 | C1: SKU | D1: 提价25%特殊控价 | E1: 特殊优惠卷 | F1: 截至时间 | G1: 人员 | H1: 特殊原因
A2: 46176 | B2: 3C-折叠带蓝牙带琴谱架电子琴61键 | C2: M4CC2450780 | D2: / | E2: 30%最高减免25RM 每日两张 | F2: 46180 | G2: 曾伟铭 | H2: 其余人未销售
A3: 46176 | B3: 3C-32英寸到55英寸带中托可移动电视支架 | C3: T4CC1120706 | D3: / | E3: 27%最高减免27RM 每日两张 | F3: 46180 | G3: 曾伟铭+饶伟铭 | H3: 其余人未销售
A4: 46176 | B4: 3B-仿真书银钱盒钥匙款蓝色 | C4: T3CC1220672 | D4: 28 | E4: / | F4: 46203 | G4: 王心怡 | H4: 超期扶持
A5: 46176 | B5: 3B-仿真书银钱盒密码款蓝色 | C5: T3CC1220673 | D5: 28 | E5: / | F5: 46203 | G5: 王心怡 | H5: 超期扶持
A6: 46176 | B6: 3B-仿真书银钱盒钥匙款蓝色 | C6: T3CC1220672 | D6: 28 | E6: / | F6: 46203 | G6: 王心怡 | H6: 超期扶持
A7: 46176 | B7: 3B-仿真书银钱盒钥匙款蓝色 | C7: T4CC2660672 | D7: 28 | E7: / | F7: 46203 | G7: 王心怡 | H7: 超期扶持
A8: 46176 | B8: 3B-仿真书银钱盒密码款蓝色 | C8: T3CC1220673 | D8: 28 | E8: / | F8: 46203 | G8: 王心怡 | H8: 超期扶持
A9: 46176 | B9: 3B-仿真书银钱盒密码款蓝色 | C9: T4CC2660673 | D9: 28 | E9: / | F9: 46203 | G9: 王心怡 | H9: 超期扶持
A10: 46176 | B10: 3B-仿真书银钱盒钥匙款红色 | C10: T4CC2660965 | D10: 28 | E10: / | F10: 46203 | G10: 王心怡 | H10: 超期扶持

Sheet 6月达人佣金特殊申请
A1: 店铺 | B1: 调整时间 | C1: 申请达人佣金 | D1: 链接ID | E1: SKU | F1: 产品中文名 | G1: 25%折扣价 | H1: 20%到手价 | I1: 控价调整项 | J1: 优惠卷调整项 | K1: 实际到手价 | L1: 达人佣金
A2: EXPSOE TK | B2: 46148 | C2: 0.12 | D2: 1731131393182042075 | E2: M4CC3300653 | F2: =_xlfn.XLOOKUP(E2,'6月控价 '!F:F,'6月控价 '!E:E) -> 3B-JY004便携式储能电源4KG | G2: =_xlfn.XLOOKUP(E2,'6月控价 '!F:F,'6月控价 '!T:T) -> 499 | H2: =_xlfn.XLOOKUP(E2,'6月控价 '!F:F,'6月控价 '!U:U) -> 399.2 | I2: / | J2: 0.19 | K2: =G2*(1-0.19) -> 404.19
A3: EXPSOE TK | B3: 46148 | C3: 0.12 | D3: 1735418725005952987 | E3: M4CC3300283 | F3: =_xlfn.XLOOKUP(E3,'6月控价 '!F:F,'6月控价 '!E:E) -> 3B-便携式储能电源 | G3: =_xlfn.XLOOKUP(E3,'6月控价 '!F:F,'6月控价 '!T:T) -> 244 | H3: =_xlfn.XLOOKUP(E3,'6月控价 '!F:F,'6月控价 '!U:U) -> 195.2 | I3: / | J3: 0.12 | K3: =G3*(1-0.12) -> 214.72
A4: EXPSOE TK | B4: 46148 | C4: 0.1 | D4: 1734938035338381275 | E4: M4CC3300653 | F4: =_xlfn.XLOOKUP(E4,'6月控价 '!F:F,'6月控价 '!E:E) -> 3B-JY004便携式储能电源4KG | G4: =_xlfn.XLOOKUP(E4,'6月控价 '!F:F,'6月控价 '!T:T) -> 499 | H4: =_xlfn.XLOOKUP(E4,'6月控价 '!F:F,'6月控价 '!U:U) -> 399.2 | I4: / | J4: 0.21 | K4: =G4*(1-0.21) -> 394.21
A5: EXPSOE TK | B5: 46148 | C5: 0.1 | D5: 1735418725005952987 | E5: M4CC3300283 | F5: =_xlfn.XLOOKUP(E5,'6月控价 '!F:F,'6月控价 '!E:E) -> 3B-便携式储能电源 | G5: =_xlfn.XLOOKUP(E5,'6月控价 '!F:F,'6月控价 '!T:T) -> 244 | H5: =_xlfn.XLOOKUP(E5,'6月控价 '!F:F,'6月控价 '!U:U) -> 195.2 | I5: / | J5: 0.14 | K5: =G5*(1-0.14) -> 209.84
A6: EXPOSE.Tech Wealth | B6: 46148 | C6: 0.12 | D6: 1734983983228290729 | E6: M4CC3300653 | F6: =_xlfn.XLOOKUP(E6,'6月控价 '!F:F,'6月控价 '!E:E) -> 3B-JY004便携式储能电源4KG | G6: =_xlfn.XLOOKUP(E6,'6月控价 '!F:F,'6月控价 '!T:T) -> 499 | H6: =_xlfn.XLOOKUP(E6,'6月控价 '!F:F,'6月控价 '!U:U) -> 399.2 | I6: / | J6: 0.19 | K6: =G6*(1-0.19) -> 404.19
A7: TechWave & EXPOSE | B7: 46148 | C7: 0.2 | D7: 1733108275034490485 | E7: M4CC2500589X9 | F7: =_xlfn.XLOOKUP(E7,'6月控价 '!F:F,'6月控价 '!E:E) -> #N/A | G7: 235 | H7: 188 | I7: /
A8: TechWave & EXPOSE | B8: 46148 | C8: 0.1 | D8: 1730401820766799477 | E8: M4CC2500589X9 | F8: =_xlfn.XLOOKUP(E8,'6月控价 '!F:F,'6月控价 '!E:E) -> #N/A | G8: 235 | H8: 188 | I8: /
A9: TechWave & EXPOSE | B9: 46148 | C9: 0.1 | D9: 1729782181369120373 | E9: T3CC1120605 | F9: =_xlfn.XLOOKUP(E9,'6月控价 '!F:F,'6月控价 '!E:E) -> 3C-32至70寸电视移动支架的单支架 | G9: 147 | H9: =_xlfn.XLOOKUP(E9,'6月控价 '!F:F,'6月控价 '!U:U) -> 102.4 | I9: / | J9: 0.14 | K9: =G9*(1-0.14) -> 126.42
A10: TechWave & EXPOSE | B10: 46150 | C10: 0.1 | E10: M4CC3300283 | F10: =_xlfn.XLOOKUP(E10,'6月控价 '!F:F,'6月控价 '!E:E) -> 3B-便携式储能电源 | G10: 244 | H10: 195.2 | I10: /
A11: EXPOSE.Tech Wealth | B11: 46168 | C11: 0.1 | D11: 1734914291005818537 | E11: M5CC1721048 | F11: 3C-高亮自动对焦灯带投影仪Z300 | G11: 624 | H11: 499 | I11: / | J11: 0.2 | K11: 499 | L11: 0.1

Sheet 6月控价 
A1: 产品信息 | J1: 拓展信息 | R1: 控价信息 | AB1: 0.54 | AH1: 8% off Capped at RM20.00, on orders ≥ RM50.00 All customers Co-funding ratio: Platform 70 % / Seller 30 % Maximum funding from seller: RM6.00 | AI1: 18% off Capped at RM70.00, on orders ≥ RM200.00 All customers Co-funding ratio: Platform 70 % / Seller 30 % Maximum funding from seller: RM21.00 | AJ1: 28% off Capped at RM350.00, on orders ≥ RM380.00 All customers Co-funding ratio: Platform 70 % / Seller 30 % Maximum funding from seller: RM105.00 | AK1: 25% off Capped at RM350.00, on orders ≥ RM380.00 All customers Co-funding ratio: Platform 70 % / Seller 30 % Maximum funding from seller: RM105.00 | AL1: 22% off Capped at RM300.00, on orders ≥ RM380.00 All customers Co-funding ratio: Platform 70 % / Seller 30 % Maximum funding from seller: RM90.00 | AM1: 18% off Capped at RM120.00, on orders ≥ RM250.00 All customers Co-funding ratio: Platform 70 % / Seller 30 % Maximum funding from seller: RM36.00 | AN1: 15% off Capped at RM60.00, on orders ≥ RM180.00 All customers Co-funding ratio: Platform 70 % / Seller 30 % Maximum funding from seller: RM18.00
A2: 一级品类 | B2: 二级品类 | C2: 三级品类 | D2: 款名 | E2: 商品名称 | F2: SKU | G2: 推品定位 | H2: 清关方式 | I2: SKU状态 | J2: 交期时长/天 | K2: 是否超期 | L2: 是否超期 | M2: 新款年月 | N2: 是否新品 | O2: 库存深度 | P2: 毛重 | Q2: 体积重 | R2: 6月成本 | S2: 6月控价 | T2: 提价25% （折扣价） | U2: 降价20% (到手价） | V2: 实际优惠卷 | W2: 标价利润 | X2: 到账利润 | Y2: 交易费 抽点 | Z2: 手续费 抽点 | AA2: 返现服务费 抽点 | AB2: 订单处理费 | AC2: 达人佣金 抽点 | AD2: 公开佣金 | AE2: 广告佣金 | AF2: 活动期间优惠卷 | AH2: 需要承担的金额 | AI2: 需要承担的金额
A3: 办公安防 | B3: 智能安防 | C3: =_xlfn.XLOOKUP(F3,'6月产品包'!B:B,'6月产品包'!H:H) -> 智能锁 | D3: =_xlfn.XLOOKUP(F3,'6月产品包'!B:B,'6月产品包'!O:O) -> 手柄门锁 | E3: 3B-四功能智能门锁 | F3: T4CC2120433 | G3: 平销款 | H3: ZQ | I3: =_xlfn.XLOOKUP($F3,'6月库存'!A:A,'6月库存'!B:B) -> 正常销售 | K3: =_xlfn.XLOOKUP(E3,'[1]6月分配 '!$B:$B,'[1]6月分配 '!$K:$K) -> #N/A | L3: =IF(ISNUMBER(K3),"是",IF(ISNA(K3),"否","")) -> 否 | M3: =_xlfn.XLOOKUP(F3,'6月产品包'!B:B,'6月产品包'!J:J) -> 2025-02-25 | N3: =IF(DATEDIF(M3,TODAY(),"m")<6,"新品","老品") -> 老品 | O3: =_xlfn.XLOOKUP(F3,'6月库存'!A:A,'6月库存'!R:R) -> 270 | P3: =_xlfn.XLOOKUP(F3,'6月产品包'!B:B,'6月产品包'!S:S) -> 1950 | R3: =_xlfn.XLOOKUP(F3,'6月产品包'!B:B,'6月产品包'!AD:AD) -> 55.448 | S3: 106 | T3: =ROUND(S3*(1+0.25),0) -> 133 | U3: =$T3*(1-0.18) -> 109.06 | V3: 0.18 | W3: =(U3-R3)/U3 -> 0.49158262 | X3: =(U3*(1-Y3-Z3-AA3-AC3-AB3)-R3)/(U3*(1-Y3-Z3-AA3-AC3-AB3)) -> 0.30643427 | Y3: 0.038 | Z3: 0.115 | AA3: 0.049 | AB3: =$AB$1/U3 -> 0.0049514029 | AC3: 0.06 | AF3: 不进 | AG3: =MAX(AH3:AN3) -> 6 | AH3: =IF(U3>=50,MIN(MIN(U3*0.2,20)*0.3,6),0) -> 6 | AI3: =IF(U3>=200,MIN(MIN(U3*0.18,70)*0.3,21),0) -> 0 | AJ3: =IF(U3>=380,MIN(MIN(U3*0.28,350)*0.3,105),0) -> 0 | AK3: =IF(U3>=380,MIN(MIN(U3*0.25,350)*0.3,105),0) -> 0 | AL3: =IF(U3>=380,MIN(MIN(U3*0.22,300)*0.3,90),0) -> 0 | AM3: =IF(U3>=250,MIN(MIN(U3*0.18,120)*0.3,36),0) -> 0 | AN3: =IF(U3>=180,MIN(MIN(U3*0.15,60)*0.3,18),0) -> 0
A4: 办公安防 | B4: 储能设备 | C4: =_xlfn.XLOOKUP(F4,'6月产品包'!B:B,'6月产品包'!H:H) -> 便携储能电源 | D4: =_xlfn.XLOOKUP(F4,'6月产品包'!B:B,'6月产品包'!O:O) -> JY004电源 | E4: 3B-JY004便携式储能电源8KG | F4: M4CC3300655 | G4: 利润款 | H4: MD | I4: =_xlfn.XLOOKUP($F4,'6月库存'!A:A,'6月库存'!B:B) -> 商品清仓 | K4: =_xlfn.XLOOKUP(E4,'[1]6月分配 '!$B:$B,'[1]6月分配 '!$K:$K) -> #N/A | L4: =IF(ISNUMBER(K4),"是",IF(ISNA(K4),"否","")) -> 否 | M4: =_xlfn.XLOOKUP(F4,'6月产品包'!B:B,'6月产品包'!J:J) -> 2025-09-11 | N4: =IF(DATEDIF(M4,TODAY(),"m")<6,"新品","老品") -> 老品 | O4: =_xlfn.XLOOKUP(F4,'6月库存'!A:A,'6月库存'!R:R) -> 0 | P4: =_xlfn.XLOOKUP(F4,'6月产品包'!B:B,'6月产品包'!S:S) -> 10750 | Q4: 11000 | R4: =_xlfn.XLOOKUP(F4,'6月产品包'!B:B,'6月产品包'!AD:AD) -> 511.9573 | S4: 1099 | T4: =ROUND(S4*(1+0.25),0) -> 1374 | U4: =$T4*(1-0.2) -> 1099.2 | V4: 0.2 | W4: =(U4-R4)/U4 -> 0.53424554 | X4: =(U4*(1-Y4-Z4-AA4-AC4-AB4)-R4)/(U4*(1-Y4-Z4-AA4-AC4-AB4)) -> 0.37692439 | Y4: 0.038 | Z4: 0.105 | AA4: 0.049 | AB4: =$AB$1/U4 -> 0.00049126638 | AC4: 0.06 | AF4: 不进 | AG4: =MAX(AH4:AN4) -> 92.3328 | AH4: =IF(U4>=50,MIN(MIN(U4*0.2,20)*0.3,6),0) -> 6 | AI4: =IF(U4>=200,MIN(MIN(U4*0.18,70)*0.3,21),0) -> 21 | AJ4: =IF(U4>=380,MIN(MIN(U4*0.28,350)*0.3,105),0) -> 92.3328 | AK4: =IF(U4>=380,MIN(MIN(U4*0.25,350)*0.3,105),0) -> 82.44 | AL4: =IF(U4>=380,MIN(MIN(U4*0.22,300)*0.3,90),0) -> 72.5472 | AM4: =IF(U4>=250,MIN(MIN(U4*0.18,120)*0.3,36),0) -> 36 | AN4: =IF(U4>=180,MIN(MIN(U4*0.15,60)*0.3,18),0) -> 18
A5: 3C数码 | B5: 电脑周边 | C5: =_xlfn.XLOOKUP(F5,'6月产品包'!B:B,'6月产品包'!H:H) -> 显示器 | D5: =_xlfn.XLOOKUP(F5,'6月产品包'!B:B,'6月产品包'!O:O) -> 15.6寸便携显示器非触摸款 | E5: 3C-15.6寸60Hz直面1K便携式显示器黑色 | F5: T3CC1910583 | G5: 平销 | H5: MD | I5: =_xlfn.XLOOKUP($F5,'6月库存'!A:A,'6月库存'!B:B) -> 正常销售 | K5: =_xlfn.XLOOKUP(E5,'[1]6月分配 '!$B:$B,'[1]6月分配 '!$K:$K) -> #N/A | L5: =IF(ISNUMBER(K5),"是",IF(ISNA(K5),"否","")) -> 否 | M5: =_xlfn.XLOOKUP(F5,'6月产品包'!B:B,'6月产品包'!J:J) -> 2024-04-01 | N5: =IF(DATEDIF(M5,TODAY(),"m")<6,"新品","老品") -> 老品 | O5: =_xlfn.XLOOKUP(F5,'6月库存'!A:A,'6月库存'!R:R) -> 1 | P5: =_xlfn.XLOOKUP(F5,'6月产品包'!B:B,'6月产品包'!S:S) -> 1378 | R5: =_xlfn.XLOOKUP(F5,'6月产品包'!B:B,'6月产品包'!AD:AD) -> 144.014 | S5: 310 | T5: =ROUND(S5*(1+0.25),0) -> 388 | U5: =$T5*(1-0.2) -> 310.4 | V5: 0.2 | W5: =(U5-R5)/U5 -> 0.53603737 | X5: =(U5*(1-Y5-Z5-AA5-AC5-AB5)-R5)/(U5*(1-Y5-Z5-AA5-AC5-AB5)) -> 0.39053354 | Y5: 0.038 | Z5: 0.09 | AA5: 0.049 | AB5: =$AB$1/U5 -> 0.0017396907 | AC5: 0.06 | AF5: 不进 | AG5: =MAX(AH5:AN5) -> 16.7616 | AH5: =IF(U5>=50,MIN(MIN(U5*0.2,20)*0.3,6),0) -> 6 | AI5: =IF(U5>=200,MIN(MIN(U5*0.18,70)*0.3,21),0) -> 16.7616 | AJ5: =IF(U5>=380,MIN(MIN(U5*0.28,350)*0.3,105),0) -> 0 | AK5: =IF(U5>=380,MIN(MIN(U5*0.25,350)*0.3,105),0) -> 0 | AL5: =IF(U5>=380,MIN(MIN(U5*0.22,300)*0.3,90),0) -> 0 | AM5: =IF(U5>=250,MIN(MIN(U5*0.18,120)*0.3,36),0) -> 16.7616 | AN5: =IF(U5>=180,MIN(MIN(U5*0.15,60)*0.3,18),0) -> 13.968
A6: 办公安防 | B6: 储能设备 | C6: =_xlfn.XLOOKUP(F6,'6月产品包'!B:B,'6月产品包'!H:H) -> 便携储能电源 | D6: =_xlfn.XLOOKUP(F6,'6月产品包'!B:B,'6月产品包'!O:O) -> 便携电源 | E6: 3B-便携式储能电源 | F6: M4CC3300283 | G6: 平销款 | H6: MD | I6: =_xlfn.XLOOKUP($F6,'6月库存'!A:A,'6月库存'!B:B) -> 商品清仓 | K6: =_xlfn.XLOOKUP(E6,'[1]6月分配 '!$B:$B,'[1]6月分配 '!$K:$K) -> 232286 | L6: =IF(ISNUMBER(K6),"是",IF(ISNA(K6),"否","")) -> 是 | M6: =_xlfn.XLOOKUP(F6,'6月产品包'!B:B,'6月产品包'!J:J) -> 2025-06-03 | N6: =IF(DATEDIF(M6,TODAY(),"m")<6,"新品","老品") -> 老品 | O6: =_xlfn.XLOOKUP(F6,'6月库存'!A:A,'6月库存'!R:R) -> 1753 | P6: =_xlfn.XLOOKUP(F6,'6月产品包'!B:B,'6月产品包'!S:S) -> 1800 | R6: =_xlfn.XLOOKUP(F6,'6月产品包'!B:B,'6月产品包'!AD:AD) -> 100.576 | S6: 195 | T6: =ROUND(S6*(1+0.25),0) -> 244 | U6: =$T6*(1-0.2) -> 195.2 | V6: 0.2 | W6: =(U6-R6)/U6 -> 0.4847541 | X6: =(U6*(1-Y6-Z6-AA6-AC6-AB6)-R6)/(U6*(1-Y6-Z6-AA6-AC6-AB6)) -> 0.30861156 | Y6: 0.038 | Z6: 0.105 | AA6: 0.049 | AB6: =$AB$1/U6 -> 0.0027663934 | AC6: 0.06 | AD6: 0.05 | AE6: 0.03 | AF6: 原价进 | AG6: =MAX(AH6:AN6) -> 8.784 | AH6: =IF(U6>=50,MIN(MIN(U6*0.2,20)*0.3,6),0) -> 6 | AI6: =IF(U6>=200,MIN(MIN(U6*0.18,70)*0.3,21),0) -> 0 | AJ6: =IF(U6>=380,MIN(MIN(U6*0.28,350)*0.3,105),0) -> 0 | AK6: =IF(U6>=380,MIN(MIN(U6*0.25,350)*0.3,105),0) -> 0 | AL6: =IF(U6>=380,MIN(MIN(U6*0.22,300)*0.3,90),0) -> 0 | AM6: =IF(U6>=250,MIN(MIN(U6*0.18,120)*0.3,36),0) -> 0 | AN6: =IF(U6>=180,MIN(MIN(U6*0.15,60)*0.3,18),0) -> 8.784
A7: 办公安防 | B7: 办公周边 | C7: =_xlfn.XLOOKUP(F7,'6月产品包'!B:B,'6月产品包'!H:H) -> 打印机 | D7: =_xlfn.XLOOKUP(F7,'6月产品包'!B:B,'6月产品包'!O:O) -> 面单打印机 | E7: 3B-快递面单打印机白色 | F7: M4CC0200477 | G7: #N/A | H7: ZQ | I7: =_xlfn.XLOOKUP($F7,'6月库存'!A:A,'6月库存'!B:B) -> 正常销售 | K7: =_xlfn.XLOOKUP(E7,'[1]6月分配 '!$B:$B,'[1]6月分配 '!$K:$K) -> #N/A | L7: =IF(ISNUMBER(K7),"是",IF(ISNA(K7),"否","")) -> 否 | M7: =_xlfn.XLOOKUP(F7,'6月产品包'!B:B,'6月产品包'!J:J) -> 2025-03-29 | N7: =IF(DATEDIF(M7,TODAY(),"m")<6,"新品","老品") -> 老品 | O7: =_xlfn.XLOOKUP(F7,'6月库存'!A:A,'6月库存'!R:R) -> 0 | P7: =_xlfn.XLOOKUP(F7,'6月产品包'!B:B,'6月产品包'!S:S) -> 2375 | R7: =_xlfn.XLOOKUP(F7,'6月产品包'!B:B,'6月产品包'!AD:AD) -> 122.177 | S7: 227 | T7: =ROUND(S7*(1+0.25),0) -> 284 | U7: =$T7*(1-0.2) -> 227.2 | V7: 0.2 | W7: =(U7-R7)/U7 -> 0.46224912 | X7: =(U7*(1-Y7-Z7-AA7-AC7-AB7)-R7)/(U7*(1-Y7-Z7-AA7-AC7-AB7)) -> 0.28168022 | Y7: 0.04 | Z7: 0.1 | AA7: 0.049 | AB7: =$AB$1/U7 -> 0.0023767606 | AC7: 0.06 | AF7: 不进 | AG7: =MAX(AH7:AN7) -> 12.2688 | AH7: =IF(U7>=50,MIN(MIN(U7*0.2,20)*0.3,6),0) -> 6 | AI7: =IF(U7>=200,MIN(MIN(U7*0.18,70)*0.3,21),0) -> 12.2688 | AJ7: =IF(U7>=380,MIN(MIN(U7*0.28,350)*0.3,105),0) -> 0 | AK7: =IF(U7>=380,MIN(MIN(U7*0.25,350)*0.3,105),0) -> 0 | AL7: =IF(U7>=380,MIN(MIN(U7*0.22,300)*0.3,90),0) -> 0 | AM7: =IF(U7>=250,MIN(MIN(U7*0.18,120)*0.3,36),0) -> 0 | AN7: =IF(U7>=180,MIN(MIN(U7*0.15,60)*0.3,18),0) -> 10.224
A8: 办公安防 | B8: 办公周边 | C8: =_xlfn.XLOOKUP(F8,'6月产品包'!B:B,'6月产品包'!H:H) -> 打印机 | D8: =_xlfn.XLOOKUP(F8,'6月产品包'!B:B,'6月产品包'!O:O) -> 面单打印机 | E8: 3B-快递面单打印机白色 | F8: M4CC2500477 | G8: #N/A | H8: ZQ | I8: =_xlfn.XLOOKUP($F8,'6月库存'!A:A,'6月库存'!B:B) -> 正常销售 | K8: =_xlfn.XLOOKUP(E8,'[1]6月分配 '!$B:$B,'[1]6月分配 '!$K:$K) -> #N/A | L8: =IF(ISNUMBER(K8),"是",IF(ISNA(K8),"否","")) -> 否 | M8: =_xlfn.XLOOKUP(F8,'6月产品包'!B:B,'6月产品包'!J:J) -> 2025-09-27 | N8: =IF(DATEDIF(M8,TODAY(),"m")<6,"新品","老品") -> 老品 | O8: =_xlfn.XLOOKUP(F8,'6月库存'!A:A,'6月库存'!R:R) -> 12 | P8: =_xlfn.XLOOKUP(F8,'6月产品包'!B:B,'6月产品包'!S:S) -> 1688 | R8: =_xlfn.XLOOKUP(F8,'6月产品包'!B:B,'6月产品包'!AD:AD) -> 108.6688 | S8: 207 | T8: =ROUND(S8*(1+0.25),0) -> 259 | U8: =$T8*(1-0.2) -> 207.2 | V8: 0.2 | W8: =(U8-R8)/U8 -> 0.47553668 | X8: =(U8*(1-Y8-Z8-AA8-AC8-AB8)-R8)/(U8*(1-Y8-Z8-AA8-AC8-AB8)) -> 0.29921479 | Y8: 0.04 | Z8: 0.1 | AA8: 0.049 | AB8: =$AB$1/U8 -> 0.0026061776 | AC8: 0.06 | AF8: 不进 | AG8: =MAX(AH8:AN8) -> 11.1888 | AH8: =IF(U8>=50,MIN(MIN(U8*0.2,20)*0.3,6),0) -> 6 | AI8: =IF(U8>=200,MIN(MIN(U8*0.18,70)*0.3,21),0) -> 11.1888 | AJ8: =IF(U8>=380,MIN(MIN(U8*0.28,350)*0.3,105),0) -> 0 | AK8: =IF(U8>=380,MIN(MIN(U8*0.25,350)*0.3,105),0) -> 0 | AL8: =IF(U8>=380,MIN(MIN(U8*0.22,300)*0.3,90),0) -> 0 | AM8: =IF(U8>=250,MIN(MIN(U8*0.18,120)*0.3,36),0) -> 0 | AN8: =IF(U8>=180,MIN(MIN(U8*0.15,60)*0.3,18),0) -> 9.324
A9: 3C数码 | B9: 电脑周边 | C9: =_xlfn.XLOOKUP(F9,'6月产品包'!B:B,'6月产品包'!H:H) -> 显示器 | D9: =_xlfn.XLOOKUP(F9,'6月产品包'!B:B,'6月产品包'!O:O) -> 15.6寸便携显示器触摸款 | E9: 3C-15.6寸60Hz直面1K便携式触摸显示器黑色 | F9: T3CC1910582 | G9: 平销 | H9: MD | I9: =_xlfn.XLOOKUP($F9,'6月库存'!A:A,'6月库存'!B:B) -> 正常销售 | K9: =_xlfn.XLOOKUP(E9,'[1]6月分配 '!$B:$B,'[1]6月分配 '!$K:$K) -> #N/A | L9: =IF(ISNUMBER(K9),"是",IF(ISNA(K9),"否","")) -> 否 | M9: =_xlfn.XLOOKUP(F9,'6月产品包'!B:B,'6月产品包'!J:J) -> 2024-03-19 | N9: =IF(DATEDIF(M9,TODAY(),"m")<6,"新品","老品") -> 老品 | O9: =_xlfn.XLOOKUP(F9,'6月库存'!A:A,'6月库存'!R:R) -> 0 | P9: =_xlfn.XLOOKUP(F9,'6月产品包'!B:B,'6月产品包'!S:S) -> 1480 | R9: =_xlfn.XLOOKUP(F9,'6月产品包'!B:B,'6月产品包'!AD:AD) -> 200.9874 | S9: 420 | T9: =ROUND(S9*(1+0.25),0) -> 525 | U9: =$T9*(1-0.2) -> 420 | V9: 0.2 | W9: =(U9-R9)/U9 -> 0.52145857 | X9: =(U9*(1-Y9-Z9-AA9-AC9-AB9)-R9)/(U9*(1-Y9-Z9-AA9-AC9-AB9)) -> 0.37175731 | Y9: 0.038 | Z9: 0.09 | AA9: 0.049 | AB9: =$AB$1/U9 -> 0.0012857143 | AC9: 0.06 | AF9: 不进 | AG9: =MAX(AH9:AN9) -> 35.28 | AH9: =IF(U9>=50,MIN(MIN(U9*0.2,20)*0.3,6),0) -> 6 | AI9: =IF(U9>=200,MIN(MIN(U9*0.18,70)*0.3,21),0) -> 21 | AJ9: =IF(U9>=380,MIN(MIN(U9*0.28,350)*0.3,105),0) -> 35.28 | AK9: =IF(U9>=380,MIN(MIN(U9*0.25,350)*0.3,105),0) -> 31.5 | AL9: =IF(U9>=380,MIN(MIN(U9*0.22,300)*0.3,90),0) -> 27.72 | AM9: =IF(U9>=250,MIN(MIN(U9*0.18,120)*0.3,36),0) -> 22.68 | AN9: =IF(U9>=180,MIN(MIN(U9*0.15,60)*0.3,18),0) -> 18
A10: 办公安防 | B10: 智能安防 | C10: =_xlfn.XLOOKUP(F10,'6月产品包'!B:B,'6月产品包'!H:H) -> 智能锁 | D10: =_xlfn.XLOOKUP(F10,'6月产品包'!B:B,'6月产品包'!O:O) -> 球型门锁 | E10: 3B-球型门锁Q7豪华款 | F10: T4CC2120715 | G10: 平销款 | H10: ZQ | I10: =_xlfn.XLOOKUP($F10,'6月库存'!A:A,'6月库存'!B:B) -> 正常销售 | K10: =_xlfn.XLOOKUP(E10,'[1]6月分配 '!$B:$B,'[1]6月分配 '!$K:$K) -> #N/A | L10: =IF(ISNUMBER(K10),"是",IF(ISNA(K10),"否","")) -> 否 | M10: =_xlfn.XLOOKUP(F10,'6月产品包'!B:B,'6月产品包'!J:J) -> 2025-05-24 | N10: =IF(DATEDIF(M10,TODAY(),"m")<6,"新品","老品") -> 老品 | O10: =_xlfn.XLOOKUP(F10,'6月库存'!A:A,'6月库存'!R:R) -> 63 | P10: =_xlfn.XLOOKUP(F10,'6月产品包'!B:B,'6月产品包'!S:S) -> 797 | R10: =_xlfn.XLOOKUP(F10,'6月产品包'!B:B,'6月产品包'!AD:AD) -> 73.95 | S10: 150 | T10: =ROUND(S10*(1+0.25),0) -> 188 | U10: =$T10*(1-0.2) -> 150.4 | V10: 0.2 | W10: =(U10-R10)/U10 -> 0.50831117 | X10: =(U10*(1-Y10-Z10-AA10-AC10-AB10)-R10)/(U10*(1-Y10-Z10-AA10-AC10-AB10)) -> 0.33049779 | Y10: 0.038 | Z10: 0.115 | AA10: 0.049 | AB10: =$AB$1/U10 -> 0.0035904255 | AC10: 0.06 | AF10: 不进 | AG10: =MAX(AH10:AN10) -> 6 | AH10: =IF(U10>=50,MIN(MIN(U10*0.2,20)*0.3,6),0) -> 6 | AI10: =IF(U10>=200,MIN(MIN(U10*0.18,70)*0.3,21),0) -> 0 | AJ10: =IF(U10>=380,MIN(MIN(U10*0.28,350)*0.3,105),0) -> 0 | AK10: =IF(U10>=380,MIN(MIN(U10*0.25,350)*0.3,105),0) -> 0 | AL10: =IF(U10>=380,MIN(MIN(U10*0.22,300)*0.3,90),0) -> 0 | AM10: =IF(U10>=250,MIN(MIN(U10*0.18,120)*0.3,36),0) -> 0 | AN10: =IF(U10>=180,MIN(MIN(U10*0.15,60)*0.3,18),0) -> 0
A11: =_xlfn.XLOOKUP(F11,'6月产品包'!B:B,'6月产品包'!F:F) -> 3C数码 | B11: =_xlfn.XLOOKUP(F11,'6月产品包'!B:B,'6月产品包'!G:G) -> 影像摄影 | C11: =_xlfn.XLOOKUP(F11,'6月产品包'!B:B,'6月产品包'!H:H) -> 口袋运动相机 | D11: =_xlfn.XLOOKUP(F11,'6月产品包'!B:B,'6月产品包'!O:O) -> 运动相机 | E11: =_xlfn.XLOOKUP(F11,'6月产品包'!B:B,'6月产品包'!C:C) -> 3C-口袋运动相机11.7cm*3.4cm | F11: T4CC2310722 | G11: 平销款 | H11: MD | I11: =_xlfn.XLOOKUP($F11,'6月库存'!A:A,'6月库存'!B:B) -> 正常销售 | K11: =_xlfn.XLOOKUP(E11,'[1]6月分配 '!$B:$B,'[1]6月分配 '!$K:$K) -> #N/A | L11: =IF(ISNUMBER(K11),"是",IF(ISNA(K11),"否","")) -> 否 | M11: =_xlfn.XLOOKUP(F11,'6月产品包'!B:B,'6月产品包'!J:J) -> 2025-07-10 | N11: =IF(DATEDIF(M11,TODAY(),"m")<6,"新品","老品") -> 老品 | O11: =_xlfn.XLOOKUP(F11,'6月库存'!A:A,'6月库存'!R:R) -> 1 | P11: =_xlfn.XLOOKUP(F11,'6月产品包'!B:B,'6月产品包'!S:S) -> 335 | R11: =_xlfn.XLOOKUP(F11,'6月产品包'!B:B,'6月产品包'!AD:AD) -> 100.5952 | S11: 185 | T11: =ROUND(S11*(1+0.25),0) -> 231 | U11: =$T11*(1-0.2) -> 184.8 | V11: 0.2 | W11: =(U11-R11)/U11 -> 0.45565368 | X11: =(U11*(1-Y11-Z11-AA11-AC11-AB11)-R11)/(U11*(1-Y11-Z11-AA11-AC11-AB11)) -> 0.28382827 | Y11: 0.038 | Z11: 0.09 | AA11: 0.049 | AB11: =$AB$1/U11 -> 0.0029220779 | AC11: 0.06 | AF11: 不进 | AG11: =MAX(AH11:AN11) -> 8.316 | AH11: =IF(U11>=50,MIN(MIN(U11*0.2,20)*0.3,6),0) -> 6 | AI11: =IF(U11>=200,MIN(MIN(U11*0.18,70)*0.3,21),0) -> 0 | AJ11: =IF(U11>=380,MIN(MIN(U11*0.28,350)*0.3,105),0) -> 0 | AK11: =IF(U11>=380,MIN(MIN(U11*0.25,350)*0.3,105),0) -> 0 | AL11: =IF(U11>=380,MIN(MIN(U11*0.22,300)*0.3,90),0) -> 0 | AM11: =IF(U11>=250,MIN(MIN(U11*0.18,120)*0.3,36),0) -> 0 | AN11: =IF(U11>=180,MIN(MIN(U11*0.15,60)*0.3,18),0) -> 8.316
A12: 办公安防 | B12: 办公周边 | C12: =_xlfn.XLOOKUP(F12,'6月产品包'!B:B,'6月产品包'!H:H) -> 标签打印纸 | D12: =_xlfn.XLOOKUP(F12,'6月产品包'!B:B,'6月产品包'!O:O) -> 热敏打印纸 | E12: 3B-宽57cm热敏打印纸5卷 | F12: T4CC0200377 | G12: 引流款 | H12: ZQ | I12: =_xlfn.XLOOKUP($F12,'6月库存'!A:A,'6月库存'!B:B) -> 正常销售 | K12: =_xlfn.XLOOKUP(E12,'[1]6月分配 '!$B:$B,'[1]6月分配 '!$K:$K) -> #N/A | L12: =IF(ISNUMBER(K12),"是",IF(ISNA(K12),"否","")) -> 否 | M12: =_xlfn.XLOOKUP(F12,'6月产品包'!B:B,'6月产品包'!J:J) -> 2025-02-11 | N12: =IF(DATEDIF(M12,TODAY(),"m")<6,"新品","老品") -> 老品 | O12: =_xlfn.XLOOKUP(F12,'6月库存'!A:A,'6月库存'!R:R) -> 4730 | P12: =_xlfn.XLOOKUP(F12,'6月产品包'!B:B,'6月产品包'!S:S) -> 88 | R12: =_xlfn.XLOOKUP(F12,'6月产品包'!B:B,'6月产品包'!AD:AD) -> 2.4535 | S12: 6.5 | T12: =ROUND(S12*(1+0.25),0) -> 8 | U12: =$T12*(1-0.2) -> 6.4 | V12: 0.2 | W12: =(U12-R12)/U12 -> 0.61664063 | X12: =(U12*(1-Y12-Z12-AA12-AC12-AB12)-R12)/(U12*(1-Y12-Z12-AA12-AC12-AB12)) -> 0.424925 | Y12: 0.04 | Z12: 0.1 | AA12: 0.049 | AB12: =$AB$1/U12 -> 0.084375 | AC12: 0.06 | AF12: 不进 | AG12: =MAX(AH12:AN12) -> 0 | AH12: =IF(U12>=50,MIN(MIN(U12*0.2,20)*0.3,6),0) -> 0 | AI12: =IF(U12>=200,MIN(MIN(U12*0.18,70)*0.3,21),0) -> 0 | AJ12: =IF(U12>=380,MIN(MIN(U12*0.28,350)*0.3,105),0) -> 0 | AK12: =IF(U12>=380,MIN(MIN(U12*0.25,350)*0.3,105),0) -> 0 | AL12: =IF(U12>=380,MIN(MIN(U12*0.22,300)*0.3,90),0) -> 0 | AM12: =IF(U12>=250,MIN(MIN(U12*0.18,120)*0.3,36),0) -> 0 | AN12: =IF(U12>=180,MIN(MIN(U12*0.15,60)*0.3,18),0) -> 0
A13: 办公安防 | B13: 安防存储 | C13: =_xlfn.XLOOKUP(F13,'6月产品包'!B:B,'6月产品包'!H:H) -> 保险箱 | D13: =_xlfn.XLOOKUP(F13,'6月产品包'!B:B,'6月产品包'!O:O) -> 大尺寸保险箱 | E13: 3B-保险箱黑50*35*30 | F13: T4CC1200282 | G13: 平销款 | H13: ZQ | I13: =_xlfn.XLOOKUP($F13,'6月库存'!A:A,'6月库存'!B:B) -> 正常销售 | K13: =_xlfn.XLOOKUP(E13,'[1]6月分配 '!$B:$B,'[1]6月分配 '!$K:$K) -> 171787 | L13: =IF(ISNUMBER(K13),"是",IF(ISNA(K13),"否","")) -> 是 | M13: =_xlfn.XLOOKUP(F13,'6月产品包'!B:B,'6月产品包'!J:J) -> 2025-09-01 | N13: =IF(DATEDIF(M13,TODAY(),"m")<6,"新品","老品") -> 老品 | O13: =_xlfn.XLOOKUP(F13,'6月库存'!A:A,'6月库存'!R:R) -> 0 | P13: =_xlfn.XLOOKUP(F13,'6月产品包'!B:B,'6月产品包'!S:S) -> 12500 | Q13: 12500 | R13: =_xlfn.XLOOKUP(F13,'6月产品包'!B:B,'6月产品包'!AD:AD) -> 114.695 | S13: 235 | T13: =ROUND(S13*(1+0.25),0) -> 294 | U13: =$T13*(1-0.2) -> 235.2 | V13: 0.2 | W13: =(U13-R13)/U13 -> 0.51235119 | X13: =(U13*(1-Y13-Z13-AA13-AC13-AB13)-R13)/(U13*(1-Y13-Z13-AA13-AC13-AB13)) -> 0.34867617 | Y13: 0.04 | Z13: 0.1 | AA13: 0.049 | AB13: =$AB$1/U13 -> 0.0022959184 | AC13: 0.06 | AF13: 原价进 | AG13: =MAX(AH13:AN13) -> 12.7008 | AH13: =IF(U13>=50,MIN(MIN(U13*0.2,20)*0.3,6),0) -> 6 | AI13: =IF(U13>=200,MIN(MIN(U13*0.18,70)*0.3,21),0) -> 12.7008 | AJ13: =IF(U13>=380,MIN(MIN(U13*0.28,350)*0.3,105),0) -> 0 | AK13: =IF(U13>=380,MIN(MIN(U13*0.25,350)*0.3,105),0) -> 0 | AL13: =IF(U13>=380,MIN(MIN(U13*0.22,300)*0.3,90),0) -> 0 | AM13: =IF(U13>=250,MIN(MIN(U13*0.18,120)*0.3,36),0) -> 0 | AN13: =IF(U13>=180,MIN(MIN(U13*0.15,60)*0.3,18),0) -> 10.584
A14: 3C数码 | B14: 电脑周边 | C14: =_xlfn.XLOOKUP(F14,'6月产品包'!B:B,'6月产品包'!H:H) -> 显示器 | D14: =_xlfn.XLOOKUP(F14,'6月产品包'!B:B,'6月产品包'!O:O) -> 11.6寸便携显示器非触摸款 | E14: 3C-11.6寸60Hz直面1K便携式显示器无触摸黑色 | F14: T3CC1910678 | G14: 引流款 | H14: MD | I14: =_xlfn.XLOOKUP($F14,'6月库存'!A:A,'6月库存'!B:B) -> 正常销售 | K14: =_xlfn.XLOOKUP(E14,'[1]6月分配 '!$B:$B,'[1]6月分配 '!$K:$K) -> #N/A | L14: =IF(ISNUMBER(K14),"是",IF(ISNA(K14),"否","")) -> 否 | M14: =_xlfn.XLOOKUP(F14,'6月产品包'!B:B,'6月产品包'!J:J) -> 2024-06-04 | N14: =IF(DATEDIF(M14,TODAY(),"m")<6,"新品","老品") -> 老品 | O14: =_xlfn.XLOOKUP(F14,'6月库存'!A:A,'6月库存'!R:R) -> 406 | P14: =_xlfn.XLOOKUP(F14,'6月产品包'!B:B,'6月产品包'!S:S) -> 940 | R14: =_xlfn.XLOOKUP(F14,'6月产品包'!B:B,'6月产品包'!AD:AD) -> 89.9232 | S14: 176 | T14: =ROUND(S14*(1+0.25),0) -> 220 | U14: =$T14*(1-0.2) -> 176 | V14: 0.2 | W14: =(U14-R14)/U14 -> 0.48907273 | X14: =(U14*(1-Y14-Z14-AA14-AC14-AB14)-R14)/(U14*(1-Y14-Z14-AA14-AC14-AB14)) -> 0.32766696 | Y14: 0.038 | Z14: 0.09 | AA14: 0.049 | AB14: =$AB$1/U14 -> 0.0030681818 | AC14: 0.06 | AF14: 不进 | AG14: =MAX(AH14:AN14) -> 6 | AH14: =IF(U14>=50,MIN(MIN(U14*0.2,20)*0.3,6),0) -> 6 | AI14: =IF(U14>=200,MIN(MIN(U14*0.18,70)*0.3,21),0) -> 0 | AJ14: =IF(U14>=380,MIN(MIN(U14*0.28,350)*0.3,105),0) -> 0 | AK14: =IF(U14>=380,MIN(MIN(U14*0.25,350)*0.3,105),0) -> 0 | AL14: =IF(U14>=380,MIN(MIN(U14*0.22,300)*0.3,90),0) -> 0 | AM14: =IF(U14>=250,MIN(MIN(U14*0.18,120)*0.3,36),0) -> 0 | AN14: =IF(U14>=180,MIN(MIN(U14*0.15,60)*0.3,18),0) -> 0
A15: 办公安防 | B15: 储能设备 | C15: =_xlfn.XLOOKUP(F15,'6月产品包'!B:B,'6月产品包'!H:H) -> #N/A | D15: =_xlfn.XLOOKUP(F15,'6月产品包'!B:B,'6月产品包'!O:O) -> #N/A | E15: 3B-JY004便携式储能电源5KG | F15: M4CC3300654 | G15: 利润款 | H15: MD | I15: =_xlfn.XLOOKUP($F15,'6月库存'!A:A,'6月库存'!B:B) -> 停止销售 | K15: =_xlfn.XLOOKUP(E15,'[1]6月分配 '!$B:$B,'[1]6月分配 '!$K:$K) -> #N/A | L15: =IF(ISNUMBER(K15),"是",IF(ISNA(K15),"否","")) -> 否 | M15: =_xlfn.XLOOKUP(F15,'6月产品包'!B:B,'6月产品包'!J:J) -> #N/A | N15: =IF(DATEDIF(M15,TODAY(),"m")<6,"新品","老品") -> #N/A | O15: =_xlfn.XLOOKUP(F15,'6月库存'!A:A,'6月库存'!R:R) -> 0 | P15: =_xlfn.XLOOKUP(F15,'6月产品包'!B:B,'6月产品包'!S:S) -> #N/A | R15: =_xlfn.XLOOKUP(F15,'6月产品包'!B:B,'6月产品包'!AD:AD) -> #N/A | S15: 659 | T15: =ROUND(S15*(1+0.25),0) -> 824 | U15: =$T15*(1-0.2) -> 659.2 | V15: 0.2 | W15: =(U15-R15)/U15 -> #N/A | X15: =(U15*(1-Y15-Z15-AA15-AC15-AB15)-R15)/(U15*(1-Y15-Z15-AA15-AC15-AB15)) -> #N/A | Y15: 0.038 | Z15: 0.105 | AA15: 0.049 | AB15: =$AB$1/U15 -> 0.00081917476 | AC15: 0.06 | AF15: 不进 | AG15: =MAX(AH15:AN15) -> 55.3728 | AH15: =IF(U15>=50,MIN(MIN(U15*0.2,20)*0.3,6),0) -> 6 | AI15: =IF(U15>=200,MIN(MIN(U15*0.18,70)*0.3,21),0) -> 21 | AJ15: =IF(U15>=380,MIN(MIN(U15*0.28,350)*0.3,105),0) -> 55.3728 | AK15: =IF(U15>=380,MIN(MIN(U15*0.25,350)*0.3,105),0) -> 49.44 | AL15: =IF(U15>=380,MIN(MIN(U15*0.22,300)*0.3,90),0) -> 43.5072 | AM15: =IF(U15>=250,MIN(MIN(U15*0.18,120)*0.3,36),0) -> 35.5968 | AN15: =IF(U15>=180,MIN(MIN(U15*0.15,60)*0.3,18),0) -> 18
A16: 办公安防 | B16: 安防存储 | C16: =_xlfn.XLOOKUP(F16,'6月产品包'!B:B,'6月产品包'!H:H) -> 保险箱 | D16: =_xlfn.XLOOKUP(F16,'6月产品包'!B:B,'6月产品包'!O:O) -> 大尺寸保险箱 | E16: 3B-保险箱黑50*35*30 | F16: T4CC2610282 | G16: 平销款 | H16: ZQ | I16: =_xlfn.XLOOKUP($F16,'6月库存'!A:A,'6月库存'!B:B) -> 正常销售 | K16: =_xlfn.XLOOKUP(E16,'[1]6月分配 '!$B:$B,'[1]6月分配 '!$K:$K) -> 171787 | L16: =IF(ISNUMBER(K16),"是",IF(ISNA(K16),"否","")) -> 是 | M16: =_xlfn.XLOOKUP(F16,'6月产品包'!B:B,'6月产品包'!J:J) -> 2025-12-02 | N16: =IF(DATEDIF(M16,TODAY(),"m")<6,"新品","老品") -> 老品 | O16: =_xlfn.XLOOKUP(F16,'6月库存'!A:A,'6月库存'!R:R) -> 918 | P16: =_xlfn.XLOOKUP(F16,'6月产品包'!B:B,'6月产品包'!S:S) -> 12500 | Q16: 12500 | R16: =_xlfn.XLOOKUP(F16,'6月产品包'!B:B,'6月产品包'!AD:AD) -> 121.7304 | S16: 235 | T16: =ROUND(S16*(1+0.25),0) -> 294 | U16: =$T16*(1-0.2) -> 235.2 | V16: 0.2 | W16: =(U16-R16)/U16 -> 0.48243878 | X16: =(U16*(1-Y16-Z16-AA16-AC16-AB16)-R16)/(U16*(1-Y16-Z16-AA16-AC16-AB16)) -> 0.30872392 | Y16: 0.04 | Z16: 0.1 | AA16: 0.049 | AB16: =$AB$1/U16 -> 0.0022959184 | AC16: 0.06 | AF16: 原价进 | AG16: =MAX(AH16:AN16) -> 12.7008 | AH16: =IF(U16>=50,MIN(MIN(U16*0.2,20)*0.3,6),0) -> 6 | AI16: =IF(U16>=200,MIN(MIN(U16*0.18,70)*0.3,21),0) -> 12.7008 | AJ16: =IF(U16>=380,MIN(MIN(U16*0.28,350)*0.3,105),0) -> 0 | AK16: =IF(U16>=380,MIN(MIN(U16*0.25,350)*0.3,105),0) -> 0 | AL16: =IF(U16>=380,MIN(MIN(U16*0.22,300)*0.3,90),0) -> 0 | AM16: =IF(U16>=250,MIN(MIN(U16*0.18,120)*0.3,36),0) -> 0 | AN16: =IF(U16>=180,MIN(MIN(U16*0.15,60)*0.3,18),0) -> 10.584
A17: 办公安防 | B17: 安防存储 | C17: =_xlfn.XLOOKUP(F17,'6月产品包'!B:B,'6月产品包'!H:H) -> 保险箱 | D17: =_xlfn.XLOOKUP(F17,'6月产品包'!B:B,'6月产品包'!O:O) -> 大尺寸保险箱 | E17: 3B-保险箱黑50*35*30 | F17: T3CC2160282 | G17: 平销款 | H17: ZQ | I17: =_xlfn.XLOOKUP($F17,'6月库存'!A:A,'6月库存'!B:B) -> 正常销售 | K17: =_xlfn.XLOOKUP(E17,'[1]6月分配 '!$B:$B,'[1]6月分配 '!$K:$K) -> 171787 | L17: =IF(ISNUMBER(K17),"是",IF(ISNA(K17),"否","")) -> 是 | M17: =_xlfn.XLOOKUP(F17,'6月产品包'!B:B,'6月产品包'!J:J) -> 2024-11-21 | N17: =IF(DATEDIF(M17,TODAY(),"m")<6,"新品","老品") -> 老品 | O17: =_xlfn.XLOOKUP(F17,'6月库存'!A:A,'6月库存'!R:R) -> 5 | P17: =_xlfn.XLOOKUP(F17,'6月产品包'!B:B,'6月产品包'!S:S) -> 12500 | Q17: 12500 | R17: =_xlfn.XLOOKUP(F17,'6月产品包'!B:B,'6月产品包'!AD:AD) -> 126.3066 | S17: 245 | T17: =ROUND(S17*(1+0.25),0) -> 306 | U17: =$T17*(1-0.2) -> 244.8 | V17: 0.2 | W17: =(U17-R17)/U17 -> 0.48404167 | X17: =(U17*(1-Y17-Z17-AA17-AC17-AB17)-R17)/(U17*(1-Y17-Z17-AA17-AC17-AB17)) -> 0.31094767 | Y17: 0.04 | Z17: 0.1 | AA17: 0.049 | AB17: =$AB$1/U17 -> 0.0022058824 | AC17: 0.06 | AF17: 原价进 | AG17: =MAX(AH17:AN17) -> 13.2192 | AH17: =IF(U17>=50,MIN(MIN(U17*0.2,20)*0.3,6),0) -> 6 | AI17: =IF(U17>=200,MIN(MIN(U17*0.18,70)*0.3,21),0) -> 13.2192 | AJ17: =IF(U17>=380,MIN(MIN(U17*0.28,350)*0.3,105),0) -> 0 | AK17: =IF(U17>=380,MIN(MIN(U17*0.25,350)*0.3,105),0) -> 0 | AL17: =IF(U17>=380,MIN(MIN(U17*0.22,300)*0.3,90),0) -> 0 | AM17: =IF(U17>=250,MIN(MIN(U17*0.18,120)*0.3,36),0) -> 0 | AN17: =IF(U17>=180,MIN(MIN(U17*0.15,60)*0.3,18),0) -> 11.016
A18: 办公安防 | B18: 办公周边 | C18: =_xlfn.XLOOKUP(F18,'6月产品包'!B:B,'6月产品包'!H:H) -> 考勤机 | D18: =_xlfn.XLOOKUP(F18,'6月产品包'!B:B,'6月产品包'!O:O) -> 指纹考勤机 | E18: 3B-X1指纹考勤机 | F18: M2CC1530462 | G18: #N/A | H18: MD | I18: =_xlfn.XLOOKUP($F18,'6月库存'!A:A,'6月库存'!B:B) -> 正常销售 | K18: =_xlfn.XLOOKUP(E18,'[1]6月分配 '!$B:$B,'[1]6月分配 '!$K:$K) -> 156679 | L18: =IF(ISNUMBER(K18),"是",IF(ISNA(K18),"否","")) -> 是 | M18: =_xlfn.XLOOKUP(F18,'6月产品包'!B:B,'6月产品包'!J:J) -> 2023-09-11 | N18: =IF(DATEDIF(M18,TODAY(),"m")<6,"新品","老品") -> 老品 | O18: =_xlfn.XLOOKUP(F18,'6月库存'!A:A,'6月库存'!R:R) -> 2237 | P18: =_xlfn.XLOOKUP(F18,'6月产品包'!B:B,'6月产品包'!S:S) -> 466 | R18: =_xlfn.XLOOKUP(F18,'6月产品包'!B:B,'6月产品包'!AD:AD) -> 44.167 | S18: 88 | T18: =ROUND(S18*(1+0.25),0) -> 110 | U18: =$T18*(1-0.2) -> 88 | V18: 0.2 | W18: =(U18-R18)/U18 -> 0.49810227 | X18: =(U18*(1-Y18-Z18-AA18-AC18-AB18)-R18)/(U18*(1-Y18-Z18-AA18-AC18-AB18)) -> 0.32799282 | Y18: 0.038 | Z18: 0.1 | AA18: 0.049 | AB18: =$AB$1/U18 -> 0.0061363636 | AC18: 0.06 | AF18: 原价进 | AG18: =MAX(AH18:AN18) -> 5.28 | AH18: =IF(U18>=50,MIN(MIN(U18*0.2,20)*0.3,6),0) -> 5.28 | AI18: =IF(U18>=200,MIN(MIN(U18*0.18,70)*0.3,21),0) -> 0 | AJ18: =IF(U18>=380,MIN(MIN(U18*0.28,350)*0.3,105),0) -> 0 | AK18: =IF(U18>=380,MIN(MIN(U18*0.25,350)*0.3,105),0) -> 0 | AL18: =IF(U18>=380,MIN(MIN(U18*0.22,300)*0.3,90),0) -> 0 | AM18: =IF(U18>=250,MIN(MIN(U18*0.18,120)*0.3,36),0) -> 0 | AN18: =IF(U18>=180,MIN(MIN(U18*0.15,60)*0.3,18),0) -> 0
A19: =_xlfn.XLOOKUP(F19,'6月产品包'!B:B,'6月产品包'!F:F) -> 3C数码 | B19: =_xlfn.XLOOKUP(F19,'6月产品包'!B:B,'6月产品包'!G:G) -> 影像摄影 | C19: =_xlfn.XLOOKUP(F19,'6月产品包'!B:B,'6月产品包'!H:H) -> LED像素屏 | D19: =_xlfn.XLOOKUP(F19,'6月产品包'!B:B,'6月产品包'!O:O) -> 互动屏 | E19: =_xlfn.XLOOKUP(F19,'6月产品包'!B:B,'6月产品包'!C:C) -> 3C-led智能互动屏17.3cm*7cm | F19: T4CC2320725 | G19: 平销款 | H19: MD | I19: =_xlfn.XLOOKUP($F19,'6月库存'!A:A,'6月库存'!B:B) -> 正常销售 | K19: =_xlfn.XLOOKUP(E19,'[1]6月分配 '!$B:$B,'[1]6月分配 '!$K:$K) -> #N/A | L19: =IF(ISNUMBER(K19),"是",IF(ISNA(K19),"否","")) -> 否 | M19: =_xlfn.XLOOKUP(F19,'6月产品包'!B:B,'6月产品包'!J:J) -> 2025-07-10 | N19: =IF(DATEDIF(M19,TODAY(),"m")<6,"新品","老品") -> 老品 | O19: =_xlfn.XLOOKUP(F19,'6月库存'!A:A,'6月库存'!R:R) -> 157 | P19: =_xlfn.XLOOKUP(F19,'6月产品包'!B:B,'6月产品包'!S:S) -> 238 | Q19: 300 | R19: =_xlfn.XLOOKUP(F19,'6月产品包'!B:B,'6月产品包'!AD:AD) -> 20.9264 | S19: 41.5 | T19: =ROUND(S19*(1+0.25),0) -> 52 | U19: =$T19*(1-0.2) -> 41.6 | V19: 0.2 | W19: =(U19-R19)/U19 -> 0.49696154 | X19: =(U19*(1-Y19-Z19-AA19-AC19-AB19)-R19)/(U19*(1-Y19-Z19-AA19-AC19-AB19)) -> 0.31092437 | Y19: 0.038 | Z19: 0.11 | AA19: 0.049 | AB19: =$AB$1/U19 -> 0.012980769 | AC19: 0.06 | AF19: 不进 | AG19: =MAX(AH19:AN19) -> 0 | AH19: =IF(U19>=50,MIN(MIN(U19*0.2,20)*0.3,6),0) -> 0 | AI19: =IF(U19>=200,MIN(MIN(U19*0.18,70)*0.3,21),0) -> 0 | AJ19: =IF(U19>=380,MIN(MIN(U19*0.28,350)*0.3,105),0) -> 0 | AK19: =IF(U19>=380,MIN(MIN(U19*0.25,350)*0.3,105),0) -> 0 | AL19: =IF(U19>=380,MIN(MIN(U19*0.22,300)*0.3,90),0) -> 0 | AM19: =IF(U19>=250,MIN(MIN(U19*0.18,120)*0.3,36),0) -> 0 | AN19: =IF(U19>=180,MIN(MIN(U19*0.15,60)*0.3,18),0) -> 0
A20: 3C数码 | B20: 电脑周边 | C20: =_xlfn.XLOOKUP(F20,'6月产品包'!B:B,'6月产品包'!H:H) -> 显示器支架 | D20: =_xlfn.XLOOKUP(F20,'6月产品包'!B:B,'6月产品包'!O:O) -> 显示器支架单臂铁塑款 | E20: 3C-显示器支架单臂铁塑款 | F20: T4CC1270889 | G20: 引流款 | H20: ZQ | I20: =_xlfn.XLOOKUP($F20,'6月库存'!A:A,'6月库存'!B:B) -> 正常销售 | K20: =_xlfn.XLOOKUP(E20,'[1]6月分配 '!$B:$B,'[1]6月分配 '!$K:$K) -> #N/A | L20: =IF(ISNUMBER(K20),"是",IF(ISNA(K20),"否","")) -> 否 | M20: =_xlfn.XLOOKUP(F20,'6月产品包'!B:B,'6月产品包'!J:J) -> 2025-10-27 | N20: =IF(DATEDIF(M20,TODAY(),"m")<6,"新品","老品") -> 老品 | O20: =_xlfn.XLOOKUP(F20,'6月库存'!A:A,'6月库存'!R:R) -> 255 | P20: =_xlfn.XLOOKUP(F20,'6月产品包'!B:B,'6月产品包'!S:S) -> 2380 | R20: =_xlfn.XLOOKUP(F20,'6月产品包'!B:B,'6月产品包'!AD:AD) -> 25.2358 | S20: 56 | T20: =ROUND(S20*(1+0.25),0) -> 70 | U20: =$T20*(1-0.2) -> 56 | V20: 0.2 | W20: =(U20-R20)/U20 -> 0.54936071 | X20: =(U20*(1-Y20-Z20-AA20-AC20-AB20)-R20)/(U20*(1-Y20-Z20-AA20-AC20-AB20)) -> 0.38967302 | Y20: 0.038 | Z20: 0.105 | AA20: 0.049 | AB20: =$AB$1/U20 -> 0.0096428571 | AC20: 0.06 | AF20: 不进 | AG20: =MAX(AH20:AN20) -> 3.36 | AH20: =IF(U20>=50,MIN(MIN(U20*0.2,20)*0.3,6),0) -> 3.36 | AI20: =IF(U20>=200,MIN(MIN(U20*0.18,70)*0.3,21),0) -> 0 | AJ20: =IF(U20>=380,MIN(MIN(U20*0.28,350)*0.3,105),0) -> 0 | AK20: =IF(U20>=380,MIN(MIN(U20*0.25,350)*0.3,105),0) -> 0 | AL20: =IF(U20>=380,MIN(MIN(U20*0.22,300)*0.3,90),0) -> 0 | AM20: =IF(U20>=250,MIN(MIN(U20*0.18,120)*0.3,36),0) -> 0 | AN20: =IF(U20>=180,MIN(MIN(U20*0.15,60)*0.3,18),0) -> 0
A21: 3C数码 | B21: 电脑周边 | C21: =_xlfn.XLOOKUP(F21,'6月产品包'!B:B,'6月产品包'!H:H) -> 显示器支架 | D21: =_xlfn.XLOOKUP(F21,'6月产品包'!B:B,'6月产品包'!O:O) -> 显示器支架双臂铁塑款 | E21: 3C-显示器支架双臂铁塑款 | F21: T4CC1270890 | G21: 引流款 | H21: ZQ | I21: =_xlfn.XLOOKUP($F21,'6月库存'!A:A,'6月库存'!B:B) -> 正常销售 | K21: =_xlfn.XLOOKUP(E21,'[1]6月分配 '!$B:$B,'[1]6月分配 '!$K:$K) -> #N/A | L21: =IF(ISNUMBER(K21),"是",IF(ISNA(K21),"否","")) -> 否 | M21: =_xlfn.XLOOKUP(F21,'6月产品包'!B:B,'6月产品包'!J:J) -> 2025-10-27 | N21: =IF(DATEDIF(M21,TODAY(),"m")<6,"新品","老品") -> 老品 | O21: =_xlfn.XLOOKUP(F21,'6月库存'!A:A,'6月库存'!R:R) -> 36 | P21: =_xlfn.XLOOKUP(F21,'6月产品包'!B:B,'6月产品包'!S:S) -> 4480 | R21: =_xlfn.XLOOKUP(F21,'6月产品包'!B:B,'6月产品包'!AD:AD) -> 48.9346 | S21: 103 | T21: =ROUND(S21*(1+0.25),0) -> 129 | U21: =$T21*(1-0.2) -> 103.2 | V21: 0.2 | W21: =(U21-R21)/U21 -> 0.52582752 | X21: =(U21*(1-Y21-Z21-AA21-AC21-AB21)-R21)/(U21*(1-Y21-Z21-AA21-AC21-AB21)) -> 0.36161381 | Y21: 0.038 | Z21: 0.105 | AA21: 0.049 | AB21: =$AB$1/U21 -> 0.0052325581 | AC21: 0.06 | AF21: 不进 | AG21: =MAX(AH21:AN21) -> 6 | AH21: =IF(U21>=50,MIN(MIN(U21*0.2,20)*0.3,6),0) -> 6 | AI21: =IF(U21>=200,MIN(MIN(U21*0.18,70)*0.3,21),0) -> 0 | AJ21: =IF(U21>=380,MIN(MIN(U21*0.28,350)*0.3,105),0) -> 0 | AK21: =IF(U21>=380,MIN(MIN(U21*0.25,350)*0.3,105),0) -> 0 | AL21: =IF(U21>=380,MIN(MIN(U21*0.22,300)*0.3,90),0) -> 0 | AM21: =IF(U21>=250,MIN(MIN(U21*0.18,120)*0.3,36),0) -> 0 | AN21: =IF(U21>=180,MIN(MIN(U21*0.15,60)*0.3,18),0) -> 0
A22: 3C数码 | B22: 电脑周边 | C22: =_xlfn.XLOOKUP(F22,'6月产品包'!B:B,'6月产品包'!H:H) -> 显示器支架 | D22: =_xlfn.XLOOKUP(F22,'6月产品包'!B:B,'6月产品包'!O:O) -> 桌面显示器支架 | E22: 3C-桌面显示器支架钢化玻璃底座 | F22: T3CC1270279 | G22: 利润款 | H22: ZQ | I22: =_xlfn.XLOOKUP($F22,'6月库存'!A:A,'6月库存'!B:B) -> 正常销售 | K22: =_xlfn.XLOOKUP(E22,'[1]6月分配 '!$B:$B,'[1]6月分配 '!$K:$K) -> #N/A | L22: =IF(ISNUMBER(K22),"是",IF(ISNA(K22),"否","")) -> 否 | M22: =_xlfn.XLOOKUP(F22,'6月产品包'!B:B,'6月产品包'!J:J) -> 2024-11-12 | N22: =IF(DATEDIF(M22,TODAY(),"m")<6,"新品","老品") -> 老品 | O22: =_xlfn.XLOOKUP(F22,'6月库存'!A:A,'6月库存'!R:R) -> 36 | P22: =_xlfn.XLOOKUP(F22,'6月产品包'!B:B,'6月产品包'!S:S) -> 4674 | R22: =_xlfn.XLOOKUP(F22,'6月产品包'!B:B,'6月产品包'!AD:AD) -> 27.7356 | S22: 56 | T22: =ROUND(S22*(1+0.25),0) -> 70 | U22: =$T22*(1-0.2) -> 56 | V22: 0.2 | W22: =(U22-R22)/U22 -> 0.50472143 | X22: =(U22*(1-Y22-Z22-AA22-AC22-AB22)-R22)/(U22*(1-Y22-Z22-AA22-AC22-AB22)) -> 0.34947931 | Y22: 0.04 | Z22: 0.08 | AA22: 0.049 | AB22: =$AB$1/U22 -> 0.0096428571 | AC22: 0.06 | AF22: 不进 | AG22: =MAX(AH22:AN22) -> 3.36 | AH22: =IF(U22>=50,MIN(MIN(U22*0.2,20)*0.3,6),0) -> 3.36 | AI22: =IF(U22>=200,MIN(MIN(U22*0.18,70)*0.3,21),0) -> 0 | AJ22: =IF(U22>=380,MIN(MIN(U22*0.28,350)*0.3,105),0) -> 0 | AK22: =IF(U22>=380,MIN(MIN(U22*0.25,350)*0.3,105),0) -> 0 | AL22: =IF(U22>=380,MIN(MIN(U22*0.22,300)*0.3,90),0) -> 0 | AM22: =IF(U22>=250,MIN(MIN(U22*0.18,120)*0.3,36),0) -> 0 | AN22: =IF(U22>=180,MIN(MIN(U22*0.15,60)*0.3,18),0) -> 0
A23: 3C数码 | B23: 电脑周边 | C23: =_xlfn.XLOOKUP(F23,'6月产品包'!B:B,'6月产品包'!H:H) -> 显示器支架 | D23: =_xlfn.XLOOKUP(F23,'6月产品包'!B:B,'6月产品包'!O:O) -> 桌面显示器支架 | E23: 3C-桌面显示器支架钢化玻璃底座 | F23: T4CC1120279 | G23: 利润款 | H23: ZQ | I23: =_xlfn.XLOOKUP($F23,'6月库存'!A:A,'6月库存'!B:B) -> 正常销售 | K23: =_xlfn.XLOOKUP(E23,'[1]6月分配 '!$B:$B,'[1]6月分配 '!$K:$K) -> #N/A | L23: =IF(ISNUMBER(K23),"是",IF(ISNA(K23),"否","")) -> 否 | M23: =_xlfn.XLOOKUP(F23,'6月产品包'!B:B,'6月产品包'!J:J) -> 2025-05-27 | N23: =IF(DATEDIF(M23,TODAY(),"m")<6,"新品","老品") -> 老品 | O23: =_xlfn.XLOOKUP(F23,'6月库存'!A:A,'6月库存'!R:R) -> 78 | P23: =_xlfn.XLOOKUP(F23,'6月产品包'!B:B,'6月产品包'!S:S) -> 4674 | R23: =_xlfn.XLOOKUP(F23,'6月产品包'!B:B,'6月产品包'!AD:AD) -> 27.4676 | S23: 56 | T23: =ROUND(S23*(1+0.25),0) -> 70 | U23: =$T23*(1-0.2) -> 56 | V23: 0.2 | W23: =(U23-R23)/U23 -> 0.50950714 | X23: =(U23*(1-Y23-Z23-AA23-AC23-AB23)-R23)/(U23*(1-Y23-Z23-AA23-AC23-AB23)) -> 0.35576508 | Y23: 0.04 | Z23: 0.08 | AA23: 0.049 | AB23: =$AB$1/U23 -> 0.0096428571 | AC23: 0.06 | AF23: 不进 | AG23: =MAX(AH23:AN23) -> 3.36 | AH23: =IF(U23>=50,MIN(MIN(U23*0.2,20)*0.3,6),0) -> 3.36 | AI23: =IF(U23>=200,MIN(MIN(U23*0.18,70)*0.3,21),0) -> 0 | AJ23: =IF(U23>=380,MIN(MIN(U23*0.28,350)*0.3,105),0) -> 0 | AK23: =IF(U23>=380,MIN(MIN(U23*0.25,350)*0.3,105),0) -> 0 | AL23: =IF(U23>=380,MIN(MIN(U23*0.22,300)*0.3,90),0) -> 0 | AM23: =IF(U23>=250,MIN(MIN(U23*0.18,120)*0.3,36),0) -> 0 | AN23: =IF(U23>=180,MIN(MIN(U23*0.15,60)*0.3,18),0) -> 0
A24: 3C数码 | B24: 音响乐器 | C24: =_xlfn.XLOOKUP(F24,'6月产品包'!B:B,'6月产品包'!H:H) -> 未来吉他 | D24: =_xlfn.XLOOKUP(F24,'6月产品包'!B:B,'6月产品包'!O:O) -> 无弦吉他 | E24: 3C-无弦吉他 | F24: T4CC2420764 | G24: 利润款 | H24: ZQ | I24: =_xlfn.XLOOKUP($F24,'6月库存'!A:A,'6月库存'!B:B) -> 正常销售 | K24: =_xlfn.XLOOKUP(E24,'[1]6月分配 '!$B:$B,'[1]6月分配 '!$K:$K) -> 107362 | L24: =IF(ISNUMBER(K24),"是",IF(ISNA(K24),"否","")) -> 是 | M24: =_xlfn.XLOOKUP(F24,'6月产品包'!B:B,'6月产品包'!J:J) -> 2025-07-26 | N24: 新品 | O24: =_xlfn.XLOOKUP(F24,'6月库存'!A:A,'6月库存'!R:R) -> 172 | P24: =_xlfn.XLOOKUP(F24,'6月产品包'!B:B,'6月产品包'!S:S) -> 3000 | R24: =_xlfn.XLOOKUP(F24,'6月产品包'!B:B,'6月产品包'!AD:AD) -> 413.7546 | S24: 799 | T24: =ROUND(S24*(1+0.25),0) -> 999 | U24: =$T24*(1-0.18) -> 819.18 | V24: 0.18 | W24: =(U24-R24)/U24 -> 0.49491614 | X24: =(U24*(1-Y24-Z24-AA24-AC24-AB24)-R24)/(U24*(1-Y24-Z24-AA24-AC24-AB24)) -> 0.30557469 | Y24: 0.038 | Z24: 0.105 | AA24: 0.049 | AB24: =$AB$1/U24 -> 0.00065919578 | AC24: 0.08 | AD24: 0.06 | AF24: 原价进 | AG24: =MAX(AH24:AN24) -> 68.81112 | AH24: =IF(U24>=50,MIN(MIN(U24*0.2,20)*0.3,6),0) -> 6 | AI24: =IF(U24>=200,MIN(MIN(U24*0.18,70)*0.3,21),0) -> 21 | AJ24: =IF(U24>=380,MIN(MIN(U24*0.28,350)*0.3,105),0) -> 68.81112 | AK24: =IF(U24>=380,MIN(MIN(U24*0.25,350)*0.3,105),0) -> 61.4385 | AL24: =IF(U24>=380,MIN(MIN(U24*0.22,300)*0.3,90),0) -> 54.06588 | AM24: =IF(U24>=250,MIN(MIN(U24*0.18,120)*0.3,36),0) -> 36 | AN24: =IF(U24>=180,MIN(MIN(U24*0.15,60)*0.3,18),0) -> 18
A25: 办公安防 | B25: 办公周边 | C25: =_xlfn.XLOOKUP(F25,'6月产品包'!B:B,'6月产品包'!H:H) -> 点钞机 | D25: =_xlfn.XLOOKUP(F25,'6月产品包'!B:B,'6月产品包'!O:O) -> 点钞机 | E25: 3B-点钞机灰色 | F25: M4CC2580711 | G25: 引流款 | H25: ZQ | I25: =_xlfn.XLOOKUP($F25,'6月库存'!A:A,'6月库存'!B:B) -> 商品清仓 | K25: =_xlfn.XLOOKUP(E25,'[1]6月分配 '!$B:$B,'[1]6月分配 '!$K:$K) -> 83177 | L25: =IF(ISNUMBER(K25),"是",IF(ISNA(K25),"否","")) -> 是 | M25: =_xlfn.XLOOKUP(F25,'6月产品包'!B:B,'6月产品包'!J:J) -> 2025-10-16 | N25: =IF(DATEDIF(M25,TODAY(),"m")<6,"新品","老品") -> 老品 | O25: =_xlfn.XLOOKUP(F25,'6月库存'!A:A,'6月库存'!R:R) -> 1057 | P25: =_xlfn.XLOOKUP(F25,'6月产品包'!B:B,'6月产品包'!S:S) -> 5500 | R25: =_xlfn.XLOOKUP(F25,'6月产品包'!B:B,'6月产品包'!AD:AD) -> 123.6966 | S25: 220 | T25: =ROUND(S25*(1+0.25),0) -> 275 | U25: =$T25*(1-0.2) -> 220 | V25: 0.2 | W25: =(U25-R25)/U25 -> 0.43774273 | X25: =(U25*(1-Y25-Z25-AA25-AC25-AB25)-R25)/(U25*(1-Y25-Z25-AA25-AC25-AB25)) -> 0.25086846 | Y25: 0.038 | Z25: 0.1 | AA25: 0.049 | AB25: =$AB$1/U25 -> 0.0024545455 | AC25: 0.06 | AF25: 原价进 | AG25: =MAX(AH25:AN25) -> 11.88 | AH25: =IF(U25>=50,MIN(MIN(U25*0.2,20)*0.3,6),0) -> 6 | AI25: =IF(U25>=200,MIN(MIN(U25*0.18,70)*0.3,21),0) -> 11.88 | AJ25: =IF(U25>=380,MIN(MIN(U25*0.28,350)*0.3,105),0) -> 0 | AK25: =IF(U25>=380,MIN(MIN(U25*0.25,350)*0.3,105),0) -> 0 | AL25: =IF(U25>=380,MIN(MIN(U25*0.22,300)*0.3,90),0) -> 0 | AM25: =IF(U25>=250,MIN(MIN(U25*0.18,120)*0.3,36),0) -> 0 | AN25: =IF(U25>=180,MIN(MIN(U25*0.15,60)*0.3,18),0) -> 9.9
A26: 办公安防 | B26: 智能安防 | C26: =_xlfn.XLOOKUP(F26,'6月产品包'!B:B,'6月产品包'!H:H) -> 摄像头 | D26: =_xlfn.XLOOKUP(F26,'6月产品包'!B:B,'6月产品包'!O:O) -> 太阳能摄像头 | E26: 3B-户外太阳能单板摄像头WiFi版 | F26: T3CC1950595 | G26: 灭款 | H26: MD | I26: =_xlfn.XLOOKUP($F26,'6月库存'!A:A,'6月库存'!B:B) -> 商品清仓 | K26: =_xlfn.XLOOKUP(E26,'[1]6月分配 '!$B:$B,'[1]6月分配 '!$K:$K) -> #N/A | L26: =IF(ISNUMBER(K26),"是",IF(ISNA(K26),"否","")) -> 否 | M26: =_xlfn.XLOOKUP(F26,'6月产品包'!B:B,'6月产品包'!J:J) -> 2024-03-26 | N26: =IF(DATEDIF(M26,TODAY(),"m")<6,"新品","老品") -> 老品 | O26: =_xlfn.XLOOKUP(F26,'6月库存'!A:A,'6月库存'!R:R) -> 14 | P26: =_xlfn.XLOOKUP(F26,'6月产品包'!B:B,'6月产品包'!S:S) -> 1400 | R26: =_xlfn.XLOOKUP(F26,'6月产品包'!B:B,'6月产品包'!AD:AD) -> 69.8668 | S26: 102 | T26: =ROUND(S26*(1+0.25),0) -> 128 | U26: =$T26*(1-0.2) -> 102.4 | V26: 0.2 | W26: =(U26-R26)/U26 -> 0.31770703 | X26: =(U26*(1-Y26-Z26-AA26-AC26-AB26)-R26)/(U26*(1-Y26-Z26-AA26-AC26-AB26)) -> 0.13930856 | Y26: 0.038 | Z26: 0.105 | AA26: 0.049 | AB26: =$AB$1/U26 -> 0.0052734375 | AC26: 0.01 | AF26: 不进 | AG26: =MAX(AH26:AN26) -> 6 | AH26: =IF(U26>=50,MIN(MIN(U26*0.2,20)*0.3,6),0) -> 6 | AI26: =IF(U26>=200,MIN(MIN(U26*0.18,70)*0.3,21),0) -> 0 | AJ26: =IF(U26>=380,MIN(MIN(U26*0.28,350)*0.3,105),0) -> 0 | AK26: =IF(U26>=380,MIN(MIN(U26*0.25,350)*0.3,105),0) -> 0 | AL26: =IF(U26>=380,MIN(MIN(U26*0.22,300)*0.3,90),0) -> 0 | AM26: =IF(U26>=250,MIN(MIN(U26*0.18,120)*0.3,36),0) -> 0 | AN26: =IF(U26>=180,MIN(MIN(U26*0.15,60)*0.3,18),0) -> 0
A27: 3C数码 | B27: 音响乐器 | C27: =_xlfn.XLOOKUP(F27,'6月产品包'!B:B,'6月产品包'!H:H) -> 电子琴 | D27: =_xlfn.XLOOKUP(F27,'6月产品包'!B:B,'6月产品包'!O:O) -> 折叠电子琴61键 | E27: 3C-折叠带蓝牙带琴谱架电子琴61键 | F27: M4CC2450780 | G27: 平销款 | H27: ZQ | I27: =_xlfn.XLOOKUP($F27,'6月库存'!A:A,'6月库存'!B:B) -> 正常销售 | K27: =_xlfn.XLOOKUP(E27,'[1]6月分配 '!$B:$B,'[1]6月分配 '!$K:$K) -> 49772 | L27: =IF(ISNUMBER(K27),"是",IF(ISNA(K27),"否","")) -> 是 | M27: =_xlfn.XLOOKUP(F27,'6月产品包'!B:B,'6月产品包'!J:J) -> 2025-10-09 | N27: 老品 | O27: =_xlfn.XLOOKUP(F27,'6月库存'!A:A,'6月库存'!R:R) -> 271 | P27: =_xlfn.XLOOKUP(F27,'6月产品包'!B:B,'6月产品包'!S:S) -> 3300 | R27: =_xlfn.XLOOKUP(F27,'6月产品包'!B:B,'6月产品包'!AD:AD) -> 95.1142 | S27: 207 | T27: =ROUND(S27*(1+0.25),0) -> 259 | U27: =$T27*(1-0.2) -> 207.2 | V27: 0.2 | W27: =(U27-R27)/U27 -> 0.54095463 | X27: =(U27*(1-Y27-Z27-AA27-AC27-AB27)-R27)/(U27*(1-Y27-Z27-AA27-AC27-AB27)) -> 0.38415727 | Y27: 0.038 | Z27: 0.105 | AA27: 0.049 | AB27: =$AB$1/U27 -> 0.0026061776 | AC27: 0.06 | AF27: 原价进 | AG27: =MAX(AH27:AN27) -> 11.1888 | AH27: =IF(U27>=50,MIN(MIN(U27*0.2,20)*0.3,6),0) -> 6 | AI27: =IF(U27>=200,MIN(MIN(U27*0.18,70)*0.3,21),0) -> 11.1888 | AJ27: =IF(U27>=380,MIN(MIN(U27*0.28,350)*0.3,105),0) -> 0 | AK27: =IF(U27>=380,MIN(MIN(U27*0.25,350)*0.3,105),0) -> 0 | AL27: =IF(U27>=380,MIN(MIN(U27*0.22,300)*0.3,90),0) -> 0 | AM27: =IF(U27>=250,MIN(MIN(U27*0.18,120)*0.3,36),0) -> 0 | AN27: =IF(U27>=180,MIN(MIN(U27*0.15,60)*0.3,18),0) -> 9.324
A28: 办公安防 | B28: 智能安防 | C28: =_xlfn.XLOOKUP(F28,'6月产品包'!B:B,'6月产品包'!H:H) -> 路由器 | D28: =_xlfn.XLOOKUP(F28,'6月产品包'!B:B,'6月产品包'!O:O) -> P6000路由器 | E28: 3B-路由器P6000白色 | F28: M2CC0180514 | G28: #N/A | H28: MD | I28: =_xlfn.XLOOKUP($F28,'6月库存'!A:A,'6月库存'!B:B) -> 商品清仓 | K28: =_xlfn.XLOOKUP(E28,'[1]6月分配 '!$B:$B,'[1]6月分配 '!$K:$K) -> 46767 | L28: =IF(ISNUMBER(K28),"是",IF(ISNA(K28),"否","")) -> 是 | M28: =_xlfn.XLOOKUP(F28,'6月产品包'!B:B,'6月产品包'!J:J) -> 2023-07-25 | N28: =IF(DATEDIF(M28,TODAY(),"m")<6,"新品","老品") -> 老品 | O28: =_xlfn.XLOOKUP(F28,'6月库存'!A:A,'6月库存'!R:R) -> 361 | P28: =_xlfn.XLOOKUP(F28,'6月产品包'!B:B,'6月产品包'!S:S) -> 300 | R28: =_xlfn.XLOOKUP(F28,'6月产品包'!B:B,'6月产品包'!AD:AD) -> 54.1952 | S28: 108 | T28: =ROUND(S28*(1+0.25),0) -> 135 | U28: =$T28*(1-0.2) -> 108 | V28: 0.2 | W28: =(U28-R28)/U28 -> 0.49819259 | X28: =(U28*(1-Y28-Z28-AA28-AC28-AB28)-R28)/(U28*(1-Y28-Z28-AA28-AC28-AB28)) -> 0.32461991 | Y28: 0.038 | Z28: 0.105 | AA28: 0.049 | AB28: =$AB$1/U28 -> 0.005 | AC28: 0.06 | AF28: 不进 | AG28: =MAX(AH28:AN28) -> 6 | AH28: =IF(U28>=50,MIN(MIN(U28*0.2,20)*0.3,6),0) -> 6 | AI28: =IF(U28>=200,MIN(MIN(U28*0.18,70)*0.3,21),0) -> 0 | AJ28: =IF(U28>=380,MIN(MIN(U28*0.28,350)*0.3,105),0) -> 0 | AK28: =IF(U28>=380,MIN(MIN(U28*0.25,350)*0.3,105),0) -> 0 | AL28: =IF(U28>=380,MIN(MIN(U28*0.22,300)*0.3,90),0) -> 0 | AM28: =IF(U28>=250,MIN(MIN(U28*0.18,120)*0.3,36),0) -> 0 | AN28: =IF(U28>=180,MIN(MIN(U28*0.15,60)*0.3,18),0) -> 0
A29: 办公安防 | B29: 安防存储 | C29: =_xlfn.XLOOKUP(F29,'6月产品包'!B:B,'6月产品包'!H:H) -> 保险箱 | D29: =_xlfn.XLOOKUP(F29,'6月产品包'!B:B,'6月产品包'!O:O) -> 液晶保险箱 | E29: 3B-液晶面板保险柜45cm*38cm*30cm | F29: T4CC2610739 | G29: 利润款 | H29: ZQ | I29: =_xlfn.XLOOKUP($F29,'6月库存'!A:A,'6月库存'!B:B) -> 正常销售 | K29: =_xlfn.XLOOKUP(E29,'[1]6月分配 '!$B:$B,'[1]6月分配 '!$K:$K) -> 44452 | L29: =IF(ISNUMBER(K29),"是",IF(ISNA(K29),"否","")) -> 是 | M29: =_xlfn.XLOOKUP(F29,'6月产品包'!B:B,'6月产品包'!J:J) -> 2025-11-13 | N29: =IF(DATEDIF(M29,TODAY(),"m")<6,"新品","老品") -> 老品 | O29: =_xlfn.XLOOKUP(F29,'6月库存'!A:A,'6月库存'!R:R) -> 191 | P29: =_xlfn.XLOOKUP(F29,'6月产品包'!B:B,'6月产品包'!S:S) -> 13950 | R29: =_xlfn.XLOOKUP(F29,'6月产品包'!B:B,'6月产品包'!AD:AD) -> 160.6368 | S29: 350 | T29: =ROUND(S29*(1+0.25),0) -> 438 | U29: =$T29*(1-0.2) -> 350.4 | V29: 0.2 | W29: =(U29-R29)/U29 -> 0.54156164 | X29: =(U29*(1-Y29-Z29-AA29-AC29-AB29)-R29)/(U29*(1-Y29-Z29-AA29-AC29-AB29)) -> 0.38993556 | Y29: 0.038 | Z29: 0.1 | AA29: 0.049 | AB29: =$AB$1/U29 -> 0.0015410959 | AC29: 0.06 | AF29: 原价进 | AG29: =MAX(AH29:AN29) -> 18.9216 | AH29: =IF(U29>=50,MIN(MIN(U29*0.2,20)*0.3,6),0) -> 6 | AI29: =IF(U29>=200,MIN(MIN(U29*0.18,70)*0.3,21),0) -> 18.9216 | AJ29: =IF(U29>=380,MIN(MIN(U29*0.28,350)*0.3,105),0) -> 0 | AK29: =IF(U29>=380,MIN(MIN(U29*0.25,350)*0.3,105),0) -> 0 | AL29: =IF(U29>=380,MIN(MIN(U29*0.22,300)*0.3,90),0) -> 0 | AM29: =IF(U29>=250,MIN(MIN(U29*0.18,120)*0.3,36),0) -> 18.9216 | AN29: =IF(U29>=180,MIN(MIN(U29*0.15,60)*0.3,18),0) -> 15.768
A30: 3C数码 | B30: 电脑周边 | C30: =_xlfn.XLOOKUP(F30,'6月产品包'!B:B,'6月产品包'!H:H) -> 显示器支架 | D30: =_xlfn.XLOOKUP(F30,'6月产品包'!B:B,'6月产品包'!O:O) -> 立式显示器支架 | E30: 3C-立式显示器支架不带托盘 | F30: T3CC1270257 | G30: 灭款 | H30: ZQ | I30: =_xlfn.XLOOKUP($F30,'6月库存'!A:A,'6月库存'!B:B) -> 正常销售 | K30: =_xlfn.XLOOKUP(E30,'[1]6月分配 '!$B:$B,'[1]6月分配 '!$K:$K) -> #N/A | L30: =IF(ISNUMBER(K30),"是",IF(ISNA(K30),"否","")) -> 否 | M30: =_xlfn.XLOOKUP(F30,'6月产品包'!B:B,'6月产品包'!J:J) -> 2024-11-12 | N30: =IF(DATEDIF(M30,TODAY(),"m")<6,"新品","老品") -> 老品 | O30: =_xlfn.XLOOKUP(F30,'6月库存'!A:A,'6月库存'!R:R) -> 0 | P30: =_xlfn.XLOOKUP(F30,'6月产品包'!B:B,'6月产品包'!S:S) -> 5500 | R30: =_xlfn.XLOOKUP(F30,'6月产品包'!B:B,'6月产品包'!AD:AD) -> 62.0716 | S30: 109 | T30: =ROUND(S30*(1+0.25),0) -> 136 | U30: =$T30*(1-0.2) -> 108.8 | V30: 0.2 | W30: =(U30-R30)/U30 -> 0.42948897 | X30: =(U30*(1-Y30-Z30-AA30-AC30-AB30)-R30)/(U30*(1-Y30-Z30-AA30-AC30-AB30)) -> 0.24738343 | Y30: 0.038 | Z30: 0.09 | AA30: 0.049 | AB30: =$AB$1/U30 -> 0.0049632353 | AC30: 0.06 | AF30: 不进 | AG30: =MAX(AH30:AN30) -> 6 | AH30: =IF(U30>=50,MIN(MIN(U30*0.2,20)*0.3,6),0) -> 6 | AI30: =IF(U30>=200,MIN(MIN(U30*0.18,70)*0.3,21),0) -> 0 | AJ30: =IF(U30>=380,MIN(MIN(U30*0.28,350)*0.3,105),0) -> 0 | AK30: =IF(U30>=380,MIN(MIN(U30*0.25,350)*0.3,105),0) -> 0 | AL30: =IF(U30>=380,MIN(MIN(U30*0.22,300)*0.3,90),0) -> 0 | AM30: =IF(U30>=250,MIN(MIN(U30*0.18,120)*0.3,36),0) -> 0 | AN30: =IF(U30>=180,MIN(MIN(U30*0.15,60)*0.3,18),0) -> 0
A31: 3C数码 | B31: 电脑周边 | C31: =_xlfn.XLOOKUP(F31,'6月产品包'!B:B,'6月产品包'!H:H) -> 显示器支架 | D31: =_xlfn.XLOOKUP(F31,'6月产品包'!B:B,'6月产品包'!O:O) -> 气钢单臂显示器支架 | E31: 3C-电脑显示器支架 | F31: T3CC1270169 | G31: 平销款 | H31: ZQ | I31: =_xlfn.XLOOKUP($F31,'6月库存'!A:A,'6月库存'!B:B) -> 正常销售 | K31: =_xlfn.XLOOKUP(E31,'[1]6月分配 '!$B:$B,'[1]6月分配 '!$K:$K) -> #N/A | L31: =IF(ISNUMBER(K31),"是",IF(ISNA(K31),"否","")) -> 否 | M31: =_xlfn.XLOOKUP(F31,'6月产品包'!B:B,'6月产品包'!J:J) -> 2024-10-10 | N31: =IF(DATEDIF(M31,TODAY(),"m")<6,"新品","老品") -> 老品 | O31: =_xlfn.XLOOKUP(F31,'6月库存'!A:A,'6月库存'!R:R) -> 1582 | P31: =_xlfn.XLOOKUP(F31,'6月产品包'!B:B,'6月产品包'!S:S) -> 2331 | R31: =_xlfn.XLOOKUP(F31,'6月产品包'!B:B,'6月产品包'!AD:AD) -> 30.7284 | S31: 65 | T31: =ROUND(S31*(1+0.25),0) -> 81 | U31: =$T31*(1-0.2) -> 64.8 | V31: 0.2 | W31: =(U31-R31)/U31 -> 0.5257963 | X31: =(U31*(1-Y31-Z31-AA31-AC31-AB31)-R31)/(U31*(1-Y31-Z31-AA31-AC31-AB31)) -> 0.3588954 | Y31: 0.038 | Z31: 0.105 | AA31: 0.049 | AB31: =$AB$1/U31 -> 0.0083333333 | AC31: 0.06 | AF31: 不进 | AG31: =MAX(AH31:AN31) -> 3.888 | AH31: =IF(U31>=50,MIN(MIN(U31*0.2,20)*0.3,6),0) -> 3.888 | AI31: =IF(U31>=200,MIN(MIN(U31*0.18,70)*0.3,21),0) -> 0 | AJ31: =IF(U31>=380,MIN(MIN(U31*0.28,350)*0.3,105),0) -> 0 | AK31: =IF(U31>=380,MIN(MIN(U31*0.25,350)*0.3,105),0) -> 0 | AL31: =IF(U31>=380,MIN(MIN(U31*0.22,300)*0.3,90),0) -> 0 | AM31: =IF(U31>=250,MIN(MIN(U31*0.18,120)*0.3,36),0) -> 0 | AN31: =IF(U31>=180,MIN(MIN(U31*0.15,60)*0.3,18),0) -> 0
A32: 3C数码 | B32: 电脑周边 | C32: =_xlfn.XLOOKUP(F32,'6月产品包'!B:B,'6月产品包'!H:H) -> 电脑机箱 | D32: =_xlfn.XLOOKUP(F32,'6月产品包'!B:B,'6月产品包'!O:O) -> 电脑机箱T6风扇款 | E32: 3C-电脑机箱T6款白色3风扇 | F32: T4CC2351009 | G32: 平销款 | H32: ZQ | I32: =_xlfn.XLOOKUP($F32,'6月库存'!A:A,'6月库存'!B:B) -> 正常销售 | K32: =_xlfn.XLOOKUP(E32,'[1]6月分配 '!$B:$B,'[1]6月分配 '!$K:$K) -> #N/A | L32: =IF(ISNUMBER(K32),"是",IF(ISNA(K32),"否","")) -> 否 | M32: =_xlfn.XLOOKUP(F32,'6月产品包'!B:B,'6月产品包'!J:J) -> 2025-12-23 | N32: =IF(DATEDIF(M32,TODAY(),"m")<6,"新品","老品") -> 新品 | O32: =_xlfn.XLOOKUP(F32,'6月库存'!A:A,'6月库存'!R:R) -> 13 | P32: =_xlfn.XLOOKUP(F32,'6月产品包'!B:B,'6月产品包'!S:S) -> 5890 | R32: =_xlfn.XLOOKUP(F32,'6月产品包'!B:B,'6月产品包'!AD:AD) -> 117.2586 | S32: 215 | T32: =ROUND(S32*(1+0.25),0) -> 269 | U32: =$T32*(1-0.2) -> 215.2 | V32: 0.2 | W32: =(U32-R32)/U32 -> 0.45511803 | X32: =(U32*(1-Y32-Z32-AA32-AC32-AB32)-R32)/(U32*(1-Y32-Z32-AA32-AC32-AB32)) -> 0.28539198 | Y32: 0.04 | Z32: 0.086 | AA32: 0.049 | AB32: =$AB$1/U32 -> 0.0025092937 | AC32: 0.06 | AF32: 不进 | AG32: =MAX(AH32:AN32) -> 11.6208 | AH32: =IF(U32>=50,MIN(MIN(U32*0.2,20)*0.3,6),0) -> 6 | AI32: =IF(U32>=200,MIN(MIN(U32*0.18,70)*0.3,21),0) -> 11.6208 | AJ32: =IF(U32>=380,MIN(MIN(U32*0.28,350)*0.3,105),0) -> 0 | AK32: =IF(U32>=380,MIN(MIN(U32*0.25,350)*0.3,105),0) -> 0 | AL32: =IF(U32>=380,MIN(MIN(U32*0.22,300)*0.3,90),0) -> 0 | AM32: =IF(U32>=250,MIN(MIN(U32*0.18,120)*0.3,36),0) -> 0 | AN32: =IF(U32>=180,MIN(MIN(U32*0.15,60)*0.3,18),0) -> 9.684
A33: =_xlfn.XLOOKUP(F33,'6月产品包'!B:B,'6月产品包'!F:F) -> 3C数码 | B33: =_xlfn.XLOOKUP(F33,'6月产品包'!B:B,'6月产品包'!G:G) -> 影像摄影 | C33: =_xlfn.XLOOKUP(F33,'6月产品包'!B:B,'6月产品包'!H:H) -> 家用音视频设备*投影仪 | D33: =_xlfn.XLOOKUP(F33,'6月产品包'!B:B,'6月产品包'!O:O) -> 投影仪Z300 | E33: =_xlfn.XLOOKUP(F33,'6月产品包'!B:B,'6月产品包'!C:C) -> 3C-高亮自动对焦灯带投影仪Z300 | F33: M5CC1721048 | G33: 利润款 | H33: MD | I33: =_xlfn.XLOOKUP($F33,'6月库存'!A:A,'6月库存'!B:B) -> 正常销售 | K33: =_xlfn.XLOOKUP(E33,'[1]6月分配 '!$B:$B,'[1]6月分配 '!$K:$K) -> 40438 | L33: =IF(ISNUMBER(K33),"是",IF(ISNA(K33),"否","")) -> 是 | M33: =_xlfn.XLOOKUP(F33,'6月产品包'!B:B,'6月产品包'!J:J) -> 2026-04-13 | N33: =IF(DATEDIF(M33,TODAY(),"m")<6,"新品","老品") -> 新品 | O33: =_xlfn.XLOOKUP(F33,'6月库存'!A:A,'6月库存'!R:R) -> 74 | P33: =_xlfn.XLOOKUP(F33,'6月产品包'!B:B,'6月产品包'!S:S) -> 1800 | R33: =_xlfn.XLOOKUP(F33,'6月产品包'!B:B,'6月产品包'!AD:AD) -> 234.5404 | S33: 489 | T33: =ROUND(S33*(1+0.25),0) -> 611 | U33: =$T33*(1-0.2) -> 488.8 | V33: 0.2 | W33: =(U33-R33)/U33 -> 0.52017103 | X33: =(U33*(1-Y33-Z33-AA33-AC33-AB33)-R33)/(U33*(1-Y33-Z33-AA33-AC33-AB33)) -> 0.30949454 | Y33: 0.04 | Z33: 0.115 | AA33: 0.049 | AB33: =$AB$1/U33 -> 0.0011047463 | AC33: 0.1 | AD33: 0.08 | AE33: 0.05 | AF33: 0.18 | AG33: =MAX(AH33:AN33) -> 41.0592 | AH33: =IF(U33>=50,MIN(MIN(U33*0.2,20)*0.3,6),0) -> 6 | AI33: =IF(U33>=200,MIN(MIN(U33*0.18,70)*0.3,21),0) -> 21 | AJ33: =IF(U33>=380,MIN(MIN(U33*0.28,350)*0.3,105),0) -> 41.0592 | AK33: =IF(U33>=380,MIN(MIN(U33*0.25,350)*0.3,105),0) -> 36.66 | AL33: =IF(U33>=380,MIN(MIN(U33*0.22,300)*0.3,90),0) -> 32.2608 | AM33: =IF(U33>=250,MIN(MIN(U33*0.18,120)*0.3,36),0) -> 26.3952 | AN33: =IF(U33>=180,MIN(MIN(U33*0.15,60)*0.3,18),0) -> 18
A34: 3C数码 | B34: 电脑周边 | C34: =_xlfn.XLOOKUP(F34,'6月产品包'!B:B,'6月产品包'!H:H) -> 显示器支架 | D34: =_xlfn.XLOOKUP(F34,'6月产品包'!B:B,'6月产品包'!O:O) -> 双臂显示器支架 | E34: 3C-双臂带托盘显示器支架 | F34: T2CC1270162 | G34: 平销款 | H34: ZQ | I34: =_xlfn.XLOOKUP($F34,'6月库存'!A:A,'6月库存'!B:B) -> 正常销售 | K34: =_xlfn.XLOOKUP(E34,'[1]6月分配 '!$B:$B,'[1]6月分配 '!$K:$K) -> #N/A | L34: =IF(ISNUMBER(K34),"是",IF(ISNA(K34),"否","")) -> 否 | M34: =_xlfn.XLOOKUP(F34,'6月产品包'!B:B,'6月产品包'!J:J) -> 2024-01-01 | N34: =IF(DATEDIF(M34,TODAY(),"m")<6,"新品","老品") -> 老品 | O34: =_xlfn.XLOOKUP(F34,'6月库存'!A:A,'6月库存'!R:R) -> 278 | P34: =_xlfn.XLOOKUP(F34,'6月产品包'!B:B,'6月产品包'!S:S) -> 4000 | R34: =_xlfn.XLOOKUP(F34,'6月产品包'!B:B,'6月产品包'!AD:AD) -> 41.9572 | S34: 78 | T34: =ROUND(S34*(1+0.25),0) -> 98 | U34: =$T34*(1-0.2) -> 78.4 | V34: 0.2 | W34: =(U34-R34)/U34 -> 0.46483163 | X34: =(U34*(1-Y34-Z34-AA34-AC34-AB34)-R34)/(U34*(1-Y34-Z34-AA34-AC34-AB34)) -> 0.27788487 | Y34: 0.038 | Z34: 0.105 | AA34: 0.049 | AB34: =$AB$1/U34 -> 0.0068877551 | AC34: 0.06 | AF34: 不进 | AG34: =MAX(AH34:AN34) -> 4.704 | AH34: =IF(U34>=50,MIN(MIN(U34*0.2,20)*0.3,6),0) -> 4.704 | AI34: =IF(U34>=200,MIN(MIN(U34*0.18,70)*0.3,21),0) -> 0 | AJ34: =IF(U34>=380,MIN(MIN(U34*0.28,350)*0.3,105),0) -> 0 | AK34: =IF(U34>=380,MIN(MIN(U34*0.25,350)*0.3,105),0) -> 0 | AL34: =IF(U34>=380,MIN(MIN(U34*0.22,300)*0.3,90),0) -> 0 | AM34: =IF(U34>=250,MIN(MIN(U34*0.18,120)*0.3,36),0) -> 0 | AN34: =IF(U34>=180,MIN(MIN(U34*0.15,60)*0.3,18),0) -> 0
A35: 3C数码 | B35: 电视设备 | C35: =_xlfn.XLOOKUP(F35,'6月产品包'!B:B,'6月产品包'!H:H) -> 电视支架 | D35: =_xlfn.XLOOKUP(F35,'6月产品包'!B:B,'6月产品包'!O:O) -> 移动电视支架 | E35: 3C-32英寸到55英寸带中托可移动电视支架 | F35: T4CC1120706 | G35: 平销款 | H35: ZQ | I35: =_xlfn.XLOOKUP($F35,'6月库存'!A:A,'6月库存'!B:B) -> 正常销售 | K35: =_xlfn.XLOOKUP(E35,'[1]6月分配 '!$B:$B,'[1]6月分配 '!$K:$K) -> 38775 | L35: =IF(ISNUMBER(K35),"是",IF(ISNA(K35),"否","")) -> 是 | M35: =_xlfn.XLOOKUP(F35,'6月产品包'!B:B,'6月产品包'!J:J) -> 2025-04-24 | N35: 老品 | O35: =_xlfn.XLOOKUP(F35,'6月库存'!A:A,'6月库存'!R:R) -> 453 | P35: =_xlfn.XLOOKUP(F35,'6月产品包'!B:B,'6月产品包'!S:S) -> 9400 | R35: =_xlfn.XLOOKUP(F35,'6月产品包'!B:B,'6月产品包'!AD:AD) -> 71.5082 | S35: 129 | T35: =ROUND(S35*(1+0.25),0) -> 161 | U35: =$T35*(1-0.2) -> 128.8 | V35: 0.2 | W35: =(U35-R35)/U35 -> 0.44481211 | X35: =(U35*(1-Y35-Z35-AA35-AC35-AB35)-R35)/(U35*(1-Y35-Z35-AA35-AC35-AB35)) -> 0.26834155 | Y35: 0.038 | Z35: 0.09 | AA35: 0.049 | AB35: =$AB$1/U35 -> 0.0041925466 | AC35: 0.06 | AF35: 原价进 | AG35: =MAX(AH35:AN35) -> 6 | AH35: =IF(U35>=50,MIN(MIN(U35*0.2,20)*0.3,6),0) -> 6 | AI35: =IF(U35>=200,MIN(MIN(U35*0.18,70)*0.3,21),0) -> 0 | AJ35: =IF(U35>=380,MIN(MIN(U35*0.28,350)*0.3,105),0) -> 0 | AK35: =IF(U35>=380,MIN(MIN(U35*0.25,350)*0.3,105),0) -> 0 | AL35: =IF(U35>=380,MIN(MIN(U35*0.22,300)*0.3,90),0) -> 0 | AM35: =IF(U35>=250,MIN(MIN(U35*0.18,120)*0.3,36),0) -> 0 | AN35: =IF(U35>=180,MIN(MIN(U35*0.15,60)*0.3,18),0) -> 0
A36: 办公安防 | B36: 安防存储 | C36: =_xlfn.XLOOKUP(F36,'6月产品包'!B:B,'6月产品包'!H:H) -> 保险柜 | D36: =_xlfn.XLOOKUP(F36,'6月产品包'!B:B,'6月产品包'!O:O) -> XT保险箱密码款 | E36: 3B-XT保险箱45*38*32cm灰白色密码款 | F36: T4CC2610979 | G36: 利润款 | H36: ZQ | I36: =_xlfn.XLOOKUP($F36,'6月库存'!A:A,'6月库存'!B:B) -> 正常销售 | K36: =_xlfn.XLOOKUP(E36,'[1]6月分配 '!$B:$B,'[1]6月分配 '!$K:$K) -> 36560 | L36: =IF(ISNUMBER(K36),"是",IF(ISNA(K36),"否","")) -> 是 | M36: =_xlfn.XLOOKUP(F36,'6月产品包'!B:B,'6月产品包'!J:J) -> 2025-12-02 | N36: =IF(DATEDIF(M36,TODAY(),"m")<6,"新品","老品") -> 老品 | O36: =_xlfn.XLOOKUP(F36,'6月库存'!A:A,'6月库存'!R:R) -> 95 | P36: =_xlfn.XLOOKUP(F36,'6月产品包'!B:B,'6月产品包'!S:S) -> 15000 | R36: =_xlfn.XLOOKUP(F36,'6月产品包'!B:B,'6月产品包'!AD:AD) -> 157.6556 | S36: 339 | T36: =ROUND(S36*(1+0.25),0) -> 424 | U36: =$T36*(1-0.2) -> 339.2 | V36: 0.2 | W36: =(U36-R36)/U36 -> 0.53521344 | X36: =(U36*(1-Y36-Z36-AA36-AC36-AB36)-R36)/(U36*(1-Y36-Z36-AA36-AC36-AB36)) -> 0.38956966 | Y36: 0.038 | Z36: 0.09 | AA36: 0.049 | AB36: =$AB$1/U36 -> 0.0015919811 | AC36: 0.06 | AF36: 原价进 | AG36: =MAX(AH36:AN36) -> 18.3168 | AH36: =IF(U36>=50,MIN(MIN(U36*0.2,20)*0.3,6),0) -> 6 | AI36: =IF(U36>=200,MIN(MIN(U36*0.18,70)*0.3,21),0) -> 18.3168 | AJ36: =IF(U36>=380,MIN(MIN(U36*0.28,350)*0.3,105),0) -> 0 | AK36: =IF(U36>=380,MIN(MIN(U36*0.25,350)*0.3,105),0) -> 0 | AL36: =IF(U36>=380,MIN(MIN(U36*0.22,300)*0.3,90),0) -> 0 | AM36: =IF(U36>=250,MIN(MIN(U36*0.18,120)*0.3,36),0) -> 18.3168 | AN36: =IF(U36>=180,MIN(MIN(U36*0.15,60)*0.3,18),0) -> 15.264
A37: 办公安防 | B37: 智能安防 | C37: =_xlfn.XLOOKUP(F37,'6月产品包'!B:B,'6月产品包'!H:H) -> 密码锁 | D37: =_xlfn.XLOOKUP(F37,'6月产品包'!B:B,'6月产品包'!O:O) -> R4A房间门锁单锁舌五功能带APP | E37: 3B-R4A房间门锁单锁舌五功能带APP | F37: T4CC2530877 | G37: 利润款 | H37: ZQ | I37: =_xlfn.XLOOKUP($F37,'6月库存'!A:A,'6月库存'!B:B) -> 正常销售 | K37: =_xlfn.XLOOKUP(E37,'[1]6月分配 '!$B:$B,'[1]6月分配 '!$K:$K) -> #N/A | L37: =IF(ISNUMBER(K37),"是",IF(ISNA(K37),"否","")) -> 否 | M37: =_xlfn.XLOOKUP(F37,'6月产品包'!B:B,'6月产品包'!J:J) -> 2025-10-30 | N37: =IF(DATEDIF(M37,TODAY(),"m")<6,"新品","老品") -> 老品 | O37: =_xlfn.XLOOKUP(F37,'6月库存'!A:A,'6月库存'!R:R) -> 1 | P37: =_xlfn.XLOOKUP(F37,'6月产品包'!B:B,'6月产品包'!S:S) -> 1631 | R37: =_xlfn.XLOOKUP(F37,'6月产品包'!B:B,'6月产品包'!AD:AD) -> 79.663 | S37: 169 | T37: =ROUND(S37*(1+0.25),0) -> 211 | U37: =$T37*(1-0.2) -> 168.8 | V37: 0.2 | W37: =(U37-R37)/U37 -> 0.5280628 | X37: =(U37*(1-Y37-Z37-AA37-AC37-AB37)-R37)/(U37*(1-Y37-Z37-AA37-AC37-AB37)) -> 0.35773463 | Y37: 0.038 | Z37: 0.115 | AA37: 0.049 | AB37: =$AB$1/U37 -> 0.0031990521 | AC37: 0.06 | AF37: 不进 | AG37: =MAX(AH37:AN37) -> 6 | AH37: =IF(U37>=50,MIN(MIN(U37*0.2,20)*0.3,6),0) -> 6 | AI37: =IF(U37>=200,MIN(MIN(U37*0.18,70)*0.3,21),0) -> 0 | AJ37: =IF(U37>=380,MIN(MIN(U37*0.28,350)*0.3,105),0) -> 0 | AK37: =IF(U37>=380,MIN(MIN(U37*0.25,350)*0.3,105),0) -> 0 | AL37: =IF(U37>=380,MIN(MIN(U37*0.22,300)*0.3,90),0) -> 0 | AM37: =IF(U37>=250,MIN(MIN(U37*0.18,120)*0.3,36),0) -> 0 | AN37: =IF(U37>=180,MIN(MIN(U37*0.15,60)*0.3,18),0) -> 0
A38: 3C数码 | B38: 电脑周边 | C38: =_xlfn.XLOOKUP(F38,'6月产品包'!B:B,'6月产品包'!H:H) -> 电脑机箱 | D38: =_xlfn.XLOOKUP(F38,'6月产品包'!B:B,'6月产品包'!O:O) -> 电脑机箱T6款 | E38: 3C-电脑机箱T6款白色 | F38: T4CC2351007 | G38: 平销款 | H38: ZQ | I38: =_xlfn.XLOOKUP($F38,'6月库存'!A:A,'6月库存'!B:B) -> 正常销售 | K38: =_xlfn.XLOOKUP(E38,'[1]6月分配 '!$B:$B,'[1]6月分配 '!$K:$K) -> #N/A | L38: =IF(ISNUMBER(K38),"是",IF(ISNA(K38),"否","")) -> 否 | M38: =_xlfn.XLOOKUP(F38,'6月产品包'!B:B,'6月产品包'!J:J) -> 2025-12-23 | N38: =IF(DATEDIF(M38,TODAY(),"m")<6,"新品","老品") -> 新品 | O38: =_xlfn.XLOOKUP(F38,'6月库存'!A:A,'6月库存'!R:R) -> 5 | P38: =_xlfn.XLOOKUP(F38,'6月产品包'!B:B,'6月产品包'!S:S) -> 5250 | R38: =_xlfn.XLOOKUP(F38,'6月产品包'!B:B,'6月产品包'!AD:AD) -> 91.8836 | S38: 178 | T38: =ROUND(S38*(1+0.25),0) -> 223 | U38: =$T38*(1-0.2) -> 178.4 | V38: 0.2 | W38: =(U38-R38)/U38 -> 0.4849574 | X38: =(U38*(1-Y38-Z38-AA38-AC38-AB38)-R38)/(U38*(1-Y38-Z38-AA38-AC38-AB38)) -> 0.32406721 | Y38: 0.04 | Z38: 0.086 | AA38: 0.049 | AB38: =$AB$1/U38 -> 0.0030269058 | AC38: 0.06 | AF38: 不进 | AG38: =MAX(AH38:AN38) -> 6 | AH38: =IF(U38>=50,MIN(MIN(U38*0.2,20)*0.3,6),0) -> 6 | AI38: =IF(U38>=200,MIN(MIN(U38*0.18,70)*0.3,21),0) -> 0 | AJ38: =IF(U38>=380,MIN(MIN(U38*0.28,350)*0.3,105),0) -> 0 | AK38: =IF(U38>=380,MIN(MIN(U38*0.25,350)*0.3,105),0) -> 0 | AL38: =IF(U38>=380,MIN(MIN(U38*0.22,300)*0.3,90),0) -> 0 | AM38: =IF(U38>=250,MIN(MIN(U38*0.18,120)*0.3,36),0) -> 0 | AN38: =IF(U38>=180,MIN(MIN(U38*0.15,60)*0.3,18),0) -> 0
A39: 办公安防 | B39: 安防存储 | C39: =_xlfn.XLOOKUP(F39,'6月产品包'!B:B,'6月产品包'!H:H) -> 保险箱 | D39: =_xlfn.XLOOKUP(F39,'6月产品包'!B:B,'6月产品包'!O:O) -> 液晶面板保险柜密码A15款 | E39: 3B-液晶面板保险柜密码A15款 | F39: T4CC2610898 | G39: 利润款 | H39: MD | I39: =_xlfn.XLOOKUP($F39,'6月库存'!A:A,'6月库存'!B:B) -> 正常销售 | K39: =_xlfn.XLOOKUP(E39,'[1]6月分配 '!$B:$B,'[1]6月分配 '!$K:$K) -> 29786 | L39: =IF(ISNUMBER(K39),"是",IF(ISNA(K39),"否","")) -> 是 | M39: =_xlfn.XLOOKUP(F39,'6月产品包'!B:B,'6月产品包'!J:J) -> 2025-10-27 | N39: =IF(DATEDIF(M39,TODAY(),"m")<6,"新品","老品") -> 老品 | O39: =_xlfn.XLOOKUP(F39,'6月库存'!A:A,'6月库存'!R:R) -> 204 | P39: =_xlfn.XLOOKUP(F39,'6月产品包'!B:B,'6月产品包'!S:S) -> 15000 | R39: =_xlfn.XLOOKUP(F39,'6月产品包'!B:B,'6月产品包'!AD:AD) -> 134.9718 | S39: 290 | T39: =ROUND(S39*(1+0.25),0) -> 363 | U39: =$T39*(1-0.2) -> 290.4 | V39: 0.2 | W39: =(U39-R39)/U39 -> 0.53522107 | X39: =(U39*(1-Y39-Z39-AA39-AC39-AB39)-R39)/(U39*(1-Y39-Z39-AA39-AC39-AB39)) -> 0.3812357 | Y39: 0.038 | Z39: 0.1 | AA39: 0.049 | AB39: =$AB$1/U39 -> 0.0018595041 | AC39: 0.06 | AF39: 原价进 | AG39: =MAX(AH39:AN39) -> 15.6816 | AH39: =IF(U39>=50,MIN(MIN(U39*0.2,20)*0.3,6),0) -> 6 | AI39: =IF(U39>=200,MIN(MIN(U39*0.18,70)*0.3,21),0) -> 15.6816 | AJ39: =IF(U39>=380,MIN(MIN(U39*0.28,350)*0.3,105),0) -> 0 | AK39: =IF(U39>=380,MIN(MIN(U39*0.25,350)*0.3,105),0) -> 0 | AL39: =IF(U39>=380,MIN(MIN(U39*0.22,300)*0.3,90),0) -> 0 | AM39: =IF(U39>=250,MIN(MIN(U39*0.18,120)*0.3,36),0) -> 15.6816 | AN39: =IF(U39>=180,MIN(MIN(U39*0.15,60)*0.3,18),0) -> 13.068
A40: 办公安防 | B40: 安防存储 | C40: =_xlfn.XLOOKUP(F40,'6月产品包'!B:B,'6月产品包'!H:H) -> 保险柜 | D40: =_xlfn.XLOOKUP(F40,'6月产品包'!B:B,'6月产品包'!O:O) -> XT保险箱指纹款 | E40: 3B-XT保险箱45*38*32cm灰白色指纹款 | F40: T4CC2610980 | G40: 利润款 | H40: ZQ | I40: =_xlfn.XLOOKUP($F40,'6月库存'!A:A,'6月库存'!B:B) -> 正常销售 | K40: =_xlfn.XLOOKUP(E40,'[1]6月分配 '!$B:$B,'[1]6月分配 '!$K:$K) -> 28704 | L40: =IF(ISNUMBER(K40),"是",IF(ISNA(K40),"否","")) -> 是 | M40: =_xlfn.XLOOKUP(F40,'6月产品包'!B:B,'6月产品包'!J:J) -> 2025-12-02 | N40: =IF(DATEDIF(M40,TODAY(),"m")<6,"新品","老品") -> 老品 | O40: =_xlfn.XLOOKUP(F40,'6月库存'!A:A,'6月库存'!R:R) -> 81 | P40: =_xlfn.XLOOKUP(F40,'6月产品包'!B:B,'6月产品包'!S:S) -> 15000 | R40: =_xlfn.XLOOKUP(F40,'6月产品包'!B:B,'6月产品包'!AD:AD) -> 193.5866 | S40: 399 | T40: =ROUND(S40*(1+0.25),0) -> 499 | U40: =$T40*(1-0.2) -> 399.2 | V40: 0.2 | W40: =(U40-R40)/U40 -> 0.51506363 | X40: =(U40*(1-Y40-Z40-AA40-AC40-AB40)-R40)/(U40*(1-Y40-Z40-AA40-AC40-AB40)) -> 0.36330586 | Y40: 0.038 | Z40: 0.09 | AA40: 0.049 | AB40: =$AB$1/U40 -> 0.0013527054 | AC40: 0.06 | AF40: 原价进 | AG40: =MAX(AH40:AN40) -> 33.5328 | AH40: =IF(U40>=50,MIN(MIN(U40*0.2,20)*0.3,6),0) -> 6 | AI40: =IF(U40>=200,MIN(MIN(U40*0.18,70)*0.3,21),0) -> 21 | AJ40: =IF(U40>=380,MIN(MIN(U40*0.28,350)*0.3,105),0) -> 33.5328 | AK40: =IF(U40>=380,MIN(MIN(U40*0.25,350)*0.3,105),0) -> 29.94 | AL40: =IF(U40>=380,MIN(MIN(U40*0.22,300)*0.3,90),0) -> 26.3472 | AM40: =IF(U40>=250,MIN(MIN(U40*0.18,120)*0.3,36),0) -> 21.5568 | AN40: =IF(U40>=180,MIN(MIN(U40*0.15,60)*0.3,18),0) -> 17.964
A41: 办公安防 | B41: 智能安防 | C41: =_xlfn.XLOOKUP(F41,'6月产品包'!B:B,'6月产品包'!H:H) -> 路由器 | D41: =_xlfn.XLOOKUP(F41,'6月产品包'!B:B,'6月产品包'!O:O) -> 300C路由器 | E41: 3B-300CWiFi路由器 | F41: M3CC2210177 | G41: #N/A | H41: MD | I41: =_xlfn.XLOOKUP($F41,'6月库存'!A:A,'6月库存'!B:B) -> 商品清仓 | K41: =_xlfn.XLOOKUP(E41,'[1]6月分配 '!$B:$B,'[1]6月分配 '!$K:$K) -> 25977 | L41: =IF(ISNUMBER(K41),"是",IF(ISNA(K41),"否","")) -> 是 | M41: =_xlfn.XLOOKUP(F41,'6月产品包'!B:B,'6月产品包'!J:J) -> 2024-12-26 | N41: =IF(DATEDIF(M41,TODAY(),"m")<6,"新品","老品") -> 老品 | O41: =_xlfn.XLOOKUP(F41,'6月库存'!A:A,'6月库存'!R:R) -> 136 | P41: =_xlfn.XLOOKUP(F41,'6月产品包'!B:B,'6月产品包'!S:S) -> 625 | R41: =_xlfn.XLOOKUP(F41,'6月产品包'!B:B,'6月产品包'!AD:AD) -> 73.8572 | S41: 153 | T41: =ROUND(S41*(1+0.25),0) -> 191 | U41: =$T41*(1-0.2) -> 152.8 | V41: 0.2 | W41: =(U41-R41)/U41 -> 0.51664136 | X41: =(U41*(1-Y41-Z41-AA41-AC41-AB41)-R41)/(U41*(1-Y41-Z41-AA41-AC41-AB41)) -> 0.35073105 | Y41: 0.038 | Z41: 0.105 | AA41: 0.049 | AB41: =$AB$1/U41 -> 0.0035340314 | AC41: 0.06 | AF41: 不进 | AG41: =MAX(AH41:AN41) -> 6 | AH41: =IF(U41>=50,MIN(MIN(U41*0.2,20)*0.3,6),0) -> 6 | AI41: =IF(U41>=200,MIN(MIN(U41*0.18,70)*0.3,21),0) -> 0 | AJ41: =IF(U41>=380,MIN(MIN(U41*0.28,350)*0.3,105),0) -> 0 | AK41: =IF(U41>=380,MIN(MIN(U41*0.25,350)*0.3,105),0) -> 0 | AL41: =IF(U41>=380,MIN(MIN(U41*0.22,300)*0.3,90),0) -> 0 | AM41: =IF(U41>=250,MIN(MIN(U41*0.18,120)*0.3,36),0) -> 0 | AN41: =IF(U41>=180,MIN(MIN(U41*0.15,60)*0.3,18),0) -> 0
A42: 3C数码 | B42: 电脑周边 | C42: =_xlfn.XLOOKUP(F42,'6月产品包'!B:B,'6月产品包'!H:H) -> 电脑机箱 | D42: =_xlfn.XLOOKUP(F42,'6月产品包'!B:B,'6月产品包'!O:O) -> 电脑机箱T6款 | E42: 3C-电脑机箱T6款黑色 | F42: T4CC2351006 | G42: 平销款 | H42: ZQ | I42: =_xlfn.XLOOKUP($F42,'6月库存'!A:A,'6月库存'!B:B) -> 正常销售 | K42: =_xlfn.XLOOKUP(E42,'[1]6月分配 '!$B:$B,'[1]6月分配 '!$K:$K) -> #N/A | L42: =IF(ISNUMBER(K42),"是",IF(ISNA(K42),"否","")) -> 否 | M42: =_xlfn.XLOOKUP(F42,'6月产品包'!B:B,'6月产品包'!J:J) -> 2025-12-23 | N42: =IF(DATEDIF(M42,TODAY(),"m")<6,"新品","老品") -> 新品 | O42: =_xlfn.XLOOKUP(F42,'6月库存'!A:A,'6月库存'!R:R) -> 5 | P42: =_xlfn.XLOOKUP(F42,'6月产品包'!B:B,'6月产品包'!S:S) -> 5250 | R42: =_xlfn.XLOOKUP(F42,'6月产品包'!B:B,'6月产品包'!AD:AD) -> 87.8004 | S42: 158 | T42: =ROUND(S42*(1+0.25),0) -> 198 | U42: =$T42*(1-0.2) -> 158.4 | V42: 0.2 | W42: =(U42-R42)/U42 -> 0.44570455 | X42: =(U42*(1-Y42-Z42-AA42-AC42-AB42)-R42)/(U42*(1-Y42-Z42-AA42-AC42-AB42)) -> 0.27218741 | Y42: 0.04 | Z42: 0.086 | AA42: 0.049 | AB42: =$AB$1/U42 -> 0.0034090909 | AC42: 0.06 | AF42: 不进 | AG42: =MAX(AH42:AN42) -> 6 | AH42: =IF(U42>=50,MIN(MIN(U42*0.2,20)*0.3,6),0) -> 6 | AI42: =IF(U42>=200,MIN(MIN(U42*0.18,70)*0.3,21),0) -> 0 | AJ42: =IF(U42>=380,MIN(MIN(U42*0.28,350)*0.3,105),0) -> 0 | AK42: =IF(U42>=380,MIN(MIN(U42*0.25,350)*0.3,105),0) -> 0 | AL42: =IF(U42>=380,MIN(MIN(U42*0.22,300)*0.3,90),0) -> 0 | AM42: =IF(U42>=250,MIN(MIN(U42*0.18,120)*0.3,36),0) -> 0 | AN42: =IF(U42>=180,MIN(MIN(U42*0.15,60)*0.3,18),0) -> 0
A43: 3C数码 | B43: 音响乐器 | C43: =_xlfn.XLOOKUP(F43,'6月产品包'!B:B,'6月产品包'!H:H) -> 电子琴 | D43: =_xlfn.XLOOKUP(F43,'6月产品包'!B:B,'6月产品包'!O:O) -> 电子琴 | E43: 3C-电子琴61健黑色 | F43: T3CC1920634 | G43: 引流款 | H43: ZQ | I43: =_xlfn.XLOOKUP($F43,'6月库存'!A:A,'6月库存'!B:B) -> 正常销售 | K43: =_xlfn.XLOOKUP(E43,'[1]6月分配 '!$B:$B,'[1]6月分配 '!$K:$K) -> 24546 | L43: =IF(ISNUMBER(K43),"是",IF(ISNA(K43),"否","")) -> 是 | M43: =_xlfn.XLOOKUP(F43,'6月产品包'!B:B,'6月产品包'!J:J) -> 2024-03-19 | N43: 老品 | O43: =_xlfn.XLOOKUP(F43,'6月库存'!A:A,'6月库存'!R:R) -> 794 | P43: =_xlfn.XLOOKUP(F43,'6月产品包'!B:B,'6月产品包'!S:S) -> 707 | R43: =_xlfn.XLOOKUP(F43,'6月产品包'!B:B,'6月产品包'!AD:AD) -> 23.1884 | S43: 42 | T43: =ROUND(S43*(1+0.25),0) -> 53 | U43: =$T43*(1-0.2) -> 42.4 | V43: 0.2 | W43: =(U43-R43)/U43 -> 0.45310377 | X43: =(U43*(1-Y43-Z43-AA43-AC43-AB43)-R43)/(U43*(1-Y43-Z43-AA43-AC43-AB43)) -> 0.25416206 | Y43: 0.04 | Z43: 0.105 | AA43: 0.049 | AB43: =$AB$1/U43 -> 0.012735849 | AC43: 0.06 | AF43: 原价进 | AG43: =MAX(AH43:AN43) -> 0 | AH43: =IF(U43>=50,MIN(MIN(U43*0.2,20)*0.3,6),0) -> 0 | AI43: =IF(U43>=200,MIN(MIN(U43*0.18,70)*0.3,21),0) -> 0 | AJ43: =IF(U43>=380,MIN(MIN(U43*0.28,350)*0.3,105),0) -> 0 | AK43: =IF(U43>=380,MIN(MIN(U43*0.25,350)*0.3,105),0) -> 0 | AL43: =IF(U43>=380,MIN(MIN(U43*0.22,300)*0.3,90),0) -> 0 | AM43: =IF(U43>=250,MIN(MIN(U43*0.18,120)*0.3,36),0) -> 0 | AN43: =IF(U43>=180,MIN(MIN(U43*0.15,60)*0.3,18),0) -> 0
A44: =_xlfn.XLOOKUP(F44,'6月产品包'!B:B,'6月产品包'!F:F) -> 3C数码 | B44: =_xlfn.XLOOKUP(F44,'6月产品包'!B:B,'6月产品包'!G:G) -> 电视设备 | C44: =_xlfn.XLOOKUP(F44,'6月产品包'!B:B,'6月产品包'!H:H) -> 电视支架 | D44: =_xlfn.XLOOKUP(F44,'6月产品包'!B:B,'6月产品包'!O:O) -> 电视移动推车支架TG11 | E44: =_xlfn.XLOOKUP(F44,'6月产品包'!B:B,'6月产品包'!C:C) -> 3C-电视移动推车支架TG11 | F44: T5CC1121046 | G44: 利润款 | H44: ZQ | I44: =_xlfn.XLOOKUP($F44,'6月库存'!A:A,'6月库存'!B:B) -> 正常销售 | K44: =_xlfn.XLOOKUP(E44,'[1]6月分配 '!$B:$B,'[1]6月分配 '!$K:$K) -> 24393 | L44: =IF(ISNUMBER(K44),"是",IF(ISNA(K44),"否","")) -> 是 | M44: =_xlfn.XLOOKUP(F44,'6月产品包'!B:B,'6月产品包'!J:J) -> 2026-02-05 | N44: 新品 | O44: =_xlfn.XLOOKUP(F44,'6月库存'!A:A,'6月库存'!R:R) -> 116 | P44: =_xlfn.XLOOKUP(F44,'6月产品包'!B:B,'6月产品包'!S:S) -> 8675 | R44: =_xlfn.XLOOKUP(F44,'6月产品包'!B:B,'6月产品包'!AD:AD) -> 87.0638 | S44: 165 | T44: =ROUND(S44*(1+0.25),0) -> 206 | U44: =$T44*(1-0.2) -> 164.8 | V44: 0.2 | W44: =(U44-R44)/U44 -> 0.47170024 | X44: =(U44*(1-Y44-Z44-AA44-AC44-AB44)-R44)/(U44*(1-Y44-Z44-AA44-AC44-AB44)) -> 0.30461557 | Y44: 0.038 | Z44: 0.09 | AA44: 0.049 | AB44: =$AB$1/U44 -> 0.003276699 | AC44: 0.06 | AF44: 原价进 | AG44: =MAX(AH44:AN44) -> 6 | AH44: =IF(U44>=50,MIN(MIN(U44*0.2,20)*0.3,6),0) -> 6 | AI44: =IF(U44>=200,MIN(MIN(U44*0.18,70)*0.3,21),0) -> 0 | AJ44: =IF(U44>=380,MIN(MIN(U44*0.28,350)*0.3,105),0) -> 0 | AK44: =IF(U44>=380,MIN(MIN(U44*0.25,350)*0.3,105),0) -> 0 | AL44: =IF(U44>=380,MIN(MIN(U44*0.22,300)*0.3,90),0) -> 0 | AM44: =IF(U44>=250,MIN(MIN(U44*0.18,120)*0.3,36),0) -> 0 | AN44: =IF(U44>=180,MIN(MIN(U44*0.15,60)*0.3,18),0) -> 0
A45: 办公安防 | B45: 教学周边 | C45: =_xlfn.XLOOKUP(F45,'6月产品包'!B:B,'6月产品包'!H:H) -> 白板 | D45: =_xlfn.XLOOKUP(F45,'6月产品包'!B:B,'6月产品包'!O:O) -> 磁吸白板密度板夹层 | E45: 3B-磁吸白板密度板夹层90cm*150cm | F45: T4CC2340906 | G45: 利润款 | H45: ZQ | I45: =_xlfn.XLOOKUP($F45,'6月库存'!A:A,'6月库存'!B:B) -> 正常销售 | K45: =_xlfn.XLOOKUP(E45,'[1]6月分配 '!$B:$B,'[1]6月分配 '!$K:$K) -> 23542 | L45: =IF(ISNUMBER(K45),"是",IF(ISNA(K45),"否","")) -> 是 | M45: =_xlfn.XLOOKUP(F45,'6月产品包'!B:B,'6月产品包'!J:J) -> 2025-10-27 | N45: 新品 | O45: =_xlfn.XLOOKUP(F45,'6月库存'!A:A,'6月库存'!R:R) -> 495 | P45: =_xlfn.XLOOKUP(F45,'6月产品包'!B:B,'6月产品包'!S:S) -> 8320 | R45: =_xlfn.XLOOKUP(F45,'6月产品包'!B:B,'6月产品包'!AD:AD) -> 50.8544 | S45: 105 | T45: =ROUND(S45*(1+0.25),0) -> 131 | U45: =$T45*(1-0.2) -> 104.8 | V45: 0.2 | W45: =(U45-R45)/U45 -> 0.51474809 | X45: =(U45*(1-Y45-Z45-AA45-AC45-AB45)-R45)/(U45*(1-Y45-Z45-AA45-AC45-AB45)) -> 0.33146835 | Y45: 0.04 | Z45: 0.1 | AA45: 0.049 | AB45: =$AB$1/U45 -> 0.0051526718 | AC45: 0.08 | AD45: 0.05 | AE45: 0.05 | AF45: 原价进 | AG45: =MAX(AH45:AN45) -> 6 | AH45: =IF(U45>=50,MIN(MIN(U45*0.2,20)*0.3,6),0) -> 6 | AI45: =IF(U45>=200,MIN(MIN(U45*0.18,70)*0.3,21),0) -> 0 | AJ45: =IF(U45>=380,MIN(MIN(U45*0.28,350)*0.3,105),0) -> 0 | AK45: =IF(U45>=380,MIN(MIN(U45*0.25,350)*0.3,105),0) -> 0 | AL45: =IF(U45>=380,MIN(MIN(U45*0.22,300)*0.3,90),0) -> 0 | AM45: =IF(U45>=250,MIN(MIN(U45*0.18,120)*0.3,36),0) -> 0 | AN45: =IF(U45>=180,MIN(MIN(U45*0.15,60)*0.3,18),0) -> 0
A46: =_xlfn.XLOOKUP(F46,'6月产品包'!B:B,'6月产品包'!F:F) -> 办公安防 | B46: =_xlfn.XLOOKUP(F46,'6月产品包'!B:B,'6月产品包'!G:G) -> 教学周边 | C46: =_xlfn.XLOOKUP(F46,'6月产品包'!B:B,'6月产品包'!H:H) -> 白板 | D46: =_xlfn.XLOOKUP(F46,'6月产品包'!B:B,'6月产品包'!O:O) -> 磁吸白板密度板夹层 | E46: =_xlfn.XLOOKUP(F46,'6月产品包'!B:B,'6月产品包'!C:C) -> 3B-磁吸白板密度板夹层90cm*150cm | F46: T5CC2830906 | G46: 利润款 | H46: ZQ | I46: =_xlfn.XLOOKUP($F46,'6月库存'!A:A,'6月库存'!B:B) -> 等待开发 | K46: =_xlfn.XLOOKUP(E46,'[1]6月分配 '!$B:$B,'[1]6月分配 '!$K:$K) -> 23542 | L46: =IF(ISNUMBER(K46),"是",IF(ISNA(K46),"否","")) -> 是 | M46: =_xlfn.XLOOKUP(F46,'6月产品包'!B:B,'6月产品包'!J:J) -> 2026-04-16 | N46: 新品 | O46: =_xlfn.XLOOKUP(F46,'6月库存'!A:A,'6月库存'!R:R) -> 0 | P46: =_xlfn.XLOOKUP(F46,'6月产品包'!B:B,'6月产品包'!S:S) -> 8320 | R46: =_xlfn.XLOOKUP(F46,'6月产品包'!B:B,'6月产品包'!AD:AD) -> 49.2072 | S46: 105 | T46: =ROUND(S46*(1+0.25),0) -> 131 | U46: =$T46*(1-0.2) -> 104.8 | V46: 0.2 | W46: =(U46-R46)/U46 -> 0.53046565 | X46: =(U46*(1-Y46-Z46-AA46-AC46-AB46)-R46)/(U46*(1-Y46-Z46-AA46-AC46-AB46)) -> 0.35312244 | Y46: 0.04 | Z46: 0.1 | AA46: 0.049 | AB46: =$AB$1/U46 -> 0.0051526718 | AC46: 0.08 | AD46: 0.05 | AE46: 0.05 | AF46: 原价进 | AG46: =MAX(AH46:AN46) -> 6 | AH46: =IF(U46>=50,MIN(MIN(U46*0.2,20)*0.3,6),0) -> 6 | AI46: =IF(U46>=200,MIN(MIN(U46*0.18,70)*0.3,21),0) -> 0 | AJ46: =IF(U46>=380,MIN(MIN(U46*0.28,350)*0.3,105),0) -> 0 | AK46: =IF(U46>=380,MIN(MIN(U46*0.25,350)*0.3,105),0) -> 0 | AL46: =IF(U46>=380,MIN(MIN(U46*0.22,300)*0.3,90),0) -> 0 | AM46: =IF(U46>=250,MIN(MIN(U46*0.18,120)*0.3,36),0) -> 0 | AN46: =IF(U46>=180,MIN(MIN(U46*0.15,60)*0.3,18),0) -> 0
A47: 办公安防 | B47: 办公周边 | C47: =_xlfn.XLOOKUP(F47,'6月产品包'!B:B,'6月产品包'!H:H) -> 银钱盒 | D47: =_xlfn.XLOOKUP(F47,'6月产品包'!B:B,'6月产品包'!O:O) -> 迷你收银箱 | E47: 3B-仿真书银钱盒钥匙款蓝色 | F47: T3CC1220672 | G47: 平销款 | H47: ZQ | I47: =_xlfn.XLOOKUP($F47,'6月库存'!A:A,'6月库存'!B:B) -> 商品清仓 | K47: =_xlfn.XLOOKUP(E47,'[1]6月分配 '!$B:$B,'[1]6月分配 '!$K:$K) -> 22237 | L47: =IF(ISNUMBER(K47),"是",IF(ISNA(K47),"否","")) -> 是 | M47: =_xlfn.XLOOKUP(F47,'6月产品包'!B:B,'6月产品包'!J:J) -> 2024-05-23 | N47: 老品 | O47: =_xlfn.XLOOKUP(F47,'6月库存'!A:A,'6月库存'!R:R) -> 1251 | P47: =_xlfn.XLOOKUP(F47,'6月产品包'!B:B,'6月产品包'!S:S) -> 800 | R47: =_xlfn.XLOOKUP(F47,'6月产品包'!B:B,'6月产品包'!AD:AD) -> 10.9214 | S47: 22 | T47: =ROUND(S47*(1+0.25),0) -> 28 | U47: =$T47*(1-0.2) -> 22.4 | V47: 0.2 | W47: =(U47-R47)/U47 -> 0.5124375 | X47: =(U47*(1-Y47-Z47-AA47-AC47-AB47)-R47)/(U47*(1-Y47-Z47-AA47-AC47-AB47)) -> 0.32925122 | Y47: 0.04 | Z47: 0.1 | AA47: 0.049 | AB47: =$AB$1/U47 -> 0.024107143 | AC47: 0.06 | AF47: 原价进 | AG47: =MAX(AH47:AN47) -> 0 | AH47: =IF(U47>=50,MIN(MIN(U47*0.2,20)*0.3,6),0) -> 0 | AI47: =IF(U47>=200,MIN(MIN(U47*0.18,70)*0.3,21),0) -> 0 | AJ47: =IF(U47>=380,MIN(MIN(U47*0.28,350)*0.3,105),0) -> 0 | AK47: =IF(U47>=380,MIN(MIN(U47*0.25,350)*0.3,105),0) -> 0 | AL47: =IF(U47>=380,MIN(MIN(U47*0.22,300)*0.3,90),0) -> 0 | AM47: =IF(U47>=250,MIN(MIN(U47*0.18,120)*0.3,36),0) -> 0 | AN47: =IF(U47>=180,MIN(MIN(U47*0.15,60)*0.3,18),0) -> 0
A48: 办公安防 | B48: 智能安防 | C48: =_xlfn.XLOOKUP(F48,'6月产品包'!B:B,'6月产品包'!H:H) -> 摄像头 | D48: =_xlfn.XLOOKUP(F48,'6月产品包'!B:B,'6月产品包'!O:O) -> 户外摄像头 | E48: 3B-双目灯泡摄像头 | F48: T3CC1950642 | G48: 灭款 | H48: MD | I48: =_xlfn.XLOOKUP($F48,'6月库存'!A:A,'6月库存'!B:B) -> 商品清仓 | K48: =_xlfn.XLOOKUP(E48,'[1]6月分配 '!$B:$B,'[1]6月分配 '!$K:$K) -> #N/A | L48: =IF(ISNUMBER(K48),"是",IF(ISNA(K48),"否","")) -> 否 | M48: =_xlfn.XLOOKUP(F48,'6月产品包'!B:B,'6月产品包'!J:J) -> 2024-03-26 | N48: =IF(DATEDIF(M48,TODAY(),"m")<6,"新品","老品") -> 老品 | O48: =_xlfn.XLOOKUP(F48,'6月库存'!A:A,'6月库存'!R:R) -> 3 | P48: =_xlfn.XLOOKUP(F48,'6月产品包'!B:B,'6月产品包'!S:S) -> 250 | R48: =_xlfn.XLOOKUP(F48,'6月产品包'!B:B,'6月产品包'!AD:AD) -> 28.5244 | S48: 49 | T48: =ROUND(S48*(1+0.25),0) -> 61 | U48: =$T48*(1-0.2) -> 48.8 | V48: 0.2 | W48: =(U48-R48)/U48 -> 0.41548361 | X48: =(U48*(1-Y48-Z48-AA48-AC48-AB48)-R48)/(U48*(1-Y48-Z48-AA48-AC48-AB48)) -> 0.25722351 | Y48: 0.038 | Z48: 0.105 | AA48: 0.049 | AB48: =$AB$1/U48 -> 0.011065574 | AC48: 0.01 | AF48: 不进 | AG48: =MAX(AH48:AN48) -> 0 | AH48: =IF(U48>=50,MIN(MIN(U48*0.2,20)*0.3,6),0) -> 0 | AI48: =IF(U48>=200,MIN(MIN(U48*0.18,70)*0.3,21),0) -> 0 | AJ48: =IF(U48>=380,MIN(MIN(U48*0.28,350)*0.3,105),0) -> 0 | AK48: =IF(U48>=380,MIN(MIN(U48*0.25,350)*0.3,105),0) -> 0 | AL48: =IF(U48>=380,MIN(MIN(U48*0.22,300)*0.3,90),0) -> 0 | AM48: =IF(U48>=250,MIN(MIN(U48*0.18,120)*0.3,36),0) -> 0 | AN48: =IF(U48>=180,MIN(MIN(U48*0.15,60)*0.3,18),0) -> 0
A49: 办公安防 | B49: 办公周边 | C49: =_xlfn.XLOOKUP(F49,'6月产品包'!B:B,'6月产品包'!H:H) -> 扫码枪 | D49: =_xlfn.XLOOKUP(F49,'6月产品包'!B:B,'6月产品包'!O:O) -> 一维扫描枪 | E49: 3B-手持一维无线影像扫描枪 | F49: T3CC2040171 | G49: #N/A | H49: MD | I49: =_xlfn.XLOOKUP($F49,'6月库存'!A:A,'6月库存'!B:B) -> 商品清仓 | K49: =_xlfn.XLOOKUP(E49,'[1]6月分配 '!$B:$B,'[1]6月分配 '!$K:$K) -> #N/A | L49: =IF(ISNUMBER(K49),"是",IF(ISNA(K49),"否","")) -> 否 | M49: =_xlfn.XLOOKUP(F49,'6月产品包'!B:B,'6月产品包'!J:J) -> 2024-08-13 | N49: =IF(DATEDIF(M49,TODAY(),"m")<6,"新品","老品") -> 老品 | O49: =_xlfn.XLOOKUP(F49,'6月库存'!A:A,'6月库存'!R:R) -> 45 | P49: =_xlfn.XLOOKUP(F49,'6月产品包'!B:B,'6月产品包'!S:S) -> 260 | R49: =_xlfn.XLOOKUP(F49,'6月产品包'!B:B,'6月产品包'!AD:AD) -> 33.5762 | S49: 62 | T49: =ROUND(S49*(1+0.25),0) -> 78 | U49: =$T49*(1-0.2) -> 62.4 | V49: 0.2 | W49: =(U49-R49)/U49 -> 0.46191987 | X49: =(U49*(1-Y49-Z49-AA49-AC49-AB49)-R49)/(U49*(1-Y49-Z49-AA49-AC49-AB49)) -> 0.30511681 | Y49: 0.038 | Z49: 0.1 | AA49: 0.049 | AB49: =$AB$1/U49 -> 0.0086538462 | AC49: 0.03 | AF49: 不进 | AG49: =MAX(AH49:AN49) -> 3.744 | AH49: =IF(U49>=50,MIN(MIN(U49*0.2,20)*0.3,6),0) -> 3.744 | AI49: =IF(U49>=200,MIN(MIN(U49*0.18,70)*0.3,21),0) -> 0 | AJ49: =IF(U49>=380,MIN(MIN(U49*0.28,350)*0.3,105),0) -> 0 | AK49: =IF(U49>=380,MIN(MIN(U49*0.25,350)*0.3,105),0) -> 0 | AL49: =IF(U49>=380,MIN(MIN(U49*0.22,300)*0.3,90),0) -> 0 | AM49: =IF(U49>=250,MIN(MIN(U49*0.18,120)*0.3,36),0) -> 0 | AN49: =IF(U49>=180,MIN(MIN(U49*0.15,60)*0.3,18),0) -> 0
A50: 办公安防 | B50: 智能安防 | C50: =_xlfn.XLOOKUP(F50,'6月产品包'!B:B,'6月产品包'!H:H) -> 指纹锁 | D50: =_xlfn.XLOOKUP(F50,'6月产品包'!B:B,'6月产品包'!O:O) -> 面板门锁 | E50: 3B-玻璃门框指纹密码锁A16 | F50: T4CC2120721 | G50: 平销款 | H50: ZQ | I50: =_xlfn.XLOOKUP($F50,'6月库存'!A:A,'6月库存'!B:B) -> 正常销售 | K50: =_xlfn.XLOOKUP(E50,'[1]6月分配 '!$B:$B,'[1]6月分配 '!$K:$K) -> #N/A | L50: =IF(ISNUMBER(K50),"是",IF(ISNA(K50),"否","")) -> 否 | M50: =_xlfn.XLOOKUP(F50,'6月产品包'!B:B,'6月产品包'!J:J) -> 2025-06-10 | N50: =IF(DATEDIF(M50,TODAY(),"m")<6,"新品","老品") -> 老品 | O50: =_xlfn.XLOOKUP(F50,'6月库存'!A:A,'6月库存'!R:R) -> 0 | P50: =_xlfn.XLOOKUP(F50,'6月产品包'!B:B,'6月产品包'!S:S) -> 1230 | R50: =_xlfn.XLOOKUP(F50,'6月产品包'!B:B,'6月产品包'!AD:AD) -> 69.7218 | S50: 133 | T50: =ROUND(S50*(1+0.25),0) -> 166 | U50: =$T50*(1-0.2) -> 132.8 | V50: 0.2 | W50: =(U50-R50)/U50 -> 0.47498645 | X50: =(U50*(1-Y50-Z50-AA50-AC50-AB50)-R50)/(U50*(1-Y50-Z50-AA50-AC50-AB50)) -> 0.2846581 | Y50: 0.038 | Z50: 0.115 | AA50: 0.049 | AB50: =$AB$1/U50 -> 0.0040662651 | AC50: 0.06 | AF50: 不进 | AG50: =MAX(AH50:AN50) -> 6 | AH50: =IF(U50>=50,MIN(MIN(U50*0.2,20)*0.3,6),0) -> 6 | AI50: =IF(U50>=200,MIN(MIN(U50*0.18,70)*0.3,21),0) -> 0 | AJ50: =IF(U50>=380,MIN(MIN(U50*0.28,350)*0.3,105),0) -> 0 | AK50: =IF(U50>=380,MIN(MIN(U50*0.25,350)*0.3,105),0) -> 0 | AL50: =IF(U50>=380,MIN(MIN(U50*0.22,300)*0.3,90),0) -> 0 | AM50: =IF(U50>=250,MIN(MIN(U50*0.18,120)*0.3,36),0) -> 0 | AN50: =IF(U50>=180,MIN(MIN(U50*0.15,60)*0.3,18),0) -> 0
A51: 办公安防 | B51: 智能安防 | C51: =_xlfn.XLOOKUP(F51,'6月产品包'!B:B,'6月产品包'!H:H) -> 密码盒 | D51: =_xlfn.XLOOKUP(F51,'6月产品包'!B:B,'6月产品包'!O:O) -> 密码盒 | E51: 3B-全塑料密码盒 | F51: T3CC2100264 | G51: 引流款 | H51: ZQ | I51: =_xlfn.XLOOKUP($F51,'6月库存'!A:A,'6月库存'!B:B) -> 商品清仓 | K51: =_xlfn.XLOOKUP(E51,'[1]6月分配 '!$B:$B,'[1]6月分配 '!$K:$K) -> #N/A | L51: =IF(ISNUMBER(K51),"是",IF(ISNA(K51),"否","")) -> 否 | M51: =_xlfn.XLOOKUP(F51,'6月产品包'!B:B,'6月产品包'!J:J) -> 2024-10-29 | N51: =IF(DATEDIF(M51,TODAY(),"m")<6,"新品","老品") -> 老品 | O51: =_xlfn.XLOOKUP(F51,'6月库存'!A:A,'6月库存'!R:R) -> 120 | P51: =_xlfn.XLOOKUP(F51,'6月产品包'!B:B,'6月产品包'!S:S) -> 153 | R51: =_xlfn.XLOOKUP(F51,'6月产品包'!B:B,'6月产品包'!AD:AD) -> 5.5216 | S51: 9.35 | T51: =ROUND(S51*(1+0.25),0) -> 12 | U51: =$T51*(1-0.2) -> 9.6 | V51: 0.2 | W51: =(U51-R51)/U51 -> 0.42483333 | X51: =(U51*(1-Y51-Z51-AA51-AC51-AB51)-R51)/(U51*(1-Y51-Z51-AA51-AC51-AB51)) -> 0.22977346 | Y51: 0.038 | Z51: 0.1 | AA51: 0.049 | AB51: =$AB$1/U51 -> 0.05625 | AC51: 0.01 | AF51: 不进 | AG51: =MAX(AH51:AN51) -> 0 | AH51: =IF(U51>=50,MIN(MIN(U51*0.2,20)*0.3,6),0) -> 0 | AI51: =IF(U51>=200,MIN(MIN(U51*0.18,70)*0.3,21),0) -> 0 | AJ51: =IF(U51>=380,MIN(MIN(U51*0.28,350)*0.3,105),0) -> 0 | AK51: =IF(U51>=380,MIN(MIN(U51*0.25,350)*0.3,105),0) -> 0 | AL51: =IF(U51>=380,MIN(MIN(U51*0.22,300)*0.3,90),0) -> 0 | AM51: =IF(U51>=250,MIN(MIN(U51*0.18,120)*0.3,36),0) -> 0 | AN51: =IF(U51>=180,MIN(MIN(U51*0.15,60)*0.3,18),0) -> 0
A52: 办公安防 | B52: 办公周边 | C52: =_xlfn.XLOOKUP(F52,'6月产品包'!B:B,'6月产品包'!H:H) -> 银钱盒 | D52: =_xlfn.XLOOKUP(F52,'6月产品包'!B:B,'6月产品包'!O:O) -> 迷你收银箱 | E52: 3B-仿真书银钱盒钥匙款蓝色 | F52: T4CC2660672 | G52: 平销款 | H52: ZQ | I52: =_xlfn.XLOOKUP($F52,'6月库存'!A:A,'6月库存'!B:B) -> 正常销售 | K52: =_xlfn.XLOOKUP(E52,'[1]6月分配 '!$B:$B,'[1]6月分配 '!$K:$K) -> 22237 | L52: =IF(ISNUMBER(K52),"是",IF(ISNA(K52),"否","")) -> 是 | M52: =_xlfn.XLOOKUP(F52,'6月产品包'!B:B,'6月产品包'!J:J) -> 2025-11-18 | N52: 新品 | O52: =_xlfn.XLOOKUP(F52,'6月库存'!A:A,'6月库存'!R:R) -> 0 | P52: =_xlfn.XLOOKUP(F52,'6月产品包'!B:B,'6月产品包'!S:S) -> 800 | R52: =_xlfn.XLOOKUP(F52,'6月产品包'!B:B,'6月产品包'!AD:AD) -> 10.1442 | S52: 22 | T52: =ROUND(S52*(1+0.25),0) -> 28 | U52: =$T52*(1-0.2) -> 22.4 | V52: 0.2 | W52: =(U52-R52)/U52 -> 0.54713393 | X52: =(U52*(1-Y52-Z52-AA52-AC52-AB52)-R52)/(U52*(1-Y52-Z52-AA52-AC52-AB52)) -> 0.37698374 | Y52: 0.04 | Z52: 0.1 | AA52: 0.049 | AB52: =$AB$1/U52 -> 0.024107143 | AC52: 0.06 | AF52: 原价进 | AG52: =MAX(AH52:AN52) -> 0 | AH52: =IF(U52>=50,MIN(MIN(U52*0.2,20)*0.3,6),0) -> 0 | AI52: =IF(U52>=200,MIN(MIN(U52*0.18,70)*0.3,21),0) -> 0 | AJ52: =IF(U52>=380,MIN(MIN(U52*0.28,350)*0.3,105),0) -> 0 | AK52: =IF(U52>=380,MIN(MIN(U52*0.25,350)*0.3,105),0) -> 0 | AL52: =IF(U52>=380,MIN(MIN(U52*0.22,300)*0.3,90),0) -> 0 | AM52: =IF(U52>=250,MIN(MIN(U52*0.18,120)*0.3,36),0) -> 0 | AN52: =IF(U52>=180,MIN(MIN(U52*0.15,60)*0.3,18),0) -> 0
A53: 3C数码 | B53: 音响乐器 | C53: =_xlfn.XLOOKUP(F53,'6月产品包'!B:B,'6月产品包'!H:H) -> 电子琴 | D53: =_xlfn.XLOOKUP(F53,'6月产品包'!B:B,'6月产品包'!O:O) -> 折叠电子琴88键 | E53: 3C-折叠带蓝牙带琴谱架电子琴88键 | F53: M4CC2450781 | G53: 利润款 | H53: ZQ | I53: =_xlfn.XLOOKUP($F53,'6月库存'!A:A,'6月库存'!B:B) -> 正常销售 | K53: =_xlfn.XLOOKUP(E53,'[1]6月分配 '!$B:$B,'[1]6月分配 '!$K:$K) -> 22198 | L53: =IF(ISNUMBER(K53),"是",IF(ISNA(K53),"否","")) -> 是 | M53: =_xlfn.XLOOKUP(F53,'6月产品包'!B:B,'6月产品包'!J:J) -> 2025-10-09 | N53: 新品 | O53: =_xlfn.XLOOKUP(F53,'6月库存'!A:A,'6月库存'!R:R) -> 231 | P53: =_xlfn.XLOOKUP(F53,'6月产品包'!B:B,'6月产品包'!S:S) -> 4500 | R53: =_xlfn.XLOOKUP(F53,'6月产品包'!B:B,'6月产品包'!AD:AD) -> 135.5228 | S53: 300 | T53: =ROUND(S53*(1+0.25),0) -> 375 | U53: =$T53*(1-0.2) -> 300 | V53: 0.2 | W53: =(U53-R53)/U53 -> 0.54825733 | X53: =(U53*(1-Y53-Z53-AA53-AC53-AB53)-R53)/(U53*(1-Y53-Z53-AA53-AC53-AB53)) -> 0.39460913 | Y53: 0.038 | Z53: 0.105 | AA53: 0.049 | AB53: =$AB$1/U53 -> 0.0018 | AC53: 0.06 | AF53: 原价进 | AG53: =MAX(AH53:AN53) -> 16.2 | AH53: =IF(U53>=50,MIN(MIN(U53*0.2,20)*0.3,6),0) -> 6 | AI53: =IF(U53>=200,MIN(MIN(U53*0.18,70)*0.3,21),0) -> 16.2 | AJ53: =IF(U53>=380,MIN(MIN(U53*0.28,350)*0.3,105),0) -> 0 | AK53: =IF(U53>=380,MIN(MIN(U53*0.25,350)*0.3,105),0) -> 0 | AL53: =IF(U53>=380,MIN(MIN(U53*0.22,300)*0.3,90),0) -> 0 | AM53: =IF(U53>=250,MIN(MIN(U53*0.18,120)*0.3,36),0) -> 16.2 | AN53: =IF(U53>=180,MIN(MIN(U53*0.15,60)*0.3,18),0) -> 13.5
A54: 办公安防 | B54: 安防存储 | C54: =_xlfn.XLOOKUP(F54,'6月产品包'!B:B,'6月产品包'!H:H) -> 保险箱 | D54: =_xlfn.XLOOKUP(F54,'6月产品包'!B:B,'6月产品包'!O:O) -> 大尺寸保险箱 | E54: 3B-保险柜100cm*51cm*45cm | F54: T4CC1200342 | G54: 灭款 | H54: ZQ | I54: =_xlfn.XLOOKUP($F54,'6月库存'!A:A,'6月库存'!B:B) -> 正常销售 | K54: =_xlfn.XLOOKUP(E54,'[1]6月分配 '!$B:$B,'[1]6月分配 '!$K:$K) -> 21971 | L54: =IF(ISNUMBER(K54),"是",IF(ISNA(K54),"否","")) -> 是 | M54: =_xlfn.XLOOKUP(F54,'6月产品包'!B:B,'6月产品包'!J:J) -> 2025-03-15 | N54: =IF(DATEDIF(M54,TODAY(),"m")<6,"新品","老品") -> 老品 | O54: =_xlfn.XLOOKUP(F54,'6月库存'!A:A,'6月库存'!R:R) -> 33 | P54: =_xlfn.XLOOKUP(F54,'6月产品包'!B:B,'6月产品包'!S:S) -> 45000 | R54: =_xlfn.XLOOKUP(F54,'6月产品包'!B:B,'6月产品包'!AD:AD) -> 520.1266 | S54: 699 | T54: =ROUND(S54*(1+0.25),0) -> 874 | U54: =$T54*(1-0.2) -> 699.2 | V54: 0.2 | W54: =(U54-R54)/U54 -> 0.25611184 | X54: =(U54*(1-Y54-Z54-AA54-AC54-AB54)-R54)/(U54*(1-Y54-Z54-AA54-AC54-AB54)) -> 0.0084501425 | Y54: 0.04 | Z54: 0.1 | AA54: 0.049 | AB54: =$AB$1/U54 -> 0.00077231121 | AC54: 0.06 | AF54: 原价进 | AG54: =MAX(AH54:AN54) -> 58.7328 | AH54: =IF(U54>=50,MIN(MIN(U54*0.2,20)*0.3,6),0) -> 6 | AI54: =IF(U54>=200,MIN(MIN(U54*0.18,70)*0.3,21),0) -> 21 | AJ54: =IF(U54>=380,MIN(MIN(U54*0.28,350)*0.3,105),0) -> 58.7328 | AK54: =IF(U54>=380,MIN(MIN(U54*0.25,350)*0.3,105),0) -> 52.44 | AL54: =IF(U54>=380,MIN(MIN(U54*0.22,300)*0.3,90),0) -> 46.1472 | AM54: =IF(U54>=250,MIN(MIN(U54*0.18,120)*0.3,36),0) -> 36 | AN54: =IF(U54>=180,MIN(MIN(U54*0.15,60)*0.3,18),0) -> 18
A55: 办公安防 | B55: 教学周边 | C55: =_xlfn.XLOOKUP(F55,'6月产品包'!B:B,'6月产品包'!H:H) -> 白板 | D55: =_xlfn.XLOOKUP(F55,'6月产品包'!B:B,'6月产品包'!O:O) -> 橡胶白板 | E55: 3B-橡胶磁白板背胶90cm*180cm | F55: T4CC2340732 | G55: 平销款 | H55: ZQ | I55: =_xlfn.XLOOKUP($F55,'6月库存'!A:A,'6月库存'!B:B) -> 正常销售 | K55: =_xlfn.XLOOKUP(E55,'[1]6月分配 '!$B:$B,'[1]6月分配 '!$K:$K) -> 21362 | L55: =IF(ISNUMBER(K55),"是",IF(ISNA(K55),"否","")) -> 是 | M55: =_xlfn.XLOOKUP(F55,'6月产品包'!B:B,'6月产品包'!J:J) -> 2025-07-03 | N55: =IF(DATEDIF(M55,TODAY(),"m")<6,"新品","老品") -> 老品 | O55: =_xlfn.XLOOKUP(F55,'6月库存'!A:A,'6月库存'!R:R) -> 350 | P55: =_xlfn.XLOOKUP(F55,'6月产品包'!B:B,'6月产品包'!S:S) -> 3050 | R55: =_xlfn.XLOOKUP(F55,'6月产品包'!B:B,'6月产品包'!AD:AD) -> 39.0224 | S55: 79 | T55: =ROUND(S55*(1+0.25),0) -> 99 | U55: =$T55*(1-0.2) -> 79.2 | V55: 0.2 | W55: =(U55-R55)/U55 -> 0.50729293 | X55: =(U55*(1-Y55-Z55-AA55-AC55-AB55)-R55)/(U55*(1-Y55-Z55-AA55-AC55-AB55)) -> 0.31963623 | Y55: 0.04 | Z55: 0.1 | AA55: 0.049 | AB55: =$AB$1/U55 -> 0.0068181818 | AC55: 0.08 | AD55: 0.05 | AE55: 0.05 | AF55: 原价进 | AG55: =MAX(AH55:AN55) -> 4.752 | AH55: =IF(U55>=50,MIN(MIN(U55*0.2,20)*0.3,6),0) -> 4.752 | AI55: =IF(U55>=200,MIN(MIN(U55*0.18,70)*0.3,21),0) -> 0 | AJ55: =IF(U55>=380,MIN(MIN(U55*0.28,350)*0.3,105),0) -> 0 | AK55: =IF(U55>=380,MIN(MIN(U55*0.25,350)*0.3,105),0) -> 0 | AL55: =IF(U55>=380,MIN(MIN(U55*0.22,300)*0.3,90),0) -> 0 | AM55: =IF(U55>=250,MIN(MIN(U55*0.18,120)*0.3,36),0) -> 0 | AN55: =IF(U55>=180,MIN(MIN(U55*0.15,60)*0.3,18),0) -> 0
A56: 办公安防 | B56: 智能安防 | C56: =_xlfn.XLOOKUP(F56,'6月产品包'!B:B,'6月产品包'!H:H) -> 指纹锁 | D56: =_xlfn.XLOOKUP(F56,'6月产品包'!B:B,'6月产品包'!O:O) -> 手柄门锁 | E56: 3B-智能指纹门锁X7 | F56: T3CC2120278 | G56: 平销款 | H56: ZQ | I56: =_xlfn.XLOOKUP($F56,'6月库存'!A:A,'6月库存'!B:B) -> 正常销售 | K56: =_xlfn.XLOOKUP(E56,'[1]6月分配 '!$B:$B,'[1]6月分配 '!$K:$K) -> 21136 | L56: =IF(ISNUMBER(K56),"是",IF(ISNA(K56),"否","")) -> 是 | M56: =_xlfn.XLOOKUP(F56,'6月产品包'!B:B,'6月产品包'!J:J) -> 2024-11-12 | N56: =IF(DATEDIF(M56,TODAY(),"m")<6,"新品","老品") -> 老品 | O56: =_xlfn.XLOOKUP(F56,'6月库存'!A:A,'6月库存'!R:R) -> 699 | P56: =_xlfn.XLOOKUP(F56,'6月产品包'!B:B,'6月产品包'!S:S) -> 837 | R56: =_xlfn.XLOOKUP(F56,'6月产品包'!B:B,'6月产品包'!AD:AD) -> 54.4852 | S56: 99 | T56: =ROUND(S56*(1+0.25),0) -> 124 | U56: =$T56*(1-0.2) -> 99.2 | V56: 0.2 | W56: =(U56-R56)/U56 -> 0.45075403 | X56: =(U56*(1-Y56-Z56-AA56-AC56-AB56)-R56)/(U56*(1-Y56-Z56-AA56-AC56-AB56)) -> 0.25023394 | Y56: 0.038 | Z56: 0.115 | AA56: 0.049 | AB56: =$AB$1/U56 -> 0.0054435484 | AC56: 0.06 | AF56: 不进 | AG56: =MAX(AH56:AN56) -> 5.952 | AH56: =IF(U56>=50,MIN(MIN(U56*0.2,20)*0.3,6),0) -> 5.952 | AI56: =IF(U56>=200,MIN(MIN(U56*0.18,70)*0.3,21),0) -> 0 | AJ56: =IF(U56>=380,MIN(MIN(U56*0.28,350)*0.3,105),0) -> 0 | AK56: =IF(U56>=380,MIN(MIN(U56*0.25,350)*0.3,105),0) -> 0 | AL56: =IF(U56>=380,MIN(MIN(U56*0.22,300)*0.3,90),0) -> 0 | AM56: =IF(U56>=250,MIN(MIN(U56*0.18,120)*0.3,36),0) -> 0 | AN56: =IF(U56>=180,MIN(MIN(U56*0.15,60)*0.3,18),0) -> 0
A57: 3C数码 | B57: 数码配件 | C57: =_xlfn.XLOOKUP(F57,'6月产品包'!B:B,'6月产品包'!H:H) -> 辉光管 | D57: =_xlfn.XLOOKUP(F57,'6月产品包'!B:B,'6月产品包'!O:O) -> 辉光管 | E57: 3C-辉光管 | F57: T4CC2200860 | G57: 灭款 | H57: MD | I57: =_xlfn.XLOOKUP($F57,'6月库存'!A:A,'6月库存'!B:B) -> 商品清仓 | K57: =_xlfn.XLOOKUP(E57,'[1]6月分配 '!$B:$B,'[1]6月分配 '!$K:$K) -> 20630 | L57: =IF(ISNUMBER(K57),"是",IF(ISNA(K57),"否","")) -> 是 | M57: =_xlfn.XLOOKUP(F57,'6月产品包'!B:B,'6月产品包'!J:J) -> 2025-10-09 | N57: =IF(DATEDIF(M57,TODAY(),"m")<6,"新品","老品") -> 老品 | O57: =_xlfn.XLOOKUP(F57,'6月库存'!A:A,'6月库存'!R:R) -> 74 | P57: =_xlfn.XLOOKUP(F57,'6月产品包'!B:B,'6月产品包'!S:S) -> 550 | R57: =_xlfn.XLOOKUP(F57,'6月产品包'!B:B,'6月产品包'!AD:AD) -> 117.885 | S57: 189 | T57: =ROUND(S57*(1+0.25),0) -> 236 | U57: =$T57*(1-0.2) -> 188.8 | V57: 0.2 | W57: =(U57-R57)/U57 -> 0.37560911 | X57: =(U57*(1-Y57-Z57-AA57-AC57-AB57)-R57)/(U57*(1-Y57-Z57-AA57-AC57-AB57)) -> 0.15065017 | Y57: 0.038 | Z57: 0.115 | AA57: 0.049 | AB57: =$AB$1/U57 -> 0.0028601695 | AC57: 0.06 | AF57: 原价进 | AG57: =MAX(AH57:AN57) -> 8.496 | AH57: =IF(U57>=50,MIN(MIN(U57*0.2,20)*0.3,6),0) -> 6 | AI57: =IF(U57>=200,MIN(MIN(U57*0.18,70)*0.3,21),0) -> 0 | AJ57: =IF(U57>=380,MIN(MIN(U57*0.28,350)*0.3,105),0) -> 0 | AK57: =IF(U57>=380,MIN(MIN(U57*0.25,350)*0.3,105),0) -> 0 | AL57: =IF(U57>=380,MIN(MIN(U57*0.22,300)*0.3,90),0) -> 0 | AM57: =IF(U57>=250,MIN(MIN(U57*0.18,120)*0.3,36),0) -> 0 | AN57: =IF(U57>=180,MIN(MIN(U57*0.15,60)*0.3,18),0) -> 8.496
A58: 办公安防 | B58: 办公周边 | C58: =_xlfn.XLOOKUP(F58,'6月产品包'!B:B,'6月产品包'!H:H) -> 扫码枪 | D58: =_xlfn.XLOOKUP(F58,'6月产品包'!B:B,'6月产品包'!O:O) -> 二维扫描墩 | E58: 3B-有线二维扫描平台 | F58: T4CC2040418 | G58: #N/A | H58: MD | I58: =_xlfn.XLOOKUP($F58,'6月库存'!A:A,'6月库存'!B:B) -> 正常销售 | K58: =_xlfn.XLOOKUP(E58,'[1]6月分配 '!$B:$B,'[1]6月分配 '!$K:$K) -> #N/A | L58: =IF(ISNUMBER(K58),"是",IF(ISNA(K58),"否","")) -> 否 | M58: =_xlfn.XLOOKUP(F58,'6月产品包'!B:B,'6月产品包'!J:J) -> 2025-02-24 | N58: =IF(DATEDIF(M58,TODAY(),"m")<6,"新品","老品") -> 老品 | O58: =_xlfn.XLOOKUP(F58,'6月库存'!A:A,'6月库存'!R:R) -> 17 | P58: =_xlfn.XLOOKUP(F58,'6月产品包'!B:B,'6月产品包'!S:S) -> 417 | R58: =_xlfn.XLOOKUP(F58,'6月产品包'!B:B,'6月产品包'!AD:AD) -> 50.8718 | S58: 98 | T58: =ROUND(S58*(1+0.25),0) -> 123 | U58: =$T58*(1-0.2) -> 98.4 | V58: 0.2 | W58: =(U58-R58)/U58 -> 0.48301016 | X58: =(U58*(1-Y58-Z58-AA58-AC58-AB58)-R58)/(U58*(1-Y58-Z58-AA58-AC58-AB58)) -> 0.33507173 | Y58: 0.038 | Z58: 0.1 | AA58: 0.049 | AB58: =$AB$1/U58 -> 0.0054878049 | AC58: 0.03 | AF58: 不进 | AG58: =MAX(AH58:AN58) -> 5.904 | AH58: =IF(U58>=50,MIN(MIN(U58*0.2,20)*0.3,6),0) -> 5.904 | AI58: =IF(U58>=200,MIN(MIN(U58*0.18,70)*0.3,21),0) -> 0 | AJ58: =IF(U58>=380,MIN(MIN(U58*0.28,350)*0.3,105),0) -> 0 | AK58: =IF(U58>=380,MIN(MIN(U58*0.25,350)*0.3,105),0) -> 0 | AL58: =IF(U58>=380,MIN(MIN(U58*0.22,300)*0.3,90),0) -> 0 | AM58: =IF(U58>=250,MIN(MIN(U58*0.18,120)*0.3,36),0) -> 0 | AN58: =IF(U58>=180,MIN(MIN(U58*0.15,60)*0.3,18),0) -> 0
A59: 办公安防 | B59: 办公周边 | C59: =_xlfn.XLOOKUP(F59,'6月产品包'!B:B,'6月产品包'!H:H) -> 打印机 | D59: =_xlfn.XLOOKUP(F59,'6月产品包'!B:B,'6月产品包'!O:O) -> 80mm小票打印机 | E59: 3B-8360款台式票据打印机80mm黑橘 | F59: M4CC2500939 | G59: #N/A | H59: ZQ | I59: =_xlfn.XLOOKUP($F59,'6月库存'!A:A,'6月库存'!B:B) -> 正常销售 | K59: =_xlfn.XLOOKUP(E59,'[1]6月分配 '!$B:$B,'[1]6月分配 '!$K:$K) -> #N/A | L59: =IF(ISNUMBER(K59),"是",IF(ISNA(K59),"否","")) -> 否 | M59: =_xlfn.XLOOKUP(F59,'6月产品包'!B:B,'6月产品包'!J:J) -> 2025-11-13 | N59: =IF(DATEDIF(M59,TODAY(),"m")<6,"新品","老品") -> 老品 | O59: =_xlfn.XLOOKUP(F59,'6月库存'!A:A,'6月库存'!R:R) -> 4 | P59: =_xlfn.XLOOKUP(F59,'6月产品包'!B:B,'6月产品包'!S:S) -> 1160 | R59: =_xlfn.XLOOKUP(F59,'6月产品包'!B:B,'6月产品包'!AD:AD) -> 85.9386 | S59: 175 | T59: =ROUND(S59*(1+0.25),0) -> 219 | U59: =$T59*(1-0.2) -> 175.2 | V59: 0.2 | W59: =(U59-R59)/U59 -> 0.50948288 | X59: =(U59*(1-Y59-Z59-AA59-AC59-AB59)-R59)/(U59*(1-Y59-Z59-AA59-AC59-AB59)) -> 0.34415638 | Y59: 0.04 | Z59: 0.1 | AA59: 0.049 | AB59: =$AB$1/U59 -> 0.0030821918 | AC59: 0.06 | AF59: 不进 | AG59: =MAX(AH59:AN59) -> 6 | AH59: =IF(U59>=50,MIN(MIN(U59*0.2,20)*0.3,6),0) -> 6 | AI59: =IF(U59>=200,MIN(MIN(U59*0.18,70)*0.3,21),0) -> 0 | AJ59: =IF(U59>=380,MIN(MIN(U59*0.28,350)*0.3,105),0) -> 0 | AK59: =IF(U59>=380,MIN(MIN(U59*0.25,350)*0.3,105),0) -> 0 | AL59: =IF(U59>=380,MIN(MIN(U59*0.22,300)*0.3,90),0) -> 0 | AM59: =IF(U59>=250,MIN(MIN(U59*0.18,120)*0.3,36),0) -> 0 | AN59: =IF(U59>=180,MIN(MIN(U59*0.15,60)*0.3,18),0) -> 0
A60: 办公安防 | B60: 教学周边 | C60: =_xlfn.XLOOKUP(F60,'6月产品包'!B:B,'6月产品包'!H:H) -> 白板 | D60: =_xlfn.XLOOKUP(F60,'6月产品包'!B:B,'6月产品包'!O:O) -> 磁吸白板密度板夹层 | E60: 3B-磁吸白板密度板夹层70cm*100cm | F60: T4CC2340904 | G60: 利润款 | H60: ZQ | I60: =_xlfn.XLOOKUP($F60,'6月库存'!A:A,'6月库存'!B:B) -> 正常销售 | K60: =_xlfn.XLOOKUP(E60,'[1]6月分配 '!$B:$B,'[1]6月分配 '!$K:$K) -> 20087 | L60: =IF(ISNUMBER(K60),"是",IF(ISNA(K60),"否","")) -> 是 | M60: =_xlfn.XLOOKUP(F60,'6月产品包'!B:B,'6月产品包'!J:J) -> 2025-10-27 | N60: 新品 | O60: =_xlfn.XLOOKUP(F60,'6月库存'!A:A,'6月库存'!R:R) -> 1801 | P60: =_xlfn.XLOOKUP(F60,'6月产品包'!B:B,'6月产品包'!S:S) -> 4345 | R60: =_xlfn.XLOOKUP(F60,'6月产品包'!B:B,'6月产品包'!AD:AD) -> 25.056 | S60: 51 | T60: =ROUND(S60*(1+0.25),0) -> 64 | U60: =$T60*(1-0.2) -> 51.2 | V60: 0.2 | W60: =(U60-R60)/U60 -> 0.510625 | X60: =(U60*(1-Y60-Z60-AA60-AC60-AB60)-R60)/(U60*(1-Y60-Z60-AA60-AC60-AB60)) -> 0.32073999 | Y60: 0.04 | Z60: 0.1 | AA60: 0.049 | AB60: =$AB$1/U60 -> 0.010546875 | AC60: 0.08 | AD60: 0.05 | AE60: 0.05 | AF60: 原价进 | AG60: =MAX(AH60:AN60) -> 3.072 | AH60: =IF(U60>=50,MIN(MIN(U60*0.2,20)*0.3,6),0) -> 3.072 | AI60: =IF(U60>=200,MIN(MIN(U60*0.18,70)*0.3,21),0) -> 0 | AJ60: =IF(U60>=380,MIN(MIN(U60*0.28,350)*0.3,105),0) -> 0 | AK60: =IF(U60>=380,MIN(MIN(U60*0.25,350)*0.3,105),0) -> 0 | AL60: =IF(U60>=380,MIN(MIN(U60*0.22,300)*0.3,90),0) -> 0 | AM60: =IF(U60>=250,MIN(MIN(U60*0.18,120)*0.3,36),0) -> 0 | AN60: =IF(U60>=180,MIN(MIN(U60*0.15,60)*0.3,18),0) -> 0
A61: =_xlfn.XLOOKUP(F61,'6月产品包'!B:B,'6月产品包'!F:F) -> 办公安防 | B61: =_xlfn.XLOOKUP(F61,'6月产品包'!B:B,'6月产品包'!G:G) -> 教学周边 | C61: =_xlfn.XLOOKUP(F61,'6月产品包'!B:B,'6月产品包'!H:H) -> 白板 | D61: =_xlfn.XLOOKUP(F61,'6月产品包'!B:B,'6月产品包'!O:O) -> 磁吸白板密度板夹层 | E61: =_xlfn.XLOOKUP(F61,'6月产品包'!B:B,'6月产品包'!C:C) -> 3B-磁吸白板密度板夹层70cm*100cm | F61: T5CC2830904 | G61: 利润款 | H61: ZQ | I61: =_xlfn.XLOOKUP($F61,'6月库存'!A:A,'6月库存'!B:B) -> 等待开发 | K61: =_xlfn.XLOOKUP(E61,'[1]6月分配 '!$B:$B,'[1]6月分配 '!$K:$K) -> 20087 | L61: =IF(ISNUMBER(K61),"是",IF(ISNA(K61),"否","")) -> 是 | M61: =_xlfn.XLOOKUP(F61,'6月产品包'!B:B,'6月产品包'!J:J) -> 2026-04-28 | N61: 新品 | O61: =_xlfn.XLOOKUP(F61,'6月库存'!A:A,'6月库存'!R:R) -> 0 | P61: =_xlfn.XLOOKUP(F61,'6月产品包'!B:B,'6月产品包'!S:S) -> 4345 | R61: =_xlfn.XLOOKUP(F61,'6月产品包'!B:B,'6月产品包'!AD:AD) -> 25.172 | S61: 51 | T61: =ROUND(S61*(1+0.25),0) -> 64 | U61: =$T61*(1-0.2) -> 51.2 | V61: 0.2 | W61: =(U61-R61)/U61 -> 0.50835937 | X61: =(U61*(1-Y61-Z61-AA61-AC61-AB61)-R61)/(U61*(1-Y61-Z61-AA61-AC61-AB61)) -> 0.31759526 | Y61: 0.04 | Z61: 0.1 | AA61: 0.049 | AB61: =$AB$1/U61 -> 0.010546875 | AC61: 0.08 | AD61: 0.05 | AE61: 0.05 | AF61: 原价进 | AG61: =MAX(AH61:AN61) -> 3.072 | AH61: =IF(U61>=50,MIN(MIN(U61*0.2,20)*0.3,6),0) -> 3.072 | AI61: =IF(U61>=200,MIN(MIN(U61*0.18,70)*0.3,21),0) -> 0 | AJ61: =IF(U61>=380,MIN(MIN(U61*0.28,350)*0.3,105),0) -> 0 | AK61: =IF(U61>=380,MIN(MIN(U61*0.25,350)*0.3,105),0) -> 0 | AL61: =IF(U61>=380,MIN(MIN(U61*0.22,300)*0.3,90),0) -> 0 | AM61: =IF(U61>=250,MIN(MIN(U61*0.18,120)*0.3,36),0) -> 0 | AN61: =IF(U61>=180,MIN(MIN(U61*0.15,60)*0.3,18),0) -> 0
A62: 办公安防 | B62: 智能安防 | C62: =_xlfn.XLOOKUP(F62,'6月产品包'!B:B,'6月产品包'!H:H) -> 折叠锥桶 | D62: =_xlfn.XLOOKUP(F62,'6月产品包'!B:B,'6月产品包'!O:O) -> 折叠锥桶 | E62: 3B-道路警示折叠锥桶70cm | F62: T4CC2330752 | G62: 引流款 | H62: ZQ | I62: =_xlfn.XLOOKUP($F62,'6月库存'!A:A,'6月库存'!B:B) -> 等待开发 | K62: =_xlfn.XLOOKUP(E62,'[1]6月分配 '!$B:$B,'[1]6月分配 '!$K:$K) -> #N/A | L62: =IF(ISNUMBER(K62),"是",IF(ISNA(K62),"否","")) -> 否 | M62: =_xlfn.XLOOKUP(F62,'6月产品包'!B:B,'6月产品包'!J:J) -> 2025-07-03 | N62: =IF(DATEDIF(M62,TODAY(),"m")<6,"新品","老品") -> 老品 | O62: =_xlfn.XLOOKUP(F62,'6月库存'!A:A,'6月库存'!R:R) -> 0 | P62: =_xlfn.XLOOKUP(F62,'6月产品包'!B:B,'6月产品包'!S:S) -> 7000 | R62: =_xlfn.XLOOKUP(F62,'6月产品包'!B:B,'6月产品包'!AD:AD) -> 18.2468 | S62: 32 | T62: =ROUND(S62*(1+0.25),0) -> 40 | U62: =$T62*(1-0.2) -> 32 | V62: 0.2 | W62: =(U62-R62)/U62 -> 0.4297875 | X62: =(U62*(1-Y62-Z62-AA62-AC62-AB62)-R62)/(U62*(1-Y62-Z62-AA62-AC62-AB62)) -> 0.22538631 | Y62: 0.038 | Z62: 0.1 | AA62: 0.049 | AB62: =$AB$1/U62 -> 0.016875 | AC62: 0.06 | AF62: 不进 | AG62: =MAX(AH62:AN62) -> 0 | AH62: =IF(U62>=50,MIN(MIN(U62*0.2,20)*0.3,6),0) -> 0 | AI62: =IF(U62>=200,MIN(MIN(U62*0.18,70)*0.3,21),0) -> 0 | AJ62: =IF(U62>=380,MIN(MIN(U62*0.28,350)*0.3,105),0) -> 0 | AK62: =IF(U62>=380,MIN(MIN(U62*0.25,350)*0.3,105),0) -> 0 | AL62: =IF(U62>=380,MIN(MIN(U62*0.22,300)*0.3,90),0) -> 0 | AM62: =IF(U62>=250,MIN(MIN(U62*0.18,120)*0.3,36),0) -> 0 | AN62: =IF(U62>=180,MIN(MIN(U62*0.15,60)*0.3,18),0) -> 0
A63: 3C数码 | B63: 音响乐器 | C63: =_xlfn.XLOOKUP(F63,'6月产品包'!B:B,'6月产品包'!H:H) -> 电子鼓 | D63: =_xlfn.XLOOKUP(F63,'6月产品包'!B:B,'6月产品包'!O:O) -> 手卷鼓 | E63: 3C-手卷电子7垫鼓 | F63: T3CC2050176 | G63: 利润款 | H63: ZQ | I63: =_xlfn.XLOOKUP($F63,'6月库存'!A:A,'6月库存'!B:B) -> 商品清仓 | K63: =_xlfn.XLOOKUP(E63,'[1]6月分配 '!$B:$B,'[1]6月分配 '!$K:$K) -> 19470 | L63: =IF(ISNUMBER(K63),"是",IF(ISNA(K63),"否","")) -> 是 | M63: =_xlfn.XLOOKUP(F63,'6月产品包'!B:B,'6月产品包'!J:J) -> 2024-09-03 | N63: 老品 | O63: =_xlfn.XLOOKUP(F63,'6月库存'!A:A,'6月库存'!R:R) -> 0 | P63: =_xlfn.XLOOKUP(F63,'6月产品包'!B:B,'6月产品包'!S:S) -> 1000 | R63: =_xlfn.XLOOKUP(F63,'6月产品包'!B:B,'6月产品包'!AD:AD) -> 54.6418 | S63: 117 | T63: =ROUND(S63*(1+0.25),0) -> 146 | U63: =$T63*(1-0.2) -> 116.8 | V63: 0.2 | W63: =(U63-R63)/U63 -> 0.53217637 | X63: =(U63*(1-Y63-Z63-AA63-AC63-AB63)-R63)/(U63*(1-Y63-Z63-AA63-AC63-AB63)) -> 0.37067758 | Y63: 0.038 | Z63: 0.105 | AA63: 0.049 | AB63: =$AB$1/U63 -> 0.0046232877 | AC63: 0.06 | AF63: 原价进 | AG63: =MAX(AH63:AN63) -> 6 | AH63: =IF(U63>=50,MIN(MIN(U63*0.2,20)*0.3,6),0) -> 6 | AI63: =IF(U63>=200,MIN(MIN(U63*0.18,70)*0.3,21),0) -> 0 | AJ63: =IF(U63>=380,MIN(MIN(U63*0.28,350)*0.3,105),0) -> 0 | AK63: =IF(U63>=380,MIN(MIN(U63*0.25,350)*0.3,105),0) -> 0 | AL63: =IF(U63>=380,MIN(MIN(U63*0.22,300)*0.3,90),0) -> 0 | AM63: =IF(U63>=250,MIN(MIN(U63*0.18,120)*0.3,36),0) -> 0 | AN63: =IF(U63>=180,MIN(MIN(U63*0.15,60)*0.3,18),0) -> 0
A64: =_xlfn.XLOOKUP(F64,'6月产品包'!B:B,'6月产品包'!F:F) -> 3C数码 | B64: =_xlfn.XLOOKUP(F64,'6月产品包'!B:B,'6月产品包'!G:G) -> 音响乐器 | C64: =_xlfn.XLOOKUP(F64,'6月产品包'!B:B,'6月产品包'!H:H) -> 电子鼓 | D64: =_xlfn.XLOOKUP(F64,'6月产品包'!B:B,'6月产品包'!O:O) -> 手卷鼓 | E64: =_xlfn.XLOOKUP(F64,'6月产品包'!B:B,'6月产品包'!C:C) -> 3C-手卷电子7垫鼓 | F64: T5CC2790176 | G64: 利润款 | H64: MD | I64: =_xlfn.XLOOKUP($F64,'6月库存'!A:A,'6月库存'!B:B) -> 正常销售 | K64: =_xlfn.XLOOKUP(E64,'[1]6月分配 '!$B:$B,'[1]6月分配 '!$K:$K) -> 19470 | L64: =IF(ISNUMBER(K64),"是",IF(ISNA(K64),"否","")) -> 是 | M64: =_xlfn.XLOOKUP(F64,'6月产品包'!B:B,'6月产品包'!J:J) -> 2026-04-14 | N64: 新品 | O64: =_xlfn.XLOOKUP(F64,'6月库存'!A:A,'6月库存'!R:R) -> 445 | P64: =_xlfn.XLOOKUP(F64,'6月产品包'!B:B,'6月产品包'!S:S) -> 1000 | R64: =_xlfn.XLOOKUP(F64,'6月产品包'!B:B,'6月产品包'!AD:AD) -> 54.5548 | S64: 117 | T64: =ROUND(S64*(1+0.25),0) -> 146 | U64: =$T64*(1-0.2) -> 116.8 | V64: 0.2 | W64: =(U64-R64)/U64 -> 0.53292123 | X64: =(U64*(1-Y64-Z64-AA64-AC64-AB64)-R64)/(U64*(1-Y64-Z64-AA64-AC64-AB64)) -> 0.37167958 | Y64: 0.038 | Z64: 0.105 | AA64: 0.049 | AB64: =$AB$1/U64 -> 0.0046232877 | AC64: 0.06 | AF64: 原价进 | AG64: =MAX(AH64:AN64) -> 6 | AH64: =IF(U64>=50,MIN(MIN(U64*0.2,20)*0.3,6),0) -> 6 | AI64: =IF(U64>=200,MIN(MIN(U64*0.18,70)*0.3,21),0) -> 0 | AJ64: =IF(U64>=380,MIN(MIN(U64*0.28,350)*0.3,105),0) -> 0 | AK64: =IF(U64>=380,MIN(MIN(U64*0.25,350)*0.3,105),0) -> 0 | AL64: =IF(U64>=380,MIN(MIN(U64*0.22,300)*0.3,90),0) -> 0 | AM64: =IF(U64>=250,MIN(MIN(U64*0.18,120)*0.3,36),0) -> 0 | AN64: =IF(U64>=180,MIN(MIN(U64*0.15,60)*0.3,18),0) -> 0
A65: 办公安防 | B65: 办公周边 | C65: =_xlfn.XLOOKUP(F65,'6月产品包'!B:B,'6月产品包'!H:H) -> 订书机 | D65: =_xlfn.XLOOKUP(F65,'6月产品包'!B:B,'6月产品包'!O:O) -> 重型订书机 | E65: 3B-重型订书机 | F65: T4CC2400762 | G65: #N/A | H65: ZQ | I65: =_xlfn.XLOOKUP($F65,'6月库存'!A:A,'6月库存'!B:B) -> 正常销售 | K65: =_xlfn.XLOOKUP(E65,'[1]6月分配 '!$B:$B,'[1]6月分配 '!$K:$K) -> #N/A | L65: =IF(ISNUMBER(K65),"是",IF(ISNA(K65),"否","")) -> 否 | M65: =_xlfn.XLOOKUP(F65,'6月产品包'!B:B,'6月产品包'!J:J) -> 2025-07-26 | N65: =IF(DATEDIF(M65,TODAY(),"m")<6,"新品","老品") -> 老品 | O65: =_xlfn.XLOOKUP(F65,'6月库存'!A:A,'6月库存'!R:R) -> 26 | P65: =_xlfn.XLOOKUP(F65,'6月产品包'!B:B,'6月产品包'!S:S) -> 817 | R65: =_xlfn.XLOOKUP(F65,'6月产品包'!B:B,'6月产品包'!AD:AD) -> 12.0698 | S65: 24 | T65: =ROUND(S65*(1+0.25),0) -> 30 | U65: =$T65*(1-0.2) -> 24 | V65: 0.2 | W65: =(U65-R65)/U65 -> 0.49709167 | X65: =(U65*(1-Y65-Z65-AA65-AC65-AB65)-R65)/(U65*(1-Y65-Z65-AA65-AC65-AB65)) -> 0.30966598 | Y65: 0.04 | Z65: 0.1 | AA65: 0.049 | AB65: =$AB$1/U65 -> 0.0225 | AC65: 0.06 | AF65: 不进 | AG65: =MAX(AH65:AN65) -> 0 | AH65: =IF(U65>=50,MIN(MIN(U65*0.2,20)*0.3,6),0) -> 0 | AI65: =IF(U65>=200,MIN(MIN(U65*0.18,70)*0.3,21),0) -> 0 | AJ65: =IF(U65>=380,MIN(MIN(U65*0.28,350)*0.3,105),0) -> 0 | AK65: =IF(U65>=380,MIN(MIN(U65*0.25,350)*0.3,105),0) -> 0 | AL65: =IF(U65>=380,MIN(MIN(U65*0.22,300)*0.3,90),0) -> 0 | AM65: =IF(U65>=250,MIN(MIN(U65*0.18,120)*0.3,36),0) -> 0 | AN65: =IF(U65>=180,MIN(MIN(U65*0.15,60)*0.3,18),0) -> 0
A66: 办公安防 | B66: 办公周边 | C66: =_xlfn.XLOOKUP(F66,'6月产品包'!B:B,'6月产品包'!H:H) -> 银钱盒 | D66: =_xlfn.XLOOKUP(F66,'6月产品包'!B:B,'6月产品包'!O:O) -> 迷你收银箱 | E66: 3B-仿真书银钱盒密码款蓝色 | F66: T3CC1220673 | G66: 平销款 | H66: ZQ | I66: =_xlfn.XLOOKUP($F66,'6月库存'!A:A,'6月库存'!B:B) -> 商品清仓 | K66: =_xlfn.XLOOKUP(E66,'[1]6月分配 '!$B:$B,'[1]6月分配 '!$K:$K) -> 19186 | L66: =IF(ISNUMBER(K66),"是",IF(ISNA(K66),"否","")) -> 是 | M66: =_xlfn.XLOOKUP(F66,'6月产品包'!B:B,'6月产品包'!J:J) -> 2024-05-23 | N66: 老品 | O66: =_xlfn.XLOOKUP(F66,'6月库存'!A:A,'6月库存'!R:R) -> 1006 | P66: =_xlfn.XLOOKUP(F66,'6月产品包'!B:B,'6月产品包'!S:S) -> 800 | R66: =_xlfn.XLOOKUP(F66,'6月产品包'!B:B,'6月产品包'!AD:AD) -> 11.4724 | S66: 22 | T66: =ROUND(S66*(1+0.25),0) -> 28 | U66: =$T66*(1-0.2) -> 22.4 | V66: 0.2 | W66: =(U66-R66)/U66 -> 0.48783929 | X66: =(U66*(1-Y66-Z66-AA66-AC66-AB66)-R66)/(U66*(1-Y66-Z66-AA66-AC66-AB66)) -> 0.295411 | Y66: 0.04 | Z66: 0.1 | AA66: 0.049 | AB66: =$AB$1/U66 -> 0.024107143 | AC66: 0.06 | AF66: 原价进 | AG66: =MAX(AH66:AN66) -> 0 | AH66: =IF(U66>=50,MIN(MIN(U66*0.2,20)*0.3,6),0) -> 0 | AI66: =IF(U66>=200,MIN(MIN(U66*0.18,70)*0.3,21),0) -> 0 | AJ66: =IF(U66>=380,MIN(MIN(U66*0.28,350)*0.3,105),0) -> 0 | AK66: =IF(U66>=380,MIN(MIN(U66*0.25,350)*0.3,105),0) -> 0 | AL66: =IF(U66>=380,MIN(MIN(U66*0.22,300)*0.3,90),0) -> 0 | AM66: =IF(U66>=250,MIN(MIN(U66*0.18,120)*0.3,36),0) -> 0 | AN66: =IF(U66>=180,MIN(MIN(U66*0.15,60)*0.3,18),0) -> 0
A67: 办公安防 | B67: 办公周边 | C67: =_xlfn.XLOOKUP(F67,'6月产品包'!B:B,'6月产品包'!H:H) -> 银钱盒 | D67: =_xlfn.XLOOKUP(F67,'6月产品包'!B:B,'6月产品包'!O:O) -> 迷你收银箱 | E67: 3B-仿真书银钱盒密码款蓝色 | F67: T4CC2660673 | G67: 平销款 | H67: ZQ | I67: =_xlfn.XLOOKUP($F67,'6月库存'!A:A,'6月库存'!B:B) -> 正常销售 | K67: =_xlfn.XLOOKUP(E67,'[1]6月分配 '!$B:$B,'[1]6月分配 '!$K:$K) -> 19186 | L67: =IF(ISNUMBER(K67),"是",IF(ISNA(K67),"否","")) -> 是 | M67: =_xlfn.XLOOKUP(F67,'6月产品包'!B:B,'6月产品包'!J:J) -> 2025-11-18 | N67: 新品 | O67: =_xlfn.XLOOKUP(F67,'6月库存'!A:A,'6月库存'!R:R) -> 0 | P67: =_xlfn.XLOOKUP(F67,'6月产品包'!B:B,'6月产品包'!S:S) -> 800 | R67: =_xlfn.XLOOKUP(F67,'6月产品包'!B:B,'6月产品包'!AD:AD) -> 10.7068 | S67: 22 | T67: =ROUND(S67*(1+0.25),0) -> 28 | U67: =$T67*(1-0.2) -> 22.4 | V67: 0.2 | W67: =(U67-R67)/U67 -> 0.52201786 | X67: =(U67*(1-Y67-Z67-AA67-AC67-AB67)-R67)/(U67*(1-Y67-Z67-AA67-AC67-AB67)) -> 0.34243109 | Y67: 0.04 | Z67: 0.1 | AA67: 0.049 | AB67: =$AB$1/U67 -> 0.024107143 | AC67: 0.06 | AF67: 原价进 | AG67: =MAX(AH67:AN67) -> 0 | AH67: =IF(U67>=50,MIN(MIN(U67*0.2,20)*0.3,6),0) -> 0 | AI67: =IF(U67>=200,MIN(MIN(U67*0.18,70)*0.3,21),0) -> 0 | AJ67: =IF(U67>=380,MIN(MIN(U67*0.28,350)*0.3,105),0) -> 0 | AK67: =IF(U67>=380,MIN(MIN(U67*0.25,350)*0.3,105),0) -> 0 | AL67: =IF(U67>=380,MIN(MIN(U67*0.22,300)*0.3,90),0) -> 0 | AM67: =IF(U67>=250,MIN(MIN(U67*0.18,120)*0.3,36),0) -> 0 | AN67: =IF(U67>=180,MIN(MIN(U67*0.15,60)*0.3,18),0) -> 0
A68: 办公安防 | B68: 办公周边 | C68: =_xlfn.XLOOKUP(F68,'6月产品包'!B:B,'6月产品包'!H:H) -> 收银箱 | D68: =_xlfn.XLOOKUP(F68,'6月产品包'!B:B,'6月产品包'!O:O) -> 手提收银箱 | E68: 3B-手提收银箱双层黑色 | F68: T4CC2150142 | G68: #N/A | H68: ZQ | I68: =_xlfn.XLOOKUP($F68,'6月库存'!A:A,'6月库存'!B:B) -> 正常销售 | K68: =_xlfn.XLOOKUP(E68,'[1]6月分配 '!$B:$B,'[1]6月分配 '!$K:$K) -> 19070 | L68: =IF(ISNUMBER(K68),"是",IF(ISNA(K68),"否","")) -> 是 | M68: =_xlfn.XLOOKUP(F68,'6月产品包'!B:B,'6月产品包'!J:J) -> 2025-06-03 | N68: =IF(DATEDIF(M68,TODAY(),"m")<6,"新品","老品") -> 老品 | O68: =_xlfn.XLOOKUP(F68,'6月库存'!A:A,'6月库存'!R:R) -> 1886 | P68: =_xlfn.XLOOKUP(F68,'6月产品包'!B:B,'6月产品包'!S:S) -> 1800 | Q68: 2450 | R68: =_xlfn.XLOOKUP(F68,'6月产品包'!B:B,'6月产品包'!AD:AD) -> 22.3474 | S68: 48 | T68: =ROUND(S68*(1+0.25),0) -> 60 | U68: =$T68*(1-0.2) -> 48 | V68: 0.2 | W68: =(U68-R68)/U68 -> 0.53442917 | X68: =(U68*(1-Y68-Z68-AA68-AC68-AB68)-R68)/(U68*(1-Y68-Z68-AA68-AC68-AB68)) -> 0.38720522 | Y68: 0.04 | Z68: 0.1 | AA68: 0.049 | AB68: =$AB$1/U68 -> 0.01125 | AC68: 0.04 | AF68: 原价进 | AG68: =MAX(AH68:AN68) -> 0 | AH68: =IF(U68>=50,MIN(MIN(U68*0.2,20)*0.3,6),0) -> 0 | AI68: =IF(U68>=200,MIN(MIN(U68*0.18,70)*0.3,21),0) -> 0 | AJ68: =IF(U68>=380,MIN(MIN(U68*0.28,350)*0.3,105),0) -> 0 | AK68: =IF(U68>=380,MIN(MIN(U68*0.25,350)*0.3,105),0) -> 0 | AL68: =IF(U68>=380,MIN(MIN(U68*0.22,300)*0.3,90),0) -> 0 | AM68: =IF(U68>=250,MIN(MIN(U68*0.18,120)*0.3,36),0) -> 0 | AN68: =IF(U68>=180,MIN(MIN(U68*0.15,60)*0.3,18),0) -> 0
A69: 办公安防 | B69: 办公周边 | C69: =_xlfn.XLOOKUP(F69,'6月产品包'!B:B,'6月产品包'!H:H) -> 收银箱 | D69: =_xlfn.XLOOKUP(F69,'6月产品包'!B:B,'6月产品包'!O:O) -> 手提收银箱 | E69: 3B-手提收银箱双层黑色 | F69: T5CC2720142 | G69: #N/A | H69: ZQ | I69: =_xlfn.XLOOKUP($F69,'6月库存'!A:A,'6月库存'!B:B) -> 正常销售 | K69: =_xlfn.XLOOKUP(E69,'[1]6月分配 '!$B:$B,'[1]6月分配 '!$K:$K) -> 19070 | L69: =IF(ISNUMBER(K69),"是",IF(ISNA(K69),"否","")) -> 是 | M69: =_xlfn.XLOOKUP(F69,'6月产品包'!B:B,'6月产品包'!J:J) -> 2026-01-26 | N69: =IF(DATEDIF(M69,TODAY(),"m")<6,"新品","老品") -> 新品 | O69: =_xlfn.XLOOKUP(F69,'6月库存'!A:A,'6月库存'!R:R) -> 0 | P69: =_xlfn.XLOOKUP(F69,'6月产品包'!B:B,'6月产品包'!S:S) -> 1800 | Q69: 2450 | R69: =_xlfn.XLOOKUP(F69,'6月产品包'!B:B,'6月产品包'!AD:AD) -> 22.707 | S69: 48 | T69: =ROUND(S69*(1+0.25),0) -> 60 | U69: =$T69*(1-0.2) -> 48 | V69: 0.2 | W69: =(U69-R69)/U69 -> 0.5269375 | X69: =(U69*(1-Y69-Z69-AA69-AC69-AB69)-R69)/(U69*(1-Y69-Z69-AA69-AC69-AB69)) -> 0.36903968 | Y69: 0.04 | Z69: 0.09 | AA69: 0.049 | AB69: =$AB$1/U69 -> 0.01125 | AC69: 0.06 | AF69: 原价进 | AG69: =MAX(AH69:AN69) -> 0 | AH69: =IF(U69>=50,MIN(MIN(U69*0.2,20)*0.3,6),0) -> 0 | AI69: =IF(U69>=200,MIN(MIN(U69*0.18,70)*0.3,21),0) -> 0 | AJ69: =IF(U69>=380,MIN(MIN(U69*0.28,350)*0.3,105),0) -> 0 | AK69: =IF(U69>=380,MIN(MIN(U69*0.25,350)*0.3,105),0) -> 0 | AL69: =IF(U69>=380,MIN(MIN(U69*0.22,300)*0.3,90),0) -> 0 | AM69: =IF(U69>=250,MIN(MIN(U69*0.18,120)*0.3,36),0) -> 0 | AN69: =IF(U69>=180,MIN(MIN(U69*0.15,60)*0.3,18),0) -> 0
A70: =_xlfn.XLOOKUP(F70,'6月产品包'!B:B,'6月产品包'!F:F) -> 办公安防 | B70: =_xlfn.XLOOKUP(F70,'6月产品包'!B:B,'6月产品包'!G:G) -> 办公周边 | C70: =_xlfn.XLOOKUP(F70,'6月产品包'!B:B,'6月产品包'!H:H) -> 收银箱 | D70: =_xlfn.XLOOKUP(F70,'6月产品包'!B:B,'6月产品包'!O:O) -> 手提收银箱 | E70: =_xlfn.XLOOKUP(F70,'6月产品包'!B:B,'6月产品包'!C:C) -> 3B-手提收银箱双层黑色 | F70: T5CC2660142 | H70: ZQ | I70: =_xlfn.XLOOKUP($F70,'6月库存'!A:A,'6月库存'!B:B) -> 等待开发 | K70: =_xlfn.XLOOKUP(E70,'[1]6月分配 '!$B:$B,'[1]6月分配 '!$K:$K) -> 19070 | L70: =IF(ISNUMBER(K70),"是",IF(ISNA(K70),"否","")) -> 是 | M70: =_xlfn.XLOOKUP(F70,'6月产品包'!B:B,'6月产品包'!J:J) -> 2026-05-05 | N70: 新品 | O70: =_xlfn.XLOOKUP(F70,'6月库存'!A:A,'6月库存'!R:R) -> 0 | P70: =_xlfn.XLOOKUP(F70,'6月产品包'!B:B,'6月产品包'!S:S) -> 1800 | Q70: 2450 | R70: =_xlfn.XLOOKUP(F70,'6月产品包'!B:B,'6月产品包'!AD:AD) -> 20.4566 | S70: 48 | T70: =ROUND(S70*(1+0.25),0) -> 60 | U70: =$T70*(1-0.2) -> 48 | V70: 6.2 | W70: =(U70-R70)/U70 -> 0.57382083 | X70: =(U70*(1-Y70-Z70-AA70-AC70-AB70)-R70)/(U70*(1-Y70-Z70-AA70-AC70-AB70)) -> 0.41758911 | Y70: 0.038 | Z70: 0.09 | AA70: 0.049 | AB70: =$AB$1/U70 -> 0.01125 | AC70: 0.08 | AF70: 原价进 | AG70: =MAX(AH70:AN70) -> 0 | AH70: =IF(U70>=50,MIN(MIN(U70*0.2,20)*0.3,6),0) -> 0 | AI70: =IF(U70>=200,MIN(MIN(U70*0.18,70)*0.3,21),0) -> 0 | AJ70: =IF(U70>=380,MIN(MIN(U70*0.28,350)*0.3,105),0) -> 0 | AK70: =IF(U70>=380,MIN(MIN(U70*0.25,350)*0.3,105),0) -> 0 | AL70: =IF(U70>=380,MIN(MIN(U70*0.22,300)*0.3,90),0) -> 0 | AM70: =IF(U70>=250,MIN(MIN(U70*0.18,120)*0.3,36),0) -> 0 | AN70: =IF(U70>=180,MIN(MIN(U70*0.15,60)*0.3,18),0) -> 0
A71: 办公安防 | B71: 智能安防 | C71: =_xlfn.XLOOKUP(F71,'6月产品包'!B:B,'6月产品包'!H:H) -> 球型智能门锁 | D71: =_xlfn.XLOOKUP(F71,'6月产品包'!B:B,'6月产品包'!O:O) -> 可充电球形锁K06 | E71: 3B-可充电不锈钢球形锁K06 | F71: T5CC2701044 | G71: #N/A | H71: ZQ | I71: =_xlfn.XLOOKUP($F71,'6月库存'!A:A,'6月库存'!B:B) -> 正常销售 | K71: =_xlfn.XLOOKUP(E71,'[1]6月分配 '!$B:$B,'[1]6月分配 '!$K:$K) -> 17701 | L71: =IF(ISNUMBER(K71),"是",IF(ISNA(K71),"否","")) -> 是 | M71: =_xlfn.XLOOKUP(F71,'6月产品包'!B:B,'6月产品包'!J:J) -> 2026-01-22 | N71: =IF(DATEDIF(M71,TODAY(),"m")<6,"新品","老品") -> 新品 | O71: =_xlfn.XLOOKUP(F71,'6月库存'!A:A,'6月库存'!R:R) -> 120 | P71: =_xlfn.XLOOKUP(F71,'6月产品包'!B:B,'6月产品包'!S:S) -> 872 | R71: =_xlfn.XLOOKUP(F71,'6月产品包'!B:B,'6月产品包'!AD:AD) -> 57.043 | S71: 112 | T71: =ROUND(S71*(1+0.25),0) -> 140 | U71: =$T71*(1-0.2) -> 112 | V71: 0.2 | W71: =(U71-R71)/U71 -> 0.4906875 | X71: =(U71*(1-Y71-Z71-AA71-AC71-AB71)-R71)/(U71*(1-Y71-Z71-AA71-AC71-AB71)) -> 0.32824203 | Y71: 0.038 | Z71: 0.09 | AA71: 0.049 | AB71: =$AB$1/U71 -> 0.0048214286 | AC71: 0.06 | AF71: 原价进 | AG71: =MAX(AH71:AN71) -> 6 | AH71: =IF(U71>=50,MIN(MIN(U71*0.2,20)*0.3,6),0) -> 6 | AI71: =IF(U71>=200,MIN(MIN(U71*0.18,70)*0.3,21),0) -> 0 | AJ71: =IF(U71>=380,MIN(MIN(U71*0.28,350)*0.3,105),0) -> 0 | AK71: =IF(U71>=380,MIN(MIN(U71*0.25,350)*0.3,105),0) -> 0 | AL71: =IF(U71>=380,MIN(MIN(U71*0.22,300)*0.3,90),0) -> 0 | AM71: =IF(U71>=250,MIN(MIN(U71*0.18,120)*0.3,36),0) -> 0 | AN71: =IF(U71>=180,MIN(MIN(U71*0.15,60)*0.3,18),0) -> 0
A72: 办公安防 | B72: 教学周边 | C72: =_xlfn.XLOOKUP(F72,'6月产品包'!B:B,'6月产品包'!H:H) -> 白板 | D72: =_xlfn.XLOOKUP(F72,'6月产品包'!B:B,'6月产品包'!O:O) -> 磁吸白板密度板夹层 | E72: 3B-磁吸白板密度板夹层60cm*90cm | F72: T4CC2340903 | G72: 平销款 | H72: ZQ | I72: =_xlfn.XLOOKUP($F72,'6月库存'!A:A,'6月库存'!B:B) -> 正常销售 | K72: =_xlfn.XLOOKUP(E72,'[1]6月分配 '!$B:$B,'[1]6月分配 '!$K:$K) -> 17118 | L72: =IF(ISNUMBER(K72),"是",IF(ISNA(K72),"否","")) -> 是 | M72: =_xlfn.XLOOKUP(F72,'6月产品包'!B:B,'6月产品包'!J:J) -> 2025-10-27 | N72: 新品 | O72: =_xlfn.XLOOKUP(F72,'6月库存'!A:A,'6月库存'!R:R) -> 1788 | P72: =_xlfn.XLOOKUP(F72,'6月产品包'!B:B,'6月产品包'!S:S) -> 3461 | R72: =_xlfn.XLOOKUP(F72,'6月产品包'!B:B,'6月产品包'!AD:AD) -> 19.546 | S72: 42 | T72: =ROUND(S72*(1+0.25),0) -> 53 | U72: =$T72*(1-0.2) -> 42.4 | V72: 0.2 | W72: =(U72-R72)/U72 -> 0.53900943 | X72: =(U72*(1-Y72-Z72-AA72-AC72-AB72)-R72)/(U72*(1-Y72-Z72-AA72-AC72-AB72)) -> 0.35818798 | Y72: 0.04 | Z72: 0.1 | AA72: 0.049 | AB72: =$AB$1/U72 -> 0.012735849 | AC72: 0.08 | AD72: 0.05 | AE72: 0.05 | AF72: 原价进 | AG72: =MAX(AH72:AN72) -> 0 | AH72: =IF(U72>=50,MIN(MIN(U72*0.2,20)*0.3,6),0) -> 0 | AI72: =IF(U72>=200,MIN(MIN(U72*0.18,70)*0.3,21),0) -> 0 | AJ72: =IF(U72>=380,MIN(MIN(U72*0.28,350)*0.3,105),0) -> 0 | AK72: =IF(U72>=380,MIN(MIN(U72*0.25,350)*0.3,105),0) -> 0 | AL72: =IF(U72>=380,MIN(MIN(U72*0.22,300)*0.3,90),0) -> 0 | AM72: =IF(U72>=250,MIN(MIN(U72*0.18,120)*0.3,36),0) -> 0 | AN72: =IF(U72>=180,MIN(MIN(U72*0.15,60)*0.3,18),0) -> 0
A73: 办公安防 | B73: 教学周边 | C73: =_xlfn.XLOOKUP(F73,'6月产品包'!B:B,'6月产品包'!H:H) -> 白板 | D73: =_xlfn.XLOOKUP(F73,'6月产品包'!B:B,'6月产品包'!O:O) -> 橡胶白板 | E73: 3B-橡胶磁白板背胶60cm*90cm | F73: T4CC2340730 | G73: 引流款 | H73: ZQ | I73: =_xlfn.XLOOKUP($F73,'6月库存'!A:A,'6月库存'!B:B) -> 正常销售 | K73: =_xlfn.XLOOKUP(E73,'[1]6月分配 '!$B:$B,'[1]6月分配 '!$K:$K) -> #N/A | L73: =IF(ISNUMBER(K73),"是",IF(ISNA(K73),"否","")) -> 否 | M73: =_xlfn.XLOOKUP(F73,'6月产品包'!B:B,'6月产品包'!J:J) -> 2025-07-03 | N73: =IF(DATEDIF(M73,TODAY(),"m")<6,"新品","老品") -> 老品 | O73: =_xlfn.XLOOKUP(F73,'6月库存'!A:A,'6月库存'!R:R) -> 150 | P73: =_xlfn.XLOOKUP(F73,'6月产品包'!B:B,'6月产品包'!S:S) -> 1082 | R73: =_xlfn.XLOOKUP(F73,'6月产品包'!B:B,'6月产品包'!AD:AD) -> 15.8862 | S73: 31 | T73: =ROUND(S73*(1+0.25),0) -> 39 | U73: =$T73*(1-0.2) -> 31.2 | V73: 0.2 | W73: =(U73-R73)/U73 -> 0.49082692 | X73: =(U73*(1-Y73-Z73-AA73-AC73-AB73)-R73)/(U73*(1-Y73-Z73-AA73-AC73-AB73)) -> 0.28656499 | Y73: 0.04 | Z73: 0.1 | AA73: 0.049 | AB73: =$AB$1/U73 -> 0.017307692 | AC73: 0.08 | AD73: 0.05 | AE73: 0.05 | AF73: 不进 | AG73: =MAX(AH73:AN73) -> 0 | AH73: =IF(U73>=50,MIN(MIN(U73*0.2,20)*0.3,6),0) -> 0 | AI73: =IF(U73>=200,MIN(MIN(U73*0.18,70)*0.3,21),0) -> 0 | AJ73: =IF(U73>=380,MIN(MIN(U73*0.28,350)*0.3,105),0) -> 0 | AK73: =IF(U73>=380,MIN(MIN(U73*0.25,350)*0.3,105),0) -> 0 | AL73: =IF(U73>=380,MIN(MIN(U73*0.22,300)*0.3,90),0) -> 0 | AM73: =IF(U73>=250,MIN(MIN(U73*0.18,120)*0.3,36),0) -> 0 | AN73: =IF(U73>=180,MIN(MIN(U73*0.15,60)*0.3,18),0) -> 0
A74: =_xlfn.XLOOKUP(F74,'6月产品包'!B:B,'6月产品包'!F:F) -> 办公安防 | B74: =_xlfn.XLOOKUP(F74,'6月产品包'!B:B,'6月产品包'!G:G) -> 教学周边 | C74: =_xlfn.XLOOKUP(F74,'6月产品包'!B:B,'6月产品包'!H:H) -> 白板 | D74: =_xlfn.XLOOKUP(F74,'6月产品包'!B:B,'6月产品包'!O:O) -> 磁吸白板密度板夹层 | E74: =_xlfn.XLOOKUP(F74,'6月产品包'!B:B,'6月产品包'!C:C) -> 3B-磁吸白板密度板夹层60cm*90cm | F74: T5CC2830903 | G74: 利润款 | H74: ZQ | I74: =_xlfn.XLOOKUP($F74,'6月库存'!A:A,'6月库存'!B:B) -> 等待开发 | K74: =_xlfn.XLOOKUP(E74,'[1]6月分配 '!$B:$B,'[1]6月分配 '!$K:$K) -> 17118 | L74: =IF(ISNUMBER(K74),"是",IF(ISNA(K74),"否","")) -> 是 | M74: =_xlfn.XLOOKUP(F74,'6月产品包'!B:B,'6月产品包'!J:J) -> 2026-04-28 | N74: 新品 | O74: =_xlfn.XLOOKUP(F74,'6月库存'!A:A,'6月库存'!R:R) -> 0 | P74: =_xlfn.XLOOKUP(F74,'6月产品包'!B:B,'6月产品包'!S:S) -> 3461 | R74: =_xlfn.XLOOKUP(F74,'6月产品包'!B:B,'6月产品包'!AD:AD) -> 19.6388 | S74: 42 | T74: =ROUND(S74*(1+0.25),0) -> 53 | U74: =$T74*(1-0.2) -> 42.4 | V74: 0.2 | W74: =(U74-R74)/U74 -> 0.53682075 | X74: =(U74*(1-Y74-Z74-AA74-AC74-AB74)-R74)/(U74*(1-Y74-Z74-AA74-AC74-AB74)) -> 0.3551408 | Y74: 0.04 | Z74: 0.1 | AA74: 0.049 | AB74: =$AB$1/U74 -> 0.012735849 | AC74: 0.08 | AD74: 0.05 | AE74: 0.05 | AF74: 原价进 | AG74: =MAX(AH74:AN74) -> 0 | AH74: =IF(U74>=50,MIN(MIN(U74*0.2,20)*0.3,6),0) -> 0 | AI74: =IF(U74>=200,MIN(MIN(U74*0.18,70)*0.3,21),0) -> 0 | AJ74: =IF(U74>=380,MIN(MIN(U74*0.28,350)*0.3,105),0) -> 0 | AK74: =IF(U74>=380,MIN(MIN(U74*0.25,350)*0.3,105),0) -> 0 | AL74: =IF(U74>=380,MIN(MIN(U74*0.22,300)*0.3,90),0) -> 0 | AM74: =IF(U74>=250,MIN(MIN(U74*0.18,120)*0.3,36),0) -> 0 | AN74: =IF(U74>=180,MIN(MIN(U74*0.15,60)*0.3,18),0) -> 0
A75: 办公安防 | B75: 智能安防 | C75: =_xlfn.XLOOKUP(F75,'6月产品包'!B:B,'6月产品包'!H:H) -> 密码锁 | D75: =_xlfn.XLOOKUP(F75,'6月产品包'!B:B,'6月产品包'!O:O) -> 玻璃门U型密码锁 | E75: 3B-玻璃门U型密码锁 | F75: T4CC2550847 | G75: #N/A | H75: ZQ | I75: =_xlfn.XLOOKUP($F75,'6月库存'!A:A,'6月库存'!B:B) -> 正常销售 | K75: =_xlfn.XLOOKUP(E75,'[1]6月分配 '!$B:$B,'[1]6月分配 '!$K:$K) -> #N/A | L75: =IF(ISNUMBER(K75),"是",IF(ISNA(K75),"否","")) -> 否 | M75: =_xlfn.XLOOKUP(F75,'6月产品包'!B:B,'6月产品包'!J:J) -> 2025-10-21 | N75: =IF(DATEDIF(M75,TODAY(),"m")<6,"新品","老品") -> 老品 | O75: =_xlfn.XLOOKUP(F75,'6月库存'!A:A,'6月库存'!R:R) -> 1 | P75: =_xlfn.XLOOKUP(F75,'6月产品包'!B:B,'6月产品包'!S:S) -> 1260 | R75: =_xlfn.XLOOKUP(F75,'6月产品包'!B:B,'6月产品包'!AD:AD) -> 16.2516 | S75: 32 | T75: =ROUND(S75*(1+0.25),0) -> 40 | U75: =$T75*(1-0.2) -> 32 | V75: 0.2 | W75: =(U75-R75)/U75 -> 0.4921375 | X75: =(U75*(1-Y75-Z75-AA75-AC75-AB75)-R75)/(U75*(1-Y75-Z75-AA75-AC75-AB75)) -> 0.29573583 | Y75: 0.038 | Z75: 0.115 | AA75: 0.049 | AB75: =$AB$1/U75 -> 0.016875 | AC75: 0.06 | AF75: 不进 | AG75: =MAX(AH75:AN75) -> 0 | AH75: =IF(U75>=50,MIN(MIN(U75*0.2,20)*0.3,6),0) -> 0 | AI75: =IF(U75>=200,MIN(MIN(U75*0.18,70)*0.3,21),0) -> 0 | AJ75: =IF(U75>=380,MIN(MIN(U75*0.28,350)*0.3,105),0) -> 0 | AK75: =IF(U75>=380,MIN(MIN(U75*0.25,350)*0.3,105),0) -> 0 | AL75: =IF(U75>=380,MIN(MIN(U75*0.22,300)*0.3,90),0) -> 0 | AM75: =IF(U75>=250,MIN(MIN(U75*0.18,120)*0.3,36),0) -> 0 | AN75: =IF(U75>=180,MIN(MIN(U75*0.15,60)*0.3,18),0) -> 0
A76: 办公安防 | B76: 储能设备 | C76: =_xlfn.XLOOKUP(F76,'6月产品包'!B:B,'6月产品包'!H:H) -> 启动电源 | D76: =_xlfn.XLOOKUP(F76,'6月产品包'!B:B,'6月产品包'!O:O) -> 启动电源N20 | E76: 3B-启动电源N20 | F76: T4CC2250852 | G76: 灭款 | H76: MD | I76: =_xlfn.XLOOKUP($F76,'6月库存'!A:A,'6月库存'!B:B) -> 正常销售 | K76: =_xlfn.XLOOKUP(E76,'[1]6月分配 '!$B:$B,'[1]6月分配 '!$K:$K) -> 15858 | L76: =IF(ISNUMBER(K76),"是",IF(ISNA(K76),"否","")) -> 是 | M76: =_xlfn.XLOOKUP(F76,'6月产品包'!B:B,'6月产品包'!J:J) -> 2025-09-27 | N76: =IF(DATEDIF(M76,TODAY(),"m")<6,"新品","老品") -> 老品 | O76: =_xlfn.XLOOKUP(F76,'6月库存'!A:A,'6月库存'!R:R) -> 53 | P76: =_xlfn.XLOOKUP(F76,'6月产品包'!B:B,'6月产品包'!S:S) -> 1550 | R76: =_xlfn.XLOOKUP(F76,'6月产品包'!B:B,'6月产品包'!AD:AD) -> 125.1398 | S76: 229 | T76: =ROUND(S76*(1+0.25),0) -> 286 | U76: =$T76*(1-0.2) -> 228.8 | V76: 0.2 | W76: =(U76-R76)/U76 -> 0.45306031 | X76: =(U76*(1-Y76-Z76-AA76-AC76-AB76)-R76)/(U76*(1-Y76-Z76-AA76-AC76-AB76)) -> 0.26648277 | Y76: 0.038 | Z76: 0.105 | AA76: 0.049 | AB76: =$AB$1/U76 -> 0.0023601399 | AC76: 0.06 | AF76: 原价进 | AG76: =MAX(AH76:AN76) -> 12.3552 | AH76: =IF(U76>=50,MIN(MIN(U76*0.2,20)*0.3,6),0) -> 6 | AI76: =IF(U76>=200,MIN(MIN(U76*0.18,70)*0.3,21),0) -> 12.3552 | AJ76: =IF(U76>=380,MIN(MIN(U76*0.28,350)*0.3,105),0) -> 0 | AK76: =IF(U76>=380,MIN(MIN(U76*0.25,350)*0.3,105),0) -> 0 | AL76: =IF(U76>=380,MIN(MIN(U76*0.22,300)*0.3,90),0) -> 0 | AM76: =IF(U76>=250,MIN(MIN(U76*0.18,120)*0.3,36),0) -> 0 | AN76: =IF(U76>=180,MIN(MIN(U76*0.15,60)*0.3,18),0) -> 10.296
A77: 办公安防 | B77: 智能安防 | C77: =_xlfn.XLOOKUP(F77,'6月产品包'!B:B,'6月产品包'!H:H) -> 密码锁 | D77: =_xlfn.XLOOKUP(F77,'6月产品包'!B:B,'6月产品包'!O:O) -> B1A五功能断桥铝锁带APP | E77: 3B-B1A五功能断桥铝锁带APP | F77: T4CC2530876 | G77: 利润款 | H77: ZQ | I77: =_xlfn.XLOOKUP($F77,'6月库存'!A:A,'6月库存'!B:B) -> 正常销售 | K77: =_xlfn.XLOOKUP(E77,'[1]6月分配 '!$B:$B,'[1]6月分配 '!$K:$K) -> 15584 | L77: =IF(ISNUMBER(K77),"是",IF(ISNA(K77),"否","")) -> 是 | M77: =_xlfn.XLOOKUP(F77,'6月产品包'!B:B,'6月产品包'!J:J) -> 2025-10-30 | N77: =IF(DATEDIF(M77,TODAY(),"m")<6,"新品","老品") -> 老品 | O77: =_xlfn.XLOOKUP(F77,'6月库存'!A:A,'6月库存'!R:R) -> 87 | P77: =_xlfn.XLOOKUP(F77,'6月产品包'!B:B,'6月产品包'!S:S) -> 1478 | R77: =_xlfn.XLOOKUP(F77,'6月产品包'!B:B,'6月产品包'!AD:AD) -> 102.7122 | S77: 206 | T77: =ROUND(S77*(1+0.25),0) -> 258 | U77: =$T77*(1-0.2) -> 206.4 | V77: 0.2 | W77: =(U77-R77)/U77 -> 0.50236337 | X77: =(U77*(1-Y77-Z77-AA77-AC77-AB77)-R77)/(U77*(1-Y77-Z77-AA77-AC77-AB77)) -> 0.32329665 | Y77: 0.038 | Z77: 0.115 | AA77: 0.049 | AB77: =$AB$1/U77 -> 0.0026162791 | AC77: 0.06 | AF77: 原价进 | AG77: =MAX(AH77:AN77) -> 11.1456 | AH77: =IF(U77>=50,MIN(MIN(U77*0.2,20)*0.3,6),0) -> 6 | AI77: =IF(U77>=200,MIN(MIN(U77*0.18,70)*0.3,21),0) -> 11.1456 | AJ77: =IF(U77>=380,MIN(MIN(U77*0.28,350)*0.3,105),0) -> 0 | AK77: =IF(U77>=380,MIN(MIN(U77*0.25,350)*0.3,105),0) -> 0 | AL77: =IF(U77>=380,MIN(MIN(U77*0.22,300)*0.3,90),0) -> 0 | AM77: =IF(U77>=250,MIN(MIN(U77*0.18,120)*0.3,36),0) -> 0 | AN77: =IF(U77>=180,MIN(MIN(U77*0.15,60)*0.3,18),0) -> 9.288
A78: 办公安防 | B78: 办公周边 | C78: =_xlfn.XLOOKUP(F78,'6月产品包'!B:B,'6月产品包'!H:H) -> 碎纸机 | D78: =_xlfn.XLOOKUP(F78,'6月产品包'!B:B,'6月产品包'!O:O) -> 碎纸机7L | E78: 3B-碎纸机7L | F78: M4CC2410758 | G78: #N/A | H78: ZQ | I78: =_xlfn.XLOOKUP($F78,'6月库存'!A:A,'6月库存'!B:B) -> 正常销售 | K78: =_xlfn.XLOOKUP(E78,'[1]6月分配 '!$B:$B,'[1]6月分配 '!$K:$K) -> 15417 | L78: =IF(ISNUMBER(K78),"是",IF(ISNA(K78),"否","")) -> 是 | M78: =_xlfn.XLOOKUP(F78,'6月产品包'!B:B,'6月产品包'!J:J) -> 2025-07-29 | N78: =IF(DATEDIF(M78,TODAY(),"m")<6,"新品","老品") -> 老品 | O78: =_xlfn.XLOOKUP(F78,'6月库存'!A:A,'6月库存'!R:R) -> 377 | P78: =_xlfn.XLOOKUP(F78,'6月产品包'!B:B,'6月产品包'!S:S) -> 1710 | R78: =_xlfn.XLOOKUP(F78,'6月产品包'!B:B,'6月产品包'!AD:AD) -> 43.4072 | S78: 82 | T78: =ROUND(S78*(1+0.25),0) -> 103 | U78: =$T78*(1-0.2) -> 82.4 | V78: 0.2 | W78: =(U78-R78)/U78 -> 0.47321359 | X78: =(U78*(1-Y78-Z78-AA78-AC78-AB78)-R78)/(U78*(1-Y78-Z78-AA78-AC78-AB78)) -> 0.29427449 | Y78: 0.038 | Z78: 0.1 | AA78: 0.049 | AB78: =$AB$1/U78 -> 0.0065533981 | AC78: 0.06 | AF78: 原价进 | AG78: =MAX(AH78:AN78) -> 4.944 | AH78: =IF(U78>=50,MIN(MIN(U78*0.2,20)*0.3,6),0) -> 4.944 | AI78: =IF(U78>=200,MIN(MIN(U78*0.18,70)*0.3,21),0) -> 0 | AJ78: =IF(U78>=380,MIN(MIN(U78*0.28,350)*0.3,105),0) -> 0 | AK78: =IF(U78>=380,MIN(MIN(U78*0.25,350)*0.3,105),0) -> 0 | AL78: =IF(U78>=380,MIN(MIN(U78*0.22,300)*0.3,90),0) -> 0 | AM78: =IF(U78>=250,MIN(MIN(U78*0.18,120)*0.3,36),0) -> 0 | AN78: =IF(U78>=180,MIN(MIN(U78*0.15,60)*0.3,18),0) -> 0
A79: 3C数码 | B79: 电脑周边 | C79: =_xlfn.XLOOKUP(F79,'6月产品包'!B:B,'6月产品包'!H:H) -> 显示器支架 | D79: =_xlfn.XLOOKUP(F79,'6月产品包'!B:B,'6月产品包'!O:O) -> 显示器桌面支架 | E79: 3C-显示器桌面支架3屏 | F79: T4CC1120807 | G79: #N/A | H79: ZQ | I79: =_xlfn.XLOOKUP($F79,'6月库存'!A:A,'6月库存'!B:B) -> 正常销售 | K79: =_xlfn.XLOOKUP(E79,'[1]6月分配 '!$B:$B,'[1]6月分配 '!$K:$K) -> 15268 | L79: =IF(ISNUMBER(K79),"是",IF(ISNA(K79),"否","")) -> 是 | M79: =_xlfn.XLOOKUP(F79,'6月产品包'!B:B,'6月产品包'!J:J) -> 2025-09-11 | N79: =IF(DATEDIF(M79,TODAY(),"m")<6,"新品","老品") -> 老品 | O79: =_xlfn.XLOOKUP(F79,'6月库存'!A:A,'6月库存'!R:R) -> 143 | P79: =_xlfn.XLOOKUP(F79,'6月产品包'!B:B,'6月产品包'!S:S) -> 5300 | R79: =_xlfn.XLOOKUP(F79,'6月产品包'!B:B,'6月产品包'!AD:AD) -> 51.939 | S79: 99 | T79: =ROUND(S79*(1+0.25),0) -> 124 | U79: =$T79*(1-0.2) -> 99.2 | V79: 0.2 | W79: =(U79-R79)/U79 -> 0.47642137 | X79: =(U79*(1-Y79-Z79-AA79-AC79-AB79)-R79)/(U79*(1-Y79-Z79-AA79-AC79-AB79)) -> 0.29299295 | Y79: 0.04 | Z79: 0.105 | AA79: 0.049 | AB79: =$AB$1/U79 -> 0.0054435484 | AC79: 0.06 | AF79: 原价进 | AG79: =MAX(AH79:AN79) -> 5.952 | AH79: =IF(U79>=50,MIN(MIN(U79*0.2,20)*0.3,6),0) -> 5.952 | AI79: =IF(U79>=200,MIN(MIN(U79*0.18,70)*0.3,21),0) -> 0 | AJ79: =IF(U79>=380,MIN(MIN(U79*0.28,350)*0.3,105),0) -> 0 | AK79: =IF(U79>=380,MIN(MIN(U79*0.25,350)*0.3,105),0) -> 0 | AL79: =IF(U79>=380,MIN(MIN(U79*0.22,300)*0.3,90),0) -> 0 | AM79: =IF(U79>=250,MIN(MIN(U79*0.18,120)*0.3,36),0) -> 0 | AN79: =IF(U79>=180,MIN(MIN(U79*0.15,60)*0.3,18),0) -> 0
A80: =_xlfn.XLOOKUP(F80,'6月产品包'!B:B,'6月产品包'!F:F) -> 3C数码 | B80: =_xlfn.XLOOKUP(F80,'6月产品包'!B:B,'6月产品包'!G:G) -> 电视设备 | C80: =_xlfn.XLOOKUP(F80,'6月产品包'!B:B,'6月产品包'!H:H) -> 电视支架 | D80: =_xlfn.XLOOKUP(F80,'6月产品包'!B:B,'6月产品包'!O:O) -> 移动推车MY01 | E80: =_xlfn.XLOOKUP(F80,'6月产品包'!B:B,'6月产品包'!C:C) -> 3C-单柱旋转移动推车MY01 | F80: T5CC1121057 | G80: 利润款 | H80: MD | I80: =_xlfn.XLOOKUP($F80,'6月库存'!A:A,'6月库存'!B:B) -> 正常销售 | K80: =_xlfn.XLOOKUP(E80,'[1]6月分配 '!$B:$B,'[1]6月分配 '!$K:$K) -> 15034 | L80: =IF(ISNUMBER(K80),"是",IF(ISNA(K80),"否","")) -> 是 | M80: =_xlfn.XLOOKUP(F80,'6月产品包'!B:B,'6月产品包'!J:J) -> 2026-04-07 | N80: =IF(DATEDIF(M80,TODAY(),"m")<6,"新品","老品") -> 新品 | O80: =_xlfn.XLOOKUP(F80,'6月库存'!A:A,'6月库存'!R:R) -> 107 | P80: =_xlfn.XLOOKUP(F80,'6月产品包'!B:B,'6月产品包'!S:S) -> 12300 | R80: =_xlfn.XLOOKUP(F80,'6月产品包'!B:B,'6月产品包'!AD:AD) -> 78.5552 | S80: 149 | T80: =ROUND(S80*(1+0.25),0) -> 186 | U80: =$T80*(1-0.2) -> 148.8 | V80: 0.2 | W80: =(U80-R80)/U80 -> 0.47207527 | X80: =(U80*(1-Y80-Z80-AA80-AC80-AB80)-R80)/(U80*(1-Y80-Z80-AA80-AC80-AB80)) -> 0.30478679 | Y80: 0.038 | Z80: 0.09 | AA80: 0.049 | AB80: =$AB$1/U80 -> 0.0036290323 | AC80: 0.06 | AF80: 原价进 | AG80: =MAX(AH80:AN80) -> 6 | AH80: =IF(U80>=50,MIN(MIN(U80*0.2,20)*0.3,6),0) -> 6 | AI80: =IF(U80>=200,MIN(MIN(U80*0.18,70)*0.3,21),0) -> 0 | AJ80: =IF(U80>=380,MIN(MIN(U80*0.28,350)*0.3,105),0) -> 0 | AK80: =IF(U80>=380,MIN(MIN(U80*0.25,350)*0.3,105),0) -> 0 | AL80: =IF(U80>=380,MIN(MIN(U80*0.22,300)*0.3,90),0) -> 0 | AM80: =IF(U80>=250,MIN(MIN(U80*0.18,120)*0.3,36),0) -> 0 | AN80: =IF(U80>=180,MIN(MIN(U80*0.15,60)*0.3,18),0) -> 0
A81: 办公安防 | B81: 办公周边 | C81: =_xlfn.XLOOKUP(F81,'6月产品包'!B:B,'6月产品包'!H:H) -> 广告架 | D81: =_xlfn.XLOOKUP(F81,'6月产品包'!B:B,'6月产品包'!O:O) -> 广告架kt板 | E81: 3B-广告架kt板斜面3.5kg | F81: T4CC1120859 | G81: 引流款 | H81: ZQ | I81: =_xlfn.XLOOKUP($F81,'6月库存'!A:A,'6月库存'!B:B) -> 正常销售 | K81: =_xlfn.XLOOKUP(E81,'[1]6月分配 '!$B:$B,'[1]6月分配 '!$K:$K) -> 14653 | L81: =IF(ISNUMBER(K81),"是",IF(ISNA(K81),"否","")) -> 是 | M81: =_xlfn.XLOOKUP(F81,'6月产品包'!B:B,'6月产品包'!J:J) -> 2025-10-09 | N81: =IF(DATEDIF(M81,TODAY(),"m")<6,"新品","老品") -> 老品 | O81: =_xlfn.XLOOKUP(F81,'6月库存'!A:A,'6月库存'!R:R) -> 209 | P81: =_xlfn.XLOOKUP(F81,'6月产品包'!B:B,'6月产品包'!S:S) -> 1500 | R81: =_xlfn.XLOOKUP(F81,'6月产品包'!B:B,'6月产品包'!AD:AD) -> 28.5186 | S81: 55 | T81: =ROUND(S81*(1+0.25),0) -> 69 | U81: =$T81*(1-0.2) -> 55.2 | V81: 0.2 | W81: =(U81-R81)/U81 -> 0.4833587 | X81: =(U81*(1-Y81-Z81-AA81-AC81-AB81)-R81)/(U81*(1-Y81-Z81-AA81-AC81-AB81)) -> 0.30485843 | Y81: 0.038 | Z81: 0.1 | AA81: 0.049 | AB81: =$AB$1/U81 -> 0.0097826087 | AC81: 0.06 | AF81: 原价进 | AG81: =MAX(AH81:AN81) -> 3.312 | AH81: =IF(U81>=50,MIN(MIN(U81*0.2,20)*0.3,6),0) -> 3.312 | AI81: =IF(U81>=200,MIN(MIN(U81*0.18,70)*0.3,21),0) -> 0 | AJ81: =IF(U81>=380,MIN(MIN(U81*0.28,350)*0.3,105),0) -> 0 | AK81: =IF(U81>=380,MIN(MIN(U81*0.25,350)*0.3,105),0) -> 0 | AL81: =IF(U81>=380,MIN(MIN(U81*0.22,300)*0.3,90),0) -> 0 | AM81: =IF(U81>=250,MIN(MIN(U81*0.18,120)*0.3,36),0) -> 0 | AN81: =IF(U81>=180,MIN(MIN(U81*0.15,60)*0.3,18),0) -> 0
A82: 3C数码 | B82: 电脑周边 | C82: =_xlfn.XLOOKUP(F82,'6月产品包'!B:B,'6月产品包'!H:H) -> 无线蓝牙鼠标 | D82: =_xlfn.XLOOKUP(F82,'6月产品包'!B:B,'6月产品包'!O:O) -> 蓝牙鼠标 | E82: 3C-半透明蓝牙RGB背光鼠标黑色 | F82: T3CC2070276 | G82: 灭款 | H82: MD | I82: =_xlfn.XLOOKUP($F82,'6月库存'!A:A,'6月库存'!B:B) -> 商品清仓 | K82: =_xlfn.XLOOKUP(E82,'[1]6月分配 '!$B:$B,'[1]6月分配 '!$K:$K) -> #N/A | L82: =IF(ISNUMBER(K82),"是",IF(ISNA(K82),"否","")) -> 否 | M82: =_xlfn.XLOOKUP(F82,'6月产品包'!B:B,'6月产品包'!J:J) -> 2024-10-29 | N82: =IF(DATEDIF(M82,TODAY(),"m")<6,"新品","老品") -> 老品 | O82: =_xlfn.XLOOKUP(F82,'6月库存'!A:A,'6月库存'!R:R) -> 0 | P82: =_xlfn.XLOOKUP(F82,'6月产品包'!B:B,'6月产品包'!S:S) -> 122 | R82: =_xlfn.XLOOKUP(F82,'6月产品包'!B:B,'6月产品包'!AD:AD) -> 14.4594 | S82: 24.65 | T82: =ROUND(S82*(1+0.25),0) -> 31 | U82: =$T82*(1-0.2) -> 24.8 | V82: 0.2 | W82: =(U82-R82)/U82 -> 0.41695968 | X82: =(U82*(1-Y82-Z82-AA82-AC82-AB82)-R82)/(U82*(1-Y82-Z82-AA82-AC82-AB82)) -> 0.20046669 | Y82: 0.04 | Z82: 0.1 | AA82: 0.049 | AB82: =$AB$1/U82 -> 0.021774194 | AC82: 0.06 | AF82: 不进 | AG82: =MAX(AH82:AN82) -> 0 | AH82: =IF(U82>=50,MIN(MIN(U82*0.2,20)*0.3,6),0) -> 0 | AI82: =IF(U82>=200,MIN(MIN(U82*0.18,70)*0.3,21),0) -> 0 | AJ82: =IF(U82>=380,MIN(MIN(U82*0.28,350)*0.3,105),0) -> 0 | AK82: =IF(U82>=380,MIN(MIN(U82*0.25,350)*0.3,105),0) -> 0 | AL82: =IF(U82>=380,MIN(MIN(U82*0.22,300)*0.3,90),0) -> 0 | AM82: =IF(U82>=250,MIN(MIN(U82*0.18,120)*0.3,36),0) -> 0 | AN82: =IF(U82>=180,MIN(MIN(U82*0.15,60)*0.3,18),0) -> 0
A83: 办公安防 | B83: 安防存储 | C83: =_xlfn.XLOOKUP(F83,'6月产品包'!B:B,'6月产品包'!H:H) -> 保险箱 | D83: =_xlfn.XLOOKUP(F83,'6月产品包'!B:B,'6月产品包'!O:O) -> 小尺寸保险箱 | E83: 3B-密码保险箱黑 | F83: T2CC1200315 | G83: 平销款 | H83: ZQ | I83: =_xlfn.XLOOKUP($F83,'6月库存'!A:A,'6月库存'!B:B) -> 正常销售 | K83: =_xlfn.XLOOKUP(E83,'[1]6月分配 '!$B:$B,'[1]6月分配 '!$K:$K) -> 14593 | L83: =IF(ISNUMBER(K83),"是",IF(ISNA(K83),"否","")) -> 是 | M83: =_xlfn.XLOOKUP(F83,'6月产品包'!B:B,'6月产品包'!J:J) -> 2024-11-01 | N83: =IF(DATEDIF(M83,TODAY(),"m")<6,"新品","老品") -> 老品 | O83: =_xlfn.XLOOKUP(F83,'6月库存'!A:A,'6月库存'!R:R) -> 0 | P83: =_xlfn.XLOOKUP(F83,'6月产品包'!B:B,'6月产品包'!S:S) -> 6575 | R83: =_xlfn.XLOOKUP(F83,'6月产品包'!B:B,'6月产品包'!AD:AD) -> 85.8574 | S83: 169 | T83: =ROUND(S83*(1+0.25),0) -> 211 | U83: =$T83*(1-0.2) -> 168.8 | V83: 0.2 | W83: =(U83-R83)/U83 -> 0.49136611 | X83: =(U83*(1-Y83-Z83-AA83-AC83-AB83)-R83)/(U83*(1-Y83-Z83-AA83-AC83-AB83)) -> 0.31982717 | Y83: 0.04 | Z83: 0.1 | AA83: 0.049 | AB83: =$AB$1/U83 -> 0.0031990521 | AC83: 0.06 | AD83: 0.05 | AE83: 0.03 | AF83: 原价进 | AG83: =MAX(AH83:AN83) -> 6 | AH83: =IF(U83>=50,MIN(MIN(U83*0.2,20)*0.3,6),0) -> 6 | AI83: =IF(U83>=200,MIN(MIN(U83*0.18,70)*0.3,21),0) -> 0 | AJ83: =IF(U83>=380,MIN(MIN(U83*0.28,350)*0.3,105),0) -> 0 | AK83: =IF(U83>=380,MIN(MIN(U83*0.25,350)*0.3,105),0) -> 0 | AL83: =IF(U83>=380,MIN(MIN(U83*0.22,300)*0.3,90),0) -> 0 | AM83: =IF(U83>=250,MIN(MIN(U83*0.18,120)*0.3,36),0) -> 0 | AN83: =IF(U83>=180,MIN(MIN(U83*0.15,60)*0.3,18),0) -> 0
A84: 办公安防 | B84: 安防存储 | C84: =_xlfn.XLOOKUP(F84,'6月产品包'!B:B,'6月产品包'!H:H) -> 保险箱 | D84: =_xlfn.XLOOKUP(F84,'6月产品包'!B:B,'6月产品包'!O:O) -> 小尺寸保险箱 | E84: 3B-密码保险箱黑 | F84: T3CC2160315 | G84: 平销款 | H84: ZQ | I84: =_xlfn.XLOOKUP($F84,'6月库存'!A:A,'6月库存'!B:B) -> 正常销售 | K84: =_xlfn.XLOOKUP(E84,'[1]6月分配 '!$B:$B,'[1]6月分配 '!$K:$K) -> 14593 | L84: =IF(ISNUMBER(K84),"是",IF(ISNA(K84),"否","")) -> 是 | M84: =_xlfn.XLOOKUP(F84,'6月产品包'!B:B,'6月产品包'!J:J) -> 2024-11-21 | N84: =IF(DATEDIF(M84,TODAY(),"m")<6,"新品","老品") -> 老品 | O84: =_xlfn.XLOOKUP(F84,'6月库存'!A:A,'6月库存'!R:R) -> 349 | P84: =_xlfn.XLOOKUP(F84,'6月产品包'!B:B,'6月产品包'!S:S) -> 6700 | R84: =_xlfn.XLOOKUP(F84,'6月产品包'!B:B,'6月产品包'!AD:AD) -> 72.3434 | S84: 142 | T84: =ROUND(S84*(1+0.25),0) -> 178 | U84: =$T84*(1-0.2) -> 142.4 | V84: 0.2 | W84: =(U84-R84)/U84 -> 0.49197051 | X84: =(U84*(1-Y84-Z84-AA84-AC84-AB84)-R84)/(U84*(1-Y84-Z84-AA84-AC84-AB84)) -> 0.32009616 | Y84: 0.04 | Z84: 0.1 | AA84: 0.049 | AB84: =$AB$1/U84 -> 0.0037921348 | AC84: 0.06 | AD84: 0.05 | AE84: 0.03 | AF84: 原价进 | AG84: =MAX(AH84:AN84) -> 6 | AH84: =IF(U84>=50,MIN(MIN(U84*0.2,20)*0.3,6),0) -> 6 | AI84: =IF(U84>=200,MIN(MIN(U84*0.18,70)*0.3,21),0) -> 0 | AJ84: =IF(U84>=380,MIN(MIN(U84*0.28,350)*0.3,105),0) -> 0 | AK84: =IF(U84>=380,MIN(MIN(U84*0.25,350)*0.3,105),0) -> 0 | AL84: =IF(U84>=380,MIN(MIN(U84*0.22,300)*0.3,90),0) -> 0 | AM84: =IF(U84>=250,MIN(MIN(U84*0.18,120)*0.3,36),0) -> 0 | AN84: =IF(U84>=180,MIN(MIN(U84*0.15,60)*0.3,18),0) -> 0
A85: 办公安防 | B85: 教学周边 | C85: =_xlfn.XLOOKUP(F85,'6月产品包'!B:B,'6月产品包'!H:H) -> 白板 | D85: =_xlfn.XLOOKUP(F85,'6月产品包'!B:B,'6月产品包'!O:O) -> 磁吸白板密度板夹层 | E85: 3B-磁吸白板密度板夹层90cm*120cm | F85: T4CC2340905 | G85: 平销款 | H85: ZQ | I85: =_xlfn.XLOOKUP($F85,'6月库存'!A:A,'6月库存'!B:B) -> 正常销售 | K85: =_xlfn.XLOOKUP(E85,'[1]6月分配 '!$B:$B,'[1]6月分配 '!$K:$K) -> 14249 | L85: =IF(ISNUMBER(K85),"是",IF(ISNA(K85),"否","")) -> 是 | M85: =_xlfn.XLOOKUP(F85,'6月产品包'!B:B,'6月产品包'!J:J) -> 2025-10-27 | N85: 新品 | O85: =_xlfn.XLOOKUP(F85,'6月库存'!A:A,'6月库存'!R:R) -> 838 | P85: =_xlfn.XLOOKUP(F85,'6月产品包'!B:B,'6月产品包'!S:S) -> 6660 | R85: =_xlfn.XLOOKUP(F85,'6月产品包'!B:B,'6月产品包'!AD:AD) -> 45.6634 | S85: 92 | T85: =ROUND(S85*(1+0.25),0) -> 115 | U85: =$T85*(1-0.2) -> 92 | V85: 0.2 | W85: =(U85-R85)/U85 -> 0.5036587 | X85: =(U85*(1-Y85-Z85-AA85-AC85-AB85)-R85)/(U85*(1-Y85-Z85-AA85-AC85-AB85)) -> 0.31551445 | Y85: 0.04 | Z85: 0.1 | AA85: 0.049 | AB85: =$AB$1/U85 -> 0.0058695652 | AC85: 0.08 | AD85: 0.05 | AE85: 0.05 | AF85: 原价进 | AG85: =MAX(AH85:AN85) -> 5.52 | AH85: =IF(U85>=50,MIN(MIN(U85*0.2,20)*0.3,6),0) -> 5.52 | AI85: =IF(U85>=200,MIN(MIN(U85*0.18,70)*0.3,21),0) -> 0 | AJ85: =IF(U85>=380,MIN(MIN(U85*0.28,350)*0.3,105),0) -> 0 | AK85: =IF(U85>=380,MIN(MIN(U85*0.25,350)*0.3,105),0) -> 0 | AL85: =IF(U85>=380,MIN(MIN(U85*0.22,300)*0.3,90),0) -> 0 | AM85: =IF(U85>=250,MIN(MIN(U85*0.18,120)*0.3,36),0) -> 0 | AN85: =IF(U85>=180,MIN(MIN(U85*0.15,60)*0.3,18),0) -> 0
A86: =_xlfn.XLOOKUP(F86,'6月产品包'!B:B,'6月产品包'!F:F) -> 3C数码 | B86: =_xlfn.XLOOKUP(F86,'6月产品包'!B:B,'6月产品包'!G:G) -> 影像摄影 | C86: =_xlfn.XLOOKUP(F86,'6月产品包'!B:B,'6月产品包'!H:H) -> LED像素屏 | D86: =_xlfn.XLOOKUP(F86,'6月产品包'!B:B,'6月产品包'!O:O) -> 互动屏 | E86: =_xlfn.XLOOKUP(F86,'6月产品包'!B:B,'6月产品包'!C:C) -> 3C-led智能互动屏34.8cm*10.2cm | F86: T4CC2320726 | G86: 平销款 | H86: MD | I86: =_xlfn.XLOOKUP($F86,'6月库存'!A:A,'6月库存'!B:B) -> 正常销售 | K86: =_xlfn.XLOOKUP(E86,'[1]6月分配 '!$B:$B,'[1]6月分配 '!$K:$K) -> #N/A | L86: =IF(ISNUMBER(K86),"是",IF(ISNA(K86),"否","")) -> 否 | M86: =_xlfn.XLOOKUP(F86,'6月产品包'!B:B,'6月产品包'!J:J) -> 2025-07-10 | N86: =IF(DATEDIF(M86,TODAY(),"m")<6,"新品","老品") -> 老品 | O86: =_xlfn.XLOOKUP(F86,'6月库存'!A:A,'6月库存'!R:R) -> 22 | P86: =_xlfn.XLOOKUP(F86,'6月产品包'!B:B,'6月产品包'!S:S) -> 325 | Q86: 350 | R86: =_xlfn.XLOOKUP(F86,'6月产品包'!B:B,'6月产品包'!AD:AD) -> 36.4762 | S86: 70 | T86: =ROUND(S86*(1+0.25),0) -> 88 | U86: =$T86*(1-0.2) -> 70.4 | V86: 0.2 | W86: =(U86-R86)/U86 -> 0.48187216 | X86: =(U86*(1-Y86-Z86-AA86-AC86-AB86)-R86)/(U86*(1-Y86-Z86-AA86-AC86-AB86)) -> 0.29538009 | Y86: 0.038 | Z86: 0.11 | AA86: 0.049 | AB86: =$AB$1/U86 -> 0.0076704545 | AC86: 0.06 | AF86: 不进 | AG86: =MAX(AH86:AN86) -> 4.224 | AH86: =IF(U86>=50,MIN(MIN(U86*0.2,20)*0.3,6),0) -> 4.224 | AI86: =IF(U86>=200,MIN(MIN(U86*0.18,70)*0.3,21),0) -> 0 | AJ86: =IF(U86>=380,MIN(MIN(U86*0.28,350)*0.3,105),0) -> 0 | AK86: =IF(U86>=380,MIN(MIN(U86*0.25,350)*0.3,105),0) -> 0 | AL86: =IF(U86>=380,MIN(MIN(U86*0.22,300)*0.3,90),0) -> 0 | AM86: =IF(U86>=250,MIN(MIN(U86*0.18,120)*0.3,36),0) -> 0 | AN86: =IF(U86>=180,MIN(MIN(U86*0.15,60)*0.3,18),0) -> 0
A87: =_xlfn.XLOOKUP(F87,'6月产品包'!B:B,'6月产品包'!F:F) -> 办公安防 | B87: =_xlfn.XLOOKUP(F87,'6月产品包'!B:B,'6月产品包'!G:G) -> 教学周边 | C87: =_xlfn.XLOOKUP(F87,'6月产品包'!B:B,'6月产品包'!H:H) -> 白板 | D87: =_xlfn.XLOOKUP(F87,'6月产品包'!B:B,'6月产品包'!O:O) -> 磁吸白板密度板夹层 | E87: =_xlfn.XLOOKUP(F87,'6月产品包'!B:B,'6月产品包'!C:C) -> 3B-磁吸白板密度板夹层90cm*120cm | F87: T5CC2830905 | G87: 利润款 | H87: ZQ | I87: =_xlfn.XLOOKUP($F87,'6月库存'!A:A,'6月库存'!B:B) -> 等待开发 | K87: =_xlfn.XLOOKUP(E87,'[1]6月分配 '!$B:$B,'[1]6月分配 '!$K:$K) -> 14249 | L87: =IF(ISNUMBER(K87),"是",IF(ISNA(K87),"否","")) -> 是 | M87: =_xlfn.XLOOKUP(F87,'6月产品包'!B:B,'6月产品包'!J:J) -> 2026-04-16 | N87: 新品 | O87: =_xlfn.XLOOKUP(F87,'6月库存'!A:A,'6月库存'!R:R) -> 0 | P87: =_xlfn.XLOOKUP(F87,'6月产品包'!B:B,'6月产品包'!S:S) -> 6660 | R87: =_xlfn.XLOOKUP(F87,'6月产品包'!B:B,'6月产品包'!AD:AD) -> 44.2772 | S87: 92 | T87: =ROUND(S87*(1+0.25),0) -> 115 | U87: =$T87*(1-0.2) -> 92 | V87: 0.2 | W87: =(U87-R87)/U87 -> 0.51872609 | X87: =(U87*(1-Y87-Z87-AA87-AC87-AB87)-R87)/(U87*(1-Y87-Z87-AA87-AC87-AB87)) -> 0.33629332 | Y87: 0.04 | Z87: 0.1 | AA87: 0.049 | AB87: =$AB$1/U87 -> 0.0058695652 | AC87: 0.08 | AD87: 0.05 | AE87: 0.05 | AF87: 原价进 | AG87: =MAX(AH87:AN87) -> 5.52 | AH87: =IF(U87>=50,MIN(MIN(U87*0.2,20)*0.3,6),0) -> 5.52 | AI87: =IF(U87>=200,MIN(MIN(U87*0.18,70)*0.3,21),0) -> 0 | AJ87: =IF(U87>=380,MIN(MIN(U87*0.28,350)*0.3,105),0) -> 0 | AK87: =IF(U87>=380,MIN(MIN(U87*0.25,350)*0.3,105),0) -> 0 | AL87: =IF(U87>=380,MIN(MIN(U87*0.22,300)*0.3,90),0) -> 0 | AM87: =IF(U87>=250,MIN(MIN(U87*0.18,120)*0.3,36),0) -> 0 | AN87: =IF(U87>=180,MIN(MIN(U87*0.15,60)*0.3,18),0) -> 0
A88: 办公安防 | B88: 教学周边 | C88: =_xlfn.XLOOKUP(F88,'6月产品包'!B:B,'6月产品包'!H:H) -> 白板 | D88: =_xlfn.XLOOKUP(F88,'6月产品包'!B:B,'6月产品包'!O:O) -> 涂鸦板 | E88: 3B-双面涂鸦板45cm*30cm | F88: T4CC2340736 | G88: 引流款 | H88: ZQ | I88: =_xlfn.XLOOKUP($F88,'6月库存'!A:A,'6月库存'!B:B) -> 正常销售 | K88: =_xlfn.XLOOKUP(E88,'[1]6月分配 '!$B:$B,'[1]6月分配 '!$K:$K) -> #N/A | L88: =IF(ISNUMBER(K88),"是",IF(ISNA(K88),"否","")) -> 否 | M88: =_xlfn.XLOOKUP(F88,'6月产品包'!B:B,'6月产品包'!J:J) -> 2025-07-03 | N88: =IF(DATEDIF(M88,TODAY(),"m")<6,"新品","老品") -> 老品 | O88: =_xlfn.XLOOKUP(F88,'6月库存'!A:A,'6月库存'!R:R) -> 0 | P88: =_xlfn.XLOOKUP(F88,'6月产品包'!B:B,'6月产品包'!S:S) -> 320 | R88: =_xlfn.XLOOKUP(F88,'6月产品包'!B:B,'6月产品包'!AD:AD) -> 5.1446 | S88: 11.05 | T88: =ROUND(S88*(1+0.25),0) -> 14 | U88: =$T88*(1-0.2) -> 11.2 | V88: 0.2 | W88: =(U88-R88)/U88 -> 0.54066071 | X88: =(U88*(1-Y88-Z88-AA88-AC88-AB88)-R88)/(U88*(1-Y88-Z88-AA88-AC88-AB88)) -> 0.32725704 | Y88: 0.04 | Z88: 0.1 | AA88: 0.049 | AB88: =$AB$1/U88 -> 0.048214286 | AC88: 0.08 | AD88: 0.05 | AE88: 0.05 | AF88: 不进 | AG88: =MAX(AH88:AN88) -> 0 | AH88: =IF(U88>=50,MIN(MIN(U88*0.2,20)*0.3,6),0) -> 0 | AI88: =IF(U88>=200,MIN(MIN(U88*0.18,70)*0.3,21),0) -> 0 | AJ88: =IF(U88>=380,MIN(MIN(U88*0.28,350)*0.3,105),0) -> 0 | AK88: =IF(U88>=380,MIN(MIN(U88*0.25,350)*0.3,105),0) -> 0 | AL88: =IF(U88>=380,MIN(MIN(U88*0.22,300)*0.3,90),0) -> 0 | AM88: =IF(U88>=250,MIN(MIN(U88*0.18,120)*0.3,36),0) -> 0 | AN88: =IF(U88>=180,MIN(MIN(U88*0.15,60)*0.3,18),0) -> 0
A89: 办公安防 | B89: 储能设备 | C89: =_xlfn.XLOOKUP(F89,'6月产品包'!B:B,'6月产品包'!H:H) -> 太阳能充电板 | D89: =_xlfn.XLOOKUP(F89,'6月产品包'!B:B,'6月产品包'!O:O) -> 电源充电板 | E89: 3B-储能电源光伏充电板 | F89: T4CC3300691 | G89: 利润款 | H89: ZQ | I89: =_xlfn.XLOOKUP($F89,'6月库存'!A:A,'6月库存'!B:B) -> 正常销售 | K89: =_xlfn.XLOOKUP(E89,'[1]6月分配 '!$B:$B,'[1]6月分配 '!$K:$K) -> #N/A | L89: =IF(ISNUMBER(K89),"是",IF(ISNA(K89),"否","")) -> 否 | M89: =_xlfn.XLOOKUP(F89,'6月产品包'!B:B,'6月产品包'!J:J) -> 2025-07-15 | N89: =IF(DATEDIF(M89,TODAY(),"m")<6,"新品","老品") -> 老品 | O89: =_xlfn.XLOOKUP(F89,'6月库存'!A:A,'6月库存'!R:R) -> 0 | P89: =_xlfn.XLOOKUP(F89,'6月产品包'!B:B,'6月产品包'!S:S) -> 845 | R89: =_xlfn.XLOOKUP(F89,'6月产品包'!B:B,'6月产品包'!AD:AD) -> 13.3405 | S89: 26 | T89: =ROUND(S89*(1+0.25),0) -> 33 | U89: =$T89*(1-0.2) -> 26.4 | V89: 0.2 | W89: =(U89-R89)/U89 -> 0.49467803 | X89: =(U89*(1-Y89-Z89-AA89-AC89-AB89)-R89)/(U89*(1-Y89-Z89-AA89-AC89-AB89)) -> 0.30544275 | Y89: 0.038 | Z89: 0.105 | AA89: 0.049 | AB89: =$AB$1/U89 -> 0.020454545 | AC89: 0.06 | AF89: 不进 | AG89: =MAX(AH89:AN89) -> 0 | AH89: =IF(U89>=50,MIN(MIN(U89*0.2,20)*0.3,6),0) -> 0 | AI89: =IF(U89>=200,MIN(MIN(U89*0.18,70)*0.3,21),0) -> 0 | AJ89: =IF(U89>=380,MIN(MIN(U89*0.28,350)*0.3,105),0) -> 0 | AK89: =IF(U89>=380,MIN(MIN(U89*0.25,350)*0.3,105),0) -> 0 | AL89: =IF(U89>=380,MIN(MIN(U89*0.22,300)*0.3,90),0) -> 0 | AM89: =IF(U89>=250,MIN(MIN(U89*0.18,120)*0.3,36),0) -> 0 | AN89: =IF(U89>=180,MIN(MIN(U89*0.15,60)*0.3,18),0) -> 0
A90: 3C数码 | B90: 音响乐器 | C90: =_xlfn.XLOOKUP(F90,'6月产品包'!B:B,'6月产品包'!H:H) -> 有线麦克风 | D90: =_xlfn.XLOOKUP(F90,'6月产品包'!B:B,'6月产品包'!O:O) -> 动圈麦克风 | E90: 3C-专业播客动圈麦克风 | F90: T4CC2670996 | G90: 引流款/新品 | H90: ZQ | I90: =_xlfn.XLOOKUP($F90,'6月库存'!A:A,'6月库存'!B:B) -> 正常销售 | K90: =_xlfn.XLOOKUP(E90,'[1]6月分配 '!$B:$B,'[1]6月分配 '!$K:$K) -> 12515 | L90: =IF(ISNUMBER(K90),"是",IF(ISNA(K90),"否","")) -> 是 | M90: =_xlfn.XLOOKUP(F90,'6月产品包'!B:B,'6月产品包'!J:J) -> 2025-12-08 | N90: 新品 | O90: =_xlfn.XLOOKUP(F90,'6月库存'!A:A,'6月库存'!R:R) -> 65 | P90: =_xlfn.XLOOKUP(F90,'6月产品包'!B:B,'6月产品包'!S:S) -> 1238 | R90: =_xlfn.XLOOKUP(F90,'6月产品包'!B:B,'6月产品包'!AD:AD) -> 88.5196 | S90: 175 | T90: =ROUND(S90*(1+0.25),0) -> 219 | U90: =$T90*(1-0.2) -> 175.2 | V90: 0.2 | W90: =(U90-R90)/U90 -> 0.49475114 | X90: =(U90*(1-Y90-Z90-AA90-AC90-AB90)-R90)/(U90*(1-Y90-Z90-AA90-AC90-AB90)) -> 0.31991285 | Y90: 0.04 | Z90: 0.105 | AA90: 0.049 | AB90: =$AB$1/U90 -> 0.0030821918 | AC90: 0.06 | AF90: 原价进 | AG90: =MAX(AH90:AN90) -> 6 | AH90: =IF(U90>=50,MIN(MIN(U90*0.2,20)*0.3,6),0) -> 6 | AI90: =IF(U90>=200,MIN(MIN(U90*0.18,70)*0.3,21),0) -> 0 | AJ90: =IF(U90>=380,MIN(MIN(U90*0.28,350)*0.3,105),0) -> 0 | AK90: =IF(U90>=380,MIN(MIN(U90*0.25,350)*0.3,105),0) -> 0 | AL90: =IF(U90>=380,MIN(MIN(U90*0.22,300)*0.3,90),0) -> 0 | AM90: =IF(U90>=250,MIN(MIN(U90*0.18,120)*0.3,36),0) -> 0 | AN90: =IF(U90>=180,MIN(MIN(U90*0.15,60)*0.3,18),0) -> 0
A91: 3C数码 | B91: 音响乐器 | C91: =_xlfn.XLOOKUP(F91,'6月产品包'!B:B,'6月产品包'!H:H) -> 音箱 | D91: =_xlfn.XLOOKUP(F91,'6月产品包'!B:B,'6月产品包'!O:O) -> 长条桌面音箱 | E91: 3C-声霸蓝牙音箱 | F91: T4CC2230295 | G91: 平销款 | H91: MD | I91: =_xlfn.XLOOKUP($F91,'6月库存'!A:A,'6月库存'!B:B) -> 正常销售 | K91: =_xlfn.XLOOKUP(E91,'[1]6月分配 '!$B:$B,'[1]6月分配 '!$K:$K) -> 12466 | L91: =IF(ISNUMBER(K91),"是",IF(ISNA(K91),"否","")) -> 是 | M91: =_xlfn.XLOOKUP(F91,'6月产品包'!B:B,'6月产品包'!J:J) -> 2025-01-07 | N91: 老品 | O91: =_xlfn.XLOOKUP(F91,'6月库存'!A:A,'6月库存'!R:R) -> 1612 | P91: =_xlfn.XLOOKUP(F91,'6月产品包'!B:B,'6月产品包'!S:S) -> 1355 | R91: =_xlfn.XLOOKUP(F91,'6月产品包'!B:B,'6月产品包'!AD:AD) -> 36.5168 | S91: 70 | T91: =ROUND(S91*(1+0.25),0) -> 88 | U91: =$T91*(1-0.2) -> 70.4 | V91: 0.2 | W91: =(U91-R91)/U91 -> 0.48129545 | X91: =(U91*(1-Y91-Z91-AA91-AC91-AB91)-R91)/(U91*(1-Y91-Z91-AA91-AC91-AB91)) -> 0.28976645 | Y91: 0.038 | Z91: 0.115 | AA91: 0.049 | AB91: =$AB$1/U91 -> 0.0076704545 | AC91: 0.06 | AF91: 原价进 | AG91: =MAX(AH91:AN91) -> 4.224 | AH91: =IF(U91>=50,MIN(MIN(U91*0.2,20)*0.3,6),0) -> 4.224 | AI91: =IF(U91>=200,MIN(MIN(U91*0.18,70)*0.3,21),0) -> 0 | AJ91: =IF(U91>=380,MIN(MIN(U91*0.28,350)*0.3,105),0) -> 0 | AK91: =IF(U91>=380,MIN(MIN(U91*0.25,350)*0.3,105),0) -> 0 | AL91: =IF(U91>=380,MIN(MIN(U91*0.22,300)*0.3,90),0) -> 0 | AM91: =IF(U91>=250,MIN(MIN(U91*0.18,120)*0.3,36),0) -> 0 | AN91: =IF(U91>=180,MIN(MIN(U91*0.15,60)*0.3,18),0) -> 0
A92: 办公安防 | B92: 智能安防 | C92: =_xlfn.XLOOKUP(F92,'6月产品包'!B:B,'6月产品包'!H:H) -> 指纹锁 | D92: =_xlfn.XLOOKUP(F92,'6月产品包'!B:B,'6月产品包'!O:O) -> 手柄门锁 | E92: 3B-智能指纹门锁M20 | F92: T3CC2120277 | G92: 平销款 | H92: ZQ | I92: =_xlfn.XLOOKUP($F92,'6月库存'!A:A,'6月库存'!B:B) -> 正常销售 | K92: =_xlfn.XLOOKUP(E92,'[1]6月分配 '!$B:$B,'[1]6月分配 '!$K:$K) -> 12107 | L92: =IF(ISNUMBER(K92),"是",IF(ISNA(K92),"否","")) -> 是 | M92: =_xlfn.XLOOKUP(F92,'6月产品包'!B:B,'6月产品包'!J:J) -> 2024-11-12 | N92: =IF(DATEDIF(M92,TODAY(),"m")<6,"新品","老品") -> 老品 | O92: =_xlfn.XLOOKUP(F92,'6月库存'!A:A,'6月库存'!R:R) -> 320 | P92: =_xlfn.XLOOKUP(F92,'6月产品包'!B:B,'6月产品包'!S:S) -> 1134 | R92: =_xlfn.XLOOKUP(F92,'6月产品包'!B:B,'6月产品包'!AD:AD) -> 43.3492 | S92: 78 | T92: =ROUND(S92*(1+0.25),0) -> 98 | U92: =$T92*(1-0.2) -> 78.4 | V92: 0.2 | W92: =(U92-R92)/U92 -> 0.44707653 | X92: =(U92*(1-Y92-Z92-AA92-AC92-AB92)-R92)/(U92*(1-Y92-Z92-AA92-AC92-AB92)) -> 0.24372287 | Y92: 0.038 | Z92: 0.115 | AA92: 0.049 | AB92: =$AB$1/U92 -> 0.0068877551 | AC92: 0.06 | AF92: 原价进 | AG92: =MAX(AH92:AN92) -> 4.704 | AH92: =IF(U92>=50,MIN(MIN(U92*0.2,20)*0.3,6),0) -> 4.704 | AI92: =IF(U92>=200,MIN(MIN(U92*0.18,70)*0.3,21),0) -> 0 | AJ92: =IF(U92>=380,MIN(MIN(U92*0.28,350)*0.3,105),0) -> 0 | AK92: =IF(U92>=380,MIN(MIN(U92*0.25,350)*0.3,105),0) -> 0 | AL92: =IF(U92>=380,MIN(MIN(U92*0.22,300)*0.3,90),0) -> 0 | AM92: =IF(U92>=250,MIN(MIN(U92*0.18,120)*0.3,36),0) -> 0 | AN92: =IF(U92>=180,MIN(MIN(U92*0.15,60)*0.3,18),0) -> 0
A93: 办公安防 | B93: 办公周边 | C93: =_xlfn.XLOOKUP(F93,'6月产品包'!B:B,'6月产品包'!H:H) -> 碎纸机 | D93: =_xlfn.XLOOKUP(F93,'6月产品包'!B:B,'6月产品包'!O:O) -> 电动碎纸机 | E93: 3B-碎纸机10L | F93: M3CC2030181 | G93: #N/A | H93: ZQ | I93: =_xlfn.XLOOKUP($F93,'6月库存'!A:A,'6月库存'!B:B) -> 正常销售 | K93: =_xlfn.XLOOKUP(E93,'[1]6月分配 '!$B:$B,'[1]6月分配 '!$K:$K) -> 11331 | L93: =IF(ISNUMBER(K93),"是",IF(ISNA(K93),"否","")) -> 是 | M93: =_xlfn.XLOOKUP(F93,'6月产品包'!B:B,'6月产品包'!J:J) -> 2024-09-03 | N93: =IF(DATEDIF(M93,TODAY(),"m")<6,"新品","老品") -> 老品 | O93: =_xlfn.XLOOKUP(F93,'6月库存'!A:A,'6月库存'!R:R) -> 385 | P93: =_xlfn.XLOOKUP(F93,'6月产品包'!B:B,'6月产品包'!S:S) -> 1900 | R93: =_xlfn.XLOOKUP(F93,'6月产品包'!B:B,'6月产品包'!AD:AD) -> 54.3112 | S93: 102 | T93: =ROUND(S93*(1+0.25),0) -> 128 | U93: =$T93*(1-0.2) -> 102.4 | V93: 0.2 | W93: =(U93-R93)/U93 -> 0.46961719 | X93: =(U93*(1-Y93-Z93-AA93-AC93-AB93)-R93)/(U93*(1-Y93-Z93-AA93-AC93-AB93)) -> 0.29067277 | Y93: 0.038 | Z93: 0.1 | AA93: 0.049 | AB93: =$AB$1/U93 -> 0.0052734375 | AC93: 0.06 | AF93: 原价进 | AG93: =MAX(AH93:AN93) -> 6 | AH93: =IF(U93>=50,MIN(MIN(U93*0.2,20)*0.3,6),0) -> 6 | AI93: =IF(U93>=200,MIN(MIN(U93*0.18,70)*0.3,21),0) -> 0 | AJ93: =IF(U93>=380,MIN(MIN(U93*0.28,350)*0.3,105),0) -> 0 | AK93: =IF(U93>=380,MIN(MIN(U93*0.25,350)*0.3,105),0) -> 0 | AL93: =IF(U93>=380,MIN(MIN(U93*0.22,300)*0.3,90),0) -> 0 | AM93: =IF(U93>=250,MIN(MIN(U93*0.18,120)*0.3,36),0) -> 0 | AN93: =IF(U93>=180,MIN(MIN(U93*0.15,60)*0.3,18),0) -> 0
A94: =_xlfn.XLOOKUP(F94,'6月产品包'!B:B,'6月产品包'!F:F) -> 3C数码 | B94: =_xlfn.XLOOKUP(F94,'6月产品包'!B:B,'6月产品包'!G:G) -> 影像摄影 | C94: =_xlfn.XLOOKUP(F94,'6月产品包'!B:B,'6月产品包'!H:H) -> 数码相机 | D94: =_xlfn.XLOOKUP(F94,'6月产品包'!B:B,'6月产品包'!O:O) -> 翻屏数码相机 | E94: =_xlfn.XLOOKUP(F94,'6月产品包'!B:B,'6月产品包'!C:C) -> 3C-W1白色数码相机包含32gTF卡 | F94: T4CC2000352 | G94: 灭款 | H94: MD | I94: =_xlfn.XLOOKUP($F94,'6月库存'!A:A,'6月库存'!B:B) -> 商品清仓 | K94: =_xlfn.XLOOKUP(E94,'[1]6月分配 '!$B:$B,'[1]6月分配 '!$K:$K) -> #N/A | L94: =IF(ISNUMBER(K94),"是",IF(ISNA(K94),"否","")) -> 否 | M94: =_xlfn.XLOOKUP(F94,'6月产品包'!B:B,'6月产品包'!J:J) -> 2025-03-15 | N94: =IF(DATEDIF(M94,TODAY(),"m")<6,"新品","老品") -> 老品 | O94: =_xlfn.XLOOKUP(F94,'6月库存'!A:A,'6月库存'!R:R) -> 3 | P94: =_xlfn.XLOOKUP(F94,'6月产品包'!B:B,'6月产品包'!S:S) -> 460 | R94: =_xlfn.XLOOKUP(F94,'6月产品包'!B:B,'6月产品包'!AD:AD) -> 135.4358 | S94: 265 | T94: =ROUND(S94*(1+0.25),0) -> 331 | U94: =$T94*(1-0.2) -> 264.8 | V94: 0.2 | W94: =(U94-R94)/U94 -> 0.4885355 | X94: =(U94*(1-Y94-Z94-AA94-AC94-AB94)-R94)/(U94*(1-Y94-Z94-AA94-AC94-AB94)) -> 0.32787004 | Y94: 0.038 | Z94: 0.09 | AA94: 0.049 | AB94: =$AB$1/U94 -> 0.0020392749 | AC94: 0.06 | AF94: 不进 | AG94: =MAX(AH94:AN94) -> 14.2992 | AH94: =IF(U94>=50,MIN(MIN(U94*0.2,20)*0.3,6),0) -> 6 | AI94: =IF(U94>=200,MIN(MIN(U94*0.18,70)*0.3,21),0) -> 14.2992 | AJ94: =IF(U94>=380,MIN(MIN(U94*0.28,350)*0.3,105),0) -> 0 | AK94: =IF(U94>=380,MIN(MIN(U94*0.25,350)*0.3,105),0) -> 0 | AL94: =IF(U94>=380,MIN(MIN(U94*0.22,300)*0.3,90),0) -> 0 | AM94: =IF(U94>=250,MIN(MIN(U94*0.18,120)*0.3,36),0) -> 14.2992 | AN94: =IF(U94>=180,MIN(MIN(U94*0.15,60)*0.3,18),0) -> 11.916
A95: 办公安防 | B95: 办公周边 | C95: =_xlfn.XLOOKUP(F95,'6月产品包'!B:B,'6月产品包'!H:H) -> 广告架 | D95: =_xlfn.XLOOKUP(F95,'6月产品包'!B:B,'6月产品包'!O:O) -> 广告架kt板 | E95: 3B-广告架kt板斜面1.3kg | F95: T4CC1120858 | G95: #N/A | H95: ZQ | I95: =_xlfn.XLOOKUP($F95,'6月库存'!A:A,'6月库存'!B:B) -> 正常销售 | K95: =_xlfn.XLOOKUP(E95,'[1]6月分配 '!$B:$B,'[1]6月分配 '!$K:$K) -> #N/A | L95: =IF(ISNUMBER(K95),"是",IF(ISNA(K95),"否","")) -> 否 | M95: =_xlfn.XLOOKUP(F95,'6月产品包'!B:B,'6月产品包'!J:J) -> 2025-10-09 | N95: =IF(DATEDIF(M95,TODAY(),"m")<6,"新品","老品") -> 老品 | O95: =_xlfn.XLOOKUP(F95,'6月库存'!A:A,'6月库存'!R:R) -> 2 | P95: =_xlfn.XLOOKUP(F95,'6月产品包'!B:B,'6月产品包'!S:S) -> 4000 | R95: =_xlfn.XLOOKUP(F95,'6月产品包'!B:B,'6月产品包'!AD:AD) -> 22.3706 | S95: 45 | T95: =ROUND(S95*(1+0.25),0) -> 56 | U95: =$T95*(1-0.2) -> 44.8 | V95: 0.2 | W95: =(U95-R95)/U95 -> 0.50065625 | X95: =(U95*(1-Y95-Z95-AA95-AC95-AB95)-R95)/(U95*(1-Y95-Z95-AA95-AC95-AB95)) -> 0.32607307 | Y95: 0.038 | Z95: 0.1 | AA95: 0.049 | AB95: =$AB$1/U95 -> 0.012053571 | AC95: 0.06 | AF95: 不进 | AG95: =MAX(AH95:AN95) -> 0 | AH95: =IF(U95>=50,MIN(MIN(U95*0.2,20)*0.3,6),0) -> 0 | AI95: =IF(U95>=200,MIN(MIN(U95*0.18,70)*0.3,21),0) -> 0 | AJ95: =IF(U95>=380,MIN(MIN(U95*0.28,350)*0.3,105),0) -> 0 | AK95: =IF(U95>=380,MIN(MIN(U95*0.25,350)*0.3,105),0) -> 0 | AL95: =IF(U95>=380,MIN(MIN(U95*0.22,300)*0.3,90),0) -> 0 | AM95: =IF(U95>=250,MIN(MIN(U95*0.18,120)*0.3,36),0) -> 0 | AN95: =IF(U95>=180,MIN(MIN(U95*0.15,60)*0.3,18),0) -> 0
A96: 办公安防 | B96: 教学周边 | C96: =_xlfn.XLOOKUP(F96,'6月产品包'!B:B,'6月产品包'!H:H) -> 白板 | D96: =_xlfn.XLOOKUP(F96,'6月产品包'!B:B,'6月产品包'!O:O) -> 橡胶白板 | E96: 3B-橡胶磁白板背胶45cm*100cm | F96: T4CC2340729 | G96: 平销款 | H96: ZQ | I96: =_xlfn.XLOOKUP($F96,'6月库存'!A:A,'6月库存'!B:B) -> 正常销售 | K96: =_xlfn.XLOOKUP(E96,'[1]6月分配 '!$B:$B,'[1]6月分配 '!$K:$K) -> #N/A | L96: =IF(ISNUMBER(K96),"是",IF(ISNA(K96),"否","")) -> 否 | M96: =_xlfn.XLOOKUP(F96,'6月产品包'!B:B,'6月产品包'!J:J) -> 2025-07-03 | N96: =IF(DATEDIF(M96,TODAY(),"m")<6,"新品","老品") -> 老品 | O96: =_xlfn.XLOOKUP(F96,'6月库存'!A:A,'6月库存'!R:R) -> 0 | P96: =_xlfn.XLOOKUP(F96,'6月产品包'!B:B,'6月产品包'!S:S) -> 908 | R96: =_xlfn.XLOOKUP(F96,'6月产品包'!B:B,'6月产品包'!AD:AD) -> 12.2264 | S96: 23 | T96: =ROUND(S96*(1+0.25),0) -> 29 | U96: =$T96*(1-0.2) -> 23.2 | V96: 0.2 | W96: =(U96-R96)/U96 -> 0.473 | X96: =(U96*(1-Y96-Z96-AA96-AC96-AB96)-R96)/(U96*(1-Y96-Z96-AA96-AC96-AB96)) -> 0.25535958 | Y96: 0.04 | Z96: 0.1 | AA96: 0.049 | AB96: =$AB$1/U96 -> 0.023275862 | AC96: 0.08 | AD96: 0.05 | AE96: 0.05 | AF96: 不进 | AG96: =MAX(AH96:AN96) -> 0 | AH96: =IF(U96>=50,MIN(MIN(U96*0.2,20)*0.3,6),0) -> 0 | AI96: =IF(U96>=200,MIN(MIN(U96*0.18,70)*0.3,21),0) -> 0 | AJ96: =IF(U96>=380,MIN(MIN(U96*0.28,350)*0.3,105),0) -> 0 | AK96: =IF(U96>=380,MIN(MIN(U96*0.25,350)*0.3,105),0) -> 0 | AL96: =IF(U96>=380,MIN(MIN(U96*0.22,300)*0.3,90),0) -> 0 | AM96: =IF(U96>=250,MIN(MIN(U96*0.18,120)*0.3,36),0) -> 0 | AN96: =IF(U96>=180,MIN(MIN(U96*0.15,60)*0.3,18),0) -> 0
A97: 办公安防 | B97: 办公周边 | C97: =_xlfn.XLOOKUP(F97,'6月产品包'!B:B,'6月产品包'!H:H) -> 金属制品机柜 | D97: =_xlfn.XLOOKUP(F97,'6月产品包'!B:B,'6月产品包'!O:O) -> 交换机机柜 | E97: 3B-交换机机柜60cm | F97: T4CC2360756 | G97: #N/A | H97: ZQ | I97: =_xlfn.XLOOKUP($F97,'6月库存'!A:A,'6月库存'!B:B) -> 正常销售 | K97: =_xlfn.XLOOKUP(E97,'[1]6月分配 '!$B:$B,'[1]6月分配 '!$K:$K) -> 10946 | L97: =IF(ISNUMBER(K97),"是",IF(ISNA(K97),"否","")) -> 是 | M97: =_xlfn.XLOOKUP(F97,'6月产品包'!B:B,'6月产品包'!J:J) -> 2025-07-26 | N97: =IF(DATEDIF(M97,TODAY(),"m")<6,"新品","老品") -> 老品 | O97: =_xlfn.XLOOKUP(F97,'6月库存'!A:A,'6月库存'!R:R) -> 86 | P97: =_xlfn.XLOOKUP(F97,'6月产品包'!B:B,'6月产品包'!S:S) -> 11700 | R97: =_xlfn.XLOOKUP(F97,'6月产品包'!B:B,'6月产品包'!AD:AD) -> 72.1462 | S97: 150 | T97: =ROUND(S97*(1+0.25),0) -> 188 | U97: =$T97*(1-0.2) -> 150.4 | V97: 0.2 | W97: =(U97-R97)/U97 -> 0.52030452 | X97: =(U97*(1-Y97-Z97-AA97-AC97-AB97)-R97)/(U97*(1-Y97-Z97-AA97-AC97-AB97)) -> 0.35990212 | Y97: 0.038 | Z97: 0.1 | AA97: 0.049 | AB97: =$AB$1/U97 -> 0.0035904255 | AC97: 0.06 | AF97: 原价进 | AG97: =MAX(AH97:AN97) -> 6 | AH97: =IF(U97>=50,MIN(MIN(U97*0.2,20)*0.3,6),0) -> 6 | AI97: =IF(U97>=200,MIN(MIN(U97*0.18,70)*0.3,21),0) -> 0 | AJ97: =IF(U97>=380,MIN(MIN(U97*0.28,350)*0.3,105),0) -> 0 | AK97: =IF(U97>=380,MIN(MIN(U97*0.25,350)*0.3,105),0) -> 0 | AL97: =IF(U97>=380,MIN(MIN(U97*0.22,300)*0.3,90),0) -> 0 | AM97: =IF(U97>=250,MIN(MIN(U97*0.18,120)*0.3,36),0) -> 0 | AN97: =IF(U97>=180,MIN(MIN(U97*0.15,60)*0.3,18),0) -> 0
A98: 3C数码 | B98: 电脑周边 | C98: =_xlfn.XLOOKUP(F98,'6月产品包'!B:B,'6月产品包'!H:H) -> 鼠标垫 | D98: =_xlfn.XLOOKUP(F98,'6月产品包'!B:B,'6月产品包'!O:O) -> RGB鼠标垫 | E98: 3C-30*80*2cm鼠标垫RGB | F98: T4CC2230007 | G98: 引流款 | H98: ZQ | I98: =_xlfn.XLOOKUP($F98,'6月库存'!A:A,'6月库存'!B:B) -> 正常销售 | K98: =_xlfn.XLOOKUP(E98,'[1]6月分配 '!$B:$B,'[1]6月分配 '!$K:$K) -> #N/A | L98: =IF(ISNUMBER(K98),"是",IF(ISNA(K98),"否","")) -> 否 | M98: =_xlfn.XLOOKUP(F98,'6月产品包'!B:B,'6月产品包'!J:J) -> 2025-01-07 | N98: =IF(DATEDIF(M98,TODAY(),"m")<6,"新品","老品") -> 老品 | O98: =_xlfn.XLOOKUP(F98,'6月库存'!A:A,'6月库存'!R:R) -> 15 | P98: =_xlfn.XLOOKUP(F98,'6月产品包'!B:B,'6月产品包'!S:S) -> 525 | R98: =_xlfn.XLOOKUP(F98,'6月产品包'!B:B,'6月产品包'!AD:AD) -> 9.5932 | S98: 18 | T98: =ROUND(S98*(1+0.25),0) -> 23 | U98: =$T98*(1-0.2) -> 18.4 | V98: 0.2 | W98: =(U98-R98)/U98 -> 0.47863043 | X98: =(U98*(1-Y98-Z98-AA98-AC98-AB98)-R98)/(U98*(1-Y98-Z98-AA98-AC98-AB98)) -> 0.27249287 | Y98: 0.04 | Z98: 0.105 | AA98: 0.049 | AB98: =$AB$1/U98 -> 0.029347826 | AC98: 0.06 | AF98: 不进 | AG98: =MAX(AH98:AN98) -> 0 | AH98: =IF(U98>=50,MIN(MIN(U98*0.2,20)*0.3,6),0) -> 0 | AI98: =IF(U98>=200,MIN(MIN(U98*0.18,70)*0.3,21),0) -> 0 | AJ98: =IF(U98>=380,MIN(MIN(U98*0.28,350)*0.3,105),0) -> 0 | AK98: =IF(U98>=380,MIN(MIN(U98*0.25,350)*0.3,105),0) -> 0 | AL98: =IF(U98>=380,MIN(MIN(U98*0.22,300)*0.3,90),0) -> 0 | AM98: =IF(U98>=250,MIN(MIN(U98*0.18,120)*0.3,36),0) -> 0 | AN98: =IF(U98>=180,MIN(MIN(U98*0.15,60)*0.3,18),0) -> 0
A99: 3C数码 | B99: 游戏娱乐 | C99: =_xlfn.XLOOKUP(F99,'6月产品包'!B:B,'6月产品包'!H:H) -> 游戏手柄 | D99: =_xlfn.XLOOKUP(F99,'6月产品包'!B:B,'6月产品包'!O:O) -> X3游戏手柄 | E99: 3C-X3游戏手柄带手机支架 | F99: T3CC1800666 | G99: 平销款 | H99: MD | I99: =_xlfn.XLOOKUP($F99,'6月库存'!A:A,'6月库存'!B:B) -> 正常销售 | K99: =_xlfn.XLOOKUP(E99,'[1]6月分配 '!$B:$B,'[1]6月分配 '!$K:$K) -> 9965 | L99: =IF(ISNUMBER(K99),"是",IF(ISNA(K99),"否","")) -> 是 | M99: =_xlfn.XLOOKUP(F99,'6月产品包'!B:B,'6月产品包'!J:J) -> 2024-06-01 | N99: 老品 | O99: =_xlfn.XLOOKUP(F99,'6月库存'!A:A,'6月库存'!R:R) -> 998 | P99: =_xlfn.XLOOKUP(F99,'6月产品包'!B:B,'6月产品包'!S:S) -> 250 | R99: =_xlfn.XLOOKUP(F99,'6月产品包'!B:B,'6月产品包'!AD:AD) -> 14.4652 | S99: 28 | T99: =ROUND(S99*(1+0.25),0) -> 35 | U99: =$T99*(1-0.2) -> 28 | V99: 0.2 | W99: =(U99-R99)/U99 -> 0.48338571 | X99: =(U99*(1-Y99-Z99-AA99-AC99-AB99)-R99)/(U99*(1-Y99-Z99-AA99-AC99-AB99)) -> 0.28616265 | Y99: 0.038 | Z99: 0.09 | AA99: 0.049 | AB99: =$AB$1/U99 -> 0.019285714 | AC99: 0.08 | AD99: 0.08 | AE99: 0.05 | AF99: 原价进 | AG99: =MAX(AH99:AN99) -> 0 | AH99: =IF(U99>=50,MIN(MIN(U99*0.2,20)*0.3,6),0) -> 0 | AI99: =IF(U99>=200,MIN(MIN(U99*0.18,70)*0.3,21),0) -> 0 | AJ99: =IF(U99>=380,MIN(MIN(U99*0.28,350)*0.3,105),0) -> 0 | AK99: =IF(U99>=380,MIN(MIN(U99*0.25,350)*0.3,105),0) -> 0 | AL99: =IF(U99>=380,MIN(MIN(U99*0.22,300)*0.3,90),0) -> 0 | AM99: =IF(U99>=250,MIN(MIN(U99*0.18,120)*0.3,36),0) -> 0 | AN99: =IF(U99>=180,MIN(MIN(U99*0.15,60)*0.3,18),0) -> 0
A100: 3C数码 | B100: 电脑周边 | C100: =_xlfn.XLOOKUP(F100,'6月产品包'!B:B,'6月产品包'!H:H) -> 电视支架 | D100: =_xlfn.XLOOKUP(F100,'6月产品包'!B:B,'6月产品包'!O:O) -> 显示器桌面支架 | E100: 3C-显示器桌面支架4屏 | F100: T4CC1120830 | G100: #N/A | H100: ZQ | I100: =_xlfn.XLOOKUP($F100,'6月库存'!A:A,'6月库存'!B:B) -> 正常销售 | K100: =_xlfn.XLOOKUP(E100,'[1]6月分配 '!$B:$B,'[1]6月分配 '!$K:$K) -> 9777 | L100: =IF(ISNUMBER(K100),"是",IF(ISNA(K100),"否","")) -> 是 | M100: =_xlfn.XLOOKUP(F100,'6月产品包'!B:B,'6月产品包'!J:J) -> 2025-09-18 | N100: =IF(DATEDIF(M100,TODAY(),"m")<6,"新品","老品") -> 老品 | O100: =_xlfn.XLOOKUP(F100,'6月库存'!A:A,'6月库存'!R:R) -> 56 | P100: =_xlfn.XLOOKUP(F100,'6月产品包'!B:B,'6月产品包'!S:S) -> 6890 | R100: =_xlfn.XLOOKUP(F100,'6月产品包'!B:B,'6月产品包'!AD:AD) -> 72.6972 | S100: 140 | T100: =ROUND(S100*(1+0.25),0) -> 175 | U100: =$T100*(1-0.2) -> 140 | V100: 0.2 | W100: =(U100-R100)/U100 -> 0.48073429 | X100: =(U100*(1-Y100-Z100-AA100-AC100-AB100)-R100)/(U100*(1-Y100-Z100-AA100-AC100-AB100)) -> 0.30406663 | Y100: 0.038 | Z100: 0.103 | AA100: 0.049 | AB100: =$AB$1/U100 -> 0.0038571429 | AC100: 0.06 | AF100: 原价进 | AG100: =MAX(AH100:AN100) -> 6 | AH100: =IF(U100>=50,MIN(MIN(U100*0.2,20)*0.3,6),0) -> 6 | AI100: =IF(U100>=200,MIN(MIN(U100*0.18,70)*0.3,21),0) -> 0 | AJ100: =IF(U100>=380,MIN(MIN(U100*0.28,350)*0.3,105),0) -> 0 | AK100: =IF(U100>=380,MIN(MIN(U100*0.25,350)*0.3,105),0) -> 0 | AL100: =IF(U100>=380,MIN(MIN(U100*0.22,300)*0.3,90),0) -> 0 | AM100: =IF(U100>=250,MIN(MIN(U100*0.18,120)*0.3,36),0) -> 0 | AN100: =IF(U100>=180,MIN(MIN(U100*0.15,60)*0.3,18),0) -> 0
...

Sheet 6月产品包
A1: 周期 | B1: SKU | C1: 商品名称 | D1: 主SKU | E1: 国家 | F1: 一级品类 | G1: 二级品类 | H1: 三级类目 | I1: 创建日期 | J1: 新款年月 | K1: 新款月龄 | L1: 赠品 | M1: SKU状态 | N1: 款号 | O1: 款名 | P1: 销售规格 | Q1: 单品尺寸 | R1: 单品净重g | S1: 单品毛重g | T1: 外箱长cm | U1: 外箱宽cm | V1: 外箱高cm | W1: 每箱数量 | X1: 出货方式 | Y1: 仓库 | Z1: 仓存 | AA1: 规划仓 | AB1: 销售成本人民币 | AC1: 国家汇率 | AD1: 销售成本国家币 | AE1: 1档价(20%) | AF1: 2档价(25%) | AG1: 3档价(35%) | AH1: 4档价(45%) | AI1: 连带率
A2: 202606 | B2: M2CC0180514 | C2: 3B-路由器P6000白色 | D2: CC0514 | E2: 马来 | F2: 办公安防 | G2: 智能安防 | H2: 路由器 | I2: 2023-07-25 | J2: 2023-07-25 | K2: 42 | M2: 清仓商品 | N2: 3B0015 | O2: P6000路由器 | P2: 英规、支持马来波段、外贸定制版 | Q2: 14.5cm*21cm*4.05cm | R2: 250 | S2: 300 | T2: 1.3 | U2: 44 | V2: 32.5 | W2: 40 | X2: 中转 | Y2: 马来易企通-D仓-1308 | Z2: 363 | AA2: 是 | AB2: 93.44 | AC2: 0.58 | AD2: 54.1952 | AE2: 67.744 | AF2: 72.2603 | AG2: 83.3772 | AH2: 98.5367
A3: 202606 | B3: M2CC0180540 | C3: 3B-便携式路由器R5款黑色 | D3: CC0540 | E3: 马来 | F3: 办公安防 | G3: 智能安防 | H3: 路由器 | I3: 2023-08-17 | J3: 2023-08-17 | K3: 42 | M3: 清仓商品 | N3: 3B0016 | O3: R5路由器 | P3: 支持马来波段、所有无限4G卡,外贸定制版 | Q3: 9.9cm*5.85cm*1.484cm | R3: 100 | S3: 150 | T3: 0.6 | U3: 27 | V3: 29.5 | W3: 100 | X3: 中转 | Y3: 马来易企通-D仓-1308 | Z3: 1 | AA3: 是 | AB3: 61.59 | AC3: 0.58 | AD3: 35.7222 | AE3: 44.6527 | AF3: 47.6296 | AG3: 54.9572 | AH3: 64.9495
A4: 202606 | B4: M2CC1530462 | C4: 3B-X1指纹考勤机 | D4: CC0462 | E4: 马来 | F4: 办公安防 | G4: 办公周边 | H4: 考勤机 | I4: 2023-09-11 | J4: 2023-09-11 | K4: 42 | M4: 正常销售 | N4: 3B0013 | O4: 指纹考勤机 | P4: 英规插头，220V，2.4'TFT彩屏，16键实体键盘，T9英文输入及显示）横挂式；指纹+密码；指纹数量1000枚；考勤记录60000条； 支持U盘数据下载 | Q4: 17cm*12cm*4cm | R4: 207 | S4: 466 | T4: 2.4 | U4: 43.5 | V4: 30.5 | W4: 20 | X4: 中转 | Y4: 马来易企通-D仓-1308 | Z4: 2246 | AA4: 是 | AB4: 76.15 | AC4: 0.58 | AD4: 44.167 | AE4: 55.2087 | AF4: 58.8893 | AG4: 67.9492 | AH4: 80.3036
A5: 202606 | B5: M2CC1720531 | C5: 3C-X81海外智能版投影仪 | D5: CC0531 | E5: 马来 | F5: 3C数码 | G5: 影像摄影 | H5: 投影仪 | I5: 2023-08-15 | J5: 2023-08-15 | K5: 42 | M5: 清仓商品 | N5: 3C0000 | O5: 投影仪X款 | P5: 英规插头，亮度160ANSI，9000流明，内存2+16G（实际（1+8），最高1080p（实际720p），安卓 10.0，蓝牙4.0 | Q5: 16cm*17cm*20cm | R5: 827 | S5: 1358 | T5: 3.71 | U5: 42 | V5: 40 | W5: 12 | X5: 中转 | Y5: 马来易企通-D仓-1308 | Z5: 0 | AA5: 是 | AB5: 259.08 | AC5: 0.58 | AD5: 150.2664 | AE5: 187.833 | AF5: 200.3552 | AG5: 231.1791 | AH5: 273.2116
A6: 202606 | B6: M3CC0200589 | C6: 3B-小票快递单打印机黑蓝色 | D6: CC0589 | E6: 马来 | F6: 办公安防 | G6: 办公周边 | H6: 打印机 | I6: 2024-08-02 | J6: 2024-08-02 | K6: 30 | M6: 正常销售 | N6: 3B0004 | O6: 小票打印机 | P6: 英规插头，JK5802H蓝牙款，接口USB+BT，打印速度40-70mm/秒，支持ios，Android，Windows | Q6: 15.8cm*11.5cm*9.4cm | R6: 325 | S6: 625 | T6: 1.4 | U6: 51.5 | V6: 39.5 | W6: 36 | X6: 中转 | Y6: 马来易企通-D仓-1308 | Z6: 900 | AA6: 是 | AB6: 49.49 | AC6: 0.58 | AD6: 28.7042 | AE6: 35.8802 | AF6: 38.2723 | AG6: 44.1603 | AH6: 52.1895
A7: 202606 | B7: M3CC1030157 | C7: 3B-旅行AC插头充电宝10000毫安白色 | D7: CC0157 | E7: 马来 | F7: 办公安防 | G7: 储能设备 | H7: 充电宝 | I7: 2024-08-13 | J7: 2024-08-13 | K7: 30 | L7: 是 | M7: 清仓商品 | N7: 3B0000 | O7: 普通款充电宝 | P7: 配英规转接头；型号HT-DX348；配欧规转接头；电芯型号:105568*2；电池实际容量：10000mAh；保护电路:是；type-c输出:5V/3A，9V2.2A，12V1.6A；USB输出:4.5V/5A，5V3A，9V2A，12V1.5A；Lightning输出:5V/2.1A；type-c输入:5V3A，9V2A，12V1.5A；AC输入:5V2A;材质：PC+ABS | Q7: 8.8cm*8.8cm*3.3cm | R7: 360 | S7: 380 | T7: 0.6 | U7: 42.5 | V7: 30.5 | W7: 75 | X7: 散货 | Y7: 马来易企通-D仓-1308 | Z7: 2 | AA7: 是 | AB7: 66.1 | AC7: 0.58 | AD7: 38.338 | AE7: 47.9225 | AF7: 51.1173 | AG7: 58.9815 | AH7: 69.7055
A8: 202606 | B8: M3CC1720621 | C8: 3C-圆筒投影仪白色 | D8: CC0621 | E8: 马来 | F8: 3C数码 | G8: 影像摄影 | H8: 投影仪 | I8: 2024-02-27 | J8: 2024-02-27 | K8: 30 | M8: 清仓商品 | N8: 3C0000 | O8: 投影仪圆筒款 | P8: 英规，型号HY-300；安卓11.0；主板方案RK3326；分辨率1024*600；160ANSI流明（光源8000流明）；光源寿命>30000H；内存大小1+8GB(8+64Gb)；投射比1.31；电动调焦；上下自动梯形校正；采用XDR色彩调校技术、九点对焦技术（压模菲镜+进口光锥+绿膜镜头+镀膜物镜）；5G双频WiFi；解码4K/H.264/H.265/VP9视频，支持HDR10.超清画质；内置蓝牙模块；输入端口USB2.0+HDMI；电源插口AC8字尾；输出端口3.5mm耳机接口；扬声器3W；电源输入AC 100V～240V，50/60Hz支持视频格式AVI,TS,TP, MOV, DAT, MPG ,MPEG，MKV,3GP,MP4,VOB,M2TS,XVID、3GP2、MPEG1、MPEG2、MPEG3、MPEG4、H263,H264, H265,VP8,RV30,RV40，最高支持8K 。（不支持RM/RMVB/FLV格式的视频编码；不支持杜比、AC3/DTS格式的音频编码）。 | Q8: 21.9cm*13.4cm*11.9cm | R8: 730 | S8: 845 | T8: 3.1 | U8: 45.5 | V8: 28.5 | W8: 20 | X8: 中转 | Y8: 马来易企通-D仓-1308 | Z8: 45 | AA8: 是 | AB8: 171.74 | AC8: 0.58 | AD8: 99.6092 | AE8: 124.5115 | AF8: 132.8123 | AG8: 153.2449 | AH8: 181.1076
A9: 202606 | B9: M3CC1760562 | C9: 3B-热敏标签打印机H11 | D9: CC0562 | E9: 马来 | F9: 办公安防 | G9: 办公周边 | H9: 热敏打印机 | I9: 2023-09-11 | J9: 2023-09-11 | K9: 42 | M9: 清仓商品 | N9: 3B0000 | O9: 标签打印机 | P9: 电池容量：2000mAh，充满电可连续打印300米，打印速度为30mm/s，内带一卷纸 | Q9: 7.6cm*7.6cm*4cm | R9: 112 | S9: 135 | T9: 0.5 | U9: 32.5 | V9: 27.5 | W9: 63 | X9: 中转 | Y9: 马来易企通-D仓-1308 | Z9: 8 | AA9: 是 | AB9: 55.39 | AC9: 0.58 | AD9: 32.1262 | AE9: 40.1577 | AF9: 42.8349 | AG9: 49.4249 | AH9: 58.4113
A10: 202606 | B10: M3CC1830620 | C10: 3B-三天线摇头机摄像头 | D10: CC0620 | E10: 马来 | F10: 办公安防 | G10: 智能安防 | H10: 摄像头 | I10: 2024-02-01 | J10: 2024-02-01 | K10: 30 | M10: 清仓商品 | N10: 3B0000 | O10: 桌面摄像头 | P10: 软件ZIICAM；英规插头，不带网口，200万像素；1080P高清像素；上下90度，左右355度旋转（画面视野360度）；红外夜视功能；；图像质量1920*1080/1280*720；支持移动跟踪；支持图像移动侦测；支持抓图功能和视频翻转；支持远程回放；报警触发视频推送、扬声器报警、报警录像；录像文件大小2.5-4.5GB/天 (16GB TF卡可录大约5天)；无线网络2.4GHz、802.11b/g/n；支持IR-CUT；电源DC5V1.5A；灯板11颗红外灯。 | Q10: 14cm*13cm*10cm | R10: 220 | S10: 383 | T10: 2.1 | U10: 46.5 | V10: 30.5 | W10: 30 | X10: 中转 | Y10: 马来易企通-D仓-1308 | Z10: 3 | AA10: 是 | AB10: 37.71 | AC10: 0.58 | AD10: 21.8718 | AE10: 27.3397 | AF10: 29.1624 | AG10: 33.6489 | AH10: 39.7669
A11: 202606 | B11: M3CC1950638 | C11: 3B-2.4寸带屏双向可视摄像头 | D11: CC0638 | E11: 马来 | F11: 办公安防 | G11: 智能安防 | H11: 摄像头 | I11: 2024-03-26 | J11: 2024-03-26 | K11: 30 | M11: 清仓商品 | N11: 3B0000 | O11: 看护摄像头 | P11: 英规插头，V360系统，200W像素；分辨率1920*1080；电压AC110V-220V。焦距4mm；红外夜视距离5-8米。联网方式WIFI-2.4GHz。设备扫码添加，WiFi连接；垂直旋转90°，水平转速355°/S。支持语音监听，对讲，移动侦测、声音侦测报警；云存视频支持报警分类查询回放功能；支持各类手机远程监控（IOS,Android）；支持8-128GTF卡存储；工作温度：-10℃－＋55℃；双向语音对讲。英文包装、英文说明书。 | Q11: 15.3cm*92.1cm*79.1cm | R11: 200 | S11: 350 | T11: 1 | U11: 50 | V11: 40 | W11: 50 | X11: 中转 | Y11: 马来易企通-D仓-1308 | Z11: 3 | AA11: 是 | AB11: 59.3 | AC11: 0.58 | AD11: 34.394 | AE11: 42.9925 | AF11: 45.8587 | AG11: 52.9138 | AH11: 62.5345
A12: 202606 | B12: M3CC1970671 | C12: 3C-蓝牙语音机顶盒 | D12: CC0671 | E12: 马来 | F12: 3C数码 | G12: 电视设备 | H12: 机顶盒 | I12: 2024-05-23 | J12: 2024-05-23 | K12: 30 | M12: 正常销售 | N12: 3C0008 | O12: 机顶盒 | Q12: 9.5cm*9.5cm*1cm | R12: 310 | S12: 325 | T12: 1.4 | U12: 37.5 | V12: 25.5 | W12: 40 | X12: 中转 | Y12: 马来易企通-D仓-1308 | Z12: 0 | AA12: 是 | AB12: 74.01 | AC12: 0.58 | AD12: 42.9258 | AE12: 53.6572 | AF12: 57.2344 | AG12: 66.0397 | AH12: 78.0469
A13: 202606 | B13: M3CC2030181 | C13: 3B-碎纸机10L | D13: CC0181 | E13: 马来 | F13: 办公安防 | G13: 办公周边 | H13: 碎纸机 | I13: 2024-09-03 | J13: 2024-09-03 | K13: 30 | M13: 正常销售 | N13: 3B0026 | O13: 电动碎纸机 | P13: 型号:S606B，英规插头，最多切碎5张A4纸，切割尺寸6.8mm，工作宽度220mm，仓体积10L，碎纸速度3.8m/min | Q13: 30cm28cm*16.2cm | R13: 1600 | S13: 1900 | T13: 15 | U13: 33 | V13: 30 | W13: 4 | X13: 中转 | Y13: 马来易企通-D仓-1308 | Z13: 386 | AA13: 是 | AB13: 93.64 | AC13: 0.58 | AD13: 54.3112 | AE13: 67.889 | AF13: 72.4149 | AG13: 83.5557 | AH13: 98.7476
A14: 202606 | B14: M3CC2210177 | C14: 3B-300CWiFi路由器 | D14: CC0177 | E14: 马来 | F14: 办公安防 | G14: 智能安防 | H14: 路由器 | I14: 2024-12-26 | J14: 2024-12-26 | K14: 31 | M14: 清仓商品 | N14: 3B0034 | O14: 300C路由器 | Q14: 29cm*18cm*13.2cm | R14: 590 | S14: 625 | T14: 2.89 | U14: 54.2 | V14: 29.8 | W14: 20 | X14: 中转 | Y14: 马来易企通-D仓-1308 | Z14: 136 | AA14: 是 | AB14: 127.34 | AC14: 0.58 | AD14: 73.8572 | AE14: 92.3215 | AF14: 98.4763 | AG14: 113.6265 | AH14: 134.2858
A15: 202606 | B15: M3CC2210235 | C15: 3B-306CWiFi路由器 | D15: CC0235 | E15: 马来 | F15: 办公安防 | G15: 智能安防 | H15: 路由器 | I15: 2024-12-26 | J15: 2024-12-26 | K15: 31 | M15: 清仓商品 | N15: 3B0035 | O15: 306C路由器 | Q15: 16.5cm*12cm*4.2cm | R15: 371 | S15: 389 | T15: 1.52 | U15: 54.3 | V15: 27.3 | W15: 36 | X15: 中转 | Y15: 马来易企通-D仓-1308 | Z15: 47 | AA15: 是 | AB15: 109.41 | AC15: 0.58 | AD15: 63.4578 | AE15: 79.3222 | AF15: 84.6104 | AG15: 97.6274 | AH15: 115.3778
A16: 202606 | B16: M4CC0200477 | C16: 3B-快递面单打印机白色 | D16: CC0477 | E16: 马来 | F16: 办公安防 | G16: 办公周边 | H16: 打印机 | I16: 2025-03-29 | J16: 2025-03-29 | K16: 18 | M16: 正常销售 | N16: 3B0014 | O16: 面单打印机 | P16: 英规插头，打印幅面：30-108mm ，放纸宽度：110mm，撕纸方式：手动撕纸，容量：＜100mm，电源：外置24v2A【110-220v支持】，配件：电源适配件，电源线，USB线，用户手册 | Q16: 22.4cm*18cm*15.2cm | R16: 1800 | S16: 2375 | T16: 6.25 | U16: 49 | V16: 37 | W16: 8 | X16: 中转 | Y16: 马来易企通-D仓-1308 | Z16: 0 | AA16: 是 | AB16: 210.65 | AC16: 0.58 | AD16: 122.177 | AE16: 152.7212 | AF16: 162.9027 | AG16: 187.9646 | AH16: 222.14
A17: 202606 | B17: M4CC1720789 | C17: 3C-84寸16比9电子限位白塑电动幕布 | D17: CC0789 | E17: 马来 | F17: 3C数码 | G17: 影像摄影 | H17: 投影幕布 | I17: 2025-08-21 | J17: 2025-08-21 | K17: 18 | M17: 正常销售 | N17: 3C0087 | O17: 16:09电动幕布 | P17: 英规插头，外壳尺寸199.5cm，总高度尺寸124cm，下杆尺寸190cm,上黑边尺寸20至25cm,显示画面180cm*102cm，含遥控器 | Q17: 202cm*13cm*12cm | R17: 5700 | S17: 5750 | T17: 202 | U17: 13 | V17: 12 | W17: 1 | X17: 中转 | Y17: 马来易企通-D仓-1308 | Z17: 13 | AA17: 是 | AB17: 173.21 | AC17: 0.58 | AD17: 100.4618 | AE17: 125.5772 | AF17: 133.9491 | AG17: 154.5566 | AH17: 182.6578
A18: 202606 | B18: M4CC2410758 | C18: 3B-碎纸机7L | D18: CC0758 | E18: 马来 | F18: 办公安防 | G18: 办公周边 | H18: 碎纸机 | I18: 2025-07-29 | J18: 2025-07-29 | K18: 18 | M18: 正常销售 | N18: 3B0063 | O18: 碎纸机7L | P18: 插头（英标三脚插),进纸口宽度：220mm，碎纸类型：条状；最大碎纸量：6张；碎纸尺寸：6mm；欧盟保密等级：P-2；碎纸速度：2.2m/minute；噪音值：约72dB；连续工作时间：2分钟；休息时间：30分钟。 | Q18: 30.8cm*11.4cm*29.6cm | R18: 1510 | S18: 1710 | T18: 14.5 | U18: 37.2 | V18: 31 | W18: 4 | X18: 中转 | Y18: 马来易企通-D仓-1308 | Z18: 382 | AA18: 是 | AB18: 74.84 | AC18: 0.58 | AD18: 43.4072 | AE18: 54.259 | AF18: 57.8763 | AG18: 66.7803 | AH18: 78.9222
A19: 202606 | B19: M4CC2410982 | C19: 3B-A4简易过胶机 | D19: CC0982 | E19: 马来 | F19: 办公安防 | G19: 办公周边 | H19: 过胶机 | I19: 2025-12-02 | J19: 2025-12-02 | K19: 19 | M19: 正常销售 | N19: 3B0115 | O19: A4简易过胶机 | P19: 英规插头；过胶尺寸A4；塑胶外壳；胶辊数量 2；云母片发热片；温控器；预热时间 2.5 - 3分钟；过胶速度 280 mm/分钟；过胶范围 80-125mic；最大过胶厚度0.5mm；手动退胶按钮；开关档位设置 on/off （一键启动)；指示灯设置电源-红灯；预热-绿灯 | Q19: 37cm*13cm*7.6cm | R19: 1020 | S19: 1050 | T19: 4 | U19: 38.5 | V19: 28 | W19: 10 | X19: 走柜 | Y19: 马来易企通-D仓-1308 | Z19: 32 | AA19: 是 | AB19: 57.5 | AC19: 0.58 | AD19: 33.35 | AE19: 41.6875 | AF19: 44.4667 | AG19: 51.3077 | AH19: 60.6364
A20: 202606 | B20: M4CC2410983 | C20: 3B-A3简易过胶机 | D20: CC0983 | E20: 马来 | F20: 办公安防 | G20: 办公周边 | H20: 过胶机 | I20: 2025-12-02 | J20: 2025-12-02 | K20: 19 | M20: 正常销售 | N20: 3B0116 | O20: A3简易过胶机 | P20: 英规插头；过胶尺寸A3；塑胶外壳；胶辊数量2；云母片发热片；；温控器预热时间2.5至3分钟；过胶速度250mm/分钟；过胶范围80-125；最大过胶厚度0.5mm退胶方式；手动退胶；按钮开关档位设置on/off（一键启动)；指示灯设置电源-红灯，预热-绿灯 | Q20: 47cm*13cm*7.6cm | R20: 1200 | S20: 1310 | T20: 4.88 | U20: 40 | V20: 28 | W20: 10 | X20: 走柜 | Y20: 马来易企通-D仓-1308 | Z20: 35 | AA20: 是 | AB20: 70.61 | AC20: 0.58 | AD20: 40.9538 | AE20: 51.1922 | AF20: 54.6051 | AG20: 63.0058 | AH20: 74.4615
A21: 202606 | B21: M4CC2410984 | C21: 3B-专业快速过胶机A3 | D21: CC0984 | E21: 马来 | F21: 办公安防 | G21: 办公周边 | H21: 过胶机 | I21: 2025-12-02 | J21: 2025-12-02 | K21: 19 | M21: 正常销售 | N21: 3B0117 | O21: 专业快速过胶机A3 | P21: 英规插头；过胶尺寸A3；塑胶外壳胶辊数量 4发热方式 石英管温控方式 NTC + MCU预热时间 1 分钟过胶速度 500 mm/分钟过胶范围 "冷裱, 80mic, 125mic, 175mic(Japan version: 冷裱, 80mic, 100mic,150mic)"最大过胶厚度 0.6 mm退胶方式 马达自动反转(按一下REV按键，机器自动退胶膜)开关档位设置 on/off, 触摸按键调整档位指示灯设置 电源-红灯，预热-绿灯 | Q21: 49.5cm*16.7cm*8.7cm | R21: 2900 | S21: 3200 | T21: 14.2 | U21: 48 | V21: 31 | W21: 4 | X21: 走柜 | Y21: 马来易企通-D仓-1308 | Z21: 4 | AA21: 是 | AB21: 176.39 | AC21: 0.58 | AD21: 102.3062 | AE21: 127.8827 | AF21: 136.4083 | AG21: 157.3942 | AH21: 186.0113
A22: 202606 | B22: M4CC2410985 | C22: 3B-A3金属外壳过胶机STL316A | D22: CC0985 | E22: 马来 | F22: 办公安防 | G22: 办公周边 | H22: 过胶机 | I22: 2025-12-02 | J22: 2025-12-02 | K22: 19 | M22: 正常销售 | N22: 3B0118 | O22: A3金属外壳过胶机 | P22: 英规插头；过胶尺寸 A3外壳材质 金属外壳胶辊数量 2发热方式 发热片温控方式 NTC + MCU预热时间 3 - 5 分钟过胶速度 400 mm /分钟过胶范围 80 - 175 mic最大过胶厚度 0.8 mm退胶方式 手动退胶按钮开关档位设置 "on/off, 旋钮开关调节档位 (60, 80, 100, 125, 150, 175 mic)"指示灯设置 电源-红灯，预热-绿灯 | Q22: 50cm*20.3cm*14.8cm | R22: 2600 | S22: 3025 | T22: 13.13 | U22: 47.5 | V22: 33 | W22: 4 | X22: 走柜 | Y22: 马来易企通-D仓-1308 | Z22: 12 | AA22: 是 | AB22: 127.38 | AC22: 0.58 | AD22: 73.8804 | AE22: 92.3505 | AF22: 98.5072 | AG22: 113.6622 | AH22: 134.328
A23: 202606 | B23: M4CC2410987 | C23: 3B-碎纸机头不带桶WS0106 | D23: CC0987 | E23: 马来 | F23: 办公安防 | G23: 办公周边 | H23: 碎纸机 | I23: 2025-12-02 | J23: 2025-12-02 | K23: 19 | M23: 待开发 | N23: 3B0119 | O23: 碎纸机头 | P23: 英规插头；条状碎纸机；进纸口宽度：220 mm碎纸类型：条状最大碎纸量；6张碎纸尺寸6mm欧盟保密等级：P-2碎纸速度2.2米/分钟噪音值：70 dB连续工作时间2 分钟休息时间30分钟 | Q23: 34.5cm*14cm*7.5cm | R23: 1170 | S23: 1250 | T23: 6 | U23: 30.2 | V23: 24.1 | W23: 6 | X23: 走柜 | Y23: 马来易企通-D仓-1308 | Z23: 0 | AA23: 是 | AB23: 54 | AC23: 0.58 | AD23: 31.32 | AE23: 39.15 | AF23: 41.76 | AG23: 48.1846 | AH23: 56.9455
A24: 202606 | B24: M4CC2410988 | C24: 3B-碎纸机4张段状S0204B | D24: CC0988 | E24: 马来 | F24: 办公安防 | G24: 办公周边 | H24: 碎纸机 | I24: 2025-12-02 | J24: 2025-12-02 | K24: 19 | M24: 正常销售 | N24: 3B0120 | O24: 碎纸机4张段状 | P24: 英规插头；段状碎纸机；进纸口宽度220 mm碎纸类型：段状最大碎纸量4张；碎纸尺寸4 x 38 mm；欧盟保密等级P-4；碎纸速度2.5米/分钟；噪音值60dB；连续工作时间3分钟；休息时间30分钟 | Q24: 31cm*27.5cm*17cm | R24: 2430 | S24: 2650 | T24: 15.88 | U24: 35.5 | V24: 29.2 | W24: 4 | X24: 走柜 | Y24: 马来易企通-D仓-1308 | Z24: 1 | AA24: 是 | AB24: 86.28 | AC24: 0.58 | AD24: 50.0424 | AE24: 62.553 | AF24: 66.7232 | AG24: 76.9883 | AH24: 90.9862
A25: 202606 | B25: M4CC2410989 | C25: 3B-碎纸机6张段状S0206L | D25: CC0989 | E25: 马来 | F25: 办公安防 | G25: 办公周边 | H25: 碎纸机 | I25: 2025-12-02 | J25: 2025-12-02 | K25: 19 | M25: 正常销售 | N25: 3B0121 | O25: 碎纸机6张段状 | P25: 英规插头；段状碎纸机；进纸口宽度220 mm碎纸类型段状；最大碎纸量6张；碎纸尺寸4x38mm；欧盟保密等级P-4；碎纸速度2米/分钟；噪音值62dB；连续工作时间5分钟；休息时间30分钟 | Q25: 36.8cm*31cm*18cm | R25: 3200 | S25: 3800 | T25: 19.4 | U25: 37.8 | V25: 32.3 | W25: 2 | X25: 走柜 | Y25: 马来易企通-D仓-1308 | Z25: 1 | AA25: 是 | AB25: 108.96 | AC25: 0.58 | AD25: 63.1968 | AE25: 78.996 | AF25: 84.2624 | AG25: 97.2258 | AH25: 114.9033
A26: 202606 | B26: M4CC2450779 | C26: 3C-电子琴带琴谱架61键 | D26: CC0779 | E26: 马来 | F26: 3C数码 | G26: 音响乐器 | H26: 电子琴 | I26: 2025-10-09 | J26: 2025-10-09 | K26: 20 | M26: 正常销售 | N26: 3C0091 | O26: 电子琴61键 | P26: 英规插头（英标三脚插)61键儿童电子琴，适合儿童学习弹奏钢琴用的。配件：琴谱架+话筒+英文说明书+电源+中性包装 | Q26: 70cm*20cm*6cm | R26: 1100 | S26: 2000 | T26: 78 | U26: 25 | V26: 9.5 | W26: 1 | X26: 中转 | Y26: 马来易企通-D仓-1308 | Z26: 86 | AA26: 是 | AB26: 85.07 | AC26: 0.58 | AD26: 49.3406 | AE26: 61.6757 | AF26: 65.7875 | AG26: 75.9086 | AH26: 89.7102
A27: 202606 | B27: M4CC2450780 | C27: 3C-折叠带蓝牙带琴谱架电子琴61键 | D27: CC0780 | E27: 马来 | F27: 3C数码 | G27: 音响乐器 | H27: 电子琴 | I27: 2025-10-09 | J27: 2025-10-09 | K27: 20 | M27: 正常销售 | N27: 3C0092 | O27: 折叠电子琴61键 | P27: 英规插头（英标三脚插)，61键电子琴，适合儿童学习弹奏钢琴用的。配件：踏板+琴谱架+电源+小卡扣+英文说明书+中性包装。内置锂电池型号:18650，容量:1200MA。 | Q27: 47.5cm*23cm*11cm | R27: 2300 | S27: 3300 | T27: 56 | U27: 30 | V27: 18 | W27: 1 | X27: 走柜 | Y27: 马来易企通-D仓-1308 | Z27: 273 | AA27: 是 | AB27: 163.99 | AC27: 0.58 | AD27: 95.1142 | AE27: 118.8928 | AF27: 126.8189 | AG27: 146.3295 | AH27: 172.9349
... A67: 202606 | B67: M5CC3300284 | C67: 3B-便携式太阳能一体储能电源 | D67: CC0284 | E67: 马来 | F67: 办公安防 | G67: 储能设备 | H67: 便携储能电源 | I67: 2026-03-30 | J67: 2026-03-30 | K67: 6 | M67: 待开发 | N67: 3B0031 | O67: 便携电源 | P67: 英规插头，磷酸铁锂电池，电池容量12.8V,76.8WH；自带太阳能板规格16v12w，内置太阳能智能控制器，自动散热，额定功率100W，交流输出电压220V/110V，交流输出频率50Hz/60Hz，交流输出万能插座，直流输出电压USB*1输出QC18W；PD*1输出最大20W，带LED灯。AV充电器*1 | Q67: 25.3cm*21.4cm*8.4cm | R67: 1760 | S67: 2045 | T67: 7.25 | U67: 55 | V67: 34 | W67: 8 | X67: 中转 | Y67: 马来易企通-D仓-1308 | Z67: 0 | AA67: 是 | AB67: 247.0129 | AC67: 0.58 | AD67: 143.2675 | AE67: 179.0844 | AF67: 191.0233 | AG67: 220.4115 | AH67: 260.4863
A68: 202606 | B68: T1CC0200144 | C68: 3B-58mm手持蓝牙标签打印机 | D68: CC0144 | E68: 马来 | F68: 办公安防 | G68: 办公周边 | H68: 打印机 | I68: 2022-04-29 | J68: 2025-03-01 | K68: 18 | L68: 是 | M68: 正常销售 | N68: 3B0004 | O68: 小票打印机 | Q68: 10.5cm*7.8cm*4.7cm | R68: 222 | S68: 350 | T68: 1.2 | U68: 35 | V68: 30 | W68: 50 | X68: 中转 | Y68: 马来易企通-D仓-1308 | Z68: 7 | AA68: 是 | AB68: 57.49 | AC68: 0.58 | AD68: 33.3442 | AE68: 41.6802 | AF68: 44.4589 | AG68: 51.2988 | AH68: 60.6258
A69: 202606 | B69: T1CC0590138 | C69: 3C-投影仪支架 | D69: CC0138 | E69: 马来 | F69: 3C数码 | G69: 影像摄影 | H69: 投影仪支架-2 | I69: 2022-04-22 | J69: 2024-01-01 | K69: 30 | L69: 是 | M69: 正常销售 | N69: 3C0002 | O69: 投影仪支架系列 | P69: 金属材质、支架、最大可调节 1.2 米M、最大承重60公斤 | Q69: 60cm*12cm | R69: 1000 | S69: 1200 | T69: 6.4 | U69: 29 | V69: 60 | W69: 10 | X69: 中转 | Y69: 马来易企通-D仓-1308 | Z69: 279 | AA69: 是 | AB69: 40.43 | AC69: 0.58 | AD69: 23.4494 | AE69: 29.3117 | AF69: 31.2659 | AG69: 36.076 | AH69: 42.6353
A70: 202606 | B70: T1CZ0590139 | C70: 3C-投影仪支架托盘 | D70: CZ0139 | E70: 马来 | F70: 3C数码 | G70: 影像摄影 | H70: 投影仪支架-2 | I70: 2022-04-22 | J70: 2024-01-01 | K70: 30 | L70: 是 | M70: 清仓商品 | N70: 3C9999 | O70: 投影仪支架系列 | P70: 金属材质、加厚型托盘 | Q70: 26cm*36cm*1.5cm | R70: 666 | S70: 750 | T70: 1.3 | U70: 28 | V70: 23 | W70: 30 | X70: 中转 | Y70: 马来易企通-D仓-1308 | Z70: 218 | AA70: 是 | AB70: 4.0501 | AC70: 0.58 | AD70: 2.3491 | AE70: 2.9363 | AF70: 3.1321 | AG70: 3.6139 | AH70: 4.271
A71: 202606 | B71: T1CZ0590235 | C71: 3C-投影仪支架螺丝 | E71: 马来 | F71: 3C数码 | G71: 影像摄影 | H71: 螺丝配件 | I71: 2022-07-14 | J71: 2024-01-01 | K71: 30 | L71: 是 | M71: 待开发 | N71: 3C9999 | O71: 投影仪支架螺丝 | P71: 投影仪支架螺丝 | X71: 中转 | Y71: 马来易企通-D仓-1308 | Z71: 0 | AA71: 是 | AB71: 0.0001 | AC71: 0.58 | AD71: 0.0001 | AE71: 0.0001 | AF71: 0.0001 | AG71: 0.0001 | AH71: 0.0001
A72: 202606 | B72: T2CC0590108 | C72: 3C-加粗2.1米三角支架 | D72: CC0108 | E72: 马来 | F72: 3C数码 | G72: 影像摄影 | H72: 摄影器材支架 | I72: 2023-12-16 | J72: 2023-12-16 | K72: 43 | L72: 是 | M72: 正常销售 | N72: 3C0002 | O72: 投影仪支架系列 | P72: 2.1米（0.25厚钢管） | Q72: 68cm*6.5cm*6.5cm | R72: 500 | S72: 567 | T72: 2.3 | U72: 41 | V72: 35 | W72: 30 | X72: 中转 | Y72: 马来易企通-D仓-1308 | Z72: 0 | AA72: 是 | AB72: 13.32 | AC72: 0.58 | AD72: 7.7256 | AE72: 9.657 | AF72: 10.3008 | AG72: 11.8855 | AH72: 14.0465
A73: 202606 | B73: T2CC1060466 | C73: 3C-32寸电视气泡柱加厚款 | E73: 马来 | F73: 3C数码 | G73: 电视设备 | H73: 气泡柱 | I73: 2023-05-30 | J73: 2024-01-01 | K73: 30 | L73: 是 | M73: 正常销售 | N73: 3C0016 | O73: 电视气泡柱 | P73: 板尺寸：105*138cm，每套2个 | Q73: 105cm*138cm | R73: 350 | S73: 358 | T73: 0.7 | U73: 43 | V73: 18 | W73: 75 | X73: 中转 | Y73: 马来易企通-D仓-1308 | Z73: 11027 | AA73: 是 | AB73: 4.76 | AC73: 0.58 | AD73: 2.7608 | AE73: 3.451 | AF73: 3.6811 | AG73: 4.2474 | AH73: 5.0196
A74: 202606 | B74: T2CC1060467 | C74: 3C-43寸电视气泡柱加厚款 | E74: 马来 | F74: 3C数码 | G74: 电视设备 | H74: 气泡柱 | I74: 2023-05-30 | J74: 2024-01-01 | K74: 30 | L74: 是 | M74: 正常销售 | N74: 3C0016 | O74: 电视气泡柱 | P74: 板尺寸：110*177cm，每套2个 | Q74: 110cm*177cm | R74: 400 | S74: 496 | T74: 1.1 | U74: 43 | V74: 18 | W74: 50 | X74: 中转 | Y74: 马来易企通-D仓-1308 | Z74: 8999 | AA74: 是 | AB74: 6.46 | AC74: 0.58 | AD74: 3.7468 | AE74: 4.6835 | AF74: 4.9957 | AG74: 5.7643 | AH74: 6.8124
A75: 202606 | B75: T2CC1060478 | C75: 3C-50寸电视气泡柱加厚款 | E75: 马来 | F75: 3C数码 | G75: 电视设备 | H75: 气泡柱 | I75: 2023-06-09 | J75: 2024-01-01 | K75: 30 | L75: 是 | M75: 正常销售 | N75: 3C0016 | O75: 电视气泡柱 | P75: 板尺寸：110*195cm，每套2个 | Q75: 110cm*195cm | R75: 500 | S75: 540 | T75: 1.2 | U75: 43 | V75: 13 | W75: 50 | X75: 走柜 | Y75: 马来易企通-D仓-1308 | Z75: 1700 | AA75: 是 | AB75: 7.97 | AC75: 0.58 | AD75: 4.6226 | AE75: 5.7782 | AF75: 6.1635 | AG75: 7.1117 | AH75: 8.4047
A76: 202606 | B76: T2CC1120036 | C76: 3C-H型32至70寸电视壁架 | D76: CC0036 | E76: 马来 | F76: 3C数码 | G76: 电视设备 | H76: 电视支架 | I76: 2023-01-31 | J76: 2024-04-01 | K76: 30 | L76: 是 | M76: 正常销售 | N76: 3C0000 | O76: 壁挂电视支架 | P76: 升级款双臂适用32-70寸 | Q76: 67.5cm*39cm*24cm | R76: 5000 | S76: 5200 | T76: 13.4 | U76: 39 | V76: 24 | W76: 5 | X76: 走柜 | Y76: 马来易企通-D仓-1308 | Z76: 1134 | AA76: 是 | AB76: 55.05 | AC76: 0.58 | AD76: 31.929 | AE76: 39.9112 | AF76: 42.572 | AG76: 49.1215 | AH76: 58.0527
A77: 202606 | B77: T2CC1120040 | C77: 3C-X400电视壁挂架送膨胀丝等安装螺丝 | D77: CC0040 | E77: 马来 | F77: 3C数码 | G77: 电视设备 | H77: 电视支架 | I77: 2023-01-31 | J77: 2024-01-01 | K77: 30 | L77: 是 | M77: 正常销售 | N77: 3C0007 | O77: 壁挂电视支架 | P77: 英文说明书英文包装、X400适用32-55寸 | Q77: 44cm*32.5cm*24.5cm | R77: 1548 | S77: 1640 | T77: 4.2 | U77: 32 | V77: 24 | W77: 10 | X77: 走柜 | Y77: 马来易企通-D仓-1308 | Z77: 1102 | AA77: 是 | AB77: 18.45 | AC77: 0.58 | AD77: 10.701 | AE77: 13.3762 | AF77: 14.268 | AG77: 16.4631 | AH77: 19.4564
A78: 202606 | B78: T2CC1120079 | C78: 3C-电视壁挂架小一体 | D78: CC0079 | E78: 马来 | F78: 3C数码 | G78: 电视设备 | H78: 电视支架 | I78: 2023-01-31 | J78: 2024-01-01 | K78: 30 | L78: 是 | M78: 正常销售 | N78: 3C0007 | O78: 壁挂电视支架 | P78: 适用于：14-42寸、最大承重量25KG、英文说明书，中性包装 | Q78: 30cm*20cm*2.5cm | R78: 350 | S78: 470 | T78: 2.65 | U78: 31 | V78: 21 | W78: 20 | X78: 走柜 | Y78: 马来易企通-D仓-1308 | Z78: 1231 | AA78: 是 | AB78: 7.5 | AC78: 0.58 | AD78: 4.35 | AE78: 5.4375 | AF78: 5.8 | AG78: 6.6923 | AH78: 7.9091
A79: 202606 | B79: T2CC1120081 | C79: 3C-H型14至55寸电视壁架 | D79: CC0081 | E79: 马来 | F79: 3C数码 | G79: 电视设备 | H79: 电视支架 | I79: 2023-01-31 | J79: 2026-04-28 | K79: 6 | L79: 是 | M79: 正常销售 | N79: 3C0007 | O79: 壁挂电视支架 | P79: 402、承重50kg、适用于26寸-55寸、冷轧板、含膨胀丝等安装螺丝 | Q79: 57cm*40cm*24cm | R79: 4200 | S79: 4600 | T79: 11.4 | U79: 40 | V79: 24 | W79: 5 | X79: 中转 | Y79: 马来易企通-D仓-1308 | Z79: 0 | AA79: 是 | AB79: 56.61 | AC79: 0.58 | AD79: 32.8338 | AE79: 41.0422 | AF79: 43.7784 | AG79: 50.5135 | AH79: 59.6978
A80: 202606 | B80: T2CC1200005 | C80: 3B-保险箱黑小 | D80: CC0005 | E80: 马来 | F80: 办公安防 | G80: 安防存储 | H80: 保险箱 | I80: 2023-02-14 | J80: 2024-11-01 | K80: 31 | M80: 正常销售 | N80: 3B0001 | O80: 小尺寸保险箱 | P80: 23*17*17密码+钥匙 | Q80: 23cm*17cm*17cm | R80: 2000 | S80: 2600 | T80: 27 | U80: 21.5 | V80: 21.5 | W80: 1 | X80: 中转 | Y80: 马来易企通-D仓-1308 | Z80: 0 | AA80: 是 | AB80: 67 | AC80: 0.58 | AD80: 38.86 | AE80: 48.575 | AF80: 51.8133 | AG80: 59.7846 | AH80: 70.6545
A81: 202606 | B81: T2CC1200315 | C81: 3B-密码保险箱黑 | D81: CC0315 | E81: 马来 | F81: 办公安防 | G81: 安防存储 | H81: 保险箱 | I81: 2023-02-14 | J81: 2024-11-01 | K81: 31 | M81: 正常销售 | N81: 3B0001 | O81: 小尺寸保险箱 | P81: 35*25*25cm、支持密码、机械解锁 | Q81: 35cm*25cm*25cm | R81: 6000 | S81: 6575 | T81: 38 | U81: 30 | V81: 31 | W81: 1 | X81: 中转 | Y81: 马来易企通-D仓-1308 | Z81: 0 | AA81: 是 | AB81: 148.03 | AC81: 0.58 | AD81: 85.8574 | AE81: 107.3217 | AF81: 114.4765 | AG81: 132.0883 | AH81: 156.1044
A82: 202606 | B82: T2CC1200316 | C82: 3B-保险箱黑 | D82: CC0316 | E82: 马来 | F82: 办公安防 | G82: 安防存储 | H82: 保险箱 | I82: 2023-03-11 | J82: 2024-05-01 | K82: 30 | M82: 正常销售 | N82: 3B0001 | O82: 小尺寸保险箱 | P82: 31*20*20cm、支持密码、机械解锁 | Q82: 31cm*20cm*20cm | R82: 4300 | S82: 4600 | T82: 34 | U82: 25 | V82: 24.5 | W82: 1 | X82: 中转 | Y82: 马来易企通-D仓-1308 | Z82: 1 | AA82: 是 | AB82: 100.06 | AC82: 0.58 | AD82: 58.0348 | AE82: 72.5435 | AF82: 77.3797 | AG82: 89.2843 | AH82: 105.5178
A83: 202606 | B83: T2CC1220194 | C83: 3B-手提收银箱双层粉色 | D83: CC0194 | E83: 马来 | F83: 办公安防 | G83: 办公周边 | H83: 收银箱 | I83: 2023-02-14 | J83: 2024-01-01 | K83: 30 | M83: 清仓商品 | N83: 3B0009 | O83: 手提收银箱 | P83: 钱盒、四格五档双层钥匙款、 | Q83: 30cm*24cm*9cm | R83: 1700 | S83: 1800 | T83: 5 | U83: 48 | V83: 32.3 | W83: 10 | X83: 中转 | Y83: 马来易企通-D仓-1308 | Z83: 0 | AA83: 是 | AB83: 45.22 | AC83: 0.58 | AD83: 26.2276 | AE83: 32.7845 | AF83: 34.9701 | AG83: 40.3502 | AH83: 47.6865
A84: 202606 | B84: T2CC1270160 | C84: 3C-单臂显示器支架 | D84: CC0160 | E84: 马来 | F84: 3C数码 | G84: 电脑周边 | H84: 显示器支架 | I84: 2023-03-01 | J84: 2024-01-01 | K84: 30 | L84: 是 | M84: 正常销售 | N84: 3C0009 | O84: 单臂显示器支架 | P84: 适用于13寸-27寸显示器的单臂支架，180°旋转，360°旋转，倾斜度：-45~+45° | Q84: 44cm*19.5cm*6.6cm | R84: 1811 | S84: 2038 | T84: 5.63 | U84: 28 | V84: 30 | W84: 8 | X84: 中转 | Y84: 马来易企通-D仓-1308 | Z84: 2 | AA84: 是 | AB84: 41.94 | AC84: 0.58 | AD84: 24.3252 | AE84: 30.4065 | AF84: 32.4336 | AG84: 37.4234 | AH84: 44.2276
A85: 202606 | B85: T2CC1270161 | C85: 3C-双臂显示器支架 | D85: CC0161 | E85: 马来 | F85: 3C数码 | G85: 电脑周边 | H85: 显示器支架 | I85: 2023-03-01 | J85: 2024-01-01 | K85: 30 | L85: 是 | M85: 正常销售 | N85: 3C0004 | O85: 双臂显示器支架 | P85: 适用于13寸-27寸显示器的双臂支架，180°旋转，360°旋转，倾斜度：-45~+45° | Q85: 44.2cm*21cm*6.6cm | R85: 2539 | S85: 2772 | T85: 7.67 | U85: 23 | V85: 33 | W85: 6 | X85: 中转 | Y85: 马来易企通-D仓-1308 | Z85: 2 | AA85: 是 | AB85: 51.51 | AC85: 0.58 | AD85: 29.8758 | AE85: 37.3447 | AF85: 39.8344 | AG85: 45.9628 | AH85: 54.3196
A86: 202606 | B86: T2CC1270162 | C86: 3C-双臂带托盘显示器支架 | D86: CC0162 | E86: 马来 | F86: 3C数码 | G86: 电脑周边 | H86: 显示器支架 | I86: 2023-03-01 | J86: 2024-01-01 | K86: 30 | L86: 是 | M86: 正常销售 | N86: 3C0004 | O86: 双臂显示器支架 | P86: 通用双屏液晶显示器支架，带笔记本电脑托盘 | Q86: 42cm*33cm*8cm | R86: 3900 | S86: 4000 | T86: 10.4 | U86: 34 | V86: 34 | W86: 4 | X86: 走柜 | Y86: 马来易企通-D仓-1308 | Z86: 285 | AA86: 是 | AB86: 72.34 | AC86: 0.58 | AD86: 41.9572 | AE86: 52.4465 | AF86: 55.9429 | AG86: 64.5495 | AH86: 76.2858
A87: 202606 | B87: T2CC1270559 | C87: 3C-显示器支架立管ZTT003B | D87: CC0559 | E87: 马来 | F87: 3C数码 | G87: 电脑周边 | H87: 显示器支架 | I87: 2023-09-05 | J87: 2024-01-01 | K87: 30 | L87: 是 | M87: 正常销售 | N87: 3C0027 | O87: 增高显示器支架 | P87: 耐用金属搁板适合平板显示器、笔记本电脑和打印机，承重：20kg，高度可调节 | Q87: 39.2cm*24.6cm*3cm | R87: 850 | S87: 900 | T87: 3.22 | U87: 41 | V87: 27 | W87: 14 | X87: 中转 | Y87: 马来易企通-D仓-1308 | Z87: 121 | AA87: 是 | AB87: 18.96 | AC87: 0.58 | AD87: 10.9968 | AE87: 13.746 | AF87: 14.6624 | AG87: 16.9182 | AH87: 19.9942
A88: 202606 | B88: T2CC1270560 | C88: 3C-显示器支架立管带抽屉ZTT003DB | D88: CC0560 | E88: 马来 | F88: 3C数码 | G88: 电脑周边 | H88: 显示器支架 | I88: 2023-09-05 | J88: 2024-01-01 | K88: 30 | L88: 是 | M88: 正常销售 | N88: 3C0027 | O88: 增高显示器支架 | P88: 带抽屉，耐用金属搁板适合平板显示器、笔记本电脑和打印机，承重：20kg，高度可调节 | Q88: 37cm*23cm*14.5cm | R88: 980 | S88: 1194 | T88: 4.1 | U88: 36.5 | V88: 27.5 | W88: 10 | X88: 中转 | Y88: 马来易企通-D仓-1308 | Z88: 36 | AA88: 是 | AB88: 26.64 | AC88: 0.58 | AD88: 15.4512 | AE88: 19.314 | AF88: 20.6016 | AG88: 23.7711 | AH88: 28.0931
A89: 202606 | B89: T2CZ0590356 | C89: 3C-投影仪支架云台 | E89: 马来 | F89: 3C数码 | G89: 影像摄影 | H89: 投影仪支架 | I89: 2023-02-07 | J89: 2024-01-01 | K89: 30 | L89: 是 | M89: 清仓商品 | N89: 3C9999 | O89: 投影仪支架系列 | P89: 售后支架云台 | S89: 1200 | T89: 0.4 | U89: 59 | V89: 29 | W89: 170 | X89: 中转 | Y89: 马来易企通-D仓-1308 | Z89: 606 | AA89: 是 | AB89: 4.3601 | AC89: 0.58 | AD89: 2.5289 | AE89: 3.1611 | AF89: 3.3718 | AG89: 3.8906 | AH89: 4.5979
A90: 202606 | B90: T2CZ1480155 | C90: 3C-安卓电视机遥控器 | E90: 马来 | F90: 3C数码 | G90: 电视设备 | H90: 遥控器 | I90: 2023-08-17 | J90: 2024-01-01 | K90: 30 | L90: 是 | M90: 清仓商品 | N90: 3C9999 | O90: 电视机遥控器 | P90: 安卓电视机遥控器 | X90: 中转 | Y90: 马来易企通-D仓-1308 | Z90: 37 | AA90: 是 | AB90: 0.0001 | AC90: 0.58 | AD90: 0.0001 | AE90: 0.0001 | AF90: 0.0001 | AG90: 0.0001 | AH90: 0.0001
A91: 202606 | B91: T2CZ1480156 | C91: 3C-数字电视机遥控器 | E91: 马来 | F91: 3C数码 | G91: 电视设备 | H91: 遥控器 | I91: 2023-08-17 | J91: 2024-01-01 | K91: 30 | L91: 是 | M91: 清仓商品 | N91: 3C9999 | O91: 电视机遥控器 | P91: 数字电视机遥控器 | X91: 走柜 | Y91: 马来易企通-D仓-1308 | Z91: 17 | AA91: 是 | AB91: 0.0001 | AC91: 0.58 | AD91: 0.0001 | AE91: 0.0001 | AF91: 0.0001 | AG91: 0.0001 | AH91: 0.0001
A92: 202606 | B92: T3CC0960516 | C92: 3B-收银箱335金属黑色固定版 | D92: CC0516 | E92: 马来 | F92: 办公安防 | G92: 办公周边 | H92: 收银箱 | I92: 2024-01-27 | J92: 2024-01-27 | K92: 30 | M92: 正常销售 | N92: 3B0007 | O92: 商超收银箱 | P92: 335钱箱固定款、定制不含箱内数字、ABS材质、纸币格4格，硬币格3格。三档锁 | Q92: 33.5cm*36.8cm*8cm | R92: 3300 | S92: 3600 | T92: 41.5 | U92: 39.5 | V92: 14 | W92: 1 | X92: 中转 | Y92: 马来易企通-D仓-1308 | Z92: 0 | AA92: 是 | AB92: 97.88 | AC92: 0.58 | AD92: 56.7704 | AE92: 70.963 | AF92: 75.6939 | AG92: 87.3391 | AH92: 103.2189
A93: 202606 | B93: T3CC0960517 | C93: 3B-收银箱405金属黑色固定版 | D93: CC0517 | E93: 马来 | F93: 办公安防 | G93: 办公周边 | H93: 收银箱 | I93: 2024-01-27 | J93: 2024-01-27 | K93: 30 | M93: 正常销售 | N93: 3B0007 | O93: 商超收银箱 | P93: 405钱箱五档六格固定款、三档锁 | Q93: 40.5cm*42cm*10cm | R93: 4500 | S93: 5000 | T93: 48.5 | U93: 46.5 | V93: 14.5 | W93: 1 | X93: 走柜 | Y93: 马来易企通-D仓-1308 | Z93: 476 | AA93: 是 | AB93: 95.44 | AC93: 0.58 | AD93: 55.3552 | AE93: 69.194 | AF93: 73.8069 | AG93: 85.1618 | AH93: 100.6458
A94: 202606 | B94: T3CC1030076 | C94: 3B-磁吸数显快充充电宝10000mAh | D94: CC0076 | E94: 马来 | F94: 办公安防 | G94: 储能设备 | H94: 充电宝 | I94: 2024-06-27 | J94: 2024-06-27 | K94: 30 | L94: 是 | M94: 清仓商品 | N94: 3B0000 | O94: 磁吸充电宝 | P94: 型号:W017快充实标10000毫安，电池:136074*1片，材质:PC+ABS，USB1-2输出:4.5V5A5V3A9V2A12V1.6A；Type-C输出:5V3A9V2.2A12V1.6A；Type-C输入:5V3A9V2A12V1.5A；无线充输出;15W；配件：充电宝*1、数据线*1、说明书*1 | Q94: 10.3cm*6.8cm*2cm | R94: 191 | S94: 224 | T94: 0.5 | U94: 27.1 | V94: 31.5 | W94: 72 | X94: 散货 | Y94: 马来易企通-D仓-1308 | Z94: 0 | AA94: 是 | AB94: 40.27 | AC94: 0.58 | AD94: 23.3566 | AE94: 29.1957 | AF94: 31.1421 | AG94: 35.9332 | AH94: 42.4665
A95: 202606 | B95: T3CC1030155 | C95: 3B-胶囊充电宝5000毫安苹果接口白色 | D95: CC0155 | E95: 马来 | F95: 办公安防 | G95: 储能设备 | H95: 充电宝 | I95: 2024-08-13 | J95: 2024-08-13 | K95: 30 | L95: 是 | M95: 清仓商品 | N95: 3B0000 | O95: 胶囊充电宝 | P95: 型号:T186真显；电池:21700*1；电池容量：3000mAh；带真实电量数显；内含type-c数据线*1；配材质:PC+ABS；尺寸:81*28.5*49mm；输入:5V/2A输出:5V/2A；材质：PC+ABS | Q95: 8.1cm*4.9cm*2.8cm | R95: 123 | S95: 130 | T95: 0.5 | U95: 32.5 | V95: 23.5 | W95: 100 | X95: 散货 | Y95: 马来易企通-D仓-1308 | Z95: 4 | AA95: 是 | AB95: 19.6 | AC95: 0.58 | AD95: 11.368 | AE95: 14.21 | AF95: 15.1573 | AG95: 17.4892 | AH95: 20.6691
A96: 202606 | B96: T3CC1060601 | C96: 3C-55寸电视气泡柱加厚款 | E96: 马来 | F96: 3C数码 | G96: 电视设备 | H96: 气泡柱 | I96: 2023-11-30 | J96: 2023-12-01 | K96: 43 | L96: 是 | M96: 清仓商品 | N96: 3C0016 | O96: 电视气泡柱 | P96: 板尺寸：100cm*195cm，加厚，每套2个，用于55寸电视机包装 | Q96: 100cm*195cm | R96: 240 | S96: 245 | T96: 1.1 | U96: 41 | V96: 17 | W96: 50 | X96: 走柜 | Y96: 马来易企通-D仓-1308 | Z96: 896 | AA96: 是 | AB96: 8.37 | AC96: 0.58 | AD96: 4.8546 | AE96: 6.0682 | AF96: 6.4728 | AG96: 7.4686 | AH96: 8.8265
A97: 202606 | B97: T3CC1060652 | C97: 3C-气泡柱卷L150米 | E97: 马来 | F97: 3C数码 | G97: 电视设备 | H97: 气泡柱 | I97: 2024-04-09 | J97: 2024-04-09 | K97: 30 | L97: 是 | M97: 正常销售 | N97: 3C0041 | O97: 气泡柱卷 | P97: 一卷长度150米，直径0.2米，宽度1米，充气后宽度0.96米。 | Q97: 100cm*20cm*20cm | R97: 17300 | S97: 19600 | T97: 100 | U97: 20 | V97: 20 | W97: 1 | X97: 走柜 | Y97: 马来易企通-D仓-1308 | Z97: 986 | AA97: 是 | AB97: 292.4 | AC97: 0.58 | AD97: 169.592 | AE97: 211.99 | AF97: 226.1227 | AG97: 260.9108 | AH97: 308.3491
A98: 202606 | B98: T3CC1120404 | C98: 3C-26至63寸电视支架 | D98: CC0404 | E98: 马来 | F98: 3C数码 | G98: 电视设备 | H98: 电视支架 | I98: 2024-01-27 | J98: 2024-03-01 | K98: 30 | L98: 是 | M98: 正常销售 | N98: 3C0007 | O98: 壁挂电视支架 | P98: 型号：HD602B、适用于：23*55寸、冷轧板材质、英文说明书 | Q98: 53cm*49cm*22cm | R98: 520 | S98: 650 | T98: 2.7 | U98: 50 | V98: 20.5 | W98: 20 | X98: 走柜 | Y98: 马来易企通-D仓-1308 | Z98: 60 | AA98: 是 | AB98: 11.74 | AC98: 0.58 | AD98: 6.8092 | AE98: 8.5115 | AF98: 9.0789 | AG98: 10.4757 | AH98: 12.3804
A99: 202606 | B99: T3CC1120604 | C99: 3C-32至70寸电视移动支架的中托盘 | D99: CC0604 | E99: 马来 | F99: 3C数码 | G99: 电视设备 | H99: 电视支架托盘 | I99: 2023-12-16 | J99: 2024-01-01 | K99: 30 | L99: 是 | M99: 正常销售 | N99: 3C0038 | O99: 移动电视支架 | P99: 适用于：32-70寸电视移动支架专用中托盘。材质：冷轧板 | Q99: 48cm*29.5cm*0.5cm | R99: 1250 | S99: 1400 | T99: 3.34 | U99: 31.5 | V99: 30.5 | W99: 15 | X99: 走柜 | Y99: 马来易企通-D仓-1308 | Z99: 355 | AA99: 是 | AB99: 14.19 | AC99: 0.58 | AD99: 8.2302 | AE99: 10.2877 | AF99: 10.9736 | AG99: 12.6618 | AH99: 14.964
A100: 202606 | B100: T3CC1120605 | C100: 3C-32至70寸电视移动支架的单支架 | D100: CC0605 | E100: 马来 | F100: 3C数码 | G100: 电视设备 | H100: 电视支架 | I100: 2023-12-16 | J100: 2024-01-01 | K100: 30 | L100: 是 | M100: 正常销售 | N100: 3C0038 | O100: 移动电视支架 | P100: 适用于：32-70寸、材质：冷轧板；无上托盘和中托盘。 | Q100: 90cm*66cm*165cm至200cm | R100: 8050 | S100: 9300 | T100: 142.5 | U100: 34.6 | V100: 7.1 | W100: 1 | X100: 走柜 | Y100: 马来易企通-D仓-1308 | Z100: 376 | AA100: 是 | AB100: 99.81 | AC100: 0.58 | AD100: 57.8898 | AE100: 72.3622 | AF100: 77.1864 | AG100: 89.0612 | AH100: 105.2542
A101: 202606 | B101: T3CC1220672 | C101: 3B-仿真书银钱盒钥匙款蓝色 | D101: CC0672 | E101: 马来 | F101: 办公安防 | G101: 办公周边 | H101: 银钱盒 | I101: 2024-05-23 | J101: 2024-05-23 | K101: 30 | L101: 是 | M101: 清仓商品 | N101: 3B0022 | O101: 迷你收银箱 | P101: 钥匙款，中号，高度24cm | Q101: 24cm*15.5cm*5.5cm | R101: 760 | S101: 800 | T101: 3.25 | U101: 29.5 | V101: 25.5 | W101: 10 | X101: 中转 | Y101: 马来易企通-D仓-1308 | Z101: 1255 | AA101: 是 | AB101: 18.83 | AC101: 0.58 | AD101: 10.9214 | AE101: 13.6517 | AF101: 14.5619 | AG101: 16.8022 | AH101: 19.8571
A102: 202606 | B102: T3CC1220673 | C102: 3B-仿真书银钱盒密码款蓝色 | D102: CC0673 | E102: 马来 | F102: 办公安防 | G102: 办公周边 | H102: 银钱盒 | I102: 2024-05-23 | J102: 2024-05-23 | K102: 30 | L102: 是 | M102: 清仓商品 | N102: 3B0022 | O102: 迷你收银箱 | P102: 密码款，中号，高度24cm | Q102: 24cm*15.5cm*5.5cm | R102: 760 | S102: 800 | T102: 3.25 | U102: 29.5 | V102: 25.5 | W102: 10 | X102: 中转 | Y102: 马来易企通-D仓-1308 | Z102: 1009 | AA102: 是 | AB102: 19.78 | AC102: 0.58 | AD102: 11.4724 | AE102: 14.3405 | AF102: 15.2965 | AG102: 17.6498 | AH102: 20.8589
A103: 202606 | B103: T3CC1270045 | C103: 3C-组合双臂显示器支架 | D103: CC0045 | E103: 马来 | F103: 3C数码 | G103: 电脑周边 | H103: 显示器支架 | I103: 2024-10-10 | J103: 2024-10-10 | K103: 32 | M103: 正常销售 | N103: 3C0005 | O103: 气钢双臂显示器支架 | P103: 双臂支架适合屏幕13-34寸，气压调节，倾斜角度+70°至-45°，旋转范围+90°至-90°，适合桌面厚度10-70mm。 | Q103: 39.5cm*25.5cm*9.5cm | R103: 3119 | S103: 3802 | T103: 10.4 | U103: 41.5 | V103: 27 | W103: 5 | X103: 走柜 | Y103: 马来易企通-D仓-1308 | Z103: 353 | AA103: 是 | AB103: 95.46 | AC103: 0.58 | AD103: 55.3668 | AE103: 69.2085 | AF103: 73.8224 | AG103: 85.1797 | AH103: 100.6669
A104: 202606 | B104: T3CC1270169 | C104: 3C-电脑显示器支架 | D104: CC0169 | E104: 马来 | F104: 3C数码 | G104: 电脑周边 | H104: 显示器支架 | I104: 2024-10-10 | J104: 2024-10-10 | K104: 32 | L104: 是 | M104: 正常销售 | N104: 3C0003 | O104: 气钢单臂显示器支架 | P104: 单臂支架适合屏幕13-34寸，气压调节，倾斜角度+70°至-45°，旋转范围+90°至-90°，适合桌面厚度10-70mm。 | Q104: 39cm*20cm*9cm | R104: 1941 | S104: 2331 | T104: 5.13 | U104: 40 | V104: 39 | W104: 8 | X104: 走柜 | Y104: 马来易企通-D仓-1308 | Z104: 1611 | AA104: 是 | AB104: 52.98 | AC104: 0.58 | AD104: 30.7284 | AE104: 38.4105 | AF104: 40.9712 | AG104: 47.2745 | AH104: 55.8698
A105: 202606 | B105: T3CC1270257 | C105: 3C-立式显示器支架不带托盘 | D105: CC0257 | E105: 马来 | F105: 3C数码 | G105: 电脑周边 | H105: 显示器支架 | I105: 2024-11-12 | J105: 2024-11-12 | K105: 31 | M105: 正常销售 | N105: 3C0054 | O105: 立式显示器支架 | P105: 显示器尺寸: 32"-55" VESA:100x100,200x100,200x200,300x200,400x200,300x300,400x300,400x400，最大承重（屏幕）25kg，屏幕倾斜（前后）+5°~-0° | Q105: 154.5cm*40.3cm*35.2cm | R105: 4800 | S105: 5500 | T105: 43.5 | U105: 26 | V105: 13.5 | W105: 1 | X105: 中转 | Y105: 马来易企通-D仓-1308 | Z105: 0 | AA105: 是 | AB105: 107.02 | AC105: 0.58 | AD105: 62.0716 | AE105: 77.5895 | AF105: 82.7621 | AG105: 95.4948 | AH105: 112.8575
A106: 202606 | B106: T3CC1270279 | C106: 3C-桌面显示器支架钢化玻璃底座 | D106: CC0279 | E106: 马来 | F106: 3C数码 | G106: 电脑周边 | H106: 显示器支架 | I106: 2024-11-12 | J106: 2024-11-12 | K106: 31 | M106: 正常销售 | N106: 3C0061 | O106: 桌面显示器支架 | P106: 适配：32-55寸，最大承重40KG，VESA最大400*400；产品尺寸：400*260*660.5；钢化玻璃尺寸：400*260*8mm;挂钩2档高度调节，每当45mm调节，产品高度2档调节最高660.5mm.最小430.5mm | Q106: 66cm*40cm*26cm | R106: 4540 | S106: 4674 | T106: 11.5 | U106: 32 | V106: 30 | W106: 4 | X106: 走柜 | Y106: 马来易企通-D仓-1308 | Z106: 37 | AA106: 是 | AB106: 47.82 | AC106: 0.58 | AD106: 27.7356 | AE106: 34.6695 | AF106: 36.9808 | AG106: 42.6702 | AH106: 50.4284
A107: 202606 | B107: T3CC1500064 | C107: 3C-原木色吉他 | D107: CC0064 | E107: 马来 | F107: 3C数码 | G107: 音响乐器 | H107: 吉他套装 | I107: 2024-06-27 | J107: 2024-06-27 | K107: 30 | M107: 正常销售 | N107: 3C0047 | O107: 吉他 | P107: 38寸圆角吉他*1、拨片*2、琴弦*1 | Q107: 96.5cm*42cm*10.5cm | R107: 1350 | S107: 1700 | T107: 9.8 | U107: 54 | V107: 52 | W107: 10 | X107: 走柜 | Y107: 马来易企通-D仓-1308 | Z107: 6 | AA107: 是 | AB107: 71.51 | AC107: 0.58 | AD107: 41.4758 | AE107: 51.8447 | AF107: 55.3011 | AG107: 63.8089 | AH107: 75.4105
A108: 202606 | B108: T3CC1500210 | C108: 3C-黑色吉他 | D108: CC0210 | E108: 马来 | F108: 3C数码 | G108: 音响乐器 | H108: 吉他套装 | I108: 2024-09-03 | J108: 2024-09-03 | K108: 30 | M108: 正常销售 | N108: 3C0047 | O108: 吉他 | P108: 38寸圆角，亮面：吉他*1、拨片*2、琴弦*1 | Q108: 96.5cm*42cm*10.5cm | R108: 1050 | S108: 1450 | T108: 9.8 | U108: 54 | V108: 52 | W108: 10 | X108: 走柜 | Y108: 马来易企通-D仓-1308 | Z108: 0 | AA108: 是 | AB108: 71.51 | AC108: 0.58 | AD108: 41.4758 | AE108: 51.8447 | AF108: 55.3011 | AG108: 63.8089 | AH108: 75.4105
A109: 202606 | B109: T3CC1500228 | C109: 3C-黑色吉他套装 | D109: CC0228 | E109: 马来 | F109: 3C数码 | G109: 音响乐器 | H109: 吉他套装 | I109: 2024-09-14 | J109: 2024-09-14 | K109: 30 | M109: 正常销售 | N109: 3C0047 | O109: 吉他 | P109: 38寸圆角吉他，拨片*2+琴弦*1+琴包*1+调音笛*1 | Q109: 96.5cm*42cm*10.5cm | R109: 1600 | S109: 2000 | T109: 10.1 | U109: 54 | V109: 52.5 | W109: 10 | X109: 走柜 | Y109: 马来易企通-D仓-1308 | Z109: 300 | AA109: 是 | AB109: 83.02 | AC109: 0.58 | AD109: 48.1516 | AE109: 60.1895 | AF109: 64.2021 | AG109: 74.0794 | AH109: 87.5484
A110: 202606 | B110: T3CC1500261 | C110: 3C-原木色民谣吉他 | D110: CC0261 | E110: 马来 | F110: 3C数码 | G110: 音响乐器 | H110: 吉他套装 | I110: 2024-11-12 | J110: 2024-11-12 | K110: 31 | M110: 清仓商品 | N110: 3C0047 | O110: 吉他 | P110: 38寸缺角吉他、包、原木色 | Q110: 96.5cm*42cm*10.5cm | R110: 1800 | S110: 2000 | T110: 9.8 | U110: 54 | V110: 52 | W110: 10 | X110: 走柜 | Y110: 马来易企通-D仓-1308 | Z110: 0 | AA110: 是 | AB110: 86.07 | AC110: 0.58 | AD110: 49.9206 | AE110: 62.4007 | AF110: 66.5608 | AG110: 76.8009 | AH110: 90.7647
A111: 202606 | B111: T3CC1500280 | C111: 3C-黑色民谣吉他 | D111: CC0280 | E111: 马来 | F111: 3C数码 | G111: 音响乐器 | H111: 吉他套装 | I111: 2024-11-12 | J111: 2024-11-12 | K111: 31 | M111: 正常销售 | N111: 3C0047 | O111: 吉他 | P111: 38寸缺角吉他、包、黑色 | Q111: 96.5cm*42cm*10.5cm | R111: 1800 | S111: 2000 | T111: 9.8 | U111: 54 | V111: 52 | W111: 10 | X111: 走柜 | Y111: 马来易企通-D仓-1308 | Z111: 4 | AA111: 是 | AB111: 86.07 | AC111: 0.58 | AD111: 49.9206 | AE111: 62.4007 | AF111: 66.5608 | AG111: 76.8009 | AH111: 90.7647
A112: 202606 | B112: T3CC1500688 | C112: 3C-原木色吉他套装 | D112: CC0688 | E112: 马来 | F112: 3C数码 | G112: 音响乐器 | H112: 吉他套装 | I112: 2024-06-27 | J112: 2024-06-27 | K112: 30 | M112: 正常销售 | N112: 3C0047 | O112: 吉他 | P112: 38寸圆角吉他，拨片*2+琴弦*1+琴包*1+调音笛*1 | Q112: 96.5cm*42cm*10.5cm | R112: 1600 | S112: 2000 | T112: 10.1 | U112: 54 | V112: 52.5 | W112: 10 | X112: 走柜 | Y112: 马来易企通-D仓-1308 | Z112: 325 | AA112: 是 | AB112: 83.02 | AC112: 0.58 | AD112: 48.1516 | AE112: 60.1895 | AF112: 64.2021 | AG112: 74.0794 | AH112: 87.5484
A113: 202606 | B113: T3CC1500689 | C113: 3C-21寸尤克里里 | D113: CC0689 | E113: 马来 | F113: 3C数码 | G113: 音响乐器 | H113: 吉他套装 | I113: 2024-06-27 | J113: 2024-06-27 | K113: 30 | M113: 正常销售 | N113: 3C0047 | O113: 吉他 | P113: 21寸尤克里里*1、拨片*2、琴弦*1 | Q113: 53.5cm*20cm*6.7cm | R113: 400 | S113: 500 | T113: 2.9 | U113: 56 | V113: 35 | W113: 20 | X113: 走柜 | Y113: 马来易企通-D仓-1308 | Z113: 640 | AA113: 是 | AB113: 27.46 | AC113: 0.58 | AD113: 15.9268 | AE113: 19.9085 | AF113: 21.2357 | AG113: 24.5028 | AH113: 28.9578
A114: 202606 | B114: T3CC1800572 | C114: 3C-360有线游戏手柄不带耳麦黑色 | D114: CC0572 | E114: 马来 | F114: 3C数码 | G114: 游戏娱乐 | H114: 游戏手柄 | I114: 2023-10-07 | J114: 2023-10-07 | K114: 44 | L114: 是 | M114: 正常销售 | N114: 3C0030 | O114: 360游戏手柄 | P114: 型号NJP301B，USB有线连接，数字模拟，非对称双震动，连接线2米，适用设备：PC电脑、PC360、PS3主机、安卓系统。 | Q114: 15.2cm*10.5cm*5.8cm | R114: 250 | S114: 300 | T114: 1.1 | U114: 35 | V114: 33 | W114: 50 | X114: 中转 | Y114: 马来易企通-D仓-1308 | Z114: 367 | AA114: 是 | AB114: 18.56 | AC114: 0.58 | AD114: 10.7648 | AE114: 13.456 | AF114: 14.3531 | AG114: 16.5612 | AH114: 19.5724
A115: 202606 | B115: T3CC1800622 | C115: 3C-360有线游戏手柄不带耳麦白色 | D115: CC0622 | E115: 马来 | F115: 3C数码 | G115: 游戏娱乐 | H115: 游戏手柄 | I115: 2024-02-27 | J115: 2024-09-01 | K115: 30 | L115: 是 | M115: 正常销售 | N115: 3C0030 | O115: 360游戏手柄 | P115: 型号NJP301B，USB有线连接，数字模拟，非对称双震动，连接线2米，适用设备：PC电脑、PC360、PS3主机、安卓系统。 | Q115: 15.2cm*10.5cm*5.8cm | R115: 250 | S115: 285 | T115: 1.1 | U115: 35 | V115: 33 | W115: 50 | X115: 中转 | Y115: 马来易企通-D仓-1308 | Z115: 219 | AA115: 是 | AB115: 19.06 | AC115: 0.58 | AD115: 11.0548 | AE115: 13.8185 | AF115: 14.7397 | AG115: 17.0074 | AH115: 20.0996
A116: 202606 | B116: T3CC1800664 | C116: 3C-铜纤维游戏指套 | D116: CC0664 | E116: 马来 | F116: 3C数码 | G116: 游戏娱乐 | H116: 游戏指套 | I116: 2024-05-06 | J116: 2024-06-01 | K116: 30 | L116: 是 | M116: 清仓商品 | N116: 3C0046 | O116: 游戏指套 | P116: 铜纤维手指套一对装，24针工艺 | Q116: 7cm*7cm*6.5cm | R116: 2 | S116: 3 | T116: 0.01 | U116: 40 | V116: 32 | W116: 5000 | X116: 中转 | Y116: 马来易企通-D仓-1308 | Z116: 763 | AA116: 是 | AB116: 2.346 | AC116: 0.58 | AD116: 1.3607 | AE116: 1.7008 | AF116: 1.8142 | AG116: 2.0934 | AH116: 2.474
A117: 202606 | B117: T3CC1800666 | C117: 3C-X3游戏手柄带手机支架 | D117: CC0666 | E117: 马来 | F117: 3C数码 | G117: 游戏娱乐 | H117: 游戏手柄 | I117: 2024-05-06 | J117: 2024-06-01 | K117: 30 | L117: 是 | M117: 正常销售 | N117: 3C0044 | O117: X3游戏手柄 | P117: ABS材质壳料，手柄有配充电线，手柄内置聚合物电池350毫安，手柄不带震动，手柄配手机支架，充电线0.5M（或另购数据线），说明书，支持安卓系统，苹果手机，电脑，PS3主机，PS4主机，SWITCH主机 | Q117: 17cm*11cm*6.5cm | R117: 220 | S117: 250 | T117: 1.2 | U117: 35.5 | V117: 35 | W117: 50 | X117: 中转 | Y117: 马来易企通-D仓-1308 | Z117: 1000 | AA117: 是 | AB117: 24.94 | AC117: 0.58 | AD117: 14.4652 | AE117: 18.0815 | AF117: 19.2869 | AG117: 22.2542 | AH117: 26.3004
A118: 202606 | B118: T3CC1880108 | C118: 3C-加粗2.1米三角支架 | D118: CC0108 | E118: 马来 | F118: 3C数码 | G118: 影像摄影 | H118: 摄影器材支架 | I118: 2024-01-02 | J118: 2025-09-11 | K118: 18 | L118: 是 | M118: 清仓商品 | N118: 3C0000 | O118: 投影仪支架系列 | P118: 2.1米（0.25厚钢管） | Q118: 68cm*6.5cm*6.5cm | R118: 380 | S118: 500 | T118: 2.3 | U118: 42 | V118: 35 | W118: 30 | X118: 中转 | Y118: 马来易企通-D仓-1308 | Z118: 12 | AA118: 是 | AB118: 13.42 | AC118: 0.58 | AD118: 7.7836 | AE118: 9.7295 | AF118: 10.3781 | AG118: 11.9748 | AH118: 14.152
A119: 202606 | B119: T3CC1880608 | C119: 3C-投影仪支架云台32cm*25cm | D119: CC0608 | E119: 马来 | F119: 3C数码 | G119: 影像摄影 | H119: 投影仪支架 | I119: 2023-12-28 | J119: 2024-01-01 | K119: 30 | L119: 是 | M119: 正常销售 | N119: 3C0002 | O119: 投影仪支架系列 | P119: 金属，尺寸32cm*25cm，厚度0.8mm，海绵垫*1，绑带*2， 底盘螺丝接口是3/8的 | Q119: 32cm*25cm*1.5cm | R119: 740 | S119: 860 | T119: 2.7 | U119: 35 | V119: 26.3 | W119: 20 | X119: 中转 | Y119: 马来易企通-D仓-1308 | Z119: 9 | AA119: 是 | AB119: 12.24 | AC119: 0.58 | AD119: 7.0992 | AE119: 8.874 | AF119: 9.4656 | AG119: 10.9218 | AH119: 12.9076
A120: 202606 | B120: T3CC1880611 | C120: 3C-投影仪支架1.2米 | D120: CC0611 | E120: 马来 | F120: 3C数码 | G120: 影像摄影 | H120: 投影仪支架 | I120: 2024-01-09 | J120: 2024-01-09 | K120: 30 | L120: 是 | M120: 正常销售 | N120: 3C0002 | O120: 投影仪支架系列 | P120: 支架长度78.5cm-120cm*7.5cm-42cm，金属材质、支架、最大可调节 1.2 米，最大承重20公斤 | Q120: 78.5cm*8cm*8cm | R120: 530 | S120: 670 | T120: 7.6 | U120: 39 | V120: 17.8 | W120: 10 | X120: 中转 | Y120: 马来易企通-D仓-1308 | Z120: 326 | AA120: 是 | AB120: 17.57 | AC120: 0.58 | AD120: 10.1906 | AE120: 12.7382 | AF120: 13.5875 | AG120: 15.6778 | AH120: 18.5284
A121: 202606 | B121: T3CC1910582 | C121: 3C-15.6寸60Hz直面1K便携式触摸显示器黑色 | D121: CC0582 | E121: 马来 | F121: 3C数码 | G121: 电脑周边 | H121: 显示器 | I121: 2024-03-19 | J121: 2024-03-19 | K121: 30 | M121: 正常销售 | N121: 3C0033 | O121: 15.6寸便携显示器触摸款 | P121: 触摸版，不配皮套，15.6英寸，分辨率1920*1080P，IPS面板，显示比例16：9，刷新率60Hz，最大亮度240cd/㎡，全塑胶+小支架，电源输入5V-20V，功耗≤15W，内置音箱，HDR功能，USB供电；产品接口：TYPE-C信号输入 *1，迷你HDMI信号输入 *1，Type-C电源输入 *1，3.5mm音频输出 * 1；包装清单：显示器主机 *1，HDMI线 *1，TYPE-C to TYPE-C线 *1，USB 供电线 *2，说明书 *1 | Q121: 35.5cm*22.2cm*1.3cm | R121: 929 | S121: 1480 | T121: 5.5 | U121: 42 | V121: 29 | W121: 10 | X121: 中转 | Y121: 马来易企通-D仓-1308 | Z121: 0 | AA121: 是 | AB121: 346.53 | AC121: 0.58 | AD121: 200.9874 | AE121: 251.2342 | AF121: 267.9832 | AG121: 309.2114 | AH121: 365.4316
A122: 202606 | B122: T3CC1910583 | C122: 3C-15.6寸60Hz直面1K便携式显示器黑色 | D122: CC0583 | E122: 马来 | F122: 3C数码 | G122: 电脑周边 | H122: 显示器 | I122: 2024-03-19 | J122: 2024-04-01 | K122: 30 | M122: 正常销售 | N122: 3C0080 | O122: 15.6寸便携显示器非触摸款 | P122: 无触摸版，不配皮套，15.6英寸，分辨率1920*1080P，IPS面板，显示比例16：9，刷新率60Hz，最大亮度240cd/㎡，全塑胶+小支架，电源输入5V-20V，功耗≤15W，内置音箱，HDR功能，USB供电；产品接口：TYPE-C信号输入 *1，迷你HDMI信号输入 *1，Type-C电源输入 *1，3.5mm音频输出 * 1；包装清单：显示器主机 *1，HDMI线 *1，TYPE-C to TYPE-C线 *1，USB 供电线 *1，说明书 *1 | Q122: 35.5cm*22.2cm*1.3cm | R122: 830 | S122: 1378 | T122: 5.5 | U122: 42 | V122: 29 | W122: 10 | X122: 中转 | Y122: 马来易企通-D仓-1308 | Z122: 1 | AA122: 是 | AB122: 248.3 | AC122: 0.58 | AD122: 144.014 | AE122: 180.0175 | AF122: 192.0187 | AG122: 221.56 | AH122: 261.8436
A123: 202606 | B123: T3CC1910678 | C123: 3C-11.6寸60Hz直面1K便携式显示器无触摸黑色 | D123: CC0678 | E123: 马来 | F123: 3C数码 | G123: 电脑周边 | H123: 显示器 | I123: 2024-06-04 | J123: 2024-06-04 | K123: 30 | M123: 正常销售 | N123: 3C0081 | O123: 11.6寸便携显示器非触摸款 | P123: 无触摸版，配皮套，11.6英寸，分辨率1366*768P，显示比例16：9，刷新率60Hz，最大亮度240cd/㎡，全塑胶，电源输入5V-20V，功耗≤15W，内置音箱，USB供电；产品接口：TYPE-C信号输入 *1，迷你HDMI信号输入 *1，Type-C电源输入 *1，3.5mm音频输出 * 1；包装清单：显示器主机 *1，HDMI线 *1，TYPE-C to TYPE-C线 *1，USB 供电线 *1，说明书 *1，皮套*1 | Q123: 28cm*18cm*1.5cm | R123: 722 | S123: 940 | T123: 2.45 | U123: 44 | V123: 36 | W123: 20 | X123: 中转 | Y123: 马来易企通-D仓-1308 | Z123: 417 | AA123: 是 | AB123: 155.04 | AC123: 0.58 | AD123: 89.9232 | AE123: 112.404 | AF123: 119.8976 | AG123: 138.3434 | AH123: 163.4967
A124: 202606 | B124: T3CC1920633 | C124: 3C-电子琴37健黑色 | D124: CC0633 | E124: 马来 | F124: 3C数码 | G124: 音响乐器 | H124: 电子琴 | I124: 2024-03-19 | J124: 2024-03-19 | K124: 30 | M124: 正常销售 | N124: 3C0040 | O124: 电子琴 | P124: 型号1427B，37个黑白琴键，不带插头，电池款（3个五号电池插槽），英文版包装 | Q124: 35cm*13cm*4cm | R124: 253 | S124: 303 | T124: 1.21 | U124: 55 | V124: 36.5 | W124: 48 | X124: 中转 | Y124: 马来易企通-D仓-1308 | Z124: 366 | AA124: 是 | AB124: 19.64 | AC124: 0.58 | AD124: 11.3912 | AE124: 14.239 | AF124: 15.1883 | AG124: 17.5249 | AH124: 20.7113
A125: 202606 | B125: T3CC1920634 | C125: 3C-电子琴61健黑色 | D125: CC0634 | E125: 马来 | F125: 3C数码 | G125: 音响乐器 | H125: 电子琴 | I125: 2024-03-19 | J125: 2024-03-19 | K125: 30 | M125: 正常销售 | N125: 3C0040 | O125: 电子琴 | P125: 型号6106，61个黑白琴键，不带插头，配USB线*1，话筒*1，英文包装、英文说明书 | Q125: 51cm*16.5cm*5cm | R125: 657 | S125: 707 | T125: 2.9 | U125: 55 | V125: 36.5 | W125: 20 | X125: 中转 | Y125: 马来易企通-D仓-1308 | Z125: 800 | AA125: 是 | AB125: 39.98 | AC125: 0.58 | AD125: 23.1884 | AE125: 28.9855 | AF125: 30.9179 | AG125: 35.6745 | AH125: 42.1607
A126: 202606 | B126: T3CC1950595 | C126: 3B-户外太阳能单板摄像头WiFi版 | D126: CC0595 | E126: 马来 | F126: 办公安防 | G126: 智能安防 | H126: 摄像头 | I126: 2024-03-26 | J126: 2024-03-26 | K126: 30 | L126: 是 | M126: 清仓商品 | N126: 3B0020 | O126: 太阳能摄像头 | P126: V360系统，WIFI版，联网方式WIFI-2.4GHz，300W像素，数字变焦，4倍变焦，垂直旋转90°，水平旋转角度355°；分辨率1920*1080；电压5V2A，太阳能供电，焦距4mm；红外夜视距离8-15米。设备扫码添加，WiFi连接；防水防雷，语音对讲，人形追踪，手机报警。支持各类手机远程监控（IOS,Android）；支持8-128GTF卡存储；太阳能整套含5节电池（10000mah)含7W光伏板。英文包装、英文说明书。 | Q126: 37.4cm*27cm*21cm | R126: 650 | S126: 1400 | T126: 3.5 | U126: 57 | V126: 54 | W126: 18 | X126: 中转 | Y126: 马来易企通-D仓-1308 | Z126: 17 | AA126: 是 | AB126: 120.46 | AC126: 0.58 | AD126: 69.8668 | AE126: 87.3335 | AF126: 93.1557 | AG126: 107.4874 | AH126: 127.0305
A127: 202606 | B127: T3CC1950642 | C127: 3B-双目灯泡摄像头 | D127: CC0642 | E127: 马来 | F127: 办公安防 | G127: 智能安防 | H127: 摄像头 | I127: 2024-03-26 | J127: 2024-03-26 | K127: 30 | L127: 是 | M127: 清仓商品 | N127: 3B0000 | O127: 户外摄像头 | P127: 8灯双目，联网方式WIFI-2.4GHz，200万像素，分辨率1920*1080；垂直旋转20°，水平转速350°，垂直转速30°/S；室内款不防水；电压AC110V-220V；红外夜视距离20米；自动光圈，电源供电；镜头3.6mm，焦距4mm；支持语音监听，对讲，移动侦测、声音侦测报警；无线网络802.11b/g/n；支持云存储/TF卡存储；支持各类手机远程监控（IOS,Android）；英文包装、英文说明书。英文包装、英文说明书。 | Q127: 17cm*9.5cm*8cm | R127: 200 | S127: 250 | T127: 1.1 | U127: 40 | V127: 36 | W127: 40 | X127: 中转 | Y127: 马来易企通-D仓-1308 | Z127: 3 | AA127: 是 | AB127: 49.18 | AC127: 0.58 | AD127: 28.5244 | AE127: 35.6555 | AF127: 38.0325 | AG127: 43.8837 | AH127: 51.8625
A128: 202606 | B128: T3CC1970380 | C128: 3C-M98型机顶盒 | D128: CC0380 | E128: 马来 | F128: 3C数码 | G128: 电视设备 | H128: 机顶盒 | I128: 2024-05-23 | J128: 2024-09-01 | K128: 30 | M128: 正常销售 | N128: 3C0008 | O128: 机顶盒 | P128: 配遥控器、出4+64G，双wifi google ATV 版本，无蓝牙 | Q128: 8.9cm*3.5cm*1.5cm | R128: 155 | S128: 163 | T128: 0.46 | U128: 42.5 | V128: 32.5 | W128: 100 | X128: 中转 | Y128: 马来易企通-D仓-1308 | Z128: 3141 | AA128: 是 | AB128: 80.78 | AC128: 0.58 | AD128: 46.8524 | AE128: 58.5655 | AF128: 62.4699 | AG128: 72.0806 | AH128: 85.1862
A129: 202606 | B129: T3CC1980683 | C129: 3B-磁吸白板30cm*45cm | D129: CC0683 | E129: 马来 | F129: 办公安防 | G129: 教学周边 | H129: 教具白板 | I129: 2024-06-24 | J129: 2024-06-24 | K129: 30 | M129: 清仓商品 | N129: 3B0024 | O129: 磁吸白板 | P129: 30*45CM,镀锌背板，铝合金边框，蜂窝板，哑光高分子树脂烤漆涂层面板。一支红笔，一支黑笔，一块黑板擦。 | Q129: 45cm*30cm*2cm | R129: 500 | S129: 800 | T129: 55 | U129: 32.5 | V129: 3.5 | W129: 1 | X129: 走柜 | Y129: 马来易企通-D仓-1308 | Z129: 1 | AA129: 是 | AB129: 15.01 | AC129: 0.58 | AD129: 8.7058 | AE129: 10.8822 | AF129: 11.6077 | AG129: 13.3935 | AH129: 15.8287
A130: 202606 | B130: T3CC1980686 | C130: 3B-白板通用支架60cm*100cm | D130: CC0686 | E130: 马来 | F130: 办公安防 | G130: 教学周边 | H130: 支架 | I130: 2024-06-24 | J130: 2024-06-24 | K130: 30 | L130: 是 | M130: 清仓商品 | N130: 3B0023 | O130: 白板支架 | P130: 60-100CM白板通用支架，铁质，八个螺丝，四个轮子。 | Q130: 100cm*60cm*2cm | R130: 1400 | S130: 1600 | T130: 11.56 | U130: 27 | V130: 25 | W130: 9 | X130: 走柜 | Y130: 马来易企通-D仓-1308 | Z130: 20 | AA130: 是 | AB130: 23.44 | AC130: 0.58 | AD130: 13.5952 | AE130: 16.994 | AF130: 18.1269 | AG130: 20.9157 | AH130: 24.7185
A131: 202606 | B131: T3CC2000072 | C131: 3C-数码相机银色6400万像素 | D131: CC0072 | E131: 马来 | F131: 3C数码 | G131: 影像摄影 | H131: 数码相机 | I131: 2024-06-27 | J131: 2024-06-27 | K131: 30 | M131: 清仓商品 | N131: 3C0000 | O131: 数码相机 | P131: 银色，6400万像素，2.8"高清显示屏，英语、简体中文、繁体中文、日本语、德语、法语、意大利语、西班牙语、葡萄牙语、俄语、韩语、泰语，锂离子电池(BL-5B)，usb、擦镜布、说明书、挂绳。 | Q131: 15cm*15cm*7cm | R131: 90 | S131: 180 | T131: 1.1 | U131: 37 | V131: 22 | W131: 50 | X131: 中转 | Y131: 马来易企通-D仓-1308 | Z131: 47 | AA131: 是 | AB131: 102.36 | AC131: 0.58 | AD131: 59.3688 | AE131: 74.211 | AF131: 79.1584 | AG131: 91.3366 | AH131: 107.9433
A132: 202606 | B132: T3CC2010101 | C132: 3C-插电式分体电动旋转盘白色20cm | D132: CC0101 | E132: 马来 | F132: 3C数码 | G132: 数码配件 | H132: 展示台 | I132: 2024-07-18 | J132: 2024-07-18 | K132: 30 | M132: 正常销售 | N132: 3C0050 | O132: 插电式展示台 | P132: 直径:20cm，高度:5.5cm，最大承重:约3kg，方向:顺逆可调，转速:25秒每圈，电源:插电5V，13cm底座*1、20cm托盘*1、说明书*1、合格证*1、type-c数据线*1 | Q132: 20cm*13cm*5.5cm | R132: 410 | S132: 470 | T132: 2.9 | U132: 46 | V132: 27 | W132: 16 | X132: 中转 | Y132: 马来易企通-D仓-1308 | Z132: 301 | AA132: 是 | AB132: 25.61 | AC132: 0.58 | AD132: 14.8538 | AE132: 18.5672 | AF132: 19.8051 | AG132: 22.852 | AH132: 27.0069
A133: 202606 | B133: T3CC2010102 | C133: 3C-插电式分体电动旋转盘黑色13cm | D133: CC0102 | E133: 马来 | F133: 3C数码 | G133: 数码配件 | H133: 展示台 | I133: 2024-07-18 | J133: 2024-07-18 | K133: 30 | M133: 正常销售 | N133: 3C0050 | O133: 插电式展示台 | P133: 直径:13cm，高度:4.5cm，最大承重:约3kg，方向:顺逆可调，转速:25秒每圈，电源:插电5V，13cm底座*1、说明书*1、合格证*1、type-c数据线*1 | Q133: 13cm*10cm*4.5cm | R133: 240 | S133: 250 | T133: 2 | U133: 32.5 | V133: 23.5 | W133: 24 | X133: 中转 | Y133: 马来易企通-D仓-1308 | Z133: 417 | AA133: 是 | AB133: 16.54 | AC133: 0.58 | AD133: 9.5932 | AE133: 11.9915 | AF133: 12.7909 | AG133: 14.7588 | AH133: 17.4422
A134: 202606 | B134: T3CC2010111 | C134: 3C-插电式分体电动旋转盘黑色20cm | D134: CC0111 | E134: 马来 | F134: 3C数码 | G134: 数码配件 | H134: 展示台 | I134: 2024-07-18 | J134: 2024-07-18 | K134: 30 | M134: 正常销售 | N134: 3C0050 | O134: 插电式展示台 | P134: 直径:20cm，高度:5.5cm，最大承重:约3kg，方向:顺逆可调，转速:25秒每圈，电源:插电5V，13cm底座*1、20cm托盘*1、说明书*1、合格证*1、type-c数据线*1 | Q134: 20cm*13cm*5.5cm | R134: 410 | S134: 470 | T134: 2.9 | U134: 46 | V134: 27 | W134: 16 | X134: 中转 | Y134: 马来易企通-D仓-1308 | Z134: 4 | AA134: 是 | AB134: 25.61 | AC134: 0.58 | AD134: 14.8538 | AE134: 18.5672 | AF134: 19.8051 | AG134: 22.852 | AH134: 27.0069
A135: 202606 | B135: T3CC2010227 | C135: 3C-插电式分体电动旋转盘白色13cm | D135: CC0227 | E135: 马来 | F135: 3C数码 | G135: 数码配件 | H135: 展示台 | I135: 2024-09-12 | J135: 2024-09-12 | K135: 30 | M135: 正常销售 | N135: 3C0050 | O135: 插电式展示台 | P135: 直径:13cm，高度:4.5cm，最大承重:约3kg，方向:顺逆可调，转速:25秒每圈，电源:插电5V，13cm底座*1、说明书*1、合格证*1、type-c数据线*1 | Q135: 13cm*10cm*4.5cm | R135: 240 | S135: 250 | T135: 1.98 | U135: 32.5 | V135: 23.5 | W135: 24 | X135: 中转 | Y135: 马来易企通-D仓-1308 | Z135: 229 | AA135: 是 | AB135: 16.53 | AC135: 0.58 | AD135: 9.5874 | AE135: 11.9842 | AF135: 12.7832 | AG135: 14.7498 | AH135: 17.4316
A136: 202606 | B136: T3CC2040167 | C136: 3B-手持一维有线影像扫描枪 | D136: CC0167 | E136: 马来 | F136: 办公安防 | G136: 办公周边 | H136: 扫码枪 | I136: 2024-08-13 | J136: 2024-08-13 | K136: 30 | M136: 清仓商品 | N136: 3B0011 | O136: 一维扫描枪 | P136: 材质：ABS;参数：CCD,扫描一维码。它是用于读取条码所包含信息的阅读设备，利用光学原理，把条形码的内容解码后通过数据线或者无线的方式传输到电脑或者别的设备。 | Q136: 150cm*70cm*95cm | R136: 210 | S136: 220 | T136: 1 | U136: 40 | V136: 40 | W136: 50 | X136: 中转 | Y136: 马来易企通-D仓-1308 | Z136: 1 | AA136: 是 | AB136: 35.76 | AC136: 0.58 | AD136: 20.7408 | AE136: 25.926 | AF136: 27.6544 | AG136: 31.9089 | AH136: 37.7105
A137: 202606 | B137: T3CC2040171 | C137: 3B-手持一维无线影像扫描枪 | D137: CC0171 | E137: 马来 | F137: 办公安防 | G137: 办公周边 | H137: 扫码枪 | I137: 2024-08-13 | J137: 2024-08-13 | K137: 30 | M137: 清仓商品 | N137: 3B0011 | O137: 一维扫描枪 | P137: 材质：ABS;参数：CCD,扫描一维码，电池容量：1200mah。它是用于读取条码所包含信息的阅读设备，利用光学原理，把条形码的内容解码后通过数据线或者无线的方式传输到电脑或者别的设备。 | Q137: 150cm*70cm*95cm | R137: 250 | S137: 260 | T137: 1 | U137: 40 | V137: 40 | W137: 50 | X137: 中转 | Y137: 马来易企通-D仓-1308 | Z137: 45 | AA137: 是 | AB137: 57.89 | AC137: 0.58 | AD137: 33.5762 | AE137: 41.9702 | AF137: 44.7683 | AG137: 51.6557 | AH137: 61.0476
