Workbook

Sheet 6月分配 
S1: 90天-6月需销售量 | W1: SP | AA1: TK
A3: 主SKU | B3: 商品名称 | D3: 国家 | E3: 品类 | F3: 三级分类 | G3: 销售成本 | H3: 当前库存 | I3: 日销量 | J3: 周转天数 | K3: 月预估超期库存 | L3: 月预估超期金额 | M3: 日销差距（50天） | N3: 预计出清数量（50天） | O3: 出清金额（3月） | P3: 日销差距（90天） | Q3: 预计出清数量（90天） | R3: 出清金额(6月） | S3: 总数量 | T3: 目标日销 | U3: 日销差异 | V3: 总出清金额 | W3: 业绩占比 | X3: 目标日销 | Y3: 总销量 | Z3: 出清额 | AA3: 业绩占比 | AB3: 目标日销 | AC3: 总销量 | AD3: 出清额度 | AE3: TK:备注 | AF3: SP:备注 | AG3: TK:第1周 | AH3: SP:第1周
A4: CC0283 | B4: 3B-便携式储能电源 | C4: 1 | D4: 马来 | E4: 办公安防 | F4: 便携储能电源 | G4: 173.4126 | H4: 1772 | I4: 13 | J4: 136 | K4: 1077 | L4: 232286 | M4: =(H4-(I4*50))/50 -> 22.44 | N4: =31*(M4+I4) -> 1098.64 | O4: =N4*G4 -> 190518.02 | P4: =(H4-(I4*90))/90 -> 6.6888889 | Q4: =31*(P4+I4) -> 610.35556 | R4: =(P4+I4)*31*G4*1.5 -> 158765.02 | S4: =Q4 -> 610.35556 | T4: =S4/31 -> 19.688889 | U4: =T4-I4 -> 6.6888889 | V4: =R4 -> 158765.02 | W4: =_xlfn.XLOOKUP(B4,Sheet5!G:G,Sheet5!H:H) -> 0.585 | X4: =Y4/31 -> 11.518 | Y4: =S4*W4 -> 357.058 | Z4: =Y4*G4*1.5 -> 92877.534 | AA4: =_xlfn.XLOOKUP(B4,Sheet5!G:G,Sheet5!I:I) -> 0.415 | AB4: =AC4/31 -> 8.1708889 | AC4: =S4*AA4 -> 253.29756 | AD4: =G4*AC4*1.5 -> 65887.482 | AE4: 重点： 全组进行推广，预估寄样数量40件，售后过不做降解动作 自营视频：雨前+伟民+罗城+心怡，每日发布数量1 | AF4: 全组重点下费用推品，每日现货开10个搭配光伏板 光伏板到货后补发，每人3条链接推品 | AG4: =$AC4/4 -> 63.324389 | AH4: =$Y4/4 -> 89.2645
A5: CC0282 | B5: 3B-保险箱黑50*35*30 | C5: 1 | D5: 马来 | E5: 办公安防 | F5: 保险箱 | G5: 209.88 | H5: 932 | I5: 6 | J5: 155 | K5: 627 | L5: 171787 | M5: =(H5-(I5*50))/50 -> 12.64 | N5: =31*(M5+I5) -> 577.84 | O5: =N5*G5 -> 121277.06 | P5: =(H5-(I5*90))/90 -> 4.3555556 | Q5: =31*(P5+I5) -> 321.02222 | R5: =(P5+I5)*31*G5*1.5 -> 101064.22 | S5: =Q5 -> 321.02222 | T5: =S5/31 -> 10.355556 | U5: =T5-I5 -> 4.3555556 | V5: =R5 -> 101064.22 | W5: =_xlfn.XLOOKUP(B5,Sheet5!G:G,Sheet5!H:H) -> 0.44 | X5: =Y5/31 -> 4.5564444 | Y5: =S5*W5 -> 141.24978 | Z5: =Y5*G5*1.5 -> 44468.255 | AA5: =_xlfn.XLOOKUP(B5,Sheet5!G:G,Sheet5!I:I) -> 0.56 | AB5: =AC5/31 -> 5.7991111 | AC5: =S5*AA5 -> 179.77244 | AD5: =G5*AC5*1.5 -> 56595.961 | AE5: 重点： 全组进行推广，预估寄样数量30件，售后过不做降解动作 自营视频：雨前+伟民+罗城+心怡，每日发布数量2 | AF5: 全组重点下费用推品，搭配灭款锁呆滞品出清 标价对标竞品下调至42% | AG5: =AC5/4 -> 44.943111 | AH5: =$Y5/4 -> 35.312444
A6: CC0462 | B6: 3B-X1指纹考勤机 | C6: 1 | D6: 马来 | E6: 办公安防 | F6: 考勤机 | G6: 76.15 | H6: 2252 | I6: 13 | J6: 173 | K6: 1557 | L6: 156679 | M6: =(H6-(I6*50))/50 -> 32.04 | N6: =31*(M6+I6) -> 1396.24 | O6: =N6*G6 -> 106323.68 | P6: =(H6-(I6*90))/90 -> 12.022222 | Q6: =31*(P6+I6) -> 775.68889 | R6: =(P6+I6)*31*G6*1.5 -> 88603.063 | S6: =Q6 -> 775.68889 | T6: =S6/31 -> 25.022222 | U6: =T6-I6 -> 12.022222 | V6: =R6 -> 88603.063 | W6: =_xlfn.XLOOKUP(B6,Sheet5!G:G,Sheet5!H:H) -> 0.48125 | X6: =Y6/31 -> 12.041944 | Y6: =S6*W6 -> 373.30028 | Z6: =Y6*G6*1.5 -> 42640.224 | AA6: =_xlfn.XLOOKUP(B6,Sheet5!G:G,Sheet5!I:I) -> 0.51875 | AB6: =AC6/31 -> 12.980278 | AC6: =S6*AA6 -> 402.38861 | AD6: =G6*AC6*1.5 -> 45962.839 | AE6: 重点： 分人进行推广，预估寄样数量50件，广告投入加大 人员：伟民+罗城+心怡 | AF6: 孝鑫+荣锦重点下费用推品 每日对标竞品低价限量4个出清 | AG6: =AC6/4 -> 100.59715 | AH6: =$Y6/4 -> 93.325069
A7: CC0764 | B7: 3C-无弦吉他 | C7: 1 | D7: 马来 | E7: 3C数码 | F7: 未来吉他 | G7: 713.37 | H7: 171 | I7: 1 | J7: 171 | K7: 115 | L7: 107362 | M7: =(H7-(I7*50))/50 -> 2.42 | N7: =31*(M7+I7) -> 106.02 | O7: =N7*G7 -> 75631.487 | P7: =(H7-(I7*90))/90 -> 0.9 | Q7: =31*(P7+I7) -> 58.9 | R7: =(P7+I7)*31*G7*1.5 -> 63026.24 | S7: =Q7 -> 58.9 | T7: =S7/31 -> 1.9 | U7: =T7-I7 -> 0.9 | V7: =R7 -> 63026.24 | W7: =_xlfn.XLOOKUP(B7,Sheet5!G:G,Sheet5!H:H) -> 0.16666667 | X7: =Y7/31 -> 0.31666667 | Y7: =S7*W7 -> 9.8166667 | Z7: =Y7*G7*1.5 -> 10504.373 | AA7: =_xlfn.XLOOKUP(B7,Sheet5!G:G,Sheet5!I:I) -> 0.83333333 | AB7: =AC7/31 -> 1.5833333 | AC7: =S7*AA7 -> 49.083333 | AD7: =G7*AC7*1.5 -> 52521.866 | AE7: 重点： 分人进行推广，预估寄样数量5-8件，广告投入加大，原价进工资活动。 人员：心怡+伟铭 | AF7: 全组下费用推品，市场体量小 联盟佣金方面会上调至12%尝试 | AG7: =AC7/4 -> 12.270833 | AH7: =$Y7/4 -> 2.4541667
A8: CC0711 | B8: 3B-点钞机灰色 | C8: 1 | D8: 马来 | E8: 办公安防 | F8: 点钞机 | G8: 213.2736 | H8: 1075 | I8: 13 | J8: 82 | K8: 390 | L8: 83177 | M8: =(H8-(I8*50))/50 -> 8.5 | N8: =31*(M8+I8) -> 666.5 | O8: =N8*G8 -> 142146.85 | P8: =(H8-(I8*90))/90 -> -1.0555556 | Q8: =31*(P8+I8) -> 370.27778 | R8: =(P8+I8)*31*G8*1.5 -> 118455.71 | S8: =Q8 -> 370.27778 | T8: =S8/31 -> 11.944444 | U8: =T8-I8 -> -1.0555556 | V8: =R8 -> 118455.71 | W8: =_xlfn.XLOOKUP(B8,Sheet5!G:G,Sheet5!H:H) -> 0.33544304 | X8: =Y8/31 -> 4.0066807 | Y8: =S8*W8 -> 124.2071 | Z8: =Y8*G8*1.5 -> 39735.144 | AA8: =_xlfn.XLOOKUP(B8,Sheet5!G:G,Sheet5!I:I) -> 0.66455696 | AB8: =AC8/31 -> 7.9377637 | AC8: =S8*AA8 -> 246.07068 | AD8: =G8*AC8*1.5 -> 78720.568 | AE8: 重点： 分人进行推广，预估寄样数量10-15件，广告投入加大，原价进工资活动。 人员：罗城+伟民 | AG8: =AC8/4 -> 61.517669 | AH8: =$Y8/4 -> 31.051776
A9: CC0780 | B9: 3C-折叠带蓝牙带琴谱架电子琴61键 | C9: 1 | D9: 马来 | E9: 3C数码 | F9: 电子琴 | G9: 163.992 | H9: 276 | I9: 1 | J9: 276 | K9: 218 | L9: 49772 | M9: =(H9-(I9*50))/50 -> 4.52 | N9: =31*(M9+I9) -> 171.12 | O9: =N9*G9 -> 28062.311 | P9: =(H9-(I9*90))/90 -> 2.0666667 | Q9: =31*(P9+I9) -> 95.066667 | R9: =(P9+I9)*31*G9*1.5 -> 23385.259 | S9: =Q9 -> 95.066667 | T9: =S9/31 -> 3.0666667 | U9: =T9-I9 -> 2.0666667 | V9: =R9 -> 23385.259 | W9: =_xlfn.XLOOKUP(B9,Sheet5!G:G,Sheet5!H:H) -> 0.375 | X9: =Y9/31 -> 1.15 | Y9: =S9*W9 -> 35.65 | Z9: =Y9*G9*1.5 -> 8769.4722 | AA9: =_xlfn.XLOOKUP(B9,Sheet5!G:G,Sheet5!I:I) -> 0.625 | AB9: =AC9/31 -> 1.9166667 | AC9: =S9*AA9 -> 59.416667 | AD9: =G9*AC9*1.5 -> 14615.787 | AE9: 重点： 分人进行推广，预估寄样数量10-15件，广告投入加大，原价进工资活动。 人员：雨倩+伟铭 | AF9: 全组下费用推品，培庆每日限量3个对标竞品28%标价 | AG9: =AC9/4 -> 14.854167 | AH9: =$Y9/4 -> 8.9125
A10: CC0514 | B10: 3B-路由器P6000白色 | C10: 1 | D10: 马来 | E10: 办公安防 | F10: 路由器 | G10: 93.44 | H10: 363 | K10: 340 | L10: 46767 | M10: =(H10-(I10*50))/50 -> 7.26 | N10: =31*(M10+I10) -> 225.06 | O10: =N10*G10 -> 21029.606 | P10: =(H10-(I10*90))/90 -> 4.0333333 | Q10: =31*(P10+I10) -> 125.03333 | R10: =(P10+I10)*31*G10*1.5 -> 17524.672 | S10: =Q10 -> 125.03333 | T10: =S10/31 -> 4.0333333 | U10: =T10-I10 -> 4.0333333 | V10: =R10 -> 17524.672 | W10: =_xlfn.XLOOKUP(B10,Sheet5!G:G,Sheet5!H:H) -> 1 | X10: =Y10/31 -> 4.0333333 | Y10: =S10*W10 -> 125.03333 | Z10: =Y10*G10*1.5 -> 17524.672 | AA10: =_xlfn.XLOOKUP(B10,Sheet5!G:G,Sheet5!I:I) -> 0 | AB10: =AC10/31 -> 0 | AC10: =S10*AA10 -> 0 | AD10: =G10*AC10*1.5 -> 0 | AE10: 无法上架，暂不规划，可以送达人5个 | AF10: 无法上架，尝试搭配交换机出清 | AG10: =AC10/4 -> 0 | AH10: =$Y10/4 -> 31.258333
A11: CC0739 | B11: 3B-液晶面板保险柜45cm*38cm*30cm | C11: 1 | D11: 马来 | E11: 办公安防 | F11: 保险箱 | G11: 276.9564 | H11: 197 | I11: 1 | J11: 197 | K11: 126 | L11: 44452 | M11: =(H11-(I11*50))/50 -> 2.94 | N11: =31*(M11+I11) -> 122.14 | O11: =N11*G11 -> 33827.455 | P11: =(H11-(I11*90))/90 -> 1.1888889 | Q11: =31*(P11+I11) -> 67.855556 | R11: =(P11+I11)*31*G11*1.5 -> 28189.546 | S11: =Q11 -> 67.855556 | T11: =S11/31 -> 2.1888889 | U11: =T11-I11 -> 1.1888889 | V11: =R11 -> 28189.546 | W11: =_xlfn.XLOOKUP(B11,Sheet5!G:G,Sheet5!H:H) -> 0.52173913 | X11: =Y11/31 -> 1.142029 | Y11: =S11*W11 -> 35.402899 | Z11: =Y11*G11*1.5 -> 14707.589 | AA11: =_xlfn.XLOOKUP(B11,Sheet5!G:G,Sheet5!I:I) -> 0.47826087 | AB11: =AC11/31 -> 1.0468599 | AC11: =S11*AA11 -> 32.452657 | AD11: =G11*AC11*1.5 -> 13481.957 | AE11: 重点： 全组进行推广，预估寄样数量10件 自营视频：罗城+心怡，每日发布数量1 | AF11: 全组重点下费用推品 | AG11: =AC11/4 -> 8.1131643 | AH11: =$Y11/4 -> 8.8507246
A12: CC1048 | B12: 3C-高亮自动对焦灯带投影仪Z300 | C12: 1 | D12: 马来 | E12: 3C数码 | F12: 家用音视频设备*投影仪 | G12: 404.3828 | H12: 77 | K12: 69 | L12: 40438 | M12: =(H12-(I12*50))/50 -> 1.54 | N12: =31*(M12+I12) -> 47.74 | O12: =N12*G12 -> 19305.235 | P12: =(H12-(I12*90))/90 -> 0.85555556 | Q12: =31*(P12+I12) -> 26.522222 | R12: =(P12+I12)*31*G12*1.5 -> 16087.696 | S12: =Q12 -> 26.522222 | T12: =S12/31 -> 0.85555556 | U12: =T12-I12 -> 0.85555556 | V12: =R12 -> 16087.696 | W12: =_xlfn.XLOOKUP(B12,Sheet5!G:G,Sheet5!H:H) -> 0 | X12: =Y12/31 -> 0 | Y12: =S12*W12 -> 0 | Z12: =Y12*G12*1.5 -> 0 | AA12: =_xlfn.XLOOKUP(B12,Sheet5!G:G,Sheet5!I:I) -> 1 | AB12: =AC12/31 -> 0.85555556 | AC12: =S12*AA12 -> 26.522222 | AD12: =G12*AC12*1.5 -> 16087.696 | AE12: 重点： 全组进行推广，预估寄样数量8件 | AF12: 全组下费用推品，投影仪+幕布+支架组合出售 | AG12: =AC12/4 -> 6.6305556 | AH12: =$Y12/4 -> 0
A13: CC0706 | B13: 3C-32英寸到55英寸带中托可移动电视支架 | C13: 1 | D13: 马来 | E13: 3C数码 | F13: 电视支架 | G13: 123.29 | H13: 463 | I13: 4 | J13: 115 | K13: 263 | L13: 38775 | M13: =(H13-(I13*50))/50 -> 5.26 | N13: =31*(M13+I13) -> 287.06 | O13: =N13*G13 -> 35391.627 | P13: =(H13-(I13*90))/90 -> 1.1444444 | Q13: =31*(P13+I13) -> 159.47778 | R13: =(P13+I13)*31*G13*1.5 -> 29493.023 | S13: =Q13 -> 159.47778 | T13: =S13/31 -> 5.1444444 | U13: =T13-I13 -> 1.1444444 | V13: =R13 -> 29493.023 | W13: 0.45 | X13: =Y13/31 -> 2.315 | Y13: =S13*W13 -> 71.765 | Z13: =Y13*G13*1.5 -> 13271.86 | AA13: 0.55 | AB13: =AC13/31 -> 2.8294444 | AC13: =S13*AA13 -> 87.712778 | AD13: =G13*AC13*1.5 -> 16221.163 | AE13: 重点： 寄样20个，主要是产品售后配件缺失的问题，成本上涨。 人员：伟民+伟铭 | AF13: 该品后续转为平销款，本月重点下调价格 另一款双层移动推车MY1700PJ作为链接主推 鹭燕小店重点给优势扶持 | AG13: =AC13/4 -> 21.928194 | AH13: =$Y13/4 -> 17.94125
A14: CC0979 | B14: 3B-XT保险箱45*38*32cm灰白色密码款 | C14: 1 | D14: 马来 | E14: 办公安防 | F14: 保险柜 | G14: 271.8192 | H14: 96 | K14: 91 | L14: 36560 | M14: =(H14-(I14*50))/50 -> 1.92 | N14: =31*(M14+I14) -> 59.52 | O14: =N14*G14 -> 16178.679 | P14: =(H14-(I14*90))/90 -> 1.0666667 | Q14: =31*(P14+I14) -> 33.066667 | R14: =(P14+I14)*31*G14*1.5 -> 13482.232 | S14: =Q14 -> 33.066667 | T14: =S14/31 -> 1.0666667 | U14: =T14-I14 -> 1.0666667 | V14: =R14 -> 13482.232 | W14: =_xlfn.XLOOKUP(B14,Sheet5!G:G,Sheet5!H:H) -> 0 | X14: =Y14/31 -> 0 | Y14: =S14*W14 -> 0 | Z14: =Y14*G14*1.5 -> 0 | AA14: =_xlfn.XLOOKUP(B14,Sheet5!G:G,Sheet5!I:I) -> 0 | AB14: =AC14/31 -> 0 | AC14: =S14*AA14 -> 0 | AD14: =G14*AC14*1.5 -> 0 | AE14: 重点： 全组进行推广，预估寄样数量5-8件 自营视频：罗城+心怡，每日发布数量1 | AF14: 全组重点下费用推品 | AG14: =AC14/4 -> 0 | AH14: =$Y14/4 -> 0
A15: CC0898 | B15: 3B-液晶面板保险柜密码A15款 | C15: 1 | D15: 马来 | E15: 办公安防 | F15: 保险箱 | G15: 232.7064 | H15: 207 | I15: 1 | J15: 207 | K15: 111 | L15: 29786 | M15: =(H15-(I15*50))/50 -> 3.14 | N15: =31*(M15+I15) -> 128.34 | O15: =N15*G15 -> 29865.539 | P15: =(H15-(I15*90))/90 -> 1.3 | Q15: =31*(P15+I15) -> 71.3 | R15: =(P15+I15)*31*G15*1.5 -> 24887.949 | S15: =Q15 -> 71.3 | T15: =S15/31 -> 2.3 | U15: =T15-I15 -> 1.3 | V15: =R15 -> 24887.949 | W15: =_xlfn.XLOOKUP(B15,Sheet5!G:G,Sheet5!H:H) -> 0.39473684 | X15: =Y15/31 -> 0.90789474 | Y15: =S15*W15 -> 28.144737 | Z15: =Y15*G15*1.5 -> 9824.1906 | AA15: =_xlfn.XLOOKUP(B15,Sheet5!G:G,Sheet5!I:I) -> 0.60526316 | AB15: =AC15/31 -> 1.3921053 | AC15: =S15*AA15 -> 43.155263 | AD15: =G15*AC15*1.5 -> 15063.759 | AE15: 无超期风险： 全组正常推 | AF15: 全组重点下费用推品 | AG15: =AC15/4 -> 10.788816 | AH15: =$Y15/4 -> 7.0361842
A16: CC0980 | B16: 3B-XT保险箱45*38*32cm灰白色指纹款 | C16: 1 | D16: 马来 | E16: 办公安防 | F16: 保险柜 | G16: 333.7692 | H16: 84 | K16: 63 | L16: 28704 | M16: =(H16-(I16*50))/50 -> 1.68 | N16: =31*(M16+I16) -> 52.08 | O16: z | P16: =(H16-(I16*90))/90 -> 0.93333333 | Q16: =31*(P16+I16) -> 28.933333 | R16: =(P16+I16)*31*G16*1.5 -> 14485.583 | S16: =Q16 -> 28.933333 | T16: =S16/31 -> 0.93333333 | U16: =T16-I16 -> 0.93333333 | V16: =R16 -> 14485.583 | W16: =_xlfn.XLOOKUP(B16,Sheet5!G:G,Sheet5!H:H) -> 0.6 | X16: =Y16/31 -> 0.56 | Y16: =S16*W16 -> 17.36 | Z16: =Y16*G16*1.5 -> 8691.35 | AA16: =_xlfn.XLOOKUP(B16,Sheet5!G:G,Sheet5!I:I) -> 0.4 | AB16: =AC16/31 -> 0.37333333 | AC16: =S16*AA16 -> 11.573333 | AD16: =G16*AC16*1.5 -> 5794.2333 | AE16: 目前不会超期，和密码的动作一致 | AF16: 全组重点下费用推品 | AG16: =AC16/4 -> 2.8933333 | AH16: =$Y16/4 -> 4.34
A17: CC0177 | B17: 3B-300CWiFi路由器 | C17: 1 | D17: 马来 | E17: 办公安防 | F17: 路由器 | G17: 127.34 | H17: 136 | K17: 136 | L17: 25977 | M17: =(H17-(I17*50))/50 -> 2.72 | N17: =31*(M17+I17) -> 84.32 | O17: =N17*G17 -> 10737.309 | P17: =(H17-(I17*90))/90 -> 1.5111111 | Q17: =31*(P17+I17) -> 46.844444 | R17: =(P17+I17)*31*G17*1.5 -> 8947.7573 | S17: =Q17 -> 46.844444 | T17: =S17/31 -> 1.5111111 | U17: =T17-I17 -> 1.5111111 | V17: =R17 -> 8947.7573 | W17: =_xlfn.XLOOKUP(B17,Sheet5!G:G,Sheet5!H:H) -> 0 | X17: =Y17/31 -> 0 | Y17: =S17*W17 -> 0 | Z17: =Y17*G17*1.5 -> 0 | AA17: =_xlfn.XLOOKUP(B17,Sheet5!G:G,Sheet5!I:I) -> 0 | AB17: =AC17/31 -> 0 | AC17: =S17*AA17 -> 0 | AD17: =G17*AC17*1.5 -> 0 | AE17: 无法上架，暂不规划，可以送达人5个 | AF17: 无法上架，尝试搭配交换机出清 | AG17: =AC17/4 -> 0 | AH17: =$Y17/4 -> 0
A18: CC0634 | B18: 3C-电子琴61健黑色 | C18: 1 | D18: 马来 | E18: 3C数码 | F18: 电子琴 | G18: 39.9772 | H18: 806 | I18: 6 | J18: 134 | K18: 493 | L18: 24546 | M18: =(H18-(I18*50))/50 -> 10.12 | N18: =31*(M18+I18) -> 499.72 | O18: =N18*G18 -> 19977.406 | P18: =(H18-(I18*90))/90 -> 2.9555556 | Q18: =31*(P18+I18) -> 277.62222 | R18: =(P18+I18)*31*G18*1.5 -> 16647.839 | S18: =Q18 -> 277.62222 | T18: =S18/31 -> 8.9555556 | U18: =T18-I18 -> 2.9555556 | V18: =R18 -> 16647.839 | W18: =_xlfn.XLOOKUP(B18,Sheet5!G:G,Sheet5!H:H) -> 0.61728395 | X18: =Y18/31 -> 5.5281207 | Y18: =S18*W18 -> 171.37174 | Z18: =Y18*G18*1.5 -> 10276.444 | AA18: =_xlfn.XLOOKUP(B18,Sheet5!G:G,Sheet5!I:I) -> 0.38271605 | AB18: =AC18/31 -> 3.4274348 | AC18: =S18*AA18 -> 106.25048 | AD18: =G18*AC18*1.5 -> 6371.395 | AE18: 超期： 导致已经控在22% | AF18: 对标竞品价格36%标价正常销售 | AG18: =AC18/4 -> 26.56262 | AH18: =$Y18/4 -> 42.842936
A19: CC1046 | B19: 3C-电视移动推车支架TG11 | C19: 1 | D19: 马来 | E19: 3C数码 | F19: 电视支架 | G19: 150.11 | H19: 116 | K19: 110 | L19: 24393 | M19: =(H19-(I19*50))/50 -> 2.32 | N19: =31*(M19+I19) -> 71.92 | O19: =N19*G19 -> 10795.911 | P19: =(H19-(I19*90))/90 -> 1.2888889 | Q19: =31*(P19+I19) -> 39.955556 | R19: =(P19+I19)*31*G19*1.5 -> 8996.5927 | S19: =Q19 -> 39.955556 | T19: =S19/31 -> 1.2888889 | U19: =T19-I19 -> 1.2888889 | V19: =R19 -> 8996.5927 | W19: =_xlfn.XLOOKUP(B19,Sheet5!G:G,Sheet5!H:H) -> 0 | X19: =Y19/31 -> 0 | Y19: =S19*W19 -> 0 | Z19: =Y19*G19*1.5 -> 0 | AA19: =_xlfn.XLOOKUP(B19,Sheet5!G:G,Sheet5!I:I) -> 1 | AB19: =AC19/31 -> 1.2888889 | AC19: =S19*AA19 -> 39.955556 | AD19: =G19*AC19*1.5 -> 8996.5927 | AE19: 新品： 寄样10个，正常推品 人员：伟民+伟铭 | AF19: 月底刚到，正常下费用插入老链接推品 鹭燕小店重点给优势扶持 | AG19: =AC19/4 -> 9.9888889 | AH19: =$Y19/4 -> 0
A20: CC0906 | B20: 3B-磁吸白板密度板夹层90cm*150cm | C20: 1 | D20: 马来 | E20: 办公安防 | F20: 白板 | G20: 87.6789 | H20: 516 | I20: 5 | J20: 103 | K20: 250 | L20: 23542 | M20: =(H20-(I20*50))/50 -> 5.32 | N20: =31*(M20+I20) -> 319.92 | O20: =N20*G20 -> 28050.234 | P20: =(H20-(I20*90))/90 -> 0.73333333 | Q20: =31*(P20+I20) -> 177.73333 | R20: =(P20+I20)*31*G20*1.5 -> 23375.195 | S20: =Q20 -> 177.73333 | T20: =S20/31 -> 5.7333333 | U20: =T20-I20 -> 0.73333333 | V20: =R20 -> 23375.195 | W20: =_xlfn.XLOOKUP(B20,Sheet5!G:G,Sheet5!H:H) -> 0.88405797 | X20: =Y20/31 -> 5.068599 | Y20: =S20*W20 -> 157.12657 | Z20: =Y20*G20*1.5 -> 20665.027 | AA20: =_xlfn.XLOOKUP(B20,Sheet5!G:G,Sheet5!I:I) -> 0.11594203 | AB20: =AC20/31 -> 0.6647343 | AC20: =S20*AA20 -> 20.606763 | AD20: =G20*AC20*1.5 -> 2710.1675 | AE20: 占比过小，正常销售 | AG20: =AC20/4 -> 5.1516908 | AH20: =$Y20/4 -> 39.281643
A21: CC0672 | B21: 3B-仿真书银钱盒钥匙款蓝色 | C21: 1 | D21: 马来 | E21: 办公安防 | F21: 银钱盒 | G21: 18.8293 | H21: 1260 | I21: 7 | J21: 180 | K21: 887 | L21: 22237 | M21: =(H21-(I21*50))/50 -> 18.2 | N21: =31*(M21+I21) -> 781.2 | O21: =N21*G21 -> 14709.449 | P21: =(H21-(I21*90))/90 -> 7 | Q21: =31*(P21+I21) -> 434 | R21: =(P21+I21)*31*G21*1.5 -> 12257.874 | S21: =Q21 -> 434 | T21: =S21/31 -> 14 | U21: =T21-I21 -> 7 | V21: =R21 -> 12257.874 | W21: =_xlfn.XLOOKUP(B21,Sheet5!G:G,Sheet5!H:H) -> 0.41558442 | X21: =Y21/31 -> 5.8181818 | Y21: =S21*W21 -> 180.36364 | Z21: 60 | AA21: =_xlfn.XLOOKUP(B21,Sheet5!G:G,Sheet5!I:I) -> 0.58441558 | AB21: =AC21/31 -> 8.1818182 | AC21: =S21*AA21 -> 253.63636 | AD21: =G21*AC21*1.5 -> 7163.6928 | AE21: 重点： 阶段降解消耗，周转控制在60 人员：心怡 | AF21: 小店重点价格扶持起量 孝鑫+鹭燕 | AG21: =AC21/4 -> 63.409091 | AH21: =$Y21/4 -> 45.090909
A22: CC0781 | B22: 3C-折叠带蓝牙带琴谱架电子琴88键 | C22: 1 | D22: 马来 | E22: 3C数码 | F22: 电子琴 | G22: 233.6648 | H22: 241 | I22: 2 | J22: 120 | K22: 95 | L22: 22198 | M22: =(H22-(I22*50))/50 -> 2.82 | N22: =31*(M22+I22) -> 149.42 | O22: =N22*G22 -> 34914.194 | P22: =(H22-(I22*90))/90 -> 0.67777778 | Q22: =31*(P22+I22) -> 83.011111 | R22: =(P22+I22)*31*G22*1.5 -> 29095.162 | S22: =Q22 -> 83.011111 | T22: =S22/31 -> 2.6777778 | U22: =T22-I22 -> 0.67777778 | V22: =R22 -> 29095.162 | W22: =_xlfn.XLOOKUP(B22,Sheet5!G:G,Sheet5!H:H) -> 0.38461538 | X22: =Y22/31 -> 1.0299145 | Y22: =S22*W22 -> 31.92735 | Z22: =Y22*G22*1.5 -> 11190.447 | AA22: =_xlfn.XLOOKUP(B22,Sheet5!G:G,Sheet5!I:I) -> 0.61538462 | AB22: =AC22/31 -> 1.6478632 | AC22: =S22*AA22 -> 51.083761 | AD22: =G22*AC22*1.5 -> 17904.715 | AE22: 无超期风险 | AF22: 对标竞品价格36%标价正常销售 | AG22: =AC22/4 -> 12.77094 | AH22: =$Y22/4 -> 7.9818376
A23: CC0342 | B23: 3B-保险柜100cm*51cm*45cm | C23: 1 | D23: 马来 | E23: 办公安防 | F23: 保险箱 | G23: 896.77 | H23: 33 | K23: 20 | L23: 21971 | M23: =(H23-(I23*50))/50 -> 0.66 | N23: =31*(M23+I23) -> 20.46 | O23: =N23*G23 -> 18347.914 | P23: =(H23-(I23*90))/90 -> 0.36666667 | Q23: =31*(P23+I23) -> 11.366667 | R23: =(P23+I23)*31*G23*1.5 -> 15289.928 | S23: =Q23 -> 11.366667 | T23: =S23/31 -> 0.36666667 | U23: =T23-I23 -> 0.36666667 | V23: =R23 -> 15289.928 | W23: 0.5 | X23: =Y23/31 -> 0.18333333 | Y23: =S23*W23 -> 5.6833333 | Z23: =Y23*G23*1.5 -> 7644.9642 | AA23: 0.5 | AB23: =AC23/31 -> 0.18333333 | AC23: =S23*AA23 -> 5.6833333 | AD23: =G23*AC23*1.5 -> 7644.9642 | AE23: 呆滞品：清除3个 成本价销售进行销售。费用进行寄样 | AF23: 正常出清，标价34%利润出清，预计本月消耗10个 | AG23: =AC23/4 -> 1.4208333 | AH23: =$Y23/4 -> 1.4208333
A24: CC0732 | B24: 3B-橡胶磁白板背胶90cm*180cm | C24: 1 | D24: 马来 | E24: 办公安防 | F24: 白板 | G24: 67.2831 | H24: 351 | I24: 2 | J24: 175 | K24: 241 | L24: 21362 | M24: =(H24-(I24*50))/50 -> 5.02 | N24: =31*(M24+I24) -> 217.62 | O24: =N24*G24 -> 14642.148 | P24: =(H24-(I24*90))/90 -> 1.9 | Q24: =31*(P24+I24) -> 120.9 | R24: =(P24+I24)*31*G24*1.5 -> 12201.79 | S24: =Q24 -> 120.9 | T24: =S24/31 -> 3.9 | U24: =T24-I24 -> 1.9 | V24: =R24 -> 12201.79 | W24: =_xlfn.XLOOKUP(B24,Sheet5!G:G,Sheet5!H:H) -> 0.78125 | X24: =Y24/31 -> 3.046875 | Y24: =S24*W24 -> 94.453125 | Z24: =Y24*G24*1.5 -> 9532.6486 | AA24: =_xlfn.XLOOKUP(B24,Sheet5!G:G,Sheet5!I:I) -> 0.21875 | AB24: =AC24/31 -> 0.853125 | AC24: =S24*AA24 -> 26.446875 | AD24: =G24*AC24*1.5 -> 2669.1416 | AE24: 新品： 降价 | AG24: =AC24/4 -> 6.6117187 | AH24: =$Y24/4 -> 23.613281
A25: CC0278 | B25: 3B-智能指纹门锁X7 | C25: 1 | D25: 马来 | E25: 办公安防 | F25: 指纹锁 | G25: 93.9397 | H25: 708 | I25: 9 | J25: 78 | K25: 225 | L25: 21136 | M25: =(H25-(I25*50))/50 -> 5.16 | N25: =31*(M25+I25) -> 438.96 | O25: =N25*G25 -> 41235.771 | P25: =(H25-(I25*90))/90 -> -1.1333333 | Q25: =31*(P25+I25) -> 243.86667 | R25: =(P25+I25)*31*G25*1.5 -> 34363.142 | S25: =Q25 -> 243.86667 | T25: =S25/31 -> 7.8666667 | U25: =T25-I25 -> -1.1333333 | V25: =R25 -> 34363.142 | W25: =_xlfn.XLOOKUP(B25,Sheet5!G:G,Sheet5!H:H) -> 0.29090909 | X25: =Y25/31 -> 2.2884848 | Y25: =S25*W25 -> 70.94303 | Z25: =Y25*G25*1.5 -> 9996.5505 | AA25: =_xlfn.XLOOKUP(B25,Sheet5!G:G,Sheet5!I:I) -> 0.70909091 | AB25: =AC25/31 -> 5.5781818 | AC25: =S25*AA25 -> 172.92364 | AD25: =G25*AC25*1.5 -> 24366.592 | AE25: 无超期风险 | AG25: =AC25/4 -> 43.230909 | AH25: =$Y25/4 -> 17.735758
A26: CC0860 | B26: 3C-辉光管 | C26: 1 | D26: 马来 | E26: 3C数码 | F26: 辉光管 | G26: 203.25 | H26: 74 | K26: 69 | L26: 20630 | M26: =(H26-(I26*50))/50 -> 1.48 | N26: =31*(M26+I26) -> 45.88 | O26: =N26*G26 -> 9325.11 | P26: =(H26-(I26*90))/90 -> 0.82222222 | Q26: =31*(P26+I26) -> 25.488889 | R26: =(P26+I26)*31*G26*1.5 -> 7770.925 | S26: =Q26 -> 25.488889 | T26: =S26/31 -> 0.82222222 | U26: =T26-I26 -> 0.82222222 | V26: =R26 -> 7770.925 | W26: =_xlfn.XLOOKUP(B26,Sheet5!G:G,Sheet5!H:H) -> 0 | X26: =Y26/31 -> 0 | Y26: =S26*W26 -> 0 | Z26: =Y26*G26*1.5 -> 0 | AA26: =_xlfn.XLOOKUP(B26,Sheet5!G:G,Sheet5!I:I) -> 1 | AB26: =AC26/31 -> 0.82222222 | AC26: =S26*AA26 -> 25.488889 | AD26: =G26*AC26*1.5 -> 7770.925 | AE26: 呆滞品：消耗15个 毛利15%销售。 人员：罗城+心怡 | AF26: 暂不规划 | AG26: =AC26/4 -> 6.3722222 | AH26: =$Y26/4 -> 0
A27: CC0904 | B27: 3B-磁吸白板密度板夹层70cm*100cm | C27: 1 | D27: 马来 | E27: 办公安防 | F27: 白板 | G27: 43.1968 | H27: 1825 | I27: 27 | J27: 67 | K27: 465 | L27: 20087 | M27: =(H27-(I27*50))/50 -> 9.5 | N27: =31*(M27+I27) -> 1131.5 | O27: =N27*G27 -> 48877.179 | P27: =(H27-(I27*90))/90 -> -6.7222222 | Q27: =31*(P27+I27) -> 628.61111 | R27: =(P27+I27)*31*G27*1.5 -> 40730.983 | S27: =Q27 -> 628.61111 | T27: =S27/31 -> 20.277778 | U27: =T27-I27 -> -6.7222222 | V27: =R27 -> 40730.983 | W27: =_xlfn.XLOOKUP(B27,Sheet5!G:G,Sheet5!H:H) -> 0.71549296 | X27: =Y27/31 -> 14.508607 | Y27: =S27*W27 -> 449.76682 | Z27: =Y27*G27*1.5 -> 29142.731 | AA27: =_xlfn.XLOOKUP(B27,Sheet5!G:G,Sheet5!I:I) -> 0.28450704 | AB27: =AC27/31 -> 5.7691706 | AC27: =S27*AA27 -> 178.84429 | AD27: =G27*AC27*1.5 -> 11588.251 | AE27: 无超期风险 | AG27: =AC27/4 -> 44.711072 | AH27: =$Y27/4 -> 112.44171
A28: CC0176 | B28: 3C-手卷电子7垫鼓 | C28: 1 | D28: 马来 | E28: 3C数码 | F28: 电子鼓 | G28: 94.0561 | H28: 457 | I28: 5 | J28: 91 | K28: 205 | L28: 19470 | M28: =(H28-(I28*50))/50 -> 4.14 | N28: =31*(M28+I28) -> 283.34 | O28: =N28*G28 -> 26649.855 | P28: =(H28-(I28*90))/90 -> 0.077777778 | Q28: =31*(P28+I28) -> 157.41111 | R28: =(P28+I28)*31*G28*1.5 -> 22208.213 | S28: =Q28 -> 157.41111 | T28: =S28/31 -> 5.0777778 | U28: =T28-I28 -> 0.077777778 | V28: =R28 -> 22208.213 | W28: =_xlfn.XLOOKUP(B28,Sheet5!G:G,Sheet5!H:H) -> 0.43137255 | X28: =Y28/31 -> 2.1904139 | Y28: =S28*W28 -> 67.902832 | Z28: =Y28*G28*1.5 -> 9580.0134 | AA28: =_xlfn.XLOOKUP(B28,Sheet5!G:G,Sheet5!I:I) -> 0.56862745 | AB28: =AC28/31 -> 2.8873638 | AC28: =S28*AA28 -> 89.508279 | AD28: =G28*AC28*1.5 -> 12628.199 | AE28: 无超期风险 | AF28: 正常销售 | AG28: =AC28/4 -> 22.37707 | AH28: =$Y28/4 -> 16.975708
A29: CC0673 | B29: 3B-仿真书银钱盒密码款蓝色 | C29: 1 | D29: 马来 | E29: 办公安防 | F29: 银钱盒 | G29: 19.7793 | H29: 1014 | I29: 5 | J29: 202 | K29: 724 | L29: 19186 | M29: =(H29-(I29*50))/50 -> 15.28 | N29: =31*(M29+I29) -> 628.68 | O29: =N29*G29 -> 12434.85 | P29: =(H29-(I29*90))/90 -> 6.2666667 | Q29: =31*(P29+I29) -> 349.26667 | R29: =(P29+I29)*31*G29*1.5 -> 10362.375 | S29: =Q29 -> 349.26667 | T29: =S29/31 -> 11.266667 | U29: =T29-I29 -> 6.2666667 | V29: =R29 -> 10362.375 | W29: =_xlfn.XLOOKUP(B29,Sheet5!G:G,Sheet5!H:H) -> 0.58333333 | X29: =Y29/31 -> 6.5722222 | Y29: =S29*W29 -> 203.73889 | Z29: =Y29*G29*1.5 -> 6044.7189 | AA29: =_xlfn.XLOOKUP(B29,Sheet5!G:G,Sheet5!I:I) -> 0.41666667 | AB29: =AC29/31 -> 4.6944444 | AC29: =S29*AA29 -> 145.52778 | AD29: =G29*AC29*1.5 -> 4317.6564 | AE29: 重点： 阶段降解消耗，周转控制在60 人员：心怡 | AF29: 小店重点价格扶持起量 孝鑫+鹭燕 | AG29: =AC29/4 -> 36.381944 | AH29: =$Y29/4 -> 50.934722
A30: CC0142 | B30: 3B-手提收银箱双层黑色 | C30: 1 | D30: 马来 | E30: 办公安防 | F30: 收银箱 | G30: 38.5262 | H30: 1934 | I30: 28 | J30: 69 | K30: 495 | L30: 19070 | M30: =(H30-(I30*50))/50 -> 10.68 | N30: =31*(M30+I30) -> 1199.08 | O30: =N30*G30 -> 46195.996 | P30: =(H30-(I30*90))/90 -> -6.5111111 | Q30: =31*(P30+I30) -> 666.15556 | R30: =(P30+I30)*31*G30*1.5 -> 38496.663 | S30: =Q30 -> 666.15556 | T30: =S30/31 -> 21.488889 | U30: =T30-I30 -> -6.5111111 | V30: =R30 -> 38496.663 | W30: =_xlfn.XLOOKUP(B30,Sheet5!G:G,Sheet5!H:H) -> 0.39622642 | X30: =Y30/31 -> 8.5144654 | Y30: =S30*W30 -> 263.94843 | Z30: =Y30*G30*1.5 -> 15253.395 | AA30: =_xlfn.XLOOKUP(B30,Sheet5!G:G,Sheet5!I:I) -> 0.60377358 | AB30: =AC30/31 -> 12.974423 | AC30: =S30*AA30 -> 402.20713 | AD30: =G30*AC30*1.5 -> 23243.268 | AE30: 无超期风险 | AG30: =AC30/4 -> 100.55178 | AH30: =$Y30/4 -> 65.987107
A31: CC1044 | B31: 3B-可充电不锈钢球形锁K06 | C31: 1 | D31: 马来 | E31: 办公安防 | F31: 球型智能门锁 | G31: 98.3411 | H31: 120 | K31: 120 | L31: 17701 | M31: =(H31-(I31*50))/50 -> 2.4 | N31: =31*(M31+I31) -> 74.4 | O31: =N31*G31 -> 7316.5778 | P31: =(H31-(I31*90))/90 -> 1.3333333 | Q31: =31*(P31+I31) -> 41.333333 | R31: =(P31+I31)*31*G31*1.5 -> 6097.1482 | S31: =Q31 -> 41.333333 | T31: =S31/31 -> 1.3333333 | U31: =T31-I31 -> 1.3333333 | V31: =R31 -> 6097.1482 | W31: 0.5 | X31: =Y31/31 -> 0.66666667 | Y31: =S31*W31 -> 20.666667 | Z31: =Y31*G31*1.5 -> 3048.5741 | AA31: 0.5 | AB31: =AC31/31 -> 0.66666667 | AC31: =S31*AA31 -> 20.666667 | AD31: =G31*AC31*1.5 -> 3048.5741 | AE31: 新品： 寄样5，加入老链接本月销售21单 | AF31: 月底刚到，正常下费用推品，每人至少上架三条链接，插入一条老链接 | AG31: =AC31/4 -> 5.1666667 | AH31: =$Y31/4 -> 5.1666667
A32: CC0903 | B32: 3B-磁吸白板密度板夹层60cm*90cm | C32: 1 | D32: 马来 | E32: 办公安防 | F32: 白板 | G32: 33.6968 | H32: 1821 | I32: 26 | J32: 70 | K32: 508 | L32: 17118 | M32: =(H32-(I32*50))/50 -> 10.42 | N32: =31*(M32+I32) -> 1129.02 | O32: =N32*G32 -> 38044.361 | P32: =(H32-(I32*90))/90 -> -5.7666667 | Q32: =31*(P32+I32) -> 627.23333 | R32: =(P32+I32)*31*G32*1.5 -> 31703.634 | S32: =Q32 -> 627.23333 | T32: =S32/31 -> 20.233333 | U32: =T32-I32 -> -5.7666667 | V32: =R32 -> 31703.634 | W32: =_xlfn.XLOOKUP(B32,Sheet5!G:G,Sheet5!H:H) -> 0.69830508 | X32: =Y32/31 -> 14.12904 | Y32: =S32*W32 -> 438.00023 | Z32: =Y32*G32*1.5 -> 22138.809 | AA32: =_xlfn.XLOOKUP(B32,Sheet5!G:G,Sheet5!I:I) -> 0.30169492 | AB32: =AC32/31 -> 6.1042938 | AC32: =S32*AA32 -> 189.23311 | AD32: =G32*AC32*1.5 -> 9564.8253 | AE32: 无超期风险 | AG32: =AC32/4 -> 47.308277 | AH32: =$Y32/4 -> 109.50006
A33: CC0852 | B33: 3B-启动电源N20 | C33: 1 | D33: 马来 | E33: 办公安防 | F33: 启动电源 | G33: 215.7607 | H33: 53 | K33: 50 | L33: 15858 | M33: =(H33-(I33*50))/50 -> 1.06 | N33: =31*(M33+I33) -> 32.86 | O33: =N33*G33 -> 7089.8966 | P33: =(H33-(I33*90))/90 -> 0.58888889 | Q33: =31*(P33+I33) -> 18.255556 | R33: =(P33+I33)*31*G33*1.5 -> 5908.2472 | S33: =Q33 -> 18.255556 | T33: =S33/31 -> 0.58888889 | U33: =T33-I33 -> 0.58888889 | V33: =R33 -> 5908.2472 | W33: =_xlfn.XLOOKUP(B33,Sheet5!G:G,Sheet5!H:H) -> 0 | X33: =Y33/31 -> 0 | Y33: =S33*W33 -> 0 | Z33: =Y33*G33*1.5 -> 0 | AA33: =_xlfn.XLOOKUP(B33,Sheet5!G:G,Sheet5!I:I) -> 0 | AB33: =AC33/31 -> 0 | AC33: =S33*AA33 -> 0 | AD33: =G33*AC33*1.5 -> 0 | AE33: 呆滞品： 寄样：5单 | AF33: 正常出清，当前标价28%，插入原有JY链接尝试 | AG33: =AC33/4 -> 0 | AH33: =$Y33/4 -> 0
A34: CC0876 | B34: 3B-B1A五功能断桥铝锁带APP | C34: 1 | D34: 马来 | E34: 办公安防 | F34: 密码锁 | G34: 177.0938 | H34: 88 | K34: 65 | L34: 15584 | M34: =(H34-(I34*50))/50 -> 1.76 | N34: =31*(M34+I34) -> 54.56 | O34: =N34*G34 -> 9662.2377 | P34: =(H34-(I34*90))/90 -> 0.97777778 | Q34: =31*(P34+I34) -> 30.311111 | R34: =(P34+I34)*31*G34*1.5 -> 8051.8648 | S34: =Q34 -> 30.311111 | T34: =S34/31 -> 0.97777778 | U34: =T34-I34 -> 0.97777778 | V34: =R34 -> 8051.8648 | W34: 0.6 | X34: =Y34/31 -> 0.58666667 | Y34: =S34*W34 -> 18.186667 | Z34: =Y34*G34*1.5 -> 4831.1189 | AA34: 0.4 | AB34: =AC34/31 -> 0.39111111 | AC34: =S34*AA34 -> 12.124444 | AD34: =G34*AC34*1.5 -> 3220.7459 | AE34: 新品： 寄样8，价格进行调整 人员：伟民+罗城+心怡 | AG34: =AC34/4 -> 3.0311111 | AH34: =$Y34/4 -> 4.5466667
A35: CC0758 | B35: 3B-碎纸机7L | C35: 1 | D35: 马来 | E35: 办公安防 | F35: 碎纸机 | G35: 74.8418 | H35: 383 | I35: 3 | J35: 127 | K35: 189 | L35: 15417 | M35: =(H35-(I35*50))/50 -> 4.66 | N35: =31*(M35+I35) -> 237.46 | O35: =N35*G35 -> 17771.934 | P35: =(H35-(I35*90))/90 -> 1.2555556 | Q35: =31*(P35+I35) -> 131.92222 | R35: =(P35+I35)*31*G35*1.5 -> 14809.945 | S35: =Q35 -> 131.92222 | T35: =S35/31 -> 4.2555556 | U35: =T35-I35 -> 1.2555556 | V35: =R35 -> 14809.945 | W35: =_xlfn.XLOOKUP(B35,Sheet5!G:G,Sheet5!H:H) -> 0.65217391 | X35: =Y35/31 -> 2.7753623 | Y35: =S35*W35 -> 86.036232 | Z35: =Y35*G35*1.5 -> 9658.6597 | AA35: =_xlfn.XLOOKUP(B35,Sheet5!G:G,Sheet5!I:I) -> 0.34782609 | AB35: =AC35/31 -> 1.4801932 | AC35: =S35*AA35 -> 45.88599 | AD35: =G35*AC35*1.5 -> 5151.2852 | AE35: 进行调价，控合理周转 | AF35: 全组消耗，竞品价格过低，标价利润13%，已每日安排10个库存对标竞品销售 后续不当主推，主推新款 | AG35: =AC35/4 -> 11.471498 | AH35: =$Y35/4 -> 21.509058
A36: CC0807 | B36: 3C-显示器桌面支架3屏 | C36: 1 | D36: 马来 | E36: 3C数码 | F36: 显示器支架 | G36: 89.55 | H36: 143 | K36: 120 | L36: 15268 | M36: =(H36-(I36*50))/50 -> 2.86 | N36: =31*(M36+I36) -> 88.66 | O36: =N36*G36 -> 7939.503 | P36: =(H36-(I36*90))/90 -> 1.5888889 | Q36: =31*(P36+I36) -> 49.255556 | R36: =(P36+I36)*31*G36*1.5 -> 6616.2525 | S36: =Q36 -> 49.255556 | T36: =S36/31 -> 1.5888889 | U36: =T36-I36 -> 1.5888889 | V36: =R36 -> 6616.2525 | W36: =_xlfn.XLOOKUP(B36,Sheet5!G:G,Sheet5!H:H) -> 1 | X36: =Y36/31 -> 1.5888889 | Y36: =S36*W36 -> 49.255556 | Z36: =Y36*G36*1.5 -> 6616.2525 | AA36: =_xlfn.XLOOKUP(B36,Sheet5!G:G,Sheet5!I:I) -> 0 | AB36: =AC36/31 -> 0 | AC36: =S36*AA36 -> 0 | AD36: =G36*AC36*1.5 -> 0 | AE36: 暂不规划 | AG36: =AC36/4 -> 0 | AH36: =$Y36/4 -> 12.313889
A37: CC1057 | B37: 3C-单柱旋转移动推车MY01 | C37: 1 | D37: 马来 | E37: 3C数码 | F37: 电视支架 | G37: 135.44 | H37: 107 | K37: 81 | L37: 15034 | M37: =(H37-(I37*50))/50 -> 2.14 | N37: =31*(M37+I37) -> 66.34 | O37: =N37*G37 -> 8985.0896 | P37: =(H37-(I37*90))/90 -> 1.1888889 | Q37: =31*(P37+I37) -> 36.855556 | R37: =(P37+I37)*31*G37*1.5 -> 7487.5747 | S37: =Q37 -> 36.855556 | T37: =S37/31 -> 1.1888889 | U37: =T37-I37 -> 1.1888889 | V37: =R37 -> 7487.5747 | W37: =_xlfn.XLOOKUP(B37,Sheet5!G:G,Sheet5!H:H) -> 0.5 | X37: =Y37/31 -> 0.59444444 | Y37: =S37*W37 -> 18.427778 | Z37: =Y37*G37*1.5 -> 3743.7873 | AA37: =_xlfn.XLOOKUP(B37,Sheet5!G:G,Sheet5!I:I) -> 0.5 | AB37: =AC37/31 -> 0.59444444 | AC37: =S37*AA37 -> 18.427778 | AD37: =G37*AC37*1.5 -> 3743.7873 | AE37: 月底刚到，正常下费用插入老链接推品 | AF37: 月底刚到，正常下费用插入老链接推品 鹭燕小店重点给优势扶持 | AG37: =AC37/4 -> 4.6069444 | AH37: =$Y37/4 -> 4.6069444
A38: CC0859 | B38: 3B-广告架kt板斜面3.5kg | C38: 1 | D38: 马来 | E38: 办公安防 | F38: 广告架 | G38: 49.17 | H38: 209 | K38: 201 | L38: 14653 | M38: =(H38-(I38*50))/50 -> 4.18 | N38: =31*(M38+I38) -> 129.58 | O38: =N38*G38 -> 6371.4486 | P38: =(H38-(I38*90))/90 -> 2.3222222 | Q38: =31*(P38+I38) -> 71.988889 | R38: =(P38+I38)*31*G38*1.5 -> 5309.5405 | S38: =Q38 -> 71.988889 | T38: =S38/31 -> 2.3222222 | U38: =T38-I38 -> 2.3222222 | V38: =R38 -> 5309.5405 | W38: =_xlfn.XLOOKUP(B38,Sheet5!G:G,Sheet5!H:H) -> 0.4 | X38: =Y38/31 -> 0.92888889 | Y38: =S38*W38 -> 28.795556 | Z38: =Y38*G38*1.5 -> 2123.8162 | AA38: =_xlfn.XLOOKUP(B38,Sheet5!G:G,Sheet5!I:I) -> 0.6 | AB38: =AC38/31 -> 1.3933333 | AC38: =S38*AA38 -> 43.193333 | AD38: =G38*AC38*1.5 -> 3185.7243 | AE38: 呆滞品： 样品送出10个 | AF38: 正常出清，当前标价28% | AG38: =AC38/4 -> 10.798333 | AH38: =$Y38/4 -> 7.1988889
A39: CC0315 | B39: 3B-密码保险箱黑 | C39: 1 | D39: 马来 | E39: 办公安防 | F39: 保险箱 | G39: 124.73 | H39: 362 | I39: 4 | J39: 90 | K39: 117 | L39: 14593 | M39: =(H39-(I39*50))/50 -> 3.24 | N39: =31*(M39+I39) -> 224.44 | O39: =N39*G39 -> 27994.401 | P39: =(H39-(I39*90))/90 -> 0.022222222 | Q39: =31*(P39+I39) -> 124.68889 | R39: =(P39+I39)*31*G39*1.5 -> 23328.668 | S39: =Q39 -> 124.68889 | T39: =S39/31 -> 4.0222222 | U39: =T39-I39 -> 0.022222222 | V39: =R39 -> 23328.668 | W39: =_xlfn.XLOOKUP(B39,Sheet5!G:G,Sheet5!H:H) -> 0.5 | X39: =Y39/31 -> 2.0111111 | Y39: =S39*W39 -> 62.344444 | Z39: 50 | AA39: =_xlfn.XLOOKUP(B39,Sheet5!G:G,Sheet5!I:I) -> 0.5 | AB39: =AC39/31 -> 2.0111111 | AC39: =S39*AA39 -> 62.344444 | AD39: =G39*AC39*1.5 -> 11664.334 | AE39: 无超期风险 | AG39: =AC39/4 -> 15.586111 | AH39: =$Y39/4 -> 15.586111
A40: CC0905 | B40: 3B-磁吸白板密度板夹层90cm*120cm | C40: 1 | D40: 马来 | E40: 办公安防 | F40: 白板 | G40: 78.7257 | H40: 849 | I40: 13 | J40: 65 | K40: 181 | L40: 14249 | M40: =(H40-(I40*50))/50 -> 3.98 | N40: =31*(M40+I40) -> 526.38 | O40: =N40*G40 -> 41439.634 | P40: =(H40-(I40*90))/90 -> -3.5666667 | Q40: =31*(P40+I40) -> 292.43333 | R40: =(P40+I40)*31*G40*1.5 -> 34533.028 | S40: =Q40 -> 292.43333 | T40: =S40/31 -> 9.4333333 | U40: =T40-I40 -> -3.5666667 | V40: =R40 -> 34533.028 | W40: =_xlfn.XLOOKUP(B40,Sheet5!G:G,Sheet5!H:H) -> 0.86451613 | X40: =Y40/31 -> 8.1552688 | Y40: =S40*W40 -> 252.81333 | Z40: =Y40*G40*1.5 -> 29854.36 | AA40: =_xlfn.XLOOKUP(B40,Sheet5!G:G,Sheet5!I:I) -> 0.13548387 | AB40: =AC40/31 -> 1.2780645 | AC40: =S40*AA40 -> 39.62 | AD40: =G40*AC40*1.5 -> 4678.6684 | AE40: 无超期风险 | AG40: =AC40/4 -> 9.905 | AH40: =$Y40/4 -> 63.203333
A41: CC0996 | B41: 3C-专业播客动圈麦克风 | C41: 1 | D41: 马来 | E41: 3C数码 | F41: 有线麦克风 | G41: 152.62 | H41: 65 | K41: 57 | L41: 12515 | M41: =(H41-(I41*50))/50 -> 1.3 | N41: =31*(M41+I41) -> 40.3 | O41: =N41*G41 -> 6150.586 | P41: =(H41-(I41*90))/90 -> 0.72222222 | Q41: =31*(P41+I41) -> 22.388889 | R41: =(P41+I41)*31*G41*1.5 -> 5125.4883 | S41: =Q41 -> 22.388889 | T41: =S41/31 -> 0.72222222 | U41: =T41-I41 -> 0.72222222 | V41: =R41 -> 5125.4883 | W41: =_xlfn.XLOOKUP(B41,Sheet5!G:G,Sheet5!H:H) -> 0 | X41: =Y41/31 -> 0 | Y41: =S41*W41 -> 0 | Z41: =Y41*G41*1.5 -> 0 | AA41: =_xlfn.XLOOKUP(B41,Sheet5!G:G,Sheet5!I:I) -> 1 | AB41: =AC41/31 -> 0.72222222 | AC41: =S41*AA41 -> 22.388889 | AD41: =G41*AC41*1.5 -> 5125.4883 | AE41: 新品：麦系列TK为主达人推广 寄样5 人员：郑雨倩+罗城+伟铭 | AF41: 暂不规划，需重新对标竞品价格 | AG41: =AC41/4 -> 5.5972222 | AH41: =$Y41/4 -> 0
A42: CC0295 | B42: 3C-声霸蓝牙音箱 | C42: 1 | D42: 马来 | E42: 3C数码 | F42: 音箱 | G42: 62.9613 | H42: 1651 | I42: 29 | J42: 56 | K42: 198 | L42: 12466 | M42: =(H42-(I42*50))/50 -> 4.02 | N42: =31*(M42+I42) -> 1023.62 | O42: =N42*G42 -> 64448.446 | P42: =(H42-(I42*90))/90 -> -10.655556 | Q42: =31*(P42+I42) -> 568.67778 | R42: =(P42+I42)*31*G42*1.5 -> 53707.038 | S42: =Q42 -> 568.67778 | T42: =S42/31 -> 18.344444 | U42: =T42-I42 -> -10.655556 | V42: =R42 -> 53707.038 | W42: =_xlfn.XLOOKUP(B42,Sheet5!G:G,Sheet5!H:H) -> 0.35329341 | X42: =Y42/31 -> 6.4809714 | Y42: =S42*W42 -> 200.91011 | Z42: =Y42*G42*1.5 -> 18974.343 | AA42: =_xlfn.XLOOKUP(B42,Sheet5!G:G,Sheet5!I:I) -> 0.64670659 | AB42: =AC42/31 -> 11.863473 | AC42: =S42*AA42 -> 367.76766 | AD42: =G42*AC42*1.5 -> 34732.695 | AE42: 无超期风险 | AG42: =AC42/4 -> 91.941916 | AH42: =$Y42/4 -> 50.227528
A43: CC0277 | B43: 3B-智能指纹门锁M20 | C43: 1 | D43: 马来 | E43: 办公安防 | F43: 指纹锁 | G43: 74.736 | H43: 322 | I43: 3 | J43: 107 | K43: 153 | L43: 12107 | M43: =(H43-(I43*50))/50 -> 3.44 | N43: =31*(M43+I43) -> 199.64 | O43: =N43*G43 -> 14920.295 | P43: =(H43-(I43*90))/90 -> 0.57777778 | Q43: =31*(P43+I43) -> 110.91111 | R43: =(P43+I43)*31*G43*1.5 -> 12433.579 | S43: =Q43 -> 110.91111 | T43: =S43/31 -> 3.5777778 | U43: =T43-I43 -> 0.57777778 | V43: =R43 -> 12433.579 | W43: =_xlfn.XLOOKUP(B43,Sheet5!G:G,Sheet5!H:H) -> 0.31578947 | X43: =Y43/31 -> 1.1298246 | Y43: =S43*W43 -> 35.024561 | Z43: =Y43*G43*1.5 -> 3926.3934 | AA43: =_xlfn.XLOOKUP(B43,Sheet5!G:G,Sheet5!I:I) -> 0.68421053 | AB43: =AC43/31 -> 2.4479532 | AC43: =S43*AA43 -> 75.88655 | AD43: =G43*AC43*1.5 -> 8507.1858 | AE43: 无超期风险 | AG43: =AC43/4 -> 18.971637 | AH43: =$Y43/4 -> 8.7561404
A44: CC0181 | B44: 3B-碎纸机10L | C44: 1 | D44: 马来 | E44: 办公安防 | F44: 碎纸机 | G44: 93.6425 | H44: 396 | I44: 5 | J44: 79 | K44: 121 | L44: 11331 | M44: =(H44-(I44*50))/50 -> 2.92 | N44: =31*(M44+I44) -> 245.52 | O44: =N44*G44 -> 22991.107 | P44: =(H44-(I44*90))/90 -> -0.6 | Q44: =31*(P44+I44) -> 136.4 | R44: =(P44+I44)*31*G44*1.5 -> 19159.255 | S44: =Q44 -> 136.4 | T44: =S44/31 -> 4.4 | U44: =T44-I44 -> -0.6 | V44: =R44 -> 19159.255 | W44: =_xlfn.XLOOKUP(B44,Sheet5!G:G,Sheet5!H:H) -> 0.86153846 | X44: =Y44/31 -> 3.7907692 | Y44: =S44*W44 -> 117.51385 | Z44: =Y44*G44*1.5 -> 16506.436 | AA44: =_xlfn.XLOOKUP(B44,Sheet5!G:G,Sheet5!I:I) -> 0.13846154 | AB44: =AC44/31 -> 0.60923077 | AC44: =S44*AA44 -> 18.886154 | AD44: =G44*AC44*1.5 -> 2652.82 | AE44: 无超期风险 | AG44: =AC44/4 -> 4.7215385 | AH44: =$Y44/4 -> 29.378462
A45: CC0756 | B45: 3B-交换机机柜60cm | C45: 1 | D45: 马来 | E45: 办公安防 | F45: 金属制品机柜 | G45: 124.39 | H45: 88 | K45: 65 | L45: 10946 | M45: =(H45-(I45*50))/50 -> 1.76 | N45: =31*(M45+I45) -> 54.56 | O45: =N45*G45 -> 6786.7184 | P45: =(H45-(I45*90))/90 -> 0.97777778 | Q45: =31*(P45+I45) -> 30.311111 | R45: =(P45+I45)*31*G45*1.5 -> 5655.5987 | S45: =Q45 -> 30.311111 | T45: =S45/31 -> 0.97777778 | U45: =T45-I45 -> 0.97777778 | V45: =R45 -> 5655.5987 | W45: =_xlfn.XLOOKUP(B45,Sheet5!G:G,Sheet5!H:H) -> 0.88888889 | X45: =Y45/31 -> 0.8691358 | Y45: =S45*W45 -> 26.94321 | Z45: =Y45*G45*1.5 -> 5027.1988 | AA45: =_xlfn.XLOOKUP(B45,Sheet5!G:G,Sheet5!I:I) -> 0.11111111 | AB45: =AC45/31 -> 0.10864198 | AC45: =S45*AA45 -> 3.3679012 | AD45: =G45*AC45*1.5 -> 628.39985 | AE45: 暂不规划 | AG45: =AC45/4 -> 0.84197531 | AH45: =$Y45/4 -> 6.7358025
A46: CC0666 | B46: 3C-X3游戏手柄带手机支架 | C46: 1 | D46: 马来 | E46: 3C数码 | F46: 游戏手柄 | G46: 24.9136 | H46: 1016 | I46: 12 | J46: 84 | K46: 400 | L46: 9965 | M46: =(H46-(I46*50))/50 -> 8.32 | N46: =31*(M46+I46) -> 629.92 | O46: =N46*G46 -> 15693.575 | P46: =(H46-(I46*90))/90 -> -0.71111111 | Q46: =31*(P46+I46) -> 349.95556 | R46: =(P46+I46)*31*G46*1.5 -> 13077.979 | S46: =Q46 -> 349.95556 | T46: =S46/31 -> 11.288889 | U46: =T46-I46 -> -0.71111111 | V46: =R46 -> 13077.979 | W46: =_xlfn.XLOOKUP(B46,Sheet5!G:G,Sheet5!H:H) -> 0.29347826 | X46: =Y46/31 -> 3.3130435 | Y46: =S46*W46 -> 102.70435 | Z46: =Y46*G46*1.5 -> 3838.1026 | AA46: =_xlfn.XLOOKUP(B46,Sheet5!G:G,Sheet5!I:I) -> 0.70652174 | AB46: =AC46/31 -> 7.9758454 | AC46: =S46*AA46 -> 247.25121 | AD46: =G46*AC46*1.5 -> 9239.8765 | AG46: =AC46/4 -> 61.812802 | AH46: =$Y46/4 -> 25.676087
A47: CC0830 | B47: 3C-显示器桌面支架4屏 | C47: 1 | D47: 马来 | E47: 3C数码 | F47: 电视支架 | G47: 125.34 | H47: 56 | K47: 53 | L47: 9777 | M47: =(H47-(I47*50))/50 -> 1.12 | N47: =31*(M47+I47) -> 34.72 | O47: =N47*G47 -> 4351.8048 | P47: =(H47-(I47*90))/90 -> 0.62222222 | Q47: =31*(P47+I47) -> 19.288889 | R47: =(P47+I47)*31*G47*1.5 -> 3626.504 | S47: =Q47 -> 19.288889 | T47: =S47/31 -> 0.62222222 | U47: =T47-I47 -> 0.62222222 | V47: =R47 -> 3626.504 | W47: 1 | X47: =Y47/31 -> 0.62222222 | Y47: =S47*W47 -> 19.288889 | Z47: =Y47*G47*1.5 -> 3626.504 | AA47: =_xlfn.XLOOKUP(B47,Sheet5!G:G,Sheet5!I:I) -> 0 | AB47: =AC47/31 -> 0 | AC47: =S47*AA47 -> 0 | AD47: =G47*AC47*1.5 -> 0 | AE47: 暂不规划 | AG47: =AC47/4 -> 0 | AH47: =$Y47/4 -> 4.8222222
A48: CC0743 | B48: 3B-道路减速带100cm*35cm*3cm | C48: 1 | D48: 马来 | E48: 办公安防 | F48: 橡胶减速带 | G48: 31.76 | H48: 355 | I48: 2 | J48: 177 | K48: 235 | L48: 9671 | M48: =(H48-(I48*50))/50 -> 5.1 | N48: =31*(M48+I48) -> 220.1 | O48: =N48*G48 -> 6990.376 | P48: =(H48-(I48*90))/90 -> 1.9444444 | Q48: =31*(P48+I48) -> 122.27778 | R48: =(P48+I48)*31*G48*1.5 -> 5825.3133 | S48: =Q48 -> 122.27778 | T48: =S48/31 -> 3.9444444 | U48: =T48-I48 -> 1.9444444 | V48: =R48 -> 5825.3133 | W48: =_xlfn.XLOOKUP(B48,Sheet5!G:G,Sheet5!H:H) -> 1 | X48: =Y48/31 -> 3.9444444 | Y48: =S48*W48 -> 122.27778 | Z48: =Y48*G48*1.5 -> 5825.3133 | AA48: =_xlfn.XLOOKUP(B48,Sheet5!G:G,Sheet5!I:I) -> 0 | AB48: =AC48/31 -> 0 | AC48: =S48*AA48 -> 0 | AD48: =G48*AC48*1.5 -> 0 | AE48: 暂不规划 | AF48: 暂不规划 | AG48: =AC48/4 -> 0 | AH48: =$Y48/4 -> 30.569444
A49: CC1010 | B49: 3C-电脑机箱T8款风扇款白色 | C49: 1 | D49: 马来 | E49: 3C数码 | F49: 电脑机箱 | G49: 83.6943 | H49: 94 | K49: 78 | L49: 9248 | M49: =(H49-(I49*50))/50 -> 1.88 | N49: =31*(M49+I49) -> 58.28 | O49: =N49*G49 -> 4877.7038 | P49: =(H49-(I49*90))/90 -> 1.0444444 | Q49: =31*(P49+I49) -> 32.377778 | R49: =(P49+I49)*31*G49*1.5 -> 4064.7532 | S49: =Q49 -> 32.377778 | T49: =S49/31 -> 1.0444444 | U49: =T49-I49 -> 1.0444444 | V49: =R49 -> 4064.7532 | W49: 0.7 | X49: =Y49/31 -> 0.73111111 | Y49: =S49*W49 -> 22.664444 | Z49: =Y49*G49*1.5 -> 2845.3272 | AA49: 0.3 | AB49: =AC49/31 -> 0.31333333 | AC49: =S49*AA49 -> 9.7133333 | AD49: =G49*AC49*1.5 -> 1219.426 | AE49: 呆滞品： 调回之前控价。 | AF49: 对标竞品价格30%标价出清 鹭燕+荣锦重点下费用 | AG49: =AC49/4 -> 2.4283333 | AH49: =$Y49/4 -> 5.6661111
A50: CC0339 | B50: 3B-保险柜80cm*44cm*40cm | C50: 1 | D50: 马来 | E50: 办公安防 | F50: 保险箱 | G50: 667.5613 | H50: 23 | K50: 12 | L50: 9012 | M50: =(H50-(I50*50))/50 -> 0.46 | N50: =31*(M50+I50) -> 14.26 | O50: =N50*G50 -> 9519.4241 | P50: =(H50-(I50*90))/90 -> 0.25555556 | Q50: =31*(P50+I50) -> 7.9222222 | R50: =(P50+I50)*31*G50*1.5 -> 7932.8534 | S50: =Q50 -> 7.9222222 | T50: =S50/31 -> 0.25555556 | U50: =T50-I50 -> 0.25555556 | V50: =R50 -> 7932.8534 | W50: 0.5 | X50: =Y50/31 -> 0.12777778 | Y50: =S50*W50 -> 3.9611111 | Z50: =Y50*G50*1.5 -> 3966.4267 | AA50: 0.5 | AB50: =AC50/31 -> 0.12777778 | AC50: =S50*AA50 -> 3.9611111 | AD50: =G50*AC50*1.5 -> 3966.4267 | AE50: 呆滞品：成本销售，寄样赠送4个 | AG50: =AC50/4 -> 0.99027778 | AH50: =$Y50/4 -> 0.99027778
A51: CC1000 | B51: 3C-跟拍自动支撑自拍杆Q625 | C51: 1 | D51: 马来 | E51: 3C数码 | F51: 自拍杆 | G51: 79.73 | H51: 78 | K51: 75 | L51: 8850 | M51: =(H51-(I51*50))/50 -> 1.56 | N51: =31*(M51+I51) -> 48.36 | O51: =N51*G51 -> 3855.7428 | P51: =(H51-(I51*90))/90 -> 0.86666667 | Q51: =31*(P51+I51) -> 26.866667 | R51: =(P51+I51)*31*G51*1.5 -> 3213.119 | S51: =Q51 -> 26.866667 | T51: =S51/31 -> 0.86666667 | U51: =T51-I51 -> 0.86666667 | V51: =R51 -> 3213.119 | W51: =_xlfn.XLOOKUP(B51,Sheet5!G:G,Sheet5!H:H) -> 0 | X51: =Y51/31 -> 0 | Y51: =S51*W51 -> 0 | Z51: =Y51*G51*1.5 -> 0 | AA51: =_xlfn.XLOOKUP(B51,Sheet5!G:G,Sheet5!I:I) -> 0 | AB51: =AC51/31 -> 0 | AC51: =S51*AA51 -> 0 | AD51: =G51*AC51*1.5 -> 0 | AE51: 新品： 寄样5， 人员：郑雨倩 | AG51: =AC51/4 -> 0 | AH51: =$Y51/4 -> 0
A52: CC0605 | B52: 3C-32至70寸电视移动支架的单支架 | C52: 1 | D52: 马来 | E52: 3C数码 | F52: 电视支架 | G52: 99.81 | H52: 379 | I52: 5 | J52: 75 | K52: 84 | L52: 8384 | M52: =(H52-(I52*50))/50 -> 2.58 | N52: =31*(M52+I52) -> 234.98 | O52: =N52*G52 -> 23453.354 | P52: =(H52-(I52*90))/90 -> -0.78888889 | Q52: =31*(P52+I52) -> 130.54444 | R52: =(P52+I52)*31*G52*1.5 -> 19544.462 | S52: =Q52 -> 130.54444 | T52: =S52/31 -> 4.2111111 | U52: =T52-I52 -> -0.78888889 | V52: =R52 -> 19544.462 | W52: =_xlfn.XLOOKUP(B52,Sheet5!G:G,Sheet5!H:H) -> 0.75 | X52: =Y52/31 -> 3.1583333 | Y52: =S52*W52 -> 97.908333 | Z52: =Y52*G52*1.5 -> 14658.346 | AA52: =_xlfn.XLOOKUP(B52,Sheet5!G:G,Sheet5!I:I) -> 0.25 | AB52: =AC52/31 -> 1.0527778 | AC52: =S52*AA52 -> 32.636111 | AD52: =G52*AC52*1.5 -> 4886.1154 | AE52: 无超期风险 | AG52: =AC52/4 -> 8.1590278 | AH52: =$Y52/4 -> 24.477083
A53: CC0960 | B53: 3B-997型号外币点钞机 | C53: 1 | D53: 马来 | E53: 办公安防 | F53: 点钞机 | G53: 405.03 | H53: 46 | K53: 20 | L53: 8101 | M53: =(H53-(I53*50))/50 -> 0.92 | N53: =31*(M53+I53) -> 28.52 | O53: =N53*G53 -> 11551.456 | P53: =(H53-(I53*90))/90 -> 0.51111111 | Q53: =31*(P53+I53) -> 15.844444 | R53: =(P53+I53)*31*G53*1.5 -> 9626.213 | S53: =Q53 -> 15.844444 | T53: =S53/31 -> 0.51111111 | U53: =T53-I53 -> 0.51111111 | V53: =R53 -> 9626.213 | W53: =_xlfn.XLOOKUP(B53,Sheet5!G:G,Sheet5!H:H) -> 0 | X53: =Y53/31 -> 0 | Y53: =S53*W53 -> 0 | Z53: =Y53*G53*1.5 -> 0 | AA53: =_xlfn.XLOOKUP(B53,Sheet5!G:G,Sheet5!I:I) -> 1 | AB53: =AC53/31 -> 0.51111111 | AC53: =S53*AA53 -> 15.844444 | AD53: =G53*AC53*1.5 -> 9626.213 | AE53: 无超期风险 | AG53: =AC53/4 -> 3.9611111 | AH53: =$Y53/4 -> 0
A54: CC0887 | B54: 3B-U9五功能玻璃门智能锁带TUYAAPP | C54: 1 | D54: 马来 | E54: 办公安防 | F54: 智能锁 | G54: 94.4512 | H54: 60 | K54: 57 | L54: 7934 | M54: =(H54-(I54*50))/50 -> 1.2 | N54: =31*(M54+I54) -> 37.2 | O54: =N54*G54 -> 3513.5846 | P54: =(H54-(I54*90))/90 -> 0.66666667 | Q54: =31*(P54+I54) -> 20.666667 | R54: =(P54+I54)*31*G54*1.5 -> 2927.9872 | S54: =Q54 -> 20.666667 | T54: =S54/31 -> 0.66666667 | U54: =T54-I54 -> 0.66666667 | V54: =R54 -> 2927.9872 | W54: =_xlfn.XLOOKUP(B54,Sheet5!G:G,Sheet5!H:H) -> 1 | X54: =Y54/31 -> 0.66666667 | Y54: =S54*W54 -> 20.666667 | Z54: =Y54*G54*1.5 -> 2927.9872 | AA54: =_xlfn.XLOOKUP(B54,Sheet5!G:G,Sheet5!I:I) -> 0 | AB54: =AC54/31 -> 0 | AC54: =S54*AA54 -> 0 | AD54: =G54*AC54*1.5 -> 0 | AE54: 暂不规划 | AG54: =AC54/4 -> 0 | AH54: =$Y54/4 -> 5.1666667
A55: CC0611 | B55: 3C-投影仪支架1.2米 | C55: 1 | D55: 马来 | E55: 3C数码 | F55: 投影仪支架 | G55: 17.5315 | H55: 441 | I55: 2 | J55: 220 | K55: 328 | L55: 7828 | M55: =(H55-(I55*50))/50 -> 6.82 | N55: =31*(M55+I55) -> 273.42 | O55: =N55*G55 -> 4793.4627 | P55: =(H55-(I55*90))/90 -> 2.9 | Q55: =31*(P55+I55) -> 151.9 | R55: =(P55+I55)*31*G55*1.5 -> 3994.5523 | S55: =Q55 -> 151.9 | T55: =S55/31 -> 4.9 | U55: =T55-I55 -> 2.9 | V55: =R55 -> 3994.5523 | W55: =_xlfn.XLOOKUP(B55,Sheet5!G:G,Sheet5!H:H) -> 0.88235294 | X55: =Y55/31 -> 4.3235294 | Y55: =S55*W55 -> 134.02941 | Z55: =Y55*G55*1.5 -> 3524.6049 | AA55: =_xlfn.XLOOKUP(B55,Sheet5!G:G,Sheet5!I:I) -> 0.11764706 | AB55: =AC55/31 -> 0.57647059 | AC55: =S55*AA55 -> 17.870588 | AD55: =G55*AC55*1.5 -> 469.94733 | AE55: 无超期风险 | AF55: 正常销售 | AG55: =AC55/4 -> 4.4676471 | AH55: =$Y55/4 -> 33.507353
A56: CC0235 | B56: 3B-306CWiFi路由器 | C56: 1 | D56: 马来 | E56: 办公安防 | F56: 路由器 | G56: 109.41 | H56: 47 | K56: 47 | L56: 7713 | M56: =(H56-(I56*50))/50 -> 0.94 | N56: =31*(M56+I56) -> 29.14 | O56: =N56*G56 -> 3188.2074 | P56: =(H56-(I56*90))/90 -> 0.52222222 | Q56: =31*(P56+I56) -> 16.188889 | R56: =(P56+I56)*31*G56*1.5 -> 2656.8395 | S56: =Q56 -> 16.188889 | T56: =S56/31 -> 0.52222222 | U56: =T56-I56 -> 0.52222222 | V56: =R56 -> 2656.8395 | W56: 1 | X56: =Y56/31 -> 0.52222222 | Y56: =S56*W56 -> 16.188889 | Z56: =Y56*G56*1.5 -> 2656.8395 | AA56: =_xlfn.XLOOKUP(B56,Sheet5!G:G,Sheet5!I:I) -> 0 | AB56: =AC56/31 -> 0 | AC56: =S56*AA56 -> 0 | AD56: =G56*AC56*1.5 -> 0 | AE56: 无法上架 | AF56: 无法上架，尝试搭配交换机出清 | AG56: =AC56/4 -> 0 | AH56: =$Y56/4 -> 4.0472222
A57: CC0851 | B57: 3C-PRO蓝牙RGB无线拉伸手机游戏手柄STK7011 | C57: 1 | D57: 马来 | E57: 3C数码 | F57: 游戏手柄 | G57: 100.1499 | H57: 116 | I57: 1 | J57: 116 | K57: 65 | L57: 7712 | M57: =(H57-(I57*50))/50 -> 1.32 | N57: =31*(M57+I57) -> 71.92 | O57: =N57*G57 -> 7202.7808 | P57: =(H57-(I57*90))/90 -> 0.28888889 | Q57: =31*(P57+I57) -> 39.955556 | R57: =(P57+I57)*31*G57*1.5 -> 6002.3173 | S57: =Q57 -> 39.955556 | T57: =S57/31 -> 1.2888889 | U57: =T57-I57 -> 0.28888889 | V57: =R57 -> 6002.3173 | W57: =_xlfn.XLOOKUP(B57,Sheet5!G:G,Sheet5!H:H) -> 0 | X57: =Y57/31 -> 0 | Y57: =S57*W57 -> 0 | Z57: =Y57*G57*1.5 -> 0 | AA57: =_xlfn.XLOOKUP(B57,Sheet5!G:G,Sheet5!I:I) -> 1 | AB57: =AC57/31 -> 1.2888889 | AC57: =S57*AA57 -> 39.955556 | AD57: =G57*AC57*1.5 -> 6002.3173 | AE57: 无超期风险 | AG57: =AC57/4 -> 9.9888889 | AH57: =$Y57/4 -> 0
A58: CC0998 | B58: 3C-RGB全透明动圈降噪桌面麦克风 | C58: 1 | D58: 马来 | E58: 3C数码 | F58: 有线麦克风 | G58: 80.27 | H58: 68 | K58: 65 | L58: 7706 | M58: =(H58-(I58*50))/50 -> 1.36 | N58: =31*(M58+I58) -> 42.16 | O58: =N58*G58 -> 3384.1832 | P58: =(H58-(I58*90))/90 -> 0.75555556 | Q58: =31*(P58+I58) -> 23.422222 | R58: =(P58+I58)*31*G58*1.5 -> 2820.1527 | S58: =Q58 -> 23.422222 | T58: =S58/31 -> 0.75555556 | U58: =T58-I58 -> 0.75555556 | V58: =R58 -> 2820.1527 | W58: =_xlfn.XLOOKUP(B58,Sheet5!G:G,Sheet5!H:H) -> 0 | X58: =Y58/31 -> 0 | Y58: =S58*W58 -> 0 | Z58: =Y58*G58*1.5 -> 0 | AA58: =_xlfn.XLOOKUP(B58,Sheet5!G:G,Sheet5!I:I) -> 1 | AB58: =AC58/31 -> 0.75555556 | AC58: =S58*AA58 -> 23.422222 | AD58: =G58*AC58*1.5 -> 2820.1527 | AE58: 新品：麦系列TK为主达人推广 寄样5 人员：郑雨倩+罗城+伟铭 | AG58: =AC58/4 -> 5.8555556 | AH58: =$Y58/4 -> 0
A59: CC0878 | B59: 3B-R5A房间门锁单锁舌四功能不带APP | C59: 1 | D59: 马来 | E59: 办公安防 | F59: 密码锁 | G59: 127.61 | H59: 58 | K59: 43 | L59: 7465 | M59: =(H59-(I59*50))/50 -> 1.16 | N59: =31*(M59+I59) -> 35.96 | O59: =N59*G59 -> 4588.8556 | P59: =(H59-(I59*90))/90 -> 0.64444444 | Q59: =31*(P59+I59) -> 19.977778 | R59: =(P59+I59)*31*G59*1.5 -> 3824.0463 | S59: =Q59 -> 19.977778 | T59: =S59/31 -> 0.64444444 | U59: =T59-I59 -> 0.64444444 | V59: =R59 -> 3824.0463 | W59: =_xlfn.XLOOKUP(B59,Sheet5!G:G,Sheet5!H:H) -> 1 | X59: =Y59/31 -> 0.64444444 | Y59: =S59*W59 -> 19.977778 | Z59: =Y59*G59*1.5 -> 3824.0463 | AA59: =_xlfn.XLOOKUP(B59,Sheet5!G:G,Sheet5!I:I) -> 0 | AB59: =AC59/31 -> 0 | AC59: =S59*AA59 -> 0 | AD59: =G59*AC59*1.5 -> 0 | AE59: 暂不规划 | AG59: =AC59/4 -> 0 | AH59: =$Y59/4 -> 4.9944444
A60: CC0621 | B60: 3C-圆筒投影仪白色 | C60: 1 | D60: 马来 | E60: 3C数码 | F60: 投影仪 | G60: 171.7044 | H60: 45 | K60: 32 | L60: 7297 | M60: =(H60-(I60*50))/50 -> 0.9 | N60: =31*(M60+I60) -> 27.9 | O60: =N60*G60 -> 4790.5528 | P60: =(H60-(I60*90))/90 -> 0.5 | Q60: =31*(P60+I60) -> 15.5 | R60: =(P60+I60)*31*G60*1.5 -> 3992.1273 | S60: =Q60 -> 15.5 | T60: =S60/31 -> 0.5 | U60: =T60-I60 -> 0.5 | V60: =R60 -> 3992.1273 | W60: =_xlfn.XLOOKUP(B60,Sheet5!G:G,Sheet5!H:H) -> 0.25 | X60: =Y60/31 -> 0.125 | Y60: =S60*W60 -> 3.875 | Z60: =Y60*G60*1.5 -> 998.03183 | AA60: =_xlfn.XLOOKUP(B60,Sheet5!G:G,Sheet5!I:I) -> 0.75 | AB60: =AC60/31 -> 0.375 | AC60: =S60*AA60 -> 11.625 | AD60: =G60*AC60*1.5 -> 2994.0955 | AE60: 仅广告消耗出清 罗城。 | AF60: 全组下费用到新投影仪链接 插入新投影仪拉低页面价格出清 | AG60: =AC60/4 -> 2.90625 | AH60: =$Y60/4 -> 0.96875
A61: CC0777 | B61: 3C-头戴式无线三模耳机K90W | C61: 1 | D61: 马来 | E61: 3C数码 | F61: 耳机 | G61: 75.23 | H61: 76 | K61: 65 | L61: 6996 | M61: =(H61-(I61*50))/50 -> 1.52 | N61: =31*(M61+I61) -> 47.12 | O61: =N61*G61 -> 3544.8376 | P61: =(H61-(I61*90))/90 -> 0.84444444 | Q61: =31*(P61+I61) -> 26.177778 | R61: =(P61+I61)*31*G61*1.5 -> 2954.0313 | S61: =Q61 -> 26.177778 | T61: =S61/31 -> 0.84444444 | U61: =T61-I61 -> 0.84444444 | V61: =R61 -> 2954.0313 | W61: =_xlfn.XLOOKUP(B61,Sheet5!G:G,Sheet5!H:H) -> 0.33333333 | X61: =Y61/31 -> 0.28148148 | Y61: =S61*W61 -> 8.7259259 | Z61: =Y61*G61*1.5 -> 984.67711 | AA61: =_xlfn.XLOOKUP(B61,Sheet5!G:G,Sheet5!I:I) -> 0.66666667 | AB61: =AC61/31 -> 0.56296296 | AC61: =S61*AA61 -> 17.451852 | AD61: =G61*AC61*1.5 -> 1969.3542 | AE61: 新品: 加入老链接，消耗17 | AG61: =AC61/4 -> 4.362963 | AH61: =$Y61/4 -> 2.1814815
A62: CC0790 | B62: 3C-相机三脚架160cm | C62: 1 | D62: 马来 | E62: 3C数码 | F62: 三脚架 | G62: 44.32 | H62: 107 | K62: 102 | L62: 6692 | M62: =(H62-(I62*50))/50 -> 2.14 | N62: =31*(M62+I62) -> 66.34 | O62: =N62*G62 -> 2940.1888 | P62: =(H62-(I62*90))/90 -> 1.1888889 | Q62: =31*(P62+I62) -> 36.855556 | R62: =(P62+I62)*31*G62*1.5 -> 2450.1573 | S62: =Q62 -> 36.855556 | T62: =S62/31 -> 1.1888889 | U62: =T62-I62 -> 1.1888889 | V62: =R62 -> 2450.1573 | W62: =_xlfn.XLOOKUP(B62,Sheet5!G:G,Sheet5!H:H) -> 0 | X62: =Y62/31 -> 0 | Y62: =S62*W62 -> 0 | Z62: =Y62*G62*1.5 -> 0 | AA62: =_xlfn.XLOOKUP(B62,Sheet5!G:G,Sheet5!I:I) -> 1 | AB62: =AC62/31 -> 1.1888889 | AC62: =S62*AA62 -> 36.855556 | AD62: =G62*AC62*1.5 -> 2450.1573 | AE62: 暂不规划 | AF62: 暂不规划 | AG62: =AC62/4 -> 9.2138889 | AH62: =$Y62/4 -> 0
A63: CC0079 | B63: 3C-电视壁挂架小一体 | C63: 1 | D63: 马来 | E63: 3C数码 | F63: 电视支架 | G63: 7.5 | H63: 1293 | I63: 11 | J63: 117 | K63: 737 | L63: 6623 | M63: =(H63-(I63*50))/50 -> 14.86 | N63: =31*(M63+I63) -> 801.66 | O63: =N63*G63 -> 6012.45 | P63: =(H63-(I63*90))/90 -> 3.3666667 | Q63: =31*(P63+I63) -> 445.36667 | R63: =(P63+I63)*31*G63*1.5 -> 5010.375 | S63: =Q63 -> 445.36667 | T63: =S63/31 -> 14.366667 | U63: =T63-I63 -> 3.3666667 | V63: =R63 -> 5010.375 | W63: =_xlfn.XLOOKUP(B63,Sheet5!G:G,Sheet5!H:H) -> 0.53424658 | X63: =Y63/31 -> 7.6753425 | Y63: =S63*W63 -> 237.93562 | Z63: =Y63*G63*1.5 -> 2676.7757 | AA63: =_xlfn.XLOOKUP(B63,Sheet5!G:G,Sheet5!I:I) -> 0.46575342 | AB63: =AC63/31 -> 6.6913242 | AC63: =S63*AA63 -> 207.43105 | AD63: =G63*AC63*1.5 -> 2333.5993 | AE63: 正常消耗，支架系列受到售后问题导致出清降环 | AF63: 正常赠品消耗 | AG63: =AC63/4 -> 51.857763 | AH63: =$Y63/4 -> 59.483904
A64: CC0589 | B64: 3B-小票快递单打印机黑蓝色 | C64: 1 | D64: 马来 | E64: 办公安防 | F64: 打印机 | G64: 49.5922 | H64: 1467 | I64: 26 | J64: 56 | K64: 132 | L64: 6546 | M64: =(H64-(I64*50))/50 -> 3.34 | N64: =31*(M64+I64) -> 909.54 | O64: =N64*G64 -> 45106.09 | P64: =(H64-(I64*90))/90 -> -9.7 | Q64: =31*(P64+I64) -> 505.3 | R64: =(P64+I64)*31*G64*1.5 -> 37588.408 | S64: =Q64 -> 505.3 | T64: =S64/31 -> 16.3 | U64: =T64-I64 -> -9.7 | V64: =R64 -> 37588.408 | W64: =_xlfn.XLOOKUP(B64,Sheet5!G:G,Sheet5!H:H) -> 0.62762763 | X64: =Y64/31 -> 10.23033 | Y64: =S64*W64 -> 317.14024 | Z64: =Y64*G64*1.5 -> 23591.523 | AA64: =_xlfn.XLOOKUP(B64,Sheet5!G:G,Sheet5!I:I) -> 0.37237237 | AB64: =AC64/31 -> 6.0696697 | AC64: =S64*AA64 -> 188.15976 | AD64: =G64*AC64*1.5 -> 13996.885 | AE64: 无超期风险 | AG64: =AC64/4 -> 47.03994 | AH64: =$Y64/4 -> 79.28506
A65: CC1061 | B65: 3B-桌面碎纸机4L桶CS201C | C65: 1 | D65: 马来 | E65: 办公安防 | F65: 碎纸机 | G65: 149.1686 | H65: 36 | K65: 30 | L65: 6340 | M65: =(H65-(I65*50))/50 -> 0.72 | N65: =31*(M65+I65) -> 22.32 | O65: =N65*G65 -> 3329.4432 | P65: =(H65-(I65*90))/90 -> 0.4 | Q65: =31*(P65+I65) -> 12.4 | R65: =(P65+I65)*31*G65*1.5 -> 2774.536 | S65: =Q65 -> 12.4 | T65: =S65/31 -> 0.4 | U65: =T65-I65 -> 0.4 | V65: =R65 -> 2774.536 | W65: =_xlfn.XLOOKUP(B65,Sheet5!G:G,Sheet5!H:H) -> 0 | X65: =Y65/31 -> 0 | Y65: =S65*W65 -> 0 | Z65: =Y65*G65*1.5 -> 0 | AA65: =_xlfn.XLOOKUP(B65,Sheet5!G:G,Sheet5!I:I) -> 1 | AB65: =AC65/31 -> 0.4 | AC65: =S65*AA65 -> 12.4 | AD65: =G65*AC65*1.5 -> 2774.536 | AE65: 新品： 寄样6， 人员：王心怡+罗城 | AG65: =AC65/4 -> 3.1 | AH65: =$Y65/4 -> 0
A66: CC1053 | B66: 3C-电脑机箱34014款风扇款黑色 | C66: 1 | D66: 马来 | E66: 3C数码 | F66: 电脑机箱 | G66: 79.16 | H66: 50 | K66: 50 | L66: 5937 | M66: =(H66-(I66*50))/50 -> 1 | N66: =31*(M66+I66) -> 31 | O66: =N66*G66 -> 2453.96 | P66: =(H66-(I66*90))/90 -> 0.55555556 | Q66: =31*(P66+I66) -> 17.222222 | R66: =(P66+I66)*31*G66*1.5 -> 2044.9667 | S66: =Q66 -> 17.222222 | T66: =S66/31 -> 0.55555556 | U66: =T66-I66 -> 0.55555556 | V66: =R66 -> 2044.9667 | W66: =_xlfn.XLOOKUP(B66,Sheet5!G:G,Sheet5!H:H) -> 0 | X66: =Y66/31 -> 0 | Y66: =S66*W66 -> 0 | Z66: =Y66*G66*1.5 -> 0 | AA66: =_xlfn.XLOOKUP(B66,Sheet5!G:G,Sheet5!I:I) -> 0 | AB66: =AC66/31 -> 0 | AC66: =S66*AA66 -> 0 | AD66: =G66*AC66*1.5 -> 0 | AE66: 暂不规划 | AF66: 插入原有机箱链接出清 | AG66: =AC66/4 -> 0 | AH66: =$Y66/4 -> 0
A67: CC1066 | B67: 3B-WIFI漏电多功能导轨表彩屏6显款2P63A | C67: 1 | D67: 马来 | E67: 办公安防 | F67: 单相电子式电度表 | G67: 59.66 | H67: 89 | K67: 71 | L67: 5906 | M67: =(H67-(I67*50))/50 -> 1.78 | N67: =31*(M67+I67) -> 55.18 | O67: =N67*G67 -> 3292.0388 | P67: =(H67-(I67*90))/90 -> 0.98888889 | Q67: =31*(P67+I67) -> 30.655556 | R67: =(P67+I67)*31*G67*1.5 -> 2743.3657 | S67: =Q67 -> 30.655556 | T67: =S67/31 -> 0.98888889 | U67: =T67-I67 -> 0.98888889 | V67: =R67 -> 2743.3657 | W67: =_xlfn.XLOOKUP(B67,Sheet5!G:G,Sheet5!H:H) -> 1 | X67: =Y67/31 -> 0.98888889 | Y67: =S67*W67 -> 30.655556 | Z67: =Y67*G67*1.5 -> 2743.3657 | AA67: =_xlfn.XLOOKUP(B67,Sheet5!G:G,Sheet5!I:I) -> 0 | AB67: =AC67/31 -> 0 | AC67: =S67*AA67 -> 0 | AD67: =G67*AC67*1.5 -> 0 | AE67: 暂不规划 | AF67: 正常销售 | AG67: =AC67/4 -> 0 | AH67: =$Y67/4 -> 7.6638889
A68: CC0040 | B68: 3C-X400电视壁挂架送膨胀丝等安装螺丝 | C68: 1 | D68: 马来 | E68: 3C数码 | F68: 电视支架 | G68: 18.4521 | H68: 1110 | I68: 16 | J68: 69 | K68: 293 | L68: 5406 | M68: =(H68-(I68*50))/50 -> 6.2 | N68: =31*(M68+I68) -> 688.2 | O68: =N68*G68 -> 12698.735 | P68: =(H68-(I68*90))/90 -> -3.6666667 | Q68: =31*(P68+I68) -> 382.33333 | R68: =(P68+I68)*31*G68*1.5 -> 10582.279 | S68: =Q68 -> 382.33333 | T68: =S68/31 -> 12.333333 | U68: =T68-I68 -> -3.6666667 | V68: =R68 -> 10582.279 | W68: =_xlfn.XLOOKUP(B68,Sheet5!G:G,Sheet5!H:H) -> 0.16289593 | X68: =Y68/31 -> 2.0090498 | Y68: =S68*W68 -> 62.280543 | Z68: =Y68*G68*1.5 -> 1723.8102 | AA68: =_xlfn.XLOOKUP(B68,Sheet5!G:G,Sheet5!I:I) -> 0.83710407 | AB68: =AC68/31 -> 10.324284 | AC68: =S68*AA68 -> 320.05279 | AD68: =G68*AC68*1.5 -> 8858.4691 | AE68: 无超期风险 | AG68: =AC68/4 -> 80.013198 | AH68: =$Y68/4 -> 15.570136
A69: CC0882 | B69: 3B-断桥铝门弯舌锁体2.2*27 | C69: 1 | D69: 马来 | E69: 办公安防 | F69: 锁体 | G69: 32.8534 | H69: 109 | K69: 104 | L69: 5059 | M69: =(H69-(I69*50))/50 -> 2.18 | N69: =31*(M69+I69) -> 67.58 | O69: =N69*G69 -> 2220.2328 | P69: =(H69-(I69*90))/90 -> 1.2111111 | Q69: =31*(P69+I69) -> 37.544444 | R69: =(P69+I69)*31*G69*1.5 -> 1850.194 | S69: =Q69 -> 37.544444 | T69: =S69/31 -> 1.2111111 | U69: =T69-I69 -> 1.2111111 | V69: =R69 -> 1850.194 | W69: =_xlfn.XLOOKUP(B69,Sheet5!G:G,Sheet5!H:H) -> 0 | X69: =Y69/31 -> 0 | Y69: =S69*W69 -> 0 | Z69: =Y69*G69*1.5 -> 0 | AA69: =_xlfn.XLOOKUP(B69,Sheet5!G:G,Sheet5!I:I) -> 1 | AB69: =AC69/31 -> 1.2111111 | AC69: =S69*AA69 -> 37.544444 | AD69: =G69*AC69*1.5 -> 1850.194 | AE69: 配件和锁规划一致 | AG69: =AC69/4 -> 9.3861111 | AH69: =$Y69/4 -> 0
A70: CC0942 | B70: 3B-9260B标签打印机4寸黑色USB蓝牙 | C70: 1 | D70: 马来 | E70: 办公安防 | F70: 打印机 | G70: 161.6481 | H70: 27 | K70: 22 | L70: 5011 | M70: =(H70-(I70*50))/50 -> 0.54 | N70: =31*(M70+I70) -> 16.74 | O70: =N70*G70 -> 2705.9892 | P70: =(H70-(I70*90))/90 -> 0.3 | Q70: =31*(P70+I70) -> 9.3 | R70: =(P70+I70)*31*G70*1.5 -> 2254.991 | S70: =Q70 -> 9.3 | T70: =S70/31 -> 0.3 | U70: =T70-I70 -> 0.3 | V70: =R70 -> 2254.991 | W70: 0.5 | X70: =Y70/31 -> 0.15 | Y70: =S70*W70 -> 4.65 | Z70: =Y70*G70*1.5 -> 1127.4955 | AA70: 0.5 | AB70: =AC70/31 -> 0.15 | AC70: =S70*AA70 -> 4.65 | AD70: =G70*AC70*1.5 -> 1127.4955 | AE70: 新品： 寄样4 心怡+伟民 | AG70: =AC70/4 -> 1.1625 | AH70: =$Y70/4 -> 1.1625
A71: CC0967 | B71: 3B-大号仿真书银钱盒钥匙款黑色 | C71: 1 | D71: 马来 | E71: 办公安防 | F71: 银钱盒 | G71: 23.3068 | H71: 148 | K71: 142 | L71: 4906 | M71: =(H71-(I71*50))/50 -> 2.96 | N71: =31*(M71+I71) -> 91.76 | O71: =N71*G71 -> 2138.632 | P71: =(H71-(I71*90))/90 -> 1.6444444 | Q71: =31*(P71+I71) -> 50.977778 | R71: =(P71+I71)*31*G71*1.5 -> 1782.1933 | S71: =Q71 -> 50.977778 | T71: =S71/31 -> 1.6444444 | U71: =T71-I71 -> 1.6444444 | V71: =R71 -> 1782.1933 | W71: =_xlfn.XLOOKUP(B71,Sheet5!G:G,Sheet5!H:H) -> 0 | X71: =Y71/31 -> 0 | Y71: =S71*W71 -> 0 | Z71: =Y71*G71*1.5 -> 0 | AA71: =_xlfn.XLOOKUP(B71,Sheet5!G:G,Sheet5!I:I) -> 1 | AB71: =AC71/31 -> 1.6444444 | AC71: =S71*AA71 -> 50.977778 | AD71: =G71*AC71*1.5 -> 1782.1933 | AE71: 重点： 阶段降解消耗，周转控制在60 人员：心怡 | AF71: 小店重点价格扶持起量 孝鑫+鹭燕 | AG71: =AC71/4 -> 12.744444 | AH71: =$Y71/4 -> 0
A72: CC1067 | B72: 3B-导轨单相计量电能表1P机械计量款 | C72: 1 | D72: 马来 | E72: 办公安防 | F72: 单相电子式电度表 | G72: 33.12 | H72: 99 | K72: 98 | L72: 4852 | M72: =(H72-(I72*50))/50 -> 1.98 | N72: =31*(M72+I72) -> 61.38 | O72: =N72*G72 -> 2032.9056 | P72: =(H72-(I72*90))/90 -> 1.1 | Q72: =31*(P72+I72) -> 34.1 | R72: =(P72+I72)*31*G72*1.5 -> 1694.088 | S72: =Q72 -> 34.1 | T72: =S72/31 -> 1.1 | U72: =T72-I72 -> 1.1 | V72: =R72 -> 1694.088 | W72: =_xlfn.XLOOKUP(B72,Sheet5!G:G,Sheet5!H:H) -> 1 | X72: =Y72/31 -> 1.1 | Y72: =S72*W72 -> 34.1 | Z72: =Y72*G72*1.5 -> 1694.088 | AA72: =_xlfn.XLOOKUP(B72,Sheet5!G:G,Sheet5!I:I) -> 0 | AB72: =AC72/31 -> 0 | AC72: =S72*AA72 -> 0 | AD72: =G72*AC72*1.5 -> 0 | AE72: 暂不规划 | AF72: 竞品价格过低，为成本价 当做链接引流款每天限量3个 人员：培庆 | AG72: =AC72/4 -> 0 | AH72: =$Y72/4 -> 8.525
A73: CC0338 | B73: 3B-大号仿真书银钱盒密码款蓝色 | C73: 1 | D73: 马来 | E73: 办公安防 | F73: 银钱盒 | G73: 24.6968 | H73: 533 | I73: 6 | J73: 88 | K73: 185 | L73: 4569 | M73: =(H73-(I73*50))/50 -> 4.66 | N73: =31*(M73+I73) -> 330.46 | O73: =N73*G73 -> 8161.3045 | P73: =(H73-(I73*90))/90 -> -0.077777778 | Q73: =31*(P73+I73) -> 183.58889 | R73: =(P73+I73)*31*G73*1.5 -> 6801.0871 | S73: =Q73 -> 183.58889 | T73: =S73/31 -> 5.9222222 | U73: =T73-I73 -> -0.077777778 | V73: =R73 -> 6801.0871 | W73: =_xlfn.XLOOKUP(B73,Sheet5!G:G,Sheet5!H:H) -> 0.14736842 | X73: =Y73/31 -> 0.87274854 | Y73: =S73*W73 -> 27.055205 | Z73: =Y73*G73*1.5 -> 1002.2655 | AA73: =_xlfn.XLOOKUP(B73,Sheet5!G:G,Sheet5!I:I) -> 0.85263158 | AB73: =AC73/31 -> 5.0494737 | AC73: =S73*AA73 -> 156.53368 | AD73: =G73*AC73*1.5 -> 5798.8216 | AE73: 重点： 阶段降解消耗，周转控制在60 人员：心怡 | AF73: 小店重点价格扶持起量 孝鑫+鹭燕 | AG73: =AC73/4 -> 39.133421 | AH73: =$Y73/4 -> 6.7638012
A74: CC1081 | B74: 3C-无线四模头戴耳机黑白色K80 | C74: 1 | D74: 马来 | E74: 3C数码 | F74: 耳机 | G74: 98.31 | H74: 37 | K74: 32 | L74: 4522 | M74: =(H74-(I74*50))/50 -> 0.74 | N74: =31*(M74+I74) -> 22.94 | O74: =N74*G74 -> 2255.2314 | P74: =(H74-(I74*90))/90 -> 0.41111111 | Q74: =31*(P74+I74) -> 12.744444 | R74: =(P74+I74)*31*G74*1.5 -> 1879.3595 | S74: =Q74 -> 12.744444 | T74: =S74/31 -> 0.41111111 | U74: =T74-I74 -> 0.41111111 | V74: =R74 -> 1879.3595 | W74: =_xlfn.XLOOKUP(B74,Sheet5!G:G,Sheet5!H:H) -> 0 | X74: =Y74/31 -> 0 | Y74: =S74*W74 -> 0 | Z74: =Y74*G74*1.5 -> 0 | AA74: =_xlfn.XLOOKUP(B74,Sheet5!G:G,Sheet5!I:I) -> 1 | AB74: =AC74/31 -> 0.41111111 | AC74: =S74*AA74 -> 12.744444 | AD74: =G74*AC74*1.5 -> 1879.3595 | AE74: 新品：寄样5 伟民+罗城 | AG74: =AC74/4 -> 3.1861111 | AH74: =$Y74/4 -> 0
A75: CC1068 | B75: 3B-导轨单相多功能电能表1P液晶计量款 | C75: 1 | D75: 马来 | E75: 办公安防 | F75: 单相电子式电度表 | G75: 28.7 | H75: 100 | K75: 100 | L75: 4305 | M75: =(H75-(I75*50))/50 -> 2 | N75: =31*(M75+I75) -> 62 | O75: =N75*G75 -> 1779.4 | P75: =(H75-(I75*90))/90 -> 1.1111111 | Q75: =31*(P75+I75) -> 34.444444 | R75: =(P75+I75)*31*G75*1.5 -> 1482.8333 | S75: =Q75 -> 34.444444 | T75: =S75/31 -> 1.1111111 | U75: =T75-I75 -> 1.1111111 | V75: =R75 -> 1482.8333 | W75: =_xlfn.XLOOKUP(B75,Sheet5!G:G,Sheet5!H:H) -> 0 | X75: =Y75/31 -> 0 | Y75: =S75*W75 -> 0 | Z75: =Y75*G75*1.5 -> 0 | AA75: =_xlfn.XLOOKUP(B75,Sheet5!G:G,Sheet5!I:I) -> 0 | AB75: =AC75/31 -> 0 | AC75: =S75*AA75 -> 0 | AD75: =G75*AC75*1.5 -> 0 | AE75: 暂不规划 | AF75: 竞品价格过低，为成本价 当做链接引流款每天限量3个 人员：培庆 | AG75: =AC75/4 -> 0 | AH75: =$Y75/4 -> 0
A76: CC0865 | B76: 3C-黑色吉他包装升级款 | C76: 1 | D76: 马来 | E76: 3C数码 | F76: 吉他套装 | G76: 90.64 | H76: 100 | I76: 1 | J76: 100 | K76: 45 | L76: 4124 | M76: =(H76-(I76*50))/50 -> 1 | N76: =31*(M76+I76) -> 62 | O76: =N76*G76 -> 5619.68 | P76: =(H76-(I76*90))/90 -> 0.11111111 | Q76: =31*(P76+I76) -> 34.444444 | R76: =(P76+I76)*31*G76*1.5 -> 4683.0667 | S76: =Q76 -> 34.444444 | T76: =S76/31 -> 1.1111111 | U76: =T76-I76 -> 0.11111111 | V76: =R76 -> 4683.0667 | W76: =_xlfn.XLOOKUP(B76,Sheet5!G:G,Sheet5!H:H) -> 0.375 | X76: =Y76/31 -> 0.41666667 | Y76: =S76*W76 -> 12.916667 | Z76: =Y76*G76*1.5 -> 1756.15 | AA76: =_xlfn.XLOOKUP(B76,Sheet5!G:G,Sheet5!I:I) -> 0.625 | AB76: =AC76/31 -> 0.69444444 | AC76: =S76*AA76 -> 21.527778 | AD76: =G76*AC76*1.5 -> 2926.9167 | AG76: =AC76/4 -> 5.3819444 | AH76: =$Y76/4 -> 3.2291667
A77: CC0297 | B77: 3C-翻页笔 | C77: 1 | D77: 马来 | E77: 3C数码 | F77: 翻页笔 | G77: 19.49 | H77: 283 | I77: 2 | J77: 141 | K77: 168 | L77: 4015 | M77: =(H77-(I77*50))/50 -> 3.66 | N77: =31*(M77+I77) -> 175.46 | O77: =N77*G77 -> 3419.7154 | P77: =(H77-(I77*90))/90 -> 1.1444444 | Q77: =31*(P77+I77) -> 97.477778 | R77: =(P77+I77)*31*G77*1.5 -> 2849.7628 | S77: =Q77 -> 97.477778 | T77: =S77/31 -> 3.1444444 | U77: =T77-I77 -> 1.1444444 | V77: =R77 -> 2849.7628 | W77: =_xlfn.XLOOKUP(B77,Sheet5!G:G,Sheet5!H:H) -> 0.625 | X77: =Y77/31 -> 1.9652778 | Y77: =S77*W77 -> 60.923611 | Z77: =Y77*G77*1.5 -> 1781.1018 | AA77: =_xlfn.XLOOKUP(B77,Sheet5!G:G,Sheet5!I:I) -> 0.375 | AB77: =AC77/31 -> 1.1791667 | AC77: =S77*AA77 -> 36.554167 | AD77: =G77*AC77*1.5 -> 1068.6611 | AG77: =AC77/4 -> 9.1385417 | AH77: =$Y77/4 -> 15.230903
A78: CC0868 | B78: 3C-原木色吉他套装包装升级款 | C78: 1 | D78: 马来 | E78: 3C数码 | F78: 吉他套装 | G78: 99.9308 | H78: 237 | I78: 3 | J78: 79 | K78: 40 | L78: 3997 | M78: =(H78-(I78*50))/50 -> 1.74 | N78: =31*(M78+I78) -> 146.94 | O78: =N78*G78 -> 14683.832 | P78: =(H78-(I78*90))/90 -> -0.36666667 | Q78: =31*(P78+I78) -> 81.633333 | R78: =(P78+I78)*31*G78*1.5 -> 12236.526 | S78: =Q78 -> 81.633333 | T78: =S78/31 -> 2.6333333 | U78: =T78-I78 -> -0.36666667 | V78: =R78 -> 12236.526 | W78: =_xlfn.XLOOKUP(B78,Sheet5!G:G,Sheet5!H:H) -> 0.31818182 | X78: =Y78/31 -> 0.83787879 | Y78: =S78*W78 -> 25.974242 | Z78: =Y78*G78*1.5 -> 3893.4402 | AA78: =_xlfn.XLOOKUP(B78,Sheet5!G:G,Sheet5!I:I) -> 0.68181818 | AB78: =AC78/31 -> 1.7954545 | AC78: =S78*AA78 -> 55.659091 | AD78: =G78*AC78*1.5 -> 8343.0862 | AE78: 无超期风险 | AG78: =AC78/4 -> 13.914773 | AH78: =$Y78/4 -> 6.4935606
A79: CC0857 | B79: 3B-广告架kt板直面3.7kg | C79: 1 | D79: 马来 | E79: 办公安防 | F79: 广告架 | G79: 46.18 | H79: 59 | K79: 58 | L79: 3995 | M79: =(H79-(I79*50))/50 -> 1.18 | N79: =31*(M79+I79) -> 36.58 | O79: =N79*G79 -> 1689.2644 | P79: =(H79-(I79*90))/90 -> 0.65555556 | Q79: =31*(P79+I79) -> 20.322222 | R79: =(P79+I79)*31*G79*1.5 -> 1407.7203 | S79: =Q79 -> 20.322222 | T79: =S79/31 -> 0.65555556 | U79: =T79-I79 -> 0.65555556 | V79: =R79 -> 1407.7203 | W79: =_xlfn.XLOOKUP(B79,Sheet5!G:G,Sheet5!H:H) -> 1 | X79: =Y79/31 -> 0.65555556 | Y79: =S79*W79 -> 20.322222 | Z79: =Y79*G79*1.5 -> 1407.7203 | AA79: =_xlfn.XLOOKUP(B79,Sheet5!G:G,Sheet5!I:I) -> 0 | AB79: =AC79/31 -> 0 | AC79: =S79*AA79 -> 0 | AD79: =G79*AC79*1.5 -> 0 | AE79: 暂不规划 | AF79: 正常出清，当前标价28% | AG79: =AC79/4 -> 0 | AH79: =$Y79/4 -> 5.0805556
A80: CC0994 | B80: 3C-RGB电容悬臂支架降噪麦克风 | C80: 1 | D80: 马来 | E80: 3C数码 | F80: 有线麦克风 | G80: 110.29 | H80: 34 | K80: 26 | L80: 3915 | M80: =(H80-(I80*50))/50 -> 0.68 | N80: =31*(M80+I80) -> 21.08 | O80: =N80*G80 -> 2324.9132 | P80: =(H80-(I80*90))/90 -> 0.37777778 | Q80: =31*(P80+I80) -> 11.711111 | R80: =(P80+I80)*31*G80*1.5 -> 1937.4277 | S80: =Q80 -> 11.711111 | T80: =S80/31 -> 0.37777778 | U80: =T80-I80 -> 0.37777778 | V80: =R80 -> 1937.4277 | W80: =_xlfn.XLOOKUP(B80,Sheet5!G:G,Sheet5!H:H) -> 0 | X80: =Y80/31 -> 0 | Y80: =S80*W80 -> 0 | Z80: =Y80*G80*1.5 -> 0 | AA80: =_xlfn.XLOOKUP(B80,Sheet5!G:G,Sheet5!I:I) -> 1 | AB80: =AC80/31 -> 0.37777778 | AC80: =S80*AA80 -> 11.711111 | AD80: =G80*AC80*1.5 -> 1937.4277 | AE80: 新品：麦系列TK为主达人推广 寄样3 人员：郑雨倩+罗城+伟铭 | AG80: =AC80/4 -> 2.9277778 | AH80: =$Y80/4 -> 0
A81: CC0823 | B81: 3B-指纹挂锁 | C81: 1 | D81: 马来 | E81: 办公安防 | F81: 智能锁 | G81: 37.334 | H81: 150 | I81: 1 | J81: 150 | K81: 84 | L81: 3715 | M81: =(H81-(I81*50))/50 -> 2 | N81: =31*(M81+I81) -> 93 | O81: =N81*G81 -> 3472.062 | P81: =(H81-(I81*90))/90 -> 0.66666667 | Q81: =31*(P81+I81) -> 51.666667 | R81: =(P81+I81)*31*G81*1.5 -> 2893.385 | S81: =Q81 -> 51.666667 | T81: =S81/31 -> 1.6666667 | U81: =T81-I81 -> 0.66666667 | V81: =R81 -> 2893.385 | W81: =_xlfn.XLOOKUP(B81,Sheet5!G:G,Sheet5!H:H) -> 0.61904762 | X81: =Y81/31 -> 1.031746 | Y81: =S81*W81 -> 31.984127 | Z81: =Y81*G81*1.5 -> 1791.1431 | AA81: =_xlfn.XLOOKUP(B81,Sheet5!G:G,Sheet5!I:I) -> 0.38095238 | AB81: =AC81/31 -> 0.63492063 | AC81: =S81*AA81 -> 19.68254 | AD81: =G81*AC81*1.5 -> 1102.2419 | AG81: =AC81/4 -> 4.9206349 | AH81: =$Y81/4 -> 7.9960317
A82: CC0976 | B82: 3B-捆钞机8011A型 | C82: 1 | D82: 马来 | E82: 办公安防 | F82: 捆钞机 | G82: 352.5688 | H82: 11 | K82: 8 | L82: 3702 | M82: =(H82-(I82*50))/50 -> 0.22 | N82: =31*(M82+I82) -> 6.82 | O82: =N82*G82 -> 2404.5192 | P82: =(H82-(I82*90))/90 -> 0.12222222 | Q82: =31*(P82+I82) -> 3.7888889 | R82: =(P82+I82)*31*G82*1.5 -> 2003.766 | S82: =Q82 -> 3.7888889 | T82: =S82/31 -> 0.12222222 | U82: =T82-I82 -> 0.12222222 | V82: =R82 -> 2003.766 | W82: =_xlfn.XLOOKUP(B82,Sheet5!G:G,Sheet5!H:H) -> 1 | X82: =Y82/31 -> 0.12222222 | Y82: =S82*W82 -> 3.7888889 | Z82: =Y82*G82*1.5 -> 2003.766 | AA82: =_xlfn.XLOOKUP(B82,Sheet5!G:G,Sheet5!I:I) -> 0 | AB82: =AC82/31 -> 0 | AC82: =S82*AA82 -> 0 | AD82: =G82*AC82*1.5 -> 0 | AE82: 寄样2 | AG82: =AC82/4 -> 0 | AH82: =$Y82/4 -> 0.94722222
A83: CC1064 | B83: 3B-WIFI漏电多功能导轨表彩屏款2P100A | C83: 1 | D83: 马来 | E83: 办公安防 | F83: 单相电子式电度表 | G83: 91.27 | H83: 33 | K83: 28 | L83: 3651 | M83: =(H83-(I83*50))/50 -> 0.66 | N83: =31*(M83+I83) -> 20.46 | O83: =N83*G83 -> 1867.3842 | P83: =(H83-(I83*90))/90 -> 0.36666667 | Q83: =31*(P83+I83) -> 11.366667 | R83: =(P83+I83)*31*G83*1.5 -> 1556.1535 | S83: =Q83 -> 11.366667 | T83: =S83/31 -> 0.36666667 | U83: =T83-I83 -> 0.36666667 | V83: =R83 -> 1556.1535 | W83: =_xlfn.XLOOKUP(B83,Sheet5!G:G,Sheet5!H:H) -> 1 | X83: =Y83/31 -> 0.36666667 | Y83: =S83*W83 -> 11.366667 | Z83: =Y83*G83*1.5 -> 1556.1535 | AA83: =_xlfn.XLOOKUP(B83,Sheet5!G:G,Sheet5!I:I) -> 0 | AB83: =AC83/31 -> 0 | AC83: =S83*AA83 -> 0 | AD83: =G83*AC83*1.5 -> 0 | AE83: 暂不规划 | AF83: 正常销售 | AG83: =AC83/4 -> 0 | AH83: =$Y83/4 -> 2.8416667
A84: CC0866 | B84: 3C-原木色民谣吉他包装升级款 | C84: 1 | D84: 马来 | E84: 3C数码 | F84: 吉他套装 | G84: 99.4908 | H84: 92 | I84: 1 | J84: 92 | K84: 36 | L84: 3582 | M84: =(H84-(I84*50))/50 -> 0.84 | N84: =31*(M84+I84) -> 57.04 | O84: =N84*G84 -> 5674.9552 | P84: =(H84-(I84*90))/90 -> 0.022222222 | Q84: =31*(P84+I84) -> 31.688889 | R84: =(P84+I84)*31*G84*1.5 -> 4729.1294 | S84: =Q84 -> 31.688889 | T84: =S84/31 -> 1.0222222 | U84: =T84-I84 -> 0.022222222 | V84: =R84 -> 4729.1294 | W84: =_xlfn.XLOOKUP(B84,Sheet5!G:G,Sheet5!H:H) -> 0.090909091 | X84: =Y84/31 -> 0.092929293 | Y84: =S84*W84 -> 2.8808081 | Z84: =Y84*G84*1.5 -> 429.92085 | AA84: =_xlfn.XLOOKUP(B84,Sheet5!G:G,Sheet5!I:I) -> 0.90909091 | AB84: =AC84/31 -> 0.92929293 | AC84: =S84*AA84 -> 28.808081 | AD84: =G84*AC84*1.5 -> 4299.2085 | AG84: =AC84/4 -> 7.2020202 | AH84: =$Y84/4 -> 0.72020202
A85: CC0983 | B85: 3B-A3简易过胶机 | C85: 1 | D85: 马来 | E85: 办公安防 | F85: 过胶机 | G85: 70.61 | H85: 35 | K85: 34 | L85: 3566 | M85: =(H85-(I85*50))/50 -> 0.7 | N85: =31*(M85+I85) -> 21.7 | O85: =N85*G85 -> 1532.237 | P85: =(H85-(I85*90))/90 -> 0.38888889 | Q85: =31*(P85+I85) -> 12.055556 | R85: =(P85+I85)*31*G85*1.5 -> 1276.8642 | S85: =Q85 -> 12.055556 | T85: =S85/31 -> 0.38888889 | U85: =T85-I85 -> 0.38888889 | V85: =R85 -> 1276.8642 | W85: =_xlfn.XLOOKUP(B85,Sheet5!G:G,Sheet5!H:H) -> 0 | X85: =Y85/31 -> 0 | Y85: =S85*W85 -> 0 | Z85: =Y85*G85*1.5 -> 0 | AA85: =_xlfn.XLOOKUP(B85,Sheet5!G:G,Sheet5!I:I) -> 1 | AB85: =AC85/31 -> 0.38888889 | AC85: =S85*AA85 -> 12.055556 | AD85: =G85*AC85*1.5 -> 1276.8642 | AG85: =AC85/4 -> 3.0138889 | AH85: =$Y85/4 -> 0
A86: CC0298 | B86: 3C-平板旋转支架 | C86: 1 | D86: 马来 | E86: 3C数码 | F86: 电脑支架 | G86: 16.07 | H86: 221 | I86: 1 | J86: 221 | K86: 161 | L86: 3495 | M86: =(H86-(I86*50))/50 -> 3.42 | N86: =31*(M86+I86) -> 137.02 | O86: =N86*G86 -> 2201.9114 | P86: =(H86-(I86*90))/90 -> 1.4555556 | Q86: =31*(P86+I86) -> 76.122222 | R86: =(P86+I86)*31*G86*1.5 -> 1834.9262 | S86: =Q86 -> 76.122222 | T86: =S86/31 -> 2.4555556 | U86: =T86-I86 -> 1.4555556 | V86: =R86 -> 1834.9262 | W86: =_xlfn.XLOOKUP(B86,Sheet5!G:G,Sheet5!H:H) -> 0.38888889 | X86: =Y86/31 -> 0.95493827 | Y86: =S86*W86 -> 29.603086 | Z86: =Y86*G86*1.5 -> 713.5824 | AA86: =_xlfn.XLOOKUP(B86,Sheet5!G:G,Sheet5!I:I) -> 0.61111111 | AB86: =AC86/31 -> 1.5006173 | AC86: =S86*AA86 -> 46.519136 | AD86: =G86*AC86*1.5 -> 1121.3438 | AE86: 呆滞品：便携显示器赠送 | AG86: =AC86/4 -> 11.629784 | AH86: =$Y86/4 -> 7.4007716
A87: CC0138 | B87: 3C-投影仪支架 | C87: 1 | D87: 马来 | E87: 3C数码 | F87: 投影仪支架-2 | G87: 40.43 | H87: 288 | I87: 4 | J87: 72 | K87: 85 | L87: 3437 | M87: =(H87-(I87*50))/50 -> 1.76 | N87: =31*(M87+I87) -> 178.56 | O87: =N87*G87 -> 7219.1808 | P87: =(H87-(I87*90))/90 -> -0.8 | Q87: =31*(P87+I87) -> 99.2 | R87: =(P87+I87)*31*G87*1.5 -> 6015.984 | S87: =Q87 -> 99.2 | T87: =S87/31 -> 3.2 | U87: =T87-I87 -> -0.8 | V87: =R87 -> 6015.984 | W87: =_xlfn.XLOOKUP(B87,Sheet5!G:G,Sheet5!H:H) -> 0.7 | X87: =Y87/31 -> 2.24 | Y87: =S87*W87 -> 69.44 | Z87: =Y87*G87*1.5 -> 4211.1888 | AA87: =_xlfn.XLOOKUP(B87,Sheet5!G:G,Sheet5!I:I) -> 0.3 | AB87: =AC87/31 -> 0.96 | AC87: =S87*AA87 -> 29.76 | AD87: =G87*AC87*1.5 -> 1804.7952 | AE87: 无超期风险 | AG87: =AC87/4 -> 7.44 | AH87: =$Y87/4 -> 17.36
A88: CC0072 | B88: 3C-数码相机银色6400万像素 | C88: 1 | D88: 马来 | E88: 3C数码 | F88: 数码相机 | G88: 102.36 | H88: 47 | K88: 27 | L88: 3327 | M88: =(H88-(I88*50))/50 -> 0.94 | N88: =31*(M88+I88) -> 29.14 | O88: =N88*G88 -> 2982.7704 | P88: =(H88-(I88*90))/90 -> 0.52222222 | Q88: =31*(P88+I88) -> 16.188889 | R88: =(P88+I88)*31*G88*1.5 -> 2485.642 | S88: =Q88 -> 16.188889 | T88: =S88/31 -> 0.52222222 | U88: =T88-I88 -> 0.52222222 | V88: =R88 -> 2485.642 | W88: =_xlfn.XLOOKUP(B88,Sheet5!G:G,Sheet5!H:H) -> 0.71428571 | X88: =Y88/31 -> 0.37301587 | Y88: =S88*W88 -> 11.563492 | Z88: =Y88*G88*1.5 -> 1775.4586 | AA88: =_xlfn.XLOOKUP(B88,Sheet5!G:G,Sheet5!I:I) -> 0.28571429 | AB88: =AC88/31 -> 0.14920635 | AC88: =S88*AA88 -> 4.6253968 | AD88: =G88*AC88*1.5 -> 710.18343 | AE88: 呆滞品：消耗5个 | AG88: =AC88/4 -> 1.1563492 | AH88: =$Y88/4 -> 2.890873
A89: CC0727 | B89: 3C-led智能互动屏59.5cm*12cm | C89: 1 | D89: 马来 | E89: 3C数码 | F89: LED像素屏 | G89: 157.1 | H89: 56 | K89: 21 | L89: 3299 | M89: =(H89-(I89*50))/50 -> 1.12 | N89: =31*(M89+I89) -> 34.72 | O89: =N89*G89 -> 5454.512 | P89: =(H89-(I89*90))/90 -> 0.62222222 | Q89: =31*(P89+I89) -> 19.288889 | R89: =(P89+I89)*31*G89*1.5 -> 4545.4267 | S89: =Q89 -> 19.288889 | T89: =S89/31 -> 0.62222222 | U89: =T89-I89 -> 0.62222222 | V89: =R89 -> 4545.4267 | W89: =_xlfn.XLOOKUP(B89,Sheet5!G:G,Sheet5!H:H) -> 0.4 | X89: =Y89/31 -> 0.24888889 | Y89: =S89*W89 -> 7.7155556 | Z89: =Y89*G89*1.5 -> 1818.1707 | AA89: =_xlfn.XLOOKUP(B89,Sheet5!G:G,Sheet5!I:I) -> 0.6 | AB89: =AC89/31 -> 0.37333333 | AC89: =S89*AA89 -> 11.573333 | AD89: =G89*AC89*1.5 -> 2727.256 | AE89: 呆滞品：成本价消耗 | AG89: =AC89/4 -> 2.8933333 | AH89: =$Y89/4 -> 1.9288889
A90: CC0770 | B90: 3B-可翻转白板70*100 | C90: 1 | D90: 马来 | E90: 办公安防 | F90: 教具白板 | G90: 115.7374 | H90: 51 | K90: 25 | L90: 3125 | M90: =(H90-(I90*50))/50 -> 1.02 | N90: =31*(M90+I90) -> 31.62 | O90: =N90*G90 -> 3659.6166 | P90: =(H90-(I90*90))/90 -> 0.56666667 | Q90: =31*(P90+I90) -> 17.566667 | R90: =(P90+I90)*31*G90*1.5 -> 3049.6805 | S90: =Q90 -> 17.566667 | T90: =S90/31 -> 0.56666667 | U90: =T90-I90 -> 0.56666667 | V90: =R90 -> 3049.6805 | W90: =_xlfn.XLOOKUP(B90,Sheet5!G:G,Sheet5!H:H) -> 1 | X90: =Y90/31 -> 0.56666667 | Y90: =S90*W90 -> 17.566667 | Z90: =Y90*G90*1.5 -> 3049.6805 | AA90: =_xlfn.XLOOKUP(B90,Sheet5!G:G,Sheet5!I:I) -> 0 | AB90: =AC90/31 -> 0 | AC90: =S90*AA90 -> 0 | AD90: =G90*AC90*1.5 -> 0 | AE90: 无超期风险 | AG90: =AC90/4 -> 0 | AH90: =$Y90/4 -> 4.3916667
A91: CC0737 | B91: 3B-多功能简易支架14.5cm*19cm | C91: 1 | D91: 马来 | E91: 办公安防 | F91: 简易支架 | G91: 7.4719 | H91: 289 | K91: 279 | L91: 3097 | M91: =(H91-(I91*50))/50 -> 5.78 | N91: =31*(M91+I91) -> 179.18 | O91: =N91*G91 -> 1338.815 | P91: =(H91-(I91*90))/90 -> 3.2111111 | Q91: =31*(P91+I91) -> 99.544444 | R91: =(P91+I91)*31*G91*1.5 -> 1115.6792 | S91: =Q91 -> 99.544444 | T91: =S91/31 -> 3.2111111 | U91: =T91-I91 -> 3.2111111 | V91: =R91 -> 1115.6792 | W91: =_xlfn.XLOOKUP(B91,Sheet5!G:G,Sheet5!H:H) -> 0 | X91: =Y91/31 -> 0 | Y91: =S91*W91 -> 0 | Z91: =Y91*G91*1.5 -> 0 | AA91: =_xlfn.XLOOKUP(B91,Sheet5!G:G,Sheet5!I:I) -> 1 | AB91: =AC91/31 -> 3.2111111 | AC91: =S91*AA91 -> 99.544444 | AD91: =G91*AC91*1.5 -> 1115.6792 | AE91: 暂不规划 | AF91: 预计小白板到货后重点搭配出清 | AG91: =AC91/4 -> 24.886111 | AH91: =$Y91/4 -> 0
A92: CC0855 | B92: 3B-广告架A4款 | C92: 1 | D92: 马来 | E92: 办公安防 | F92: 广告架 | G92: 42.85 | H92: 47 | K92: 47 | L92: 3021 | M92: =(H92-(I92*50))/50 -> 0.94 | N92: =31*(M92+I92) -> 29.14 | O92: =N92*G92 -> 1248.649 | P92: =(H92-(I92*90))/90 -> 0.52222222 | Q92: =31*(P92+I92) -> 16.188889 | R92: =(P92+I92)*31*G92*1.5 -> 1040.5408 | S92: =Q92 -> 16.188889 | T92: =S92/31 -> 0.52222222 | U92: =T92-I92 -> 0.52222222 | V92: =R92 -> 1040.5408 | W92: =_xlfn.XLOOKUP(B92,Sheet5!G:G,Sheet5!H:H) -> 0 | X92: =Y92/31 -> 0 | Y92: =S92*W92 -> 0 | Z92: =Y92*G92*1.5 -> 0 | AA92: =_xlfn.XLOOKUP(B92,Sheet5!G:G,Sheet5!I:I) -> 0 | AB92: =AC92/31 -> 0 | AC92: =S92*AA92 -> 0 | AD92: =G92*AC92*1.5 -> 0 | AE92: 暂不规划 | AF92: 正常出清，当前标价28% | AG92: =AC92/4 -> 0 | AH92: =$Y92/4 -> 0
A93: CC0972 | B93: 3B-小号仿真书银钱盒钥匙款黄色 | C93: 1 | D93: 马来 | E93: 办公安防 | F93: 银钱盒 | G93: 16.3066 | H93: 148 | K93: 127 | L93: 2968 | M93: =(H93-(I93*50))/50 -> 2.96 | N93: =31*(M93+I93) -> 91.76 | O93: =N93*G93 -> 1496.2936 | P93: =(H93-(I93*90))/90 -> 1.6444444 | Q93: =31*(P93+I93) -> 50.977778 | R93: =(P93+I93)*31*G93*1.5 -> 1246.9113 | S93: =Q93 -> 50.977778 | T93: =S93/31 -> 1.6444444 | U93: =T93-I93 -> 1.6444444 | V93: =R93 -> 1246.9113 | W93: =_xlfn.XLOOKUP(B93,Sheet5!G:G,Sheet5!H:H) -> 0 | X93: =Y93/31 -> 0 | Y93: =S93*W93 -> 0 | Z93: =Y93*G93*1.5 -> 0 | AA93: =_xlfn.XLOOKUP(B93,Sheet5!G:G,Sheet5!I:I) -> 1 | AB93: =AC93/31 -> 1.6444444 | AC93: =S93*AA93 -> 50.977778 | AD93: =G93*AC93*1.5 -> 1246.9113 | AE93: 重点： 阶段降解消耗，周转控制在60 人员：心怡 | AF93: 小店重点价格扶持起量 孝鑫+鹭燕 | AG93: =AC93/4 -> 12.744444 | AH93: =$Y93/4 -> 0
A94: CC1039 | B94: 3B-毛毡照片公告墙咖啡色60*120CM | C94: 1 | D94: 马来 | E94: 办公安防 | F94: 毛毡照片墙 | G94: 32.3712 | H94: 78 | K94: 63 | L94: 2865 | M94: =(H94-(I94*50))/50 -> 1.56 | N94: =31*(M94+I94) -> 48.36 | O94: =N94*G94 -> 1565.4712 | P94: =(H94-(I94*90))/90 -> 0.86666667 | Q94: =31*(P94+I94) -> 26.866667 | R94: =(P94+I94)*31*G94*1.5 -> 1304.5594 | S94: =Q94 -> 26.866667 | T94: =S94/31 -> 0.86666667 | U94: =T94-I94 -> 0.86666667 | V94: =R94 -> 1304.5594 | W94: 0.6 | X94: =Y94/31 -> 0.52 | Y94: =S94*W94 -> 16.12 | Z94: =Y94*G94*1.5 -> 782.73562 | AA94: 0.4 | AB94: =AC94/31 -> 0.34666667 | AC94: =S94*AA94 -> 10.746667 | AD94: =G94*AC94*1.5 -> 521.82374 | AG94: =AC94/4 -> 2.6866667 | AH94: =$Y94/4 -> 4.03
A95: CC0490 | B95: 3B-不干胶标签打印纸单卷150*100mm | C95: 1 | D95: 马来 | E95: 办公安防 | F95: 标签打印纸 | G95: 22.8026 | H95: 244 | I95: 2 | J95: 122 | K95: 116 | L95: 2793 | M95: =(H95-(I95*50))/50 -> 2.88 | N95: =31*(M95+I95) -> 151.28 | O95: =N95*G95 -> 3449.5773 | P95: =(H95-(I95*90))/90 -> 0.71111111 | Q95: =31*(P95+I95) -> 84.044444 | R95: =(P95+I95)*31*G95*1.5 -> 2874.6478 | S95: =Q95 -> 84.044444 | T95: =S95/31 -> 2.7111111 | U95: =T95-I95 -> 0.71111111 | V95: =R95 -> 2874.6478 | W95: =_xlfn.XLOOKUP(B95,Sheet5!G:G,Sheet5!H:H) -> 0.66666667 | X95: =Y95/31 -> 1.8074074 | Y95: =S95*W95 -> 56.02963 | Z95: =Y95*G95*1.5 -> 1916.4318 | AA95: =_xlfn.XLOOKUP(B95,Sheet5!G:G,Sheet5!I:I) -> 0.33333333 | AB95: =AC95/31 -> 0.9037037 | AC95: =S95*AA95 -> 28.014815 | AD95: =G95*AC95*1.5 -> 958.21592 | AG95: =AC95/4 -> 7.0037037 | AH95: =$Y95/4 -> 14.007407
A96: CC1069 | B96: 3B-导轨单相电能表2P液晶计量款 | C96: 1 | D96: 马来 | E96: 办公安防 | F96: 单相电子式电度表 | G96: 19.02 | H96: 99 | K96: 98 | L96: 2786 | M96: =(H96-(I96*50))/50 -> 1.98 | N96: =31*(M96+I96) -> 61.38 | O96: =N96*G96 -> 1167.4476 | P96: =(H96-(I96*90))/90 -> 1.1 | Q96: =31*(P96+I96) -> 34.1 | R96: =(P96+I96)*31*G96*1.5 -> 972.873 | S96: =Q96 -> 34.1 | T96: =S96/31 -> 1.1 | U96: =T96-I96 -> 1.1 | V96: =R96 -> 972.873 | W96: =_xlfn.XLOOKUP(B96,Sheet5!G:G,Sheet5!H:H) -> 1 | X96: =Y96/31 -> 1.1 | Y96: =S96*W96 -> 34.1 | Z96: =Y96*G96*1.5 -> 972.873 | AA96: =_xlfn.XLOOKUP(B96,Sheet5!G:G,Sheet5!I:I) -> 0 | AB96: =AC96/31 -> 0 | AC96: =S96*AA96 -> 0 | AD96: =G96*AC96*1.5 -> 0 | AE96: 暂不规划 | AF96: 竞品价格过低，为成本价 当做链接引流款每天限量3个 人员：培庆 | AG96: =AC96/4 -> 0 | AH96: =$Y96/4 -> 8.525
A97: CC0701 | B97: 3B-手提款双面广告展示架口字结构 | C97: 1 | D97: 马来 | E97: 办公安防 | F97: 广告支架 | G97: 41.3641 | H97: 285 | I97: 4 | J97: 71 | K97: 64 | L97: 2647 | M97: =(H97-(I97*50))/50 -> 1.7 | N97: =31*(M97+I97) -> 176.7 | O97: =N97*G97 -> 7309.0365 | P97: =(H97-(I97*90))/90 -> -0.83333333 | Q97: =31*(P97+I97) -> 98.166667 | R97: =(P97+I97)*31*G97*1.5 -> 6090.8637 | S97: =Q97 -> 98.166667 | T97: =S97/31 -> 3.1666667 | U97: =T97-I97 -> -0.83333333 | V97: =R97 -> 6090.8637 | W97: =_xlfn.XLOOKUP(B97,Sheet5!G:G,Sheet5!H:H) -> 0.13541667 | X97: =Y97/31 -> 0.42881944 | Y97: =S97*W97 -> 13.293403 | Z97: =Y97*G97*1.5 -> 824.80446 | AA97: =_xlfn.XLOOKUP(B97,Sheet5!G:G,Sheet5!I:I) -> 0.86458333 | AB97: =AC97/31 -> 2.7378472 | AC97: =S97*AA97 -> 84.873264 | AD97: =G97*AC97*1.5 -> 5266.0593 | AE97: 无超期风险 | AG97: =AC97/4 -> 21.218316 | AH97: =$Y97/4 -> 3.3233507
A98: CC0982 | B98: 3B-A4简易过胶机 | C98: 1 | D98: 马来 | E98: 办公安防 | F98: 过胶机 | G98: 57.5 | H98: 32 | K98: 31 | L98: 2645 | M98: =(H98-(I98*50))/50 -> 0.64 | N98: =31*(M98+I98) -> 19.84 | O98: =N98*G98 -> 1140.8 | P98: =(H98-(I98*90))/90 -> 0.35555556 | Q98: =31*(P98+I98) -> 11.022222 | R98: =(P98+I98)*31*G98*1.5 -> 950.66667 | S98: =Q98 -> 11.022222 | T98: =S98/31 -> 0.35555556 | U98: =T98-I98 -> 0.35555556 | V98: =R98 -> 950.66667 | W98: =_xlfn.XLOOKUP(B98,Sheet5!G:G,Sheet5!H:H) -> 0 | X98: =Y98/31 -> 0 | Y98: =S98*W98 -> 0 | Z98: =Y98*G98*1.5 -> 0 | AA98: =_xlfn.XLOOKUP(B98,Sheet5!G:G,Sheet5!I:I) -> 0 | AB98: =AC98/31 -> 0 | AC98: =S98*AA98 -> 0 | AD98: =G98*AC98*1.5 -> 0 | AG98: =AC98/4 -> 0 | AH98: =$Y98/4 -> 0
A99: CC0822 | B99: 3B-H1AP五功能防盗门锁带APP | C99: 1 | D99: 马来 | E99: 办公安防 | F99: 密码锁 | G99: 170.3434 | H99: 23 | K99: 13 | L99: 2640 | M99: =(H99-(I99*50))/50 -> 0.46 | N99: =31*(M99+I99) -> 14.26 | O99: =N99*G99 -> 2429.0969 | P99: =(H99-(I99*90))/90 -> 0.25555556 | Q99: =31*(P99+I99) -> 7.9222222 | R99: =(P99+I99)*31*G99*1.5 -> 2024.2474 | S99: =Q99 -> 7.9222222 | T99: =S99/31 -> 0.25555556 | U99: =T99-I99 -> 0.25555556 | V99: =R99 -> 2024.2474 | W99: =_xlfn.XLOOKUP(B99,Sheet5!G:G,Sheet5!H:H) -> 0.5 | X99: =Y99/31 -> 0.12777778 | Y99: =S99*W99 -> 3.9611111 | Z99: =Y99*G99*1.5 -> 1012.1237 | AA99: =_xlfn.XLOOKUP(B99,Sheet5!G:G,Sheet5!I:I) -> 0.5 | AB99: =AC99/31 -> 0.12777778 | AC99: =S99*AA99 -> 3.9611111 | AD99: =G99*AC99*1.5 -> 1012.1237 | AG99: =AC99/4 -> 0.99027778 | AH99: =$Y99/4 -> 0.99027778
A100: CC0850 | B100: 3C-RGB蓝牙无线拉伸手机游戏手柄STK7009 | C100: 1 | D100: 马来 | E100: 3C数码 | F100: 游戏手柄 | G100: 94.09 | H100: 101 | I100: 1 | J100: 101 | K100: 28 | L100: 2635 | M100: =(H100-(I100*50))/50 -> 1.02 | N100: =31*(M100+I100) -> 62.62 | O100: =N100*G100 -> 5891.9158 | P100: =(H100-(I100*90))/90 -> 0.12222222 | Q100: =31*(P100+I100) -> 34.788889 | R100: =(P100+I100)*31*G100*1.5 -> 4909.9298 | S100: =Q100 -> 34.788889 | T100: =S100/31 -> 1.1222222 | U100: =T100-I100 -> 0.12222222 | V100: =R100 -> 4909.9298 | W100: =_xlfn.XLOOKUP(B100,Sheet5!G:G,Sheet5!H:H) -> 0.066666667 | X100: =Y100/31 -> 0.074814815 | Y100: =S100*W100 -> 2.3192593 | Z100: =Y100*G100*1.5 -> 327.32866 | AA100: =_xlfn.XLOOKUP(B100,Sheet5!G:G,Sheet5!I:I) -> 0.93333333 | AB100: =AC100/31 -> 1.0474074 | AC100: =S100*AA100 -> 32.46963 | AD100: =G100*AC100*1.5 -> 4582.6012 | AE100: 无超期风险 | AG100: =AC100/4 -> 8.1174074 | AH100: =$Y100/4 -> 0.57981481
A101: CC0881 | B101: 3B-断桥铝门方舌锁体2.2*24 | C101: 1 | D101: 马来 | E101: 办公安防 | F101: 锁体 | G101: 28.1342 | H101: 81 | K101: 66 | L101: 2616 | M101: =(H101-(I101*50))/50 -> 1.62 | N101: =31*(M101+I101) -> 50.22 | O101: =N101*G101 -> 1412.8995 | P101: =(H101-(I101*90))/90 -> 0.9 | Q101: =31*(P101+I101) -> 27.9 | R101: =(P101+I101)*31*G101*1.5 -> 1177.4163 | S101: =Q101 -> 27.9 | T101: =S101/31 -> 0.9 | U101: =T101-I101 -> 0.9 | V101: =R101 -> 1177.4163 | W101: =_xlfn.XLOOKUP(B101,Sheet5!G:G,Sheet5!H:H) -> 1 | X101: =Y101/31 -> 0.9 | Y101: =S101*W101 -> 27.9 | Z101: =Y101*G101*1.5 -> 1177.4163 | AA101: =_xlfn.XLOOKUP(B101,Sheet5!G:G,Sheet5!I:I) -> 0 | AB101: =AC101/31 -> 0 | AC101: =S101*AA101 -> 0 | AD101: =G101*AC101*1.5 -> 0 | AG101: =AC101/4 -> 0 | AH101: =$Y101/4 -> 6.975
...

Sheet 5月分配 
R1: 90天-4月需销售量 | V1: SP | Z1: TK
A3: 主SKU | B3: 商品名称 | C3: 国家 | D3: 品类 | E3: 三级分类 | F3: 销售成本 | G3: 当前库存 | H3: 日销量 | I3: 周转天数 | J3: 月预估超期库存 | K3: 月预估超期金额 | L3: 日销差距（50天） | M3: 预计出清数量（50天） | N3: 出清金额（3月） | O3: 日销差距（90天） | P3: 预计出清数量（90天） | Q3: 出清金额(3月） | R3: 总数量 | S3: 目标日销 | T3: 日销差异 | U3: 总出清金额 | V3: 业绩占比 | W3: 目标日销 | X3: 总销量 | Y3: 出清额 | Z3: 业绩占比 | AA3: 目标日销 | AB3: 总销量 | AC3: 出清额度 | AD3: 策略方向
A4: CC0904 | B4: 3C-无弦吉他 | C4: 马来 | D4: 3C数码 | E4: 未来吉他 | F4: 712.84 | G4: 191 | H4: 1 | I4: 191 | J4: 111 | K4: 95877 | L4: =(G4-(H4*50))/50 -> 2.82 | M4: =31*(L4+H4) -> 118.42 | N4: =M4*F4 -> 84414.513 | O4: =(G4-(H4*90))/90 -> 1.1222222 | P4: =31*(O4+H4) -> 65.788889 | Q4: =(O4+H4)*31*F4*1.5 -> 70345.427 | R4: =P4 -> 65.788889 | S4: =R4/31 -> 2.1222222 | T4: =S4-H4 -> 1.1222222 | U4: =Q4 -> 70345.427 | V4: =_xlfn.XLOOKUP(B4,[1]Sheet1!$B:$B,[1]Sheet1!$P:$P) -> 0.11764706 | W4: =X4/31 -> 0.2496732 | X4: =R4*V4 -> 7.7398693 | Y4: =X4*F4*1.5 -> 8275.9326 | Z4: =_xlfn.XLOOKUP(B4,[1]Sheet1!$B:$B,[1]Sheet1!$Q:$Q) -> 0.88235294 | AA4: =AB4/31 -> 1.872549 | AB4: =R4*Z4 -> 58.04902 | AC4: =F4*AB4*1.5 -> 62069.495 | AD4: 主推产品，重点降解
A5: CC0517 | B5: 3B-功勋仓保险箱45*38*32cm红色密码款 | C5: 马来 | D5: 办公安防 | E5: 保险柜 | F5: 298.3692 | G5: 120 | J5: 120 | K5: 53706 | L5: =(G5-(H5*50))/50 -> 2.4 | M5: =31*(L5+H5) -> 74.4 | N5: =M5*F5 -> 22198.668 | O5: =(G5-(H5*90))/90 -> 1.3333333 | P5: =31*(O5+H5) -> 41.333333 | Q5: =(O5+H5)*31*F5*1.5 -> 18498.89 | R5: =P5 -> 41.333333 | S5: =R5/31 -> 1.3333333 | T5: =S5-H5 -> 1.3333333 | U5: =Q5 -> 18498.89 | V5: =_xlfn.XLOOKUP(B5,[1]Sheet1!$B:$B,[1]Sheet1!$P:$P) -> 0 | W5: =X5/31 -> 0 | X5: =R5*V5 -> 0 | Y5: =X5*F5*1.5 -> 0 | Z5: =_xlfn.XLOOKUP(B5,[1]Sheet1!$B:$B,[1]Sheet1!$Q:$Q) -> 0 | AA5: =AB5/31 -> 0 | AB5: =R5*Z5 -> 0 | AC5: =F5*AB5*1.5 -> 0 | AD5: 新品主推产品，重点降解
A6: CC0903 | B6: 3B-硬币清分机5188 | C6: 马来 | D6: 办公安防 | E6: 硬币清分机 | F6: 379.8 | G6: 80 | J6: 80 | K6: 45576 | L6: =(G6-(H6*50))/50 -> 1.6 | M6: =31*(L6+H6) -> 49.6 | N6: =M6*F6 -> 18838.08 | O6: =(G6-(H6*90))/90 -> 0.88888889 | P6: =31*(O6+H6) -> 27.555556 | Q6: =(O6+H6)*31*F6*1.5 -> 15698.4 | R6: =P6 -> 27.555556 | S6: =R6/31 -> 0.88888889 | T6: =S6-H6 -> 0.88888889 | U6: =Q6 -> 15698.4 | V6: =_xlfn.XLOOKUP(B6,[1]Sheet1!$B:$B,[1]Sheet1!$P:$P) -> 0 | W6: =X6/31 -> 0 | X6: =R6*V6 -> 0 | Y6: =X6*F6*1.5 -> 0 | Z6: =_xlfn.XLOOKUP(B6,[1]Sheet1!$B:$B,[1]Sheet1!$Q:$Q) -> 0 | AA6: =AB6/31 -> 0 | AB6: =R6*Z6 -> 0 | AC6: =F6*AB6*1.5 -> 0 | AD6: 新品主推产品，重点降解
A7: CC0711 | B7: 3B-58mm手持蓝牙标签打印机 | C7: 马来 | D7: 办公安防 | E7: 打印机 | F7: 52.89 | G7: 2002 | H7: 23 | I7: 87 | J7: 836 | K7: 44216 | L7: =(G7-(H7*50))/50 -> 17.04 | M7: =31*(L7+H7) -> 1241.24 | N7: =M7*F7 -> 65649.184 | O7: =(G7-(H7*90))/90 -> -0.75555556 | P7: =31*(O7+H7) -> 689.57778 | Q7: =(O7+H7)*31*F7*1.5 -> 54707.653 | R7: =P7 -> 689.57778 | S7: =R7/31 -> 22.244444 | T7: =S7-H7 -> -0.75555556 | U7: =Q7 -> 54707.653 | V7: =_xlfn.XLOOKUP(B7,[1]Sheet1!$B:$B,[1]Sheet1!$P:$P) -> 0.97515528 | W7: =X7/31 -> 21.691787 | X7: =R7*V7 -> 672.44541 | Y7: =X7*F7*1.5 -> 53348.457 | Z7: =_xlfn.XLOOKUP(B7,[1]Sheet1!$B:$B,[1]Sheet1!$Q:$Q) -> 0.02484472 | AA7: =AB7/31 -> 0.552657 | AB7: =R7*Z7 -> 17.132367 | AC7: =F7*AB7*1.5 -> 1359.1963 | AD7: 主推产品，重点降解
A8: CC0516 | B8: 3B-路由器P6000白色 | C8: 马来 | D8: 办公安防 | E8: 路由器 | F8: 93.44 | G8: 370 | H8: 1 | I8: 370 | J8: 317 | K8: 42422 | L8: =(G8-(H8*50))/50 -> 6.4 | M8: =31*(L8+H8) -> 229.4 | N8: =M8*F8 -> 21435.136 | O8: =(G8-(H8*90))/90 -> 3.1111111 | P8: =31*(O8+H8) -> 127.44444 | Q8: =(O8+H8)*31*F8*1.5 -> 17862.613 | R8: =P8 -> 127.44444 | S8: =R8/31 -> 4.1111111 | T8: =S8-H8 -> 3.1111111 | U8: =Q8 -> 17862.613 | V8: =_xlfn.XLOOKUP(B8,[1]Sheet1!$B:$B,[1]Sheet1!$P:$P) -> 1 | W8: =X8/31 -> 4.1111111 | X8: =R8*V8 -> 127.44444 | Y8: =X8*F8*1.5 -> 17862.613 | Z8: =_xlfn.XLOOKUP(B8,[1]Sheet1!$B:$B,[1]Sheet1!$Q:$Q) -> 0 | AA8: =AB8/31 -> 0 | AB8: =R8*Z8 -> 0 | AC8: =F8*AB8*1.5 -> 0 | AD8: 呆滞品，定向清理
A9: CC0706 | B9: 3B-收银箱405金属黑色固定版 | C9: 马来 | D9: 办公安防 | E9: 收银箱 | F9: 95.44 | G9: 1502 | H9: 21 | I9: 71 | J9: 439 | K9: 41898 | L9: =(G9-(H9*50))/50 -> 9.04 | M9: =31*(L9+H9) -> 931.24 | N9: =M9*F9 -> 88877.546 | O9: =(G9-(H9*90))/90 -> -4.3111111 | P9: =31*(O9+H9) -> 517.35556 | Q9: =(O9+H9)*31*F9*1.5 -> 74064.621 | R9: =P9 -> 517.35556 | S9: =R9/31 -> 16.688889 | T9: =S9-H9 -> -4.3111111 | U9: =Q9 -> 74064.621 | V9: =_xlfn.XLOOKUP(B9,[1]Sheet1!$B:$B,[1]Sheet1!$P:$P) -> 0.79099678 | W9: =X9/31 -> 13.200857 | X9: =R9*V9 -> 409.22658 | Y9: =X9*F9*1.5 -> 58584.877 | Z9: =_xlfn.XLOOKUP(B9,[1]Sheet1!$B:$B,[1]Sheet1!$Q:$Q) -> 0.20900322 | AA9: =AB9/31 -> 3.4880314 | AB9: =R9*Z9 -> 108.12897 | AC9: =F9*AB9*1.5 -> 15479.744 | AD9: 重点降解
A10: CC0906 | B10: 3B-功勋仓保险箱45*38*32cm红色指纹款 | C10: 马来 | D10: 办公安防 | E10: 保险柜 | F10: 369.1592 | G10: 77 | J10: 72 | K10: 39131 | L10: =(G10-(H10*50))/50 -> 1.54 | M10: =31*(L10+H10) -> 47.74 | N10: =M10*F10 -> 17623.66 | O10: =(G10-(H10*90))/90 -> 0.85555556 | P10: =31*(O10+H10) -> 26.522222 | Q10: =(O10+H10)*31*F10*1.5 -> 14686.384 | R10: =P10 -> 26.522222 | S10: =R10/31 -> 0.85555556 | T10: =S10-H10 -> 0.85555556 | U10: =Q10 -> 14686.384 | V10: =_xlfn.XLOOKUP(B10,[1]Sheet1!$B:$B,[1]Sheet1!$P:$P) -> 1 | W10: =X10/31 -> 0.85555556 | X10: =R10*V10 -> 26.522222 | Y10: =X10*F10*1.5 -> 14686.384 | Z10: =_xlfn.XLOOKUP(B10,[1]Sheet1!$B:$B,[1]Sheet1!$Q:$Q) -> 0 | AA10: =AB10/31 -> 0 | AB10: =R10*Z10 -> 0 | AC10: =F10*AB10*1.5 -> 0 | AD10: 新品主推产品，重点降解
A11: CC0228 | B11: 3B-磁吸白板密度板夹层70cm*100cm | C11: 马来 | D11: 办公安防 | E11: 白板 | F11: 44.98 | G11: 2254 | H11: 28 | I11: 80 | J11: 828 | K11: 37243 | L11: =(G11-(H11*50))/50 -> 17.08 | M11: =31*(L11+H11) -> 1397.48 | N11: =M11*F11 -> 62858.65 | O11: =(G11-(H11*90))/90 -> -2.9555556 | P11: =31*(O11+H11) -> 776.37778 | Q11: =(O11+H11)*31*F11*1.5 -> 52382.209 | R11: =P11 -> 776.37778 | S11: =R11/31 -> 25.044444 | T11: =S11-H11 -> -2.9555556 | U11: =Q11 -> 52382.209 | V11: =_xlfn.XLOOKUP(B11,[1]Sheet1!$B:$B,[1]Sheet1!$P:$P) -> 0.63111111 | W11: =X11/31 -> 15.805827 | X11: =R11*V11 -> 489.98064 | Y11: =X11*F11*1.5 -> 33058.994 | Z11: =_xlfn.XLOOKUP(B11,[1]Sheet1!$B:$B,[1]Sheet1!$Q:$Q) -> 0.36888889 | AA11: =AB11/31 -> 9.2386173 | AB11: =R11*Z11 -> 286.39714 | AC11: =F11*AB11*1.5 -> 19323.215 | AD11: 业绩大头，重点降解
A12: CC0764 | B12: 3B-智能指纹门锁X7 | C12: 马来 | D12: 办公安防 | E12: 指纹锁 | F12: 94.05 | G12: 973 | H12: 12 | I12: 81 | J12: 368 | K12: 34610 | L12: =(G12-(H12*50))/50 -> 7.46 | M12: =31*(L12+H12) -> 603.26 | N12: =M12*F12 -> 56736.603 | O12: =(G12-(H12*90))/90 -> -1.1888889 | P12: =31*(O12+H12) -> 335.14444 | Q12: =(O12+H12)*31*F12*1.5 -> 47280.503 | R12: =P12 -> 335.14444 | S12: =R12/31 -> 10.811111 | T12: =S12-H12 -> -1.1888889 | U12: =Q12 -> 47280.503 | V12: =_xlfn.XLOOKUP(B12,[1]Sheet1!$B:$B,[1]Sheet1!$P:$P) -> 0.21153846 | W12: =X12/31 -> 2.2869658 | X12: =R12*V12 -> 70.89594 | Y12: =X12*F12*1.5 -> 10001.645 | Z12: =_xlfn.XLOOKUP(B12,[1]Sheet1!$B:$B,[1]Sheet1!$Q:$Q) -> 0.78846154 | AA12: =AB12/31 -> 8.5241453 | AB12: =R12*Z12 -> 264.2485 | AC12: =F12*AB12*1.5 -> 37278.858 | AD12: 主推产品，重点降解
A13: CC0278 | B13: 3B-橡胶磁白板背胶90cm*180cm | C13: 马来 | D13: 办公安防 | E13: 白板 | F13: 67.79 | G13: 413 | H13: 1 | I13: 413 | J13: 325 | K13: 30641 | L13: =(G13-(H13*50))/50 -> 7.26 | M13: =31*(L13+H13) -> 256.06 | N13: z | O13: =(G13-(H13*90))/90 -> 3.5888889 | P13: =31*(O13+H13) -> 142.25556 | Q13: =(O13+H13)*31*F13*1.5 -> 14465.256 | R13: =P13 -> 142.25556 | S13: =R13/31 -> 4.5888889 | T13: =S13-H13 -> 3.5888889 | U13: =Q13 -> 14465.256 | V13: =_xlfn.XLOOKUP(B13,[1]Sheet1!$B:$B,[1]Sheet1!$P:$P) -> 0.81481481 | W13: =X13/31 -> 3.7390947 | X13: =R13*V13 -> 115.91193 | Y13: =X13*F13*1.5 -> 11786.505 | Z13: =_xlfn.XLOOKUP(B13,[1]Sheet1!$B:$B,[1]Sheet1!$Q:$Q) -> 0.18518519 | AA13: =AB13/31 -> 0.84979424 | AB13: =R13*Z13 -> 26.343621 | AC13: =F13*AB13*1.5 -> 2678.7511 | AD13: 业绩大头，重点降解
A14: CC0634 | B14: 3C-电子琴61健黑色 | C14: 马来 | D14: 3C数码 | E14: 电子琴 | F14: 37.88 | G14: 985 | H14: 8 | I14: 123 | J14: 579 | K14: 26743 | L14: =(G14-(H14*50))/50 -> 11.7 | M14: =31*(L14+H14) -> 610.7 | N14: =M14*F14 -> 23133.316 | O14: =(G14-(H14*90))/90 -> 2.9444444 | P14: =31*(O14+H14) -> 339.27778 | Q14: =(O14+H14)*31*F14*1.5 -> 19277.763 | R14: =P14 -> 339.27778 | S14: =R14/31 -> 10.944444 | T14: =S14-H14 -> 2.9444444 | U14: =Q14 -> 19277.763 | V14: =_xlfn.XLOOKUP(B14,[1]Sheet1!$B:$B,[1]Sheet1!$P:$P) -> 0.48760331 | W14: =X14/31 -> 5.3365473 | X14: =R14*V14 -> 165.43297 | Y14: =X14*F14*1.5 -> 9399.9011 | Z14: =_xlfn.XLOOKUP(B14,[1]Sheet1!$B:$B,[1]Sheet1!$Q:$Q) -> 0.51239669 | AA14: =AB14/31 -> 5.6078972 | AB14: =R14*Z14 -> 173.84481 | AC14: =F14*AB14*1.5 -> 9877.8622 | AD14: 重点降解
A15: CC0342 | B15: 3B-6088型号外币点钞机 | C15: 马来 | D15: 办公安防 | E15: 点钞机 | F15: 329.025 | G15: 58 | J15: 55 | K15: 26651 | L15: =(G15-(H15*50))/50 -> 1.16 | M15: =31*(L15+H15) -> 35.96 | N15: =M15*F15 -> 11831.739 | O15: =(G15-(H15*90))/90 -> 0.64444444 | P15: =31*(O15+H15) -> 19.977778 | Q15: =(O15+H15)*31*F15*1.5 -> 9859.7825 | R15: =P15 -> 19.977778 | S15: =R15/31 -> 0.64444444 | T15: =S15-H15 -> 0.64444444 | U15: =Q15 -> 9859.7825 | V15: =_xlfn.XLOOKUP(B15,[1]Sheet1!$B:$B,[1]Sheet1!$P:$P) -> 0 | W15: =X15/31 -> 0 | X15: =R15*V15 -> 0 | Y15: =X15*F15*1.5 -> 0 | Z15: =_xlfn.XLOOKUP(B15,[1]Sheet1!$B:$B,[1]Sheet1!$Q:$Q) -> 0 | AA15: =AB15/31 -> 0 | AB15: =R15*Z15 -> 0 | AC15: =F15*AB15*1.5 -> 0 | AD15: 新品主推产品，重点降解
A16: CC0686 | B16: 3B-300CWiFi路由器 | C16: 马来 | D16: 办公安防 | E16: 路由器 | F16: 127.34 | G16: 136 | J16: 136 | K16: 25977 | L16: =(G16-(H16*50))/50 -> 2.72 | M16: =31*(L16+H16) -> 84.32 | N16: =M16*F16 -> 10737.309 | O16: =(G16-(H16*90))/90 -> 1.5111111 | P16: =31*(O16+H16) -> 46.844444 | Q16: =(O16+H16)*31*F16*1.5 -> 8947.7573 | R16: =P16 -> 46.844444 | S16: =R16/31 -> 1.5111111 | T16: =S16-H16 -> 1.5111111 | U16: =Q16 -> 8947.7573 | V16: =_xlfn.XLOOKUP(B16,[1]Sheet1!$B:$B,[1]Sheet1!$P:$P) -> 0 | W16: =X16/31 -> 0 | X16: =R16*V16 -> 0 | Y16: =X16*F16*1.5 -> 0 | Z16: =_xlfn.XLOOKUP(B16,[1]Sheet1!$B:$B,[1]Sheet1!$Q:$Q) -> 0 | AA16: =AB16/31 -> 0 | AB16: =R16*Z16 -> 0 | AC16: =F16*AB16*1.5 -> 0 | AD16: 呆滞品，定向清理
A17: CC0907 | B17: 3C-X400电视壁挂架送膨胀丝等安装螺丝 | C17: 马来 | D17: 3C数码 | E17: 电视支架 | F17: 19.5121 | G17: 1577 | H17: 11 | I17: 143 | J17: 1001 | K17: 24819 | L17: =(G17-(H17*50))/50 -> 20.54 | M17: =31*(L17+H17) -> 977.74 | N17: =M17*F17 -> 19077.761 | O17: =(G17-(H17*90))/90 -> 6.5222222 | P17: =31*(O17+H17) -> 543.18889 | Q17: =(O17+H17)*31*F17*1.5 -> 15898.134 | R17: =P17 -> 543.18889 | S17: =R17/31 -> 17.522222 | T17: =S17-H17 -> 6.5222222 | U17: =Q17 -> 15898.134 | V17: =_xlfn.XLOOKUP(B17,[1]Sheet1!$B:$B,[1]Sheet1!$P:$P) -> 0.23943662 | W17: =X17/31 -> 4.1954617 | X17: =R17*V17 -> 130.05931 | Y17: =X17*F17*1.5 -> 3806.5954 | Z17: =_xlfn.XLOOKUP(B17,[1]Sheet1!$B:$B,[1]Sheet1!$Q:$Q) -> 0.76056338 | AA17: =AB17/31 -> 13.326761 | AB17: =R17*Z17 -> 413.12958 | AC17: =F17*AB17*1.5 -> 12091.538 | AD17: 重点降解
A18: CC0514 | B18: 3B-保险柜80cm*44cm*40cm | C18: 马来 | D18: 办公安防 | E18: 保险箱 | F18: 616.96 | G18: 30 | J18: 24 | K18: 20668 | L18: =(G18-(H18*50))/50 -> 0.6 | M18: =31*(L18+H18) -> 18.6 | N18: =M18*F18 -> 11475.456 | O18: =(G18-(H18*90))/90 -> 0.33333333 | P18: =31*(O18+H18) -> 10.333333 | Q18: =(O18+H18)*31*F18*1.5 -> 9562.88 | R18: =P18 -> 10.333333 | S18: =R18/31 -> 0.33333333 | T18: =S18-H18 -> 0.33333333 | U18: =Q18 -> 9562.88 | V18: =_xlfn.XLOOKUP(B18,[1]Sheet1!$B:$B,[1]Sheet1!$P:$P) -> 0 | W18: =X18/31 -> 0 | X18: =R18*V18 -> 0 | Y18: =X18*F18*1.5 -> 0 | Z18: =_xlfn.XLOOKUP(B18,[1]Sheet1!$B:$B,[1]Sheet1!$Q:$Q) -> 1 | AA18: =AB18/31 -> 0.33333333 | AB18: =R18*Z18 -> 10.333333 | AC18: =F18*AB18*1.5 -> 9562.88 | AD18: 呆滞品，定向清理
A19: CC0688 | B19: 3B-保险柜100cm*51cm*45cm | C19: 马来 | D19: 办公安防 | E19: 保险箱 | F19: 823.74 | G19: 39 | J19: 21 | K19: 19770 | L19: =(G19-(H19*50))/50 -> 0.78 | M19: =31*(L19+H19) -> 24.18 | N19: =M19*F19 -> 19918.033 | O19: =(G19-(H19*90))/90 -> 0.43333333 | P19: =31*(O19+H19) -> 13.433333 | Q19: =(O19+H19)*31*F19*1.5 -> 16598.361 | R19: =P19 -> 13.433333 | S19: =R19/31 -> 0.43333333 | T19: =S19-H19 -> 0.43333333 | U19: =Q19 -> 16598.361 | V19: =_xlfn.XLOOKUP(B19,[1]Sheet1!$B:$B,[1]Sheet1!$P:$P) -> 0.2 | W19: =X19/31 -> 0.086666667 | X19: =R19*V19 -> 2.6866667 | Y19: =X19*F19*1.5 -> 3319.6722 | Z19: =_xlfn.XLOOKUP(B19,[1]Sheet1!$B:$B,[1]Sheet1!$Q:$Q) -> 0.8 | AA19: =AB19/31 -> 0.34666667 | AB19: =R19*Z19 -> 10.746667 | AC19: =F19*AB19*1.5 -> 13278.689 | AD19: 呆滞品，定向清理
A20: CC0732 | B20: 3C-32至70寸电视移动支架的单支架 | C20: 马来 | D20: 3C数码 | E20: 电视支架 | F20: 99.81 | G20: 547 | H20: 6 | I20: 91 | J20: 198 | K20: 19762 | L20: =(G20-(H20*50))/50 -> 4.94 | M20: =31*(L20+H20) -> 339.14 | N20: =M20*F20 -> 33849.563 | O20: =(G20-(H20*90))/90 -> 0.077777778 | P20: =31*(O20+H20) -> 188.41111 | Q20: =(O20+H20)*31*F20*1.5 -> 28207.969 | R20: =P20 -> 188.41111 | S20: =R20/31 -> 6.0777778 | T20: =S20-H20 -> 0.077777778 | U20: =Q20 -> 28207.969 | V20: =_xlfn.XLOOKUP(B20,[1]Sheet1!$B:$B,[1]Sheet1!$P:$P) -> 0.6043956 | W20: =X20/31 -> 3.6733822 | X20: =R20*V20 -> 113.87485 | Y20: =X20*F20*1.5 -> 17048.773 | Z20: =_xlfn.XLOOKUP(B20,[1]Sheet1!$B:$B,[1]Sheet1!$Q:$Q) -> 0.3956044 | AA20: =AB20/31 -> 2.4043956 | AB20: =R20*Z20 -> 74.536264 | AC20: =F20*AB20*1.5 -> 11159.197 | AD20: 重点降解
A21: CC0315 | B21: 3C-辉光管 | C21: 马来 | D21: 3C数码 | E21: 辉光管 | F21: 203.25 | G21: 77 | J21: 67 | K21: 19614 | L21: =(G21-(H21*50))/50 -> 1.54 | M21: =31*(L21+H21) -> 47.74 | N21: =M21*F21 -> 9703.155 | O21: =(G21-(H21*90))/90 -> 0.85555556 | P21: =31*(O21+H21) -> 26.522222 | Q21: =(O21+H21)*31*F21*1.5 -> 8085.9625 | R21: =P21 -> 26.522222 | S21: =R21/31 -> 0.85555556 | T21: =S21-H21 -> 0.85555556 | U21: =Q21 -> 8085.9625 | V21: =_xlfn.XLOOKUP(B21,[1]Sheet1!$B:$B,[1]Sheet1!$P:$P) -> 0.5 | W21: =X21/31 -> 0.42777778 | X21: =R21*V21 -> 13.261111 | Y21: 60 | Z21: =_xlfn.XLOOKUP(B21,[1]Sheet1!$B:$B,[1]Sheet1!$Q:$Q) -> 0.5 | AA21: =AB21/31 -> 0.42777778 | AB21: =R21*Z21 -> 13.261111 | AC21: =F21*AB21*1.5 -> 4042.9812 | AD21: 呆滞品，定向清理
A22: CC0277 | B22: 3B-交换机机柜60cm | C22: 马来 | D22: 办公安防 | E22: 金属制品机柜 | F22: 124.39 | G22: 100 | J22: 100 | K22: 18659 | L22: =(G22-(H22*50))/50 -> 2 | M22: =31*(L22+H22) -> 62 | N22: =M22*F22 -> 7712.18 | O22: =(G22-(H22*90))/90 -> 1.1111111 | P22: =31*(O22+H22) -> 34.444444 | Q22: =(O22+H22)*31*F22*1.5 -> 6426.8167 | R22: =P22 -> 34.444444 | S22: =R22/31 -> 1.1111111 | T22: =S22-H22 -> 1.1111111 | U22: =Q22 -> 6426.8167 | V22: =_xlfn.XLOOKUP(B22,[1]Sheet1!$B:$B,[1]Sheet1!$P:$P) -> 0 | W22: =X22/31 -> 0 | X22: =R22*V22 -> 0 | Y22: =X22*F22*1.5 -> 0 | Z22: =_xlfn.XLOOKUP(B22,[1]Sheet1!$B:$B,[1]Sheet1!$Q:$Q) -> 0 | AA22: =AB22/31 -> 0 | AB22: =R22*Z22 -> 0 | AC22: =F22*AB22*1.5 -> 0 | AD22: 主推产品，重点降解
A23: CC0377 | B23: 3B-仿真书银钱盒钥匙款蓝色 | C23: 马来 | D23: 办公安防 | E23: 银钱盒 | F23: 18.36 | G23: 1466 | H23: 12 | I23: 122 | J23: 828 | K23: 18112 | L23: =(G23-(H23*50))/50 -> 17.32 | M23: =31*(L23+H23) -> 908.92 | N23: =M23*F23 -> 16687.771 | O23: =(G23-(H23*90))/90 -> 4.2888889 | P23: =31*(O23+H23) -> 504.95556 | Q23: =(O23+H23)*31*F23*1.5 -> 13906.476 | R23: =P23 -> 504.95556 | S23: =R23/31 -> 16.288889 | T23: =S23-H23 -> 4.2888889 | U23: =Q23 -> 13906.476 | V23: =_xlfn.XLOOKUP(B23,[1]Sheet1!$B:$B,[1]Sheet1!$P:$P) -> 0.3375 | W23: =X23/31 -> 5.4975 | X23: =R23*V23 -> 170.4225 | Y23: =X23*F23*1.5 -> 4693.4357 | Z23: =_xlfn.XLOOKUP(B23,[1]Sheet1!$B:$B,[1]Sheet1!$Q:$Q) -> 0.6625 | AA23: =AB23/31 -> 10.791389 | AB23: =R23*Z23 -> 334.53306 | AC23: =F23*AB23*1.5 -> 9213.0403 | AD23: 主推产品，重点降解
A24: CC0768 | B24: 3B-可充电不锈钢球形锁K06 | C24: 马来 | D24: 办公安防 | E24: 球型智能门锁 | F24: 98.3251 | G24: 120 | J24: 120 | K24: 17699 | L24: =(G24-(H24*50))/50 -> 2.4 | M24: =31*(L24+H24) -> 74.4 | N24: =M24*F24 -> 7315.3874 | O24: =(G24-(H24*90))/90 -> 1.3333333 | P24: =31*(O24+H24) -> 41.333333 | Q24: =(O24+H24)*31*F24*1.5 -> 6096.1562 | R24: =P24 -> 41.333333 | S24: =R24/31 -> 1.3333333 | T24: =S24-H24 -> 1.3333333 | U24: =Q24 -> 6096.1562 | V24: =_xlfn.XLOOKUP(B24,[1]Sheet1!$B:$B,[1]Sheet1!$P:$P) -> #N/A | W24: =X24/31 -> #N/A | X24: =R24*V24 -> #N/A | Y24: =X24*F24*1.5 -> #N/A | Z24: =_xlfn.XLOOKUP(B24,[1]Sheet1!$B:$B,[1]Sheet1!$Q:$Q) -> #N/A | AA24: =AB24/31 -> #N/A | AB24: =R24*Z24 -> #N/A | AC24: =F24*AB24*1.5 -> #N/A | AD24: 新品降解
A25: CC0181 | B25: 3C-显示器桌面支架3屏 | C25: 马来 | D25: 3C数码 | E25: 显示器支架 | F25: 89.55 | G25: 157 | J25: 136 | K25: 17507 | L25: =(G25-(H25*50))/50 -> 3.14 | M25: =31*(L25+H25) -> 97.34 | N25: =M25*F25 -> 8716.797 | O25: =(G25-(H25*90))/90 -> 1.7444444 | P25: =31*(O25+H25) -> 54.077778 | Q25: =(O25+H25)*31*F25*1.5 -> 7263.9975 | R25: =P25 -> 54.077778 | S25: =R25/31 -> 1.7444444 | T25: =S25-H25 -> 1.7444444 | U25: =Q25 -> 7263.9975 | V25: =_xlfn.XLOOKUP(B25,[1]Sheet1!$B:$B,[1]Sheet1!$P:$P) -> 1 | W25: =X25/31 -> 1.7444444 | X25: =R25*V25 -> 54.077778 | Y25: =X25*F25*1.5 -> 7263.9975 | Z25: =_xlfn.XLOOKUP(B25,[1]Sheet1!$B:$B,[1]Sheet1!$Q:$Q) -> 0 | AA25: =AB25/31 -> 0 | AB25: =R25*Z25 -> 0 | AC25: =F25*AB25*1.5 -> 0 | AD25: 长期日销偏低，系列降解
A26: CC0876 | B26: 3B-仿真书银钱盒密码款蓝色 | C26: 马来 | D26: 办公安防 | E26: 银钱盒 | F26: 19.31 | G26: 1179 | H26: 9 | I26: 131 | J26: 709 | K26: 16906 | L26: =(G26-(H26*50))/50 -> 14.58 | M26: =31*(L26+H26) -> 730.98 | N26: =M26*F26 -> 14115.224 | O26: =(G26-(H26*90))/90 -> 4.1 | P26: =31*(O26+H26) -> 406.1 | Q26: =(O26+H26)*31*F26*1.5 -> 11762.686 | R26: =P26 -> 406.1 | S26: =R26/31 -> 13.1 | T26: =S26-H26 -> 4.1 | U26: =Q26 -> 11762.686 | V26: =_xlfn.XLOOKUP(B26,[1]Sheet1!$B:$B,[1]Sheet1!$P:$P) -> 0.51041667 | W26: =X26/31 -> 6.6864583 | X26: =R26*V26 -> 207.28021 | Y26: =X26*F26*1.5 -> 6003.8712 | Z26: =_xlfn.XLOOKUP(B26,[1]Sheet1!$B:$B,[1]Sheet1!$Q:$Q) -> 0.48958333 | AA26: =AB26/31 -> 6.4135417 | AB26: =R26*Z26 -> 198.81979 | AC26: =F26*AB26*1.5 -> 5758.8153 | AD26: 主推产品，重点降解
A27: CC0678 | B27: 3B-碎纸机7L | C27: 马来 | D27: 办公安防 | E27: 碎纸机 | F27: 74.34 | G27: 491 | H27: 5 | I27: 98 | J27: 223 | K27: 16875 | L27: =(G27-(H27*50))/50 -> 4.82 | M27: =31*(L27+H27) -> 304.42 | N27: =M27*F27 -> 22630.583 | O27: =(G27-(H27*90))/90 -> 0.45555556 | P27: =31*(O27+H27) -> 169.12222 | Q27: =(O27+H27)*31*F27*1.5 -> 18858.819 | R27: =P27 -> 169.12222 | S27: =R27/31 -> 5.4555556 | T27: =S27-H27 -> 0.45555556 | U27: =Q27 -> 18858.819 | V27: =_xlfn.XLOOKUP(B27,[1]Sheet1!$B:$B,[1]Sheet1!$P:$P) -> 0.6 | W27: =X27/31 -> 3.2733333 | X27: =R27*V27 -> 101.47333 | Y27: =X27*F27*1.5 -> 11315.291 | Z27: =_xlfn.XLOOKUP(B27,[1]Sheet1!$B:$B,[1]Sheet1!$Q:$Q) -> 0.4 | AA27: =AB27/31 -> 2.1822222 | AB27: =R27*Z27 -> 67.648889 | AC27: =F27*AB27*1.5 -> 7543.5276 | AD27: 主推产品，重点降解
A28: CC0177 | B28: 3B-收银箱335金属黑色固定版 | C28: 马来 | D28: 办公安防 | E28: 收银箱 | F28: 78.76 | G28: 1061 | H28: 16 | I28: 66 | J28: 212 | K28: 16697 | L28: =(G28-(H28*50))/50 -> 5.22 | M28: =31*(L28+H28) -> 657.82 | N28: =M28*F28 -> 51809.903 | O28: =(G28-(H28*90))/90 -> -4.2111111 | P28: =31*(O28+H28) -> 365.45556 | Q28: =(O28+H28)*31*F28*1.5 -> 43174.919 | R28: =P28 -> 365.45556 | S28: =R28/31 -> 11.788889 | T28: =S28-H28 -> -4.2111111 | U28: =Q28 -> 43174.919 | V28: =_xlfn.XLOOKUP(B28,[1]Sheet1!$B:$B,[1]Sheet1!$P:$P) -> 0.79090909 | W28: =X28/31 -> 9.3239394 | X28: =R28*V28 -> 289.04212 | Y28: =X28*F28*1.5 -> 34147.436 | Z28: =_xlfn.XLOOKUP(B28,[1]Sheet1!$B:$B,[1]Sheet1!$Q:$Q) -> 0.20909091 | AA28: =AB28/31 -> 2.4649495 | AB28: =R28*Z28 -> 76.413434 | AC28: =F28*AB28*1.5 -> 9027.4831 | AD28: 主推产品，重点降解
A29: CC0860 | B29: 3B-新A6保险箱指纹款35cm*26cm*25cm | C29: 马来 | D29: 办公安防 | E29: 保险箱 | F29: 228.17 | G29: 48 | J29: 45 | K29: 15059 | L29: =(G29-(H29*50))/50 -> 0.96 | M29: =31*(L29+H29) -> 29.76 | N29: =M29*F29 -> 6790.3392 | O29: =(G29-(H29*90))/90 -> 0.53333333 | P29: =31*(O29+H29) -> 16.533333 | Q29: =(O29+H29)*31*F29*1.5 -> 5658.616 | R29: =P29 -> 16.533333 | S29: =R29/31 -> 0.53333333 | T29: =S29-H29 -> 0.53333333 | U29: =Q29 -> 5658.616 | V29: =_xlfn.XLOOKUP(B29,[1]Sheet1!$B:$B,[1]Sheet1!$P:$P) -> 1 | W29: =X29/31 -> 0.53333333 | X29: =R29*V29 -> 16.533333 | Y29: =X29*F29*1.5 -> 5658.616 | Z29: =_xlfn.XLOOKUP(B29,[1]Sheet1!$B:$B,[1]Sheet1!$Q:$Q) -> 0 | AA29: =AB29/31 -> 0 | AB29: =R29*Z29 -> 0 | AC29: =F29*AB29*1.5 -> 0 | AD29: 新品主推产品，重点降解
A30: CC0850 | B30: 3B-广告架kt板斜面3.5kg | C30: 马来 | D30: 办公安防 | E30: 广告架 | F30: 49.17 | G30: 214 | J30: 206 | K30: 15021 | L30: =(G30-(H30*50))/50 -> 4.28 | M30: =31*(L30+H30) -> 132.68 | N30: =M30*F30 -> 6523.8756 | O30: =(G30-(H30*90))/90 -> 2.3777778 | P30: =31*(O30+H30) -> 73.711111 | Q30: =(O30+H30)*31*F30*1.5 -> 5436.563 | R30: =P30 -> 73.711111 | S30: =R30/31 -> 2.3777778 | T30: =S30-H30 -> 2.3777778 | U30: =Q30 -> 5436.563 | V30: =_xlfn.XLOOKUP(B30,[1]Sheet1!$B:$B,[1]Sheet1!$P:$P) -> 0 | W30: =X30/31 -> 0 | X30: =R30*V30 -> 0 | Y30: =X30*F30*1.5 -> 0 | Z30: =_xlfn.XLOOKUP(B30,[1]Sheet1!$B:$B,[1]Sheet1!$Q:$Q) -> 1 | AA30: =AB30/31 -> 2.3777778 | AB30: =R30*Z30 -> 73.711111 | AC30: =F30*AB30*1.5 -> 5436.563 | AD30: 呆滞品，定向清理
A31: CC0807 | B31: 3B-B1A五功能断桥铝锁带APP | C31: 马来 | D31: 办公安防 | E31: 密码锁 | F31: 176.53 | G31: 102 | J31: 66 | K31: 14917 | L31: =(G31-(H31*50))/50 -> 2.04 | M31: =31*(L31+H31) -> 63.24 | N31: =M31*F31 -> 11163.757 | O31: =(G31-(H31*90))/90 -> 1.1333333 | P31: =31*(O31+H31) -> 35.133333 | Q31: =(O31+H31)*31*F31*1.5 -> 9303.131 | R31: =P31 -> 35.133333 | S31: =R31/31 -> 1.1333333 | T31: =S31-H31 -> 1.1333333 | U31: =Q31 -> 9303.131 | V31: =_xlfn.XLOOKUP(B31,[1]Sheet1!$B:$B,[1]Sheet1!$P:$P) -> 0.69230769 | W31: =X31/31 -> 0.78461538 | X31: =R31*V31 -> 24.323077 | Y31: =X31*F31*1.5 -> 6440.6292 | Z31: =_xlfn.XLOOKUP(B31,[1]Sheet1!$B:$B,[1]Sheet1!$Q:$Q) -> 0.30769231 | AA31: =AB31/31 -> 0.34871795 | AB31: =R31*Z31 -> 10.810256 | AC31: =F31*AB31*1.5 -> 2862.5018 | AD31: 重点降解
A32: CC0905 | B32: 3B-宽57cm热敏打印纸5卷 | C32: 马来 | D32: 办公安防 | E32: 标签打印纸 | F32: 4.1901 | G32: 7560 | H32: 82 | I32: 92 | J32: 3432 | K32: 14655 | L32: =(G32-(H32*50))/50 -> 69.2 | M32: =31*(L32+H32) -> 4687.2 | N32: =M32*F32 -> 19639.837 | O32: =(G32-(H32*90))/90 -> 2 | P32: =31*(O32+H32) -> 2604 | Q32: =(O32+H32)*31*F32*1.5 -> 16366.531 | R32: =P32 -> 2604 | S32: =R32/31 -> 84 | T32: =S32-H32 -> 2 | U32: =Q32 -> 16366.531 | V32: =_xlfn.XLOOKUP(B32,[1]Sheet1!$B:$B,[1]Sheet1!$P:$P) -> 0.89295039 | W32: =X32/31 -> 75.007833 | X32: =R32*V32 -> 2325.2428 | Y32: =X32*F32*1.5 -> 14614.5 | Z32: =_xlfn.XLOOKUP(B32,[1]Sheet1!$B:$B,[1]Sheet1!$Q:$Q) -> 0.10704961 | AA32: =AB32/31 -> 8.9921671 | AB32: =R32*Z32 -> 278.75718 | AC32: =F32*AB32*1.5 -> 1752.0307 | AD32: 主推配套，降解打印机
A33: CC0763 | B33: 3B-智能指纹门锁M20 | C33: 马来 | D33: 办公安防 | E33: 指纹锁 | F33: 74.88 | G33: 396 | H33: 4 | I33: 99 | J33: 184 | K33: 14340 | L33: =(G33-(H33*50))/50 -> 3.92 | M33: =31*(L33+H33) -> 245.52 | N33: =M33*F33 -> 18384.538 | O33: =(G33-(H33*90))/90 -> 0.4 | P33: =31*(O33+H33) -> 136.4 | Q33: =(O33+H33)*31*F33*1.5 -> 15320.448 | R33: =P33 -> 136.4 | S33: =R33/31 -> 4.4 | T33: =S33-H33 -> 0.4 | U33: =Q33 -> 15320.448 | V33: =_xlfn.XLOOKUP(B33,[1]Sheet1!$B:$B,[1]Sheet1!$P:$P) -> 0.26530612 | W33: =X33/31 -> 1.1673469 | X33: =R33*V33 -> 36.187755 | Y33: =X33*F33*1.5 -> 4064.6087 | Z33: =_xlfn.XLOOKUP(B33,[1]Sheet1!$B:$B,[1]Sheet1!$Q:$Q) -> 0.73469388 | AA33: =AB33/31 -> 3.2326531 | AB33: =R33*Z33 -> 100.21224 | AC33: =F33*AB33*1.5 -> 11255.839 | AD33: 主推产品，重点降解
A34: CC0339 | B34: 3B-密码保险箱黑 | C34: 马来 | D34: 办公安防 | E34: 保险箱 | F34: 124.73 | G34: 500 | H34: 7 | I34: 71 | J34: 112 | K34: 13970 | L34: =(G34-(H34*50))/50 -> 3 | M34: =31*(L34+H34) -> 310 | N34: =M34*F34 -> 38666.3 | O34: =(G34-(H34*90))/90 -> -1.4444444 | P34: =31*(O34+H34) -> 172.22222 | Q34: =(O34+H34)*31*F34*1.5 -> 32221.917 | R34: =P34 -> 172.22222 | S34: =R34/31 -> 5.5555556 | T34: =S34-H34 -> -1.4444444 | U34: =Q34 -> 32221.917 | V34: =_xlfn.XLOOKUP(B34,[1]Sheet1!$B:$B,[1]Sheet1!$P:$P) -> 0.41304348 | W34: =X34/31 -> 2.294686 | X34: =R34*V34 -> 71.135266 | Y34: =X34*F34*1.5 -> 13309.053 | Z34: =_xlfn.XLOOKUP(B34,[1]Sheet1!$B:$B,[1]Sheet1!$Q:$Q) -> 0.58695652 | AA34: =AB34/31 -> 3.2608696 | AB34: =R34*Z34 -> 101.08696 | AC34: =F34*AB34*1.5 -> 18912.864 | AD34: 主推产品，重点降解
A35: CC0730 | B35: 3C-专业播客动圈麦克风 | C35: 马来 | D35: 3C数码 | E35: 有线麦克风 | F35: 152.62 | G35: 70 | J35: 62 | K35: 13659 | L35: =(G35-(H35*50))/50 -> 1.4 | M35: =31*(L35+H35) -> 43.4 | N35: =M35*F35 -> 6623.708 | O35: =(G35-(H35*90))/90 -> 0.77777778 | P35: =31*(O35+H35) -> 24.111111 | Q35: =(O35+H35)*31*F35*1.5 -> 5519.7567 | R35: =P35 -> 24.111111 | S35: =R35/31 -> 0.77777778 | T35: =S35-H35 -> 0.77777778 | U35: =Q35 -> 5519.7567 | V35: =_xlfn.XLOOKUP(B35,[1]Sheet1!$B:$B,[1]Sheet1!$P:$P) -> 0 | W35: =X35/31 -> 0 | X35: =R35*V35 -> 0 | Y35: =X35*F35*1.5 -> 0 | Z35: =_xlfn.XLOOKUP(B35,[1]Sheet1!$B:$B,[1]Sheet1!$Q:$Q) -> 1 | AA35: =AB35/31 -> 0.77777778 | AB35: =R35*Z35 -> 24.111111 | AC35: =F35*AB35*1.5 -> 5519.7567 | AD35: 新品长期动销不住
A36: CC0733 | B36: 3C-显示器支架单臂铁塑款 | C36: 马来 | D36: 3C数码 | E36: 显示器支架 | F36: 44.2577 | G36: 808 | H36: 10 | I36: 80 | J36: 303 | K36: 13410 | L36: =(G36-(H36*50))/50 -> 6.16 | M36: =31*(L36+H36) -> 500.96 | N36: =M36*F36 -> 22171.337 | O36: =(G36-(H36*90))/90 -> -1.0222222 | P36: =31*(O36+H36) -> 278.31111 | Q36: =(O36+H36)*31*F36*1.5 -> 18476.114 | R36: =P36 -> 278.31111 | S36: =R36/31 -> 8.9777778 | T36: =S36-H36 -> -1.0222222 | U36: =Q36 -> 18476.114 | V36: =_xlfn.XLOOKUP(B36,[1]Sheet1!$B:$B,[1]Sheet1!$P:$P) -> 0.22857143 | W36: =X36/31 -> 2.0520635 | X36: =R36*V36 -> 63.613968 | Y36: =X36*F36*1.5 -> 4223.1119 | Z36: =_xlfn.XLOOKUP(B36,[1]Sheet1!$B:$B,[1]Sheet1!$Q:$Q) -> 0.77142857 | AA36: =AB36/31 -> 6.9257143 | AB36: =R36*Z36 -> 214.69714 | AC36: =F36*AB36*1.5 -> 14253.003 | AD36: 主推产品，重点降解
A37: CC0731 | B37: 3C-32英寸到55英寸带中托可移动电视支架 | C37: 马来 | D37: 3C数码 | E37: 电视支架 | F37: 123.29 | G37: 570 | H37: 9 | I37: 63 | J37: 108 | K37: 13315 | L37: =(G37-(H37*50))/50 -> 2.4 | M37: =31*(L37+H37) -> 353.4 | N37: =M37*F37 -> 43570.686 | O37: =(G37-(H37*90))/90 -> -2.6666667 | P37: =31*(O37+H37) -> 196.33333 | Q37: =(O37+H37)*31*F37*1.5 -> 36308.905 | R37: =P37 -> 196.33333 | S37: =R37/31 -> 6.3333333 | T37: =S37-H37 -> -2.6666667 | U37: =Q37 -> 36308.905 | V37: =_xlfn.XLOOKUP(B37,[1]Sheet1!$B:$B,[1]Sheet1!$P:$P) -> 0.19672131 | W37: =X37/31 -> 1.2459016 | X37: =R37*V37 -> 38.622951 | Y37: =X37*F37*1.5 -> 7142.7354 | Z37: =_xlfn.XLOOKUP(B37,[1]Sheet1!$B:$B,[1]Sheet1!$Q:$Q) -> 0.80327869 | AA37: =AB37/31 -> 5.0874317 | AB37: =R37*Z37 -> 157.71038 | AC37: =F37*AB37*1.5 -> 29166.17 | AD37: 重点降解
A38: CC0433 | B38: 3C-双层移动推车MY1700PJ | C38: 马来 | D38: 3C数码 | E38: 电视支架 | F38: 120.02 | G38: 78 | J38: 73 | K38: 12902 | L38: =(G38-(H38*50))/50 -> 1.56 | M38: =31*(L38+H38) -> 48.36 | N38: =M38*F38 -> 5804.1672 | O38: =(G38-(H38*90))/90 -> 0.86666667 | P38: =31*(O38+H38) -> 26.866667 | Q38: =(O38+H38)*31*F38*1.5 -> 4836.806 | R38: =P38 -> 26.866667 | S38: =R38/31 -> 0.86666667 | T38: =S38-H38 -> 0.86666667 | U38: =Q38 -> 4836.806 | V38: =_xlfn.XLOOKUP(B38,[1]Sheet1!$B:$B,[1]Sheet1!$P:$P) -> 1 | W38: =X38/31 -> 0.86666667 | X38: =R38*V38 -> 26.866667 | Y38: =X38*F38*1.5 -> 4836.806 | Z38: =_xlfn.XLOOKUP(B38,[1]Sheet1!$B:$B,[1]Sheet1!$Q:$Q) -> 0 | AA38: =AB38/31 -> 0 | AB38: =R38*Z38 -> 0 | AC38: =F38*AB38*1.5 -> 0 | AD38: 新品降解
A39: CC0727 | B39: 3C-黑色吉他套装 | C39: 马来 | D39: 3C数码 | E39: 吉他套装 | F39: 83.02 | G39: 606 | H39: 8 | I39: 75 | J39: 155 | K39: 12868 | L39: =(G39-(H39*50))/50 -> 4.12 | M39: =31*(L39+H39) -> 375.72 | N39: =M39*F39 -> 31192.274 | O39: =(G39-(H39*90))/90 -> -1.2666667 | P39: =31*(O39+H39) -> 208.73333 | Q39: =(O39+H39)*31*F39*1.5 -> 25993.562 | R39: =P39 -> 208.73333 | S39: =R39/31 -> 6.7333333 | T39: =S39-H39 -> -1.2666667 | U39: =Q39 -> 25993.562 | V39: =_xlfn.XLOOKUP(B39,[1]Sheet1!$B:$B,[1]Sheet1!$P:$P) -> 0.42372881 | W39: =X39/31 -> 2.8531073 | X39: =R39*V39 -> 88.446328 | Y39: =X39*F39*1.5 -> 11014.221 | Z39: =_xlfn.XLOOKUP(B39,[1]Sheet1!$B:$B,[1]Sheet1!$Q:$Q) -> 0.57627119 | AA39: =AB39/31 -> 3.880226 | AB39: =R39*Z39 -> 120.28701 | AC39: =F39*AB39*1.5 -> 14979.341 | AD39: 主推产品，重点降解
A40: CC0101 | B40: 3C-原木色吉他套装 | C40: 马来 | D40: 3C数码 | E40: 吉他套装 | F40: 83.02 | G40: 586 | H40: 8 | I40: 73 | J40: 153 | K40: 12702 | L40: =(G40-(H40*50))/50 -> 3.72 | M40: =31*(L40+H40) -> 363.32 | N40: =M40*F40 -> 30162.826 | O40: =(G40-(H40*90))/90 -> -1.4888889 | P40: =31*(O40+H40) -> 201.84444 | Q40: =(O40+H40)*31*F40*1.5 -> 25135.689 | R40: =P40 -> 201.84444 | S40: =R40/31 -> 6.5111111 | T40: =S40-H40 -> -1.4888889 | U40: =Q40 -> 25135.689 | V40: =_xlfn.XLOOKUP(B40,[1]Sheet1!$B:$B,[1]Sheet1!$P:$P) -> 0.40707965 | W40: =X40/31 -> 2.6505408 | X40: =R40*V40 -> 82.166765 | Y40: =X40*F40*1.5 -> 10232.227 | Z40: =_xlfn.XLOOKUP(B40,[1]Sheet1!$B:$B,[1]Sheet1!$Q:$Q) -> 0.59292035 | AA40: =AB40/31 -> 3.8605703 | AB40: =R40*Z40 -> 119.67768 | AC40: =F40*AB40*1.5 -> 14903.461 | AD40: 主推产品，重点降解
A41: CC0695 | B41: 3B-8360款台式票据打印机80mm黑橘 | C41: 马来 | D41: 办公安防 | E41: 打印机 | F41: 146.25 | G41: 59 | J41: 58 | K41: 12651 | L41: =(G41-(H41*50))/50 -> 1.18 | M41: =31*(L41+H41) -> 36.58 | N41: =M41*F41 -> 5349.825 | O41: =(G41-(H41*90))/90 -> 0.65555556 | P41: =31*(O41+H41) -> 20.322222 | Q41: =(O41+H41)*31*F41*1.5 -> 4458.1875 | R41: =P41 -> 20.322222 | S41: =R41/31 -> 0.65555556 | T41: =S41-H41 -> 0.65555556 | U41: =Q41 -> 4458.1875 | V41: =_xlfn.XLOOKUP(B41,[1]Sheet1!$B:$B,[1]Sheet1!$P:$P) -> 0 | W41: =X41/31 -> 0 | X41: =R41*V41 -> 0 | Y41: =X41*F41*1.5 -> 0 | Z41: =_xlfn.XLOOKUP(B41,[1]Sheet1!$B:$B,[1]Sheet1!$Q:$Q) -> 0 | AA41: =AB41/31 -> 0 | AB41: =R41*Z41 -> 0 | AC41: =F41*AB41*1.5 -> 0 | AD41: 主推产品，重点降解
A42: CC0996 | B42: 3C-V8H型电视机支架 | C42: 马来 | D42: 3C数码 | E42: 电视支架 | F42: 108.34 | G42: 150 | H42: 1 | I42: 150 | J42: 92 | K42: 12405 | L42: =(G42-(H42*50))/50 -> 2 | M42: =31*(L42+H42) -> 93 | N42: =M42*F42 -> 10075.62 | O42: =(G42-(H42*90))/90 -> 0.66666667 | P42: =31*(O42+H42) -> 51.666667 | Q42: =(O42+H42)*31*F42*1.5 -> 8396.35 | R42: =P42 -> 51.666667 | S42: =R42/31 -> 1.6666667 | T42: =S42-H42 -> 0.66666667 | U42: =Q42 -> 8396.35 | V42: =_xlfn.XLOOKUP(B42,[1]Sheet1!$B:$B,[1]Sheet1!$P:$P) -> 0.24 | W42: =X42/31 -> 0.4 | X42: =R42*V42 -> 12.4 | Y42: =X42*F42*1.5 -> 2015.124 | Z42: =_xlfn.XLOOKUP(B42,[1]Sheet1!$B:$B,[1]Sheet1!$Q:$Q) -> 0.76 | AA42: =AB42/31 -> 1.2666667 | AB42: =R42*Z42 -> 39.266667 | AC42: =F42*AB42*1.5 -> 6381.226 | AD42: 新品降解
A43: CC0477 | B43: 3B-磁吸白板密度板夹层90cm*150cm | C43: 马来 | D43: 办公安防 | E43: 白板 | F43: 90.7 | G43: 506 | H43: 7 | I43: 72 | J43: 135 | K43: 12245 | L43: =(G43-(H43*50))/50 -> 3.12 | M43: =31*(L43+H43) -> 313.72 | N43: =M43*F43 -> 28454.404 | O43: =(G43-(H43*90))/90 -> -1.3777778 | P43: =31*(O43+H43) -> 174.28889 | Q43: =(O43+H43)*31*F43*1.5 -> 23712.003 | R43: =P43 -> 174.28889 | S43: =R43/31 -> 5.6222222 | T43: =S43-H43 -> -1.3777778 | U43: =Q43 -> 23712.003 | V43: =_xlfn.XLOOKUP(B43,[1]Sheet1!$B:$B,[1]Sheet1!$P:$P) -> 0.9296875 | W43: =X43/31 -> 5.2269097 | X43: =R43*V43 -> 162.0342 | Y43: =X43*F43*1.5 -> 22044.753 | Z43: =_xlfn.XLOOKUP(B43,[1]Sheet1!$B:$B,[1]Sheet1!$Q:$Q) -> 0.0703125 | AA43: =AB43/31 -> 0.3953125 | AB43: =R43*Z43 -> 12.254687 | AC43: =F43*AB43*1.5 -> 1667.2502 | AD43: 业绩大头，重点降解
A44: CC0823 | B44: 3C-显示器桌面支架4屏 | C44: 马来 | D44: 3C数码 | E44: 电视支架 | F44: 125.34 | G44: 58 | J44: 58 | K44: 10905 | L44: =(G44-(H44*50))/50 -> 1.16 | M44: =31*(L44+H44) -> 35.96 | N44: =M44*F44 -> 4507.2264 | O44: =(G44-(H44*90))/90 -> 0.64444444 | P44: =31*(O44+H44) -> 19.977778 | Q44: =(O44+H44)*31*F44*1.5 -> 3756.022 | R44: =P44 -> 19.977778 | S44: =R44/31 -> 0.64444444 | T44: =S44-H44 -> 0.64444444 | U44: =Q44 -> 3756.022 | V44: =_xlfn.XLOOKUP(B44,[1]Sheet1!$B:$B,[1]Sheet1!$P:$P) -> 0 | W44: =X44/31 -> 0 | X44: =R44*V44 -> 0 | Y44: =X44*F44*1.5 -> 0 | Z44: =_xlfn.XLOOKUP(B44,[1]Sheet1!$B:$B,[1]Sheet1!$Q:$Q) -> 0 | AA44: =AB44/31 -> 0 | AB44: =R44*Z44 -> 0 | AC44: =F44*AB44*1.5 -> 0 | AD44: 长期日销偏低，系列降解
A45: CC0728 | B45: 3C-投影仪支架 | C45: 马来 | D45: 3C数码 | E45: 投影仪支架-2 | F45: 37.42 | G45: 407 | H45: 3 | I45: 135 | J45: 234 | K45: 10534 | L45: =(G45-(H45*50))/50 -> 5.14 | M45: =31*(L45+H45) -> 252.34 | N45: =M45*F45 -> 9442.5628 | O45: =(G45-(H45*90))/90 -> 1.5222222 | P45: =31*(O45+H45) -> 140.18889 | Q45: =(O45+H45)*31*F45*1.5 -> 7868.8023 | R45: =P45 -> 140.18889 | S45: =R45/31 -> 4.5222222 | T45: =S45-H45 -> 1.5222222 | U45: =Q45 -> 7868.8023 | V45: =_xlfn.XLOOKUP(B45,[1]Sheet1!$B:$B,[1]Sheet1!$P:$P) -> 0.67567568 | W45: =X45/31 -> 3.0555556 | X45: =R45*V45 -> 94.722222 | Y45: =X45*F45*1.5 -> 5316.7583 | Z45: =_xlfn.XLOOKUP(B45,[1]Sheet1!$B:$B,[1]Sheet1!$Q:$Q) -> 0.32432432 | AA45: =AB45/31 -> 1.4666667 | AB45: =R45*Z45 -> 45.466667 | AC45: =F45*AB45*1.5 -> 2552.044 | AD45: 长期日销偏低，系列降解
A46: CC0102 | B46: 3B-便携式点钞机V30 | C46: 马来 | D46: 办公安防 | E46: 点钞机 | F46: 115.68 | G46: 60 | J46: 60 | K46: 10411 | L46: =(G46-(H46*50))/50 -> 1.2 | M46: =31*(L46+H46) -> 37.2 | N46: =M46*F46 -> 4303.296 | O46: =(G46-(H46*90))/90 -> 0.66666667 | P46: =31*(O46+H46) -> 20.666667 | Q46: =(O46+H46)*31*F46*1.5 -> 3586.08 | R46: =P46 -> 20.666667 | S46: =R46/31 -> 0.66666667 | T46: =S46-H46 -> 0.66666667 | U46: =Q46 -> 3586.08 | V46: =_xlfn.XLOOKUP(B46,[1]Sheet1!$B:$B,[1]Sheet1!$P:$P) -> 0 | W46: =X46/31 -> 0 | X46: =R46*V46 -> 0 | Y46: =X46*F46*1.5 -> 0 | Z46: =_xlfn.XLOOKUP(B46,[1]Sheet1!$B:$B,[1]Sheet1!$Q:$Q) -> 0 | AA46: =AB46/31 -> 0 | AB46: =R46*Z46 -> 0 | AC46: =F46*AB46*1.5 -> 0 | AD46: 新品主推产品，重点降解
A47: CC0611 | B47: 3B-碎纸机10L | C47: 马来 | D47: 办公安防 | E47: 碎纸机 | F47: 83.69 | G47: 546 | H47: 8 | I47: 68 | J47: 120 | K47: 10043 | L47: =(G47-(H47*50))/50 -> 2.92 | M47: =31*(L47+H47) -> 338.52 | N47: =M47*F47 -> 28330.739 | O47: =(G47-(H47*90))/90 -> -1.9333333 | P47: =31*(O47+H47) -> 188.06667 | Q47: =(O47+H47)*31*F47*1.5 -> 23608.949 | R47: =P47 -> 188.06667 | S47: =R47/31 -> 6.0666667 | T47: =S47-H47 -> -1.9333333 | U47: =Q47 -> 23608.949 | V47: =_xlfn.XLOOKUP(B47,[1]Sheet1!$B:$B,[1]Sheet1!$P:$P) -> 0.68627451 | W47: =X47/31 -> 4.1633987 | X47: =R47*V47 -> 129.06536 | Y47: =X47*F47*1.5 -> 16202.22 | Z47: =_xlfn.XLOOKUP(B47,[1]Sheet1!$B:$B,[1]Sheet1!$Q:$Q) -> 0.31372549 | AA47: =AB47/31 -> 1.903268 | AB47: =R47*Z47 -> 59.001307 | AC47: =F47*AB47*1.5 -> 7406.7291 | AD47: 主推产品，重点降解
A48: CC0386 | B48: 3B-可翻转白板50*70 | C48: 马来 | D48: 办公安防 | E48: 教具白板 | F48: 80.32 | G48: 289 | H48: 3 | I48: 96 | J48: 124 | K48: 9960 | L48: =(G48-(H48*50))/50 -> 2.78 | M48: =31*(L48+H48) -> 179.18 | N48: =M48*F48 -> 14391.738 | O48: =(G48-(H48*90))/90 -> 0.21111111 | P48: =31*(O48+H48) -> 99.544444 | Q48: =(O48+H48)*31*F48*1.5 -> 11993.115 | R48: =P48 -> 99.544444 | S48: =R48/31 -> 3.2111111 | T48: =S48-H48 -> 0.21111111 | U48: =Q48 -> 11993.115 | V48: =_xlfn.XLOOKUP(B48,[1]Sheet1!$B:$B,[1]Sheet1!$P:$P) -> 0.81632653 | W48: =X48/31 -> 2.6213152 | X48: =R48*V48 -> 81.260771 | Y48: =X48*F48*1.5 -> 9790.2977 | Z48: =_xlfn.XLOOKUP(B48,[1]Sheet1!$B:$B,[1]Sheet1!$Q:$Q) -> 0.18367347 | AA48: =AB48/31 -> 0.58979592 | AB48: =R48*Z48 -> 18.283673 | AC48: =F48*AB48*1.5 -> 2202.817 | AD48: 长期日销偏低，系列降解
A49: CC0633 | B49: 3C-跟拍自动支撑自拍杆Q625 | C49: 马来 | D49: 3C数码 | E49: 自拍杆 | F49: 79.73 | G49: 80 | J49: 80 | K49: 9568 | L49: =(G49-(H49*50))/50 -> 1.6 | M49: =31*(L49+H49) -> 49.6 | N49: =M49*F49 -> 3954.608 | O49: =(G49-(H49*90))/90 -> 0.88888889 | P49: =31*(O49+H49) -> 27.555556 | Q49: =(O49+H49)*31*F49*1.5 -> 3295.5067 | R49: =P49 -> 27.555556 | S49: =R49/31 -> 0.88888889 | T49: =S49-H49 -> 0.88888889 | U49: =Q49 -> 3295.5067 | V49: =_xlfn.XLOOKUP(B49,[1]Sheet1!$B:$B,[1]Sheet1!$P:$P) -> 0 | W49: =X49/31 -> 0 | X49: =R49*V49 -> 0 | Y49: =X49*F49*1.5 -> 0 | Z49: =_xlfn.XLOOKUP(B49,[1]Sheet1!$B:$B,[1]Sheet1!$Q:$Q) -> 0 | AA49: =AB49/31 -> 0 | AB49: =R49*Z49 -> 0 | AC49: =F49*AB49*1.5 -> 0 | AD49: 新品长期动销不住
A50: CC1008 | B50: 3C-投影仪支架1.2米 | C50: 马来 | D50: 3C数码 | E50: 投影仪支架 | F50: 17.1 | G50: 509 | H50: 2 | I50: 254 | J50: 394 | K50: 9320 | L50: =(G50-(H50*50))/50 -> 8.18 | M50: =31*(L50+H50) -> 315.58 | N50: =M50*F50 -> 5396.418 | O50: =(G50-(H50*90))/90 -> 3.6555556 | P50: =31*(O50+H50) -> 175.32222 | Q50: =(O50+H50)*31*F50*1.5 -> 4497.015 | R50: =P50 -> 175.32222 | S50: =R50/31 -> 5.6555556 | T50: =S50-H50 -> 3.6555556 | U50: =Q50 -> 4497.015 | V50: =_xlfn.XLOOKUP(B50,[1]Sheet1!$B:$B,[1]Sheet1!$P:$P) -> 0.94594595 | W50: =X50/31 -> 5.3498498 | X50: =R50*V50 -> 165.84535 | Y50: =X50*F50*1.5 -> 4253.9331 | Z50: =_xlfn.XLOOKUP(B50,[1]Sheet1!$B:$B,[1]Sheet1!$Q:$Q) -> 0.054054054 | AA50: =AB50/31 -> 0.30570571 | AB50: =R50*Z50 -> 9.4768769 | AC50: =F50*AB50*1.5 -> 243.08189 | AD50: 长期日销偏低，系列降解
A51: CC0769 | B51: 3B-R5A房间门锁单锁舌四功能不带APP | C51: 马来 | D51: 办公安防 | E51: 密码锁 | F51: 127.26 | G51: 64 | J51: 51 | K51: 9035 | L51: =(G51-(H51*50))/50 -> 1.28 | M51: =31*(L51+H51) -> 39.68 | N51: =M51*F51 -> 5049.6768 | O51: =(G51-(H51*90))/90 -> 0.71111111 | P51: =31*(O51+H51) -> 22.044444 | Q51: =(O51+H51)*31*F51*1.5 -> 4208.064 | R51: =P51 -> 22.044444 | S51: =R51/31 -> 0.71111111 | T51: =S51-H51 -> 0.71111111 | U51: =Q51 -> 4208.064 | V51: =_xlfn.XLOOKUP(B51,[1]Sheet1!$B:$B,[1]Sheet1!$P:$P) -> 1 | W51: =X51/31 -> 0.71111111 | X51: =R51*V51 -> 22.044444 | Y51: =X51*F51*1.5 -> 4208.064 | Z51: =_xlfn.XLOOKUP(B51,[1]Sheet1!$B:$B,[1]Sheet1!$Q:$Q) -> 0 | AA51: =AB51/31 -> 0 | AB51: =R51*Z51 -> 0 | AC51: =F51*AB51*1.5 -> 0 | AD51: 长期日销偏低，系列降解
A52: CC0741 | B52: 3B-WIFI漏电多功能导轨表彩屏6显款2P63A | C52: 马来 | D52: 办公安防 | E52: 单相电子式电度表 | F52: 59.66 | G52: 100 | J52: 100 | K52: 8949 | L52: =(G52-(H52*50))/50 -> 2 | M52: =31*(L52+H52) -> 62 | N52: =M52*F52 -> 3698.92 | O52: =(G52-(H52*90))/90 -> 1.1111111 | P52: =31*(O52+H52) -> 34.444444 | Q52: =(O52+H52)*31*F52*1.5 -> 3082.4333 | R52: =P52 -> 34.444444 | S52: =R52/31 -> 1.1111111 | T52: =S52-H52 -> 1.1111111 | U52: =Q52 -> 3082.4333 | V52: =_xlfn.XLOOKUP(B52,[1]Sheet1!$B:$B,[1]Sheet1!$P:$P) -> 0 | W52: =X52/31 -> 0 | X52: =R52*V52 -> 0 | Y52: =X52*F52*1.5 -> 0 | Z52: =_xlfn.XLOOKUP(B52,[1]Sheet1!$B:$B,[1]Sheet1!$Q:$Q) -> 0 | AA52: =AB52/31 -> 0 | AB52: =R52*Z52 -> 0 | AC52: =F52*AB52*1.5 -> 0 | AD52: 新品降解
A53: CC0878 | B53: 3B-U9五功能玻璃门智能锁带TUYAAPP | C53: 马来 | D53: 办公安防 | E53: 智能锁 | F53: 94.25 | G53: 62 | J53: 62 | K53: 8765 | L53: =(G53-(H53*50))/50 -> 1.24 | M53: =31*(L53+H53) -> 38.44 | N53: =M53*F53 -> 3622.97 | O53: =(G53-(H53*90))/90 -> 0.68888889 | P53: =31*(O53+H53) -> 21.355556 | Q53: =(O53+H53)*31*F53*1.5 -> 3019.1417 | R53: =P53 -> 21.355556 | S53: =R53/31 -> 0.68888889 | T53: =S53-H53 -> 0.68888889 | U53: =Q53 -> 3019.1417 | V53: =_xlfn.XLOOKUP(B53,[1]Sheet1!$B:$B,[1]Sheet1!$P:$P) -> 0 | W53: =X53/31 -> 0 | X53: =R53*V53 -> 0 | Y53: =X53*F53*1.5 -> 0 | Z53: =_xlfn.XLOOKUP(B53,[1]Sheet1!$B:$B,[1]Sheet1!$Q:$Q) -> 0 | AA53: =AB53/31 -> 0 | AB53: =R53*Z53 -> 0 | AC53: =F53*AB53*1.5 -> 0 | AD53: 呆滞品，定向清理
A54: CC0605 | B54: 3C-插电式分体电动旋转盘黑色13cm | C54: 马来 | D54: 3C数码 | E54: 展示台 | F54: 16.54 | G54: 602 | H54: 3 | I54: 200 | J54: 404 | K54: 8708 | L54: =(G54-(H54*50))/50 -> 9.04 | M54: =31*(L54+H54) -> 373.24 | N54: =M54*F54 -> 6173.3896 | O54: =(G54-(H54*90))/90 -> 3.6888889 | P54: =31*(O54+H54) -> 207.35556 | Q54: =(O54+H54)*31*F54*1.5 -> 5144.4913 | R54: =P54 -> 207.35556 | S54: =R54/31 -> 6.6888889 | T54: =S54-H54 -> 3.6888889 | U54: =Q54 -> 5144.4913 | V54: =_xlfn.XLOOKUP(B54,[1]Sheet1!$B:$B,[1]Sheet1!$P:$P) -> 0.859375 | W54: =X54/31 -> 5.7482639 | X54: =R54*V54 -> 178.19618 | Y54: =X54*F54*1.5 -> 4421.0472 | Z54: =_xlfn.XLOOKUP(B54,[1]Sheet1!$B:$B,[1]Sheet1!$Q:$Q) -> 0.140625 | AA54: =AB54/31 -> 0.940625 | AB54: =R54*Z54 -> 29.159375 | AC54: =F54*AB54*1.5 -> 723.44409 | AD54: 长期日销偏低，系列降解
A55: CC0297 | B55: 3B-新A6保险箱密码款35cm*26cm*25cm | C55: 马来 | D55: 办公安防 | E55: 保险箱 | F55: 175.07 | G55: 45 | J55: 35 | K55: 8491 | L55: =(G55-(H55*50))/50 -> 0.9 | M55: =31*(L55+H55) -> 27.9 | N55: =M55*F55 -> 4884.453 | O55: =(G55-(H55*90))/90 -> 0.5 | P55: =31*(O55+H55) -> 15.5 | Q55: =(O55+H55)*31*F55*1.5 -> 4070.3775 | R55: =P55 -> 15.5 | S55: =R55/31 -> 0.5 | T55: =S55-H55 -> 0.5 | U55: =Q55 -> 4070.3775 | V55: =_xlfn.XLOOKUP(B55,[1]Sheet1!$B:$B,[1]Sheet1!$P:$P) -> 1 | W55: =X55/31 -> 0.5 | X55: =R55*V55 -> 15.5 | Y55: =X55*F55*1.5 -> 4070.3775 | Z55: =_xlfn.XLOOKUP(B55,[1]Sheet1!$B:$B,[1]Sheet1!$Q:$Q) -> 0 | AA55: =AB55/31 -> 0 | AB55: =R55*Z55 -> 0 | AC55: =F55*AB55*1.5 -> 0 | AD55: 新品主推产品，重点降解
A56: CC0830 | B56: 3C-RGB全透明动圈降噪桌面麦克风 | C56: 马来 | D56: 3C数码 | E56: 有线麦克风 | F56: 80.27 | G56: 70 | J56: 69 | K56: 8268 | L56: =(G56-(H56*50))/50 -> 1.4 | M56: =31*(L56+H56) -> 43.4 | N56: =M56*F56 -> 3483.718 | O56: =(G56-(H56*90))/90 -> 0.77777778 | P56: =31*(O56+H56) -> 24.111111 | Q56: =(O56+H56)*31*F56*1.5 -> 2903.0983 | R56: =P56 -> 24.111111 | S56: =R56/31 -> 0.77777778 | T56: =S56-H56 -> 0.77777778 | U56: =Q56 -> 2903.0983 | V56: =_xlfn.XLOOKUP(B56,[1]Sheet1!$B:$B,[1]Sheet1!$P:$P) -> 0 | W56: =X56/31 -> 0 | X56: =R56*V56 -> 0 | Y56: =X56*F56*1.5 -> 0 | Z56: =_xlfn.XLOOKUP(B56,[1]Sheet1!$B:$B,[1]Sheet1!$Q:$Q) -> 1 | AA56: =AB56/31 -> 0.77777778 | AB56: =R56*Z56 -> 24.111111 | AC56: =F56*AB56*1.5 -> 2903.0983 | AD56: 新品长期动销不住
A57: CC0780 | B57: 3C-圆筒投影仪白色 | C57: 马来 | D57: 3C数码 | E57: 投影仪 | F57: 171.26 | G57: 52 | J57: 36 | K57: 8135 | L57: =(G57-(H57*50))/50 -> 1.04 | M57: =31*(L57+H57) -> 32.24 | N57: =M57*F57 -> 5521.4224 | O57: =(G57-(H57*90))/90 -> 0.57777778 | P57: =31*(O57+H57) -> 17.911111 | Q57: =(O57+H57)*31*F57*1.5 -> 4601.1853 | R57: =P57 -> 17.911111 | S57: =R57/31 -> 0.57777778 | T57: =S57-H57 -> 0.57777778 | U57: =Q57 -> 4601.1853 | V57: =_xlfn.XLOOKUP(B57,[1]Sheet1!$B:$B,[1]Sheet1!$P:$P) -> 0 | W57: =X57/31 -> 0 | X57: =R57*V57 -> 0 | Y57: =X57*F57*1.5 -> 0 | Z57: =_xlfn.XLOOKUP(B57,[1]Sheet1!$B:$B,[1]Sheet1!$Q:$Q) -> 1 | AA57: =AB57/31 -> 0.57777778 | AB57: =R57*Z57 -> 17.911111 | AC57: =F57*AB57*1.5 -> 4601.1853 | AD57: 长期日销偏低，系列降解
A58: CC0490 | B58: 3C-组合双臂显示器支架 | C58: 马来 | D58: 3C数码 | E58: 显示器支架 | F58: 95.4554 | G58: 799 | H58: 14 | I58: 57 | J58: 83 | K58: 7923 | L58: =(G58-(H58*50))/50 -> 1.98 | M58: =31*(L58+H58) -> 495.38 | N58: =M58*F58 -> 47286.696 | O58: =(G58-(H58*90))/90 -> -5.1222222 | P58: =31*(O58+H58) -> 275.21111 | Q58: =(O58+H58)*31*F58*1.5 -> 39405.58 | R58: =P58 -> 275.21111 | S58: =R58/31 -> 8.8777778 | T58: =S58-H58 -> -5.1222222 | U58: =Q58 -> 39405.58 | V58: =_xlfn.XLOOKUP(B58,[1]Sheet1!$B:$B,[1]Sheet1!$P:$P) -> 0.65104167 | W58: =X58/31 -> 5.7798032 | X58: =R58*V58 -> 179.1739 | Y58: =X58*F58*1.5 -> 25654.675 | Z58: =_xlfn.XLOOKUP(B58,[1]Sheet1!$B:$B,[1]Sheet1!$Q:$Q) -> 0.34895833 | AA58: =AB58/31 -> 3.0979745 | AB58: =R58*Z58 -> 96.037211 | AC58: =F58*AB58*1.5 -> 13750.906
A59: CC0430 | B59: 3C-翻页笔 | C59: 马来 | D59: 3C数码 | E59: 翻页笔 | F59: 19.49 | G59: 349 | H59: 1 | I59: 349 | J59: 278 | K59: 7572 | L59: =(G59-(H59*50))/50 -> 5.98 | M59: =31*(L59+H59) -> 216.38 | N59: =M59*F59 -> 4217.2462 | O59: =(G59-(H59*90))/90 -> 2.8777778 | P59: =31*(O59+H59) -> 120.21111 | Q59: =(O59+H59)*31*F59*1.5 -> 3514.3718 | R59: =P59 -> 120.21111 | S59: =R59/31 -> 3.8777778 | T59: =S59-H59 -> 2.8777778 | U59: =Q59 -> 3514.3718 | V59: =_xlfn.XLOOKUP(B59,[1]Sheet1!$B:$B,[1]Sheet1!$P:$P) -> 0.57692308 | W59: =X59/31 -> 2.2371795 | X59: =R59*V59 -> 69.352564 | Y59: =X59*F59*1.5 -> 2027.5222 | Z59: =_xlfn.XLOOKUP(B59,[1]Sheet1!$B:$B,[1]Sheet1!$Q:$Q) -> 0.42307692 | AA59: =AB59/31 -> 1.6405983 | AB59: =R59*Z59 -> 50.858547 | AC59: =F59*AB59*1.5 -> 1486.8496 | AD59: 呆滞品，定向清理
A60: CC0887 | B60: 3B-交换机机柜45cm | C60: 马来 | D60: 办公安防 | E60: 金属制品机柜 | F60: 102.79 | G60: 50 | J60: 49 | K60: 7504 | L60: =(G60-(H60*50))/50 -> 1 | M60: =31*(L60+H60) -> 31 | N60: =M60*F60 -> 3186.49 | O60: =(G60-(H60*90))/90 -> 0.55555556 | P60: =31*(O60+H60) -> 17.222222 | Q60: =(O60+H60)*31*F60*1.5 -> 2655.4083 | R60: =P60 -> 17.222222 | S60: =R60/31 -> 0.55555556 | T60: =S60-H60 -> 0.55555556 | U60: =Q60 -> 2655.4083 | V60: =_xlfn.XLOOKUP(B60,[1]Sheet1!$B:$B,[1]Sheet1!$P:$P) -> 0 | W60: =X60/31 -> 0 | X60: =R60*V60 -> 0 | Y60: =X60*F60*1.5 -> 0 | Z60: =_xlfn.XLOOKUP(B60,[1]Sheet1!$B:$B,[1]Sheet1!$Q:$Q) -> 1 | AA60: =AB60/31 -> 0.55555556 | AB60: =R60*Z60 -> 17.222222 | AC60: =F60*AB60*1.5 -> 2655.4083 | AD60: 新品降解
A61: CC0942 | B61: 3B-WIFI漏电多功能导轨表彩屏款2P63A | C61: 马来 | D61: 办公安防 | E61: 单相电子式电度表 | F61: 50.85 | G61: 99 | J61: 98 | K61: 7450 | L61: =(G61-(H61*50))/50 -> 1.98 | M61: =31*(L61+H61) -> 61.38 | N61: =M61*F61 -> 3121.173 | O61: =(G61-(H61*90))/90 -> 1.1 | P61: =31*(O61+H61) -> 34.1 | Q61: =(O61+H61)*31*F61*1.5 -> 2600.9775 | R61: =P61 -> 34.1 | S61: =R61/31 -> 1.1 | T61: =S61-H61 -> 1.1 | U61: =Q61 -> 2600.9775 | V61: =_xlfn.XLOOKUP(B61,[1]Sheet1!$B:$B,[1]Sheet1!$P:$P) -> 0 | W61: =X61/31 -> 0 | X61: =R61*V61 -> 0 | Y61: =X61*F61*1.5 -> 0 | Z61: =_xlfn.XLOOKUP(B61,[1]Sheet1!$B:$B,[1]Sheet1!$Q:$Q) -> 0 | AA61: =AB61/31 -> 0 | AB61: =R61*Z61 -> 0 | AC61: =F61*AB61*1.5 -> 0 | AD61: 新品降解
A62: CC0998 | B62: 3C-双扇散热支架5档调节 | C62: 马来 | D62: 3C数码 | E62: 电脑散热器 | F62: 27.04 | G62: 195 | J62: 180 | K62: 7139 | L62: =(G62-(H62*50))/50 -> 3.9 | M62: =31*(L62+H62) -> 120.9 | N62: =M62*F62 -> 3269.136 | O62: =(G62-(H62*90))/90 -> 2.1666667 | P62: =31*(O62+H62) -> 67.166667 | Q62: =(O62+H62)*31*F62*1.5 -> 2724.28 | R62: =P62 -> 67.166667 | S62: =R62/31 -> 2.1666667 | T62: =S62-H62 -> 2.1666667 | U62: =Q62 -> 2724.28 | V62: =_xlfn.XLOOKUP(B62,[1]Sheet1!$B:$B,[1]Sheet1!$P:$P) -> 0.33333333 | W62: =X62/31 -> 0.72222222 | X62: =R62*V62 -> 22.388889 | Y62: =X62*F62*1.5 -> 908.09333 | Z62: =_xlfn.XLOOKUP(B62,[1]Sheet1!$B:$B,[1]Sheet1!$Q:$Q) -> 0.66666667 | AA62: =AB62/31 -> 1.4444444 | AB62: =R62*Z62 -> 44.777778 | AC62: =F62*AB62*1.5 -> 1816.1867 | AD62: 长期日销偏低，系列降解
A63: CC0138 | B63: 3B-保险箱黑 | C63: 马来 | D63: 办公安防 | E63: 保险箱 | F63: 90.58 | G63: 413 | H63: 6 | I63: 68 | J63: 77 | K63: 6975 | L63: =(G63-(H63*50))/50 -> 2.26 | M63: =31*(L63+H63) -> 256.06 | N63: =M63*F63 -> 23193.915 | O63: =(G63-(H63*90))/90 -> -1.4111111 | P63: =31*(O63+H63) -> 142.25556 | Q63: =(O63+H63)*31*F63*1.5 -> 19328.262 | R63: =P63 -> 142.25556 | S63: =R63/31 -> 4.5888889 | T63: =S63-H63 -> -1.4111111 | U63: =Q63 -> 19328.262 | V63: =_xlfn.XLOOKUP(B63,[1]Sheet1!$B:$B,[1]Sheet1!$P:$P) -> 0.50684932 | W63: =X63/31 -> 2.3258752 | X63: =R63*V63 -> 72.102131 | Y63: =X63*F63*1.5 -> 9796.5165 | Z63: =_xlfn.XLOOKUP(B63,[1]Sheet1!$B:$B,[1]Sheet1!$Q:$Q) -> 0.49315068 | AA63: =AB63/31 -> 2.2630137 | AB63: =R63*Z63 -> 70.153425 | AC63: =F63*AB63*1.5 -> 9531.7458 | AD63: 主推产品，重点降解
A64: CC0235 | B64: 3C-相机三脚架160cm | C64: 马来 | D64: 3C数码 | E64: 三脚架 | F64: 44.15 | G64: 110 | J64: 104 | K64: 6777 | L64: =(G64-(H64*50))/50 -> 2.2 | M64: =31*(L64+H64) -> 68.2 | N64: =M64*F64 -> 3011.03 | O64: =(G64-(H64*90))/90 -> 1.2222222 | P64: =31*(O64+H64) -> 37.888889 | Q64: =(O64+H64)*31*F64*1.5 -> 2509.1917 | R64: =P64 -> 37.888889 | S64: =R64/31 -> 1.2222222 | T64: =S64-H64 -> 1.2222222 | U64: =Q64 -> 2509.1917 | V64: =_xlfn.XLOOKUP(B64,[1]Sheet1!$B:$B,[1]Sheet1!$P:$P) -> 0 | W64: =X64/31 -> 0 | X64: =R64*V64 -> 0 | Y64: =X64*F64*1.5 -> 0 | Z64: =_xlfn.XLOOKUP(B64,[1]Sheet1!$B:$B,[1]Sheet1!$Q:$Q) -> 0 | AA64: =AB64/31 -> 0 | AB64: =R64*Z64 -> 0 | AC64: =F64*AB64*1.5 -> 0 | AD64: 呆滞品，定向清理
A65: CC0280 | B65: 3B-306CWiFi路由器 | C65: 马来 | D65: 办公安防 | E65: 路由器 | F65: 109.41 | G65: 47 | J65: 42 | K65: 6674 | L65: =(G65-(H65*50))/50 -> 0.94 | M65: =31*(L65+H65) -> 29.14 | N65: =M65*F65 -> 3188.2074 | O65: =(G65-(H65*90))/90 -> 0.52222222 | P65: =31*(O65+H65) -> 16.188889 | Q65: =(O65+H65)*31*F65*1.5 -> 2656.8395 | R65: =P65 -> 16.188889 | S65: =R65/31 -> 0.52222222 | T65: =S65-H65 -> 0.52222222 | U65: =Q65 -> 2656.8395 | V65: =_xlfn.XLOOKUP(B65,[1]Sheet1!$B:$B,[1]Sheet1!$P:$P) -> 1 | W65: =X65/31 -> 0.52222222 | X65: =R65*V65 -> 16.188889 | Y65: =X65*F65*1.5 -> 2656.8395 | Z65: =_xlfn.XLOOKUP(B65,[1]Sheet1!$B:$B,[1]Sheet1!$Q:$Q) -> 0 | AA65: =AB65/31 -> 0 | AB65: =R65*Z65 -> 0 | AC65: =F65*AB65*1.5 -> 0 | AD65: 呆滞品，定向清理
A66: CC0036 | B66: 3C-桌面显示器支架钢化玻璃底座 | C66: 马来 | D66: 3C数码 | E66: 显示器支架 | F66: 47.82 | G66: 251 | H66: 2 | I66: 125 | J66: 123 | K66: 6360 | L66: =(G66-(H66*50))/50 -> 3.02 | M66: =31*(L66+H66) -> 155.62 | N66: =M66*F66 -> 7441.7484 | O66: =(G66-(H66*90))/90 -> 0.78888889 | P66: =31*(O66+H66) -> 86.455556 | Q66: =(O66+H66)*31*F66*1.5 -> 6201.457 | R66: =P66 -> 86.455556 | S66: =R66/31 -> 2.7888889 | T66: =S66-H66 -> 0.78888889 | U66: =Q66 -> 6201.457 | V66: =_xlfn.XLOOKUP(B66,[1]Sheet1!$B:$B,[1]Sheet1!$P:$P) -> 0.1875 | W66: =X66/31 -> 0.52291667 | X66: =R66*V66 -> 16.210417 | Y66: =X66*F66*1.5 -> 1162.7732 | Z66: =_xlfn.XLOOKUP(B66,[1]Sheet1!$B:$B,[1]Sheet1!$Q:$Q) -> 0.8125 | AA66: =AB66/31 -> 2.2659722 | AB66: =R66*Z66 -> 70.245139 | AC66: =F66*AB66*1.5 -> 5038.6838 | AD66: 主推产品，重点降解
A67: CC0790 | B67: 3B-交换机机柜30cm | C67: 马来 | D67: 办公安防 | E67: 金属制品机柜 | F67: 87.02 | G67: 50 | J67: 49 | K67: 6352 | L67: =(G67-(H67*50))/50 -> 1 | M67: =31*(L67+H67) -> 31 | N67: =M67*F67 -> 2697.62 | O67: =(G67-(H67*90))/90 -> 0.55555556 | P67: =31*(O67+H67) -> 17.222222 | Q67: =(O67+H67)*31*F67*1.5 -> 2248.0167 | R67: =P67 -> 17.222222 | S67: =R67/31 -> 0.55555556 | T67: =S67-H67 -> 0.55555556 | U67: =Q67 -> 2248.0167 | V67: =_xlfn.XLOOKUP(B67,[1]Sheet1!$B:$B,[1]Sheet1!$P:$P) -> 0 | W67: =X67/31 -> 0 | X67: =R67*V67 -> 0 | Y67: =X67*F67*1.5 -> 0 | Z67: =_xlfn.XLOOKUP(B67,[1]Sheet1!$B:$B,[1]Sheet1!$Q:$Q) -> 0 | AA67: =AB67/31 -> 0 | AB67: =R67*Z67 -> 0 | AC67: =F67*AB67*1.5 -> 0 | AD67: 定点降解
A68: CC0976 | B68: 3B-打孔机 | C68: 马来 | D68: 办公安防 | E68: 装订机 | F68: 116.93 | G68: 143 | H68: 1 | I68: 143 | J68: 53 | K68: 6197 | L68: =(G68-(H68*50))/50 -> 1.86 | M68: =31*(L68+H68) -> 88.66 | N68: =M68*F68 -> 10367.014 | O68: =(G68-(H68*90))/90 -> 0.58888889 | P68: =31*(O68+H68) -> 49.255556 | Q68: =(O68+H68)*31*F68*1.5 -> 8639.1782 | R68: =P68 -> 49.255556 | S68: =R68/31 -> 1.5888889 | T68: =S68-H68 -> 0.58888889 | U68: =Q68 -> 8639.1782 | V68: =_xlfn.XLOOKUP(B68,[1]Sheet1!$B:$B,[1]Sheet1!$P:$P) -> 0.20833333 | W68: =X68/31 -> 0.33101852 | X68: =R68*V68 -> 10.261574 | Y68: =X68*F68*1.5 -> 1799.8288 | Z68: =_xlfn.XLOOKUP(B68,[1]Sheet1!$B:$B,[1]Sheet1!$Q:$Q) -> 0.79166667 | AA68: =AB68/31 -> 1.2578704 | AB68: =R68*Z68 -> 38.993981 | AC68: =F68*AB68*1.5 -> 6839.3494 | AD68: 新品长期动销不住
A69: CC0729 | B69: 3C-led智能互动屏59.5cm*12cm | C69: 马来 | D69: 3C数码 | E69: LED像素屏 | F69: 157.1 | G69: 76 | J69: 36 | K69: 5970 | L69: =(G69-(H69*50))/50 -> 1.52 | M69: =31*(L69+H69) -> 47.12 | N69: =M69*F69 -> 7402.552 | O69: =(G69-(H69*90))/90 -> 0.84444444 | P69: =31*(O69+H69) -> 26.177778 | Q69: =(O69+H69)*31*F69*1.5 -> 6168.7933 | R69: =P69 -> 26.177778 | S69: =R69/31 -> 0.84444444 | T69: =S69-H69 -> 0.84444444 | U69: =Q69 -> 6168.7933 | V69: =_xlfn.XLOOKUP(B69,[1]Sheet1!$B:$B,[1]Sheet1!$P:$P) -> 0.33333333 | W69: =X69/31 -> 0.28148148 | X69: =R69*V69 -> 8.7259259 | Y69: =X69*F69*1.5 -> 2056.2644 | Z69: =_xlfn.XLOOKUP(B69,[1]Sheet1!$B:$B,[1]Sheet1!$Q:$Q) -> 0.66666667 | AA69: =AB69/31 -> 0.56296296 | AB69: =R69*Z69 -> 17.451852 | AC69: =F69*AB69*1.5 -> 4112.5289 | AD69: 呆滞品，定向清理
A70: CC0814 | B70: 3C-RGB电容悬臂支架降噪麦克风 | C70: 马来 | D70: 3C数码 | E70: 有线麦克风 | F70: 110.29 | G70: 39 | J70: 36 | K70: 5790 | L70: =(G70-(H70*50))/50 -> 0.78 | M70: =31*(L70+H70) -> 24.18 | N70: =M70*F70 -> 2666.8122 | O70: =(G70-(H70*90))/90 -> 0.43333333 | P70: =31*(O70+H70) -> 13.433333 | Q70: =(O70+H70)*31*F70*1.5 -> 2222.3435 | R70: =P70 -> 13.433333 | S70: =R70/31 -> 0.43333333 | T70: =S70-H70 -> 0.43333333 | U70: =Q70 -> 2222.3435 | V70: =_xlfn.XLOOKUP(B70,[1]Sheet1!$B:$B,[1]Sheet1!$P:$P) -> 0 | W70: =X70/31 -> 0 | X70: =R70*V70 -> 0 | Y70: =X70*F70*1.5 -> 0 | Z70: =_xlfn.XLOOKUP(B70,[1]Sheet1!$B:$B,[1]Sheet1!$Q:$Q) -> 1 | AA70: =AB70/31 -> 0.43333333 | AB70: =R70*Z70 -> 13.433333 | AC70: =F70*AB70*1.5 -> 2222.3435 | AD70: 新品长期动销不住
A71: CC0801 | B71: 3B-道路广角镜60cm | C71: 马来 | D71: 办公安防 | E71: 道路反光镜 | F71: 53.22 | G71: 152 | H71: 1 | I71: 152 | J71: 89 | K71: 5748 | L71: =(G71-(H71*50))/50 -> 2.04 | M71: =31*(L71+H71) -> 94.24 | N71: =M71*F71 -> 5015.4528 | O71: =(G71-(H71*90))/90 -> 0.68888889 | P71: =31*(O71+H71) -> 52.355556 | Q71: =(O71+H71)*31*F71*1.5 -> 4179.544 | R71: =P71 -> 52.355556 | S71: =R71/31 -> 1.6888889 | T71: =S71-H71 -> 0.68888889 | U71: =Q71 -> 4179.544 | V71: =_xlfn.XLOOKUP(B71,[1]Sheet1!$B:$B,[1]Sheet1!$P:$P) -> 0.33333333 | W71: =X71/31 -> 0.56296296 | X71: =R71*V71 -> 17.451852 | Y71: =X71*F71*1.5 -> 1393.1813 | Z71: =_xlfn.XLOOKUP(B71,[1]Sheet1!$B:$B,[1]Sheet1!$Q:$Q) -> 0.66666667 | AA71: =AB71/31 -> 1.1259259 | AB71: =R71*Z71 -> 34.903704 | AC71: =F71*AB71*1.5 -> 2786.3627 | AD71: 长期日销偏低，系列降解
A72: CC0800 | B72: 3C-电视壁挂架小一体 | C72: 马来 | D72: 3C数码 | E72: 电视支架 | F72: 7.5 | G72: 1613 | H72: 17 | I72: 94 | J72: 736 | K72: 5655 | L72: =(G72-(H72*50))/50 -> 15.26 | M72: =31*(L72+H72) -> 1000.06 | N72: =M72*F72 -> 7500.45 | O72: =(G72-(H72*90))/90 -> 0.92222222 | P72: =31*(O72+H72) -> 555.58889 | Q72: =(O72+H72)*31*F72*1.5 -> 6250.375 | R72: =P72 -> 555.58889 | S72: =R72/31 -> 17.922222 | T72: =S72-H72 -> 0.92222222 | U72: =Q72 -> 6250.375 | V72: =_xlfn.XLOOKUP(B72,[1]Sheet1!$B:$B,[1]Sheet1!$P:$P) -> 0.52325581 | W72: =X72/31 -> 9.377907 | X72: =R72*V72 -> 290.71512 | Y72: =X72*F72*1.5 -> 3270.5451 | Z72: =_xlfn.XLOOKUP(B72,[1]Sheet1!$B:$B,[1]Sheet1!$Q:$Q) -> 0.47674419 | AA72: =AB72/31 -> 8.5443152 | AB72: =R72*Z72 -> 264.87377 | AC72: =F72*AB72*1.5 -> 2979.8299 | AD72: 新品降解
A73: CC0265 | B73: 3B-H1AP五功能防盗门锁带APP | C73: 马来 | D73: 办公安防 | E73: 密码锁 | F73: 169.9 | G73: 29 | J73: 23 | K73: 5437 | L73: =(G73-(H73*50))/50 -> 0.58 | M73: =31*(L73+H73) -> 17.98 | N73: =M73*F73 -> 3054.802 | O73: =(G73-(H73*90))/90 -> 0.32222222 | P73: =31*(O73+H73) -> 9.9888889 | Q73: =(O73+H73)*31*F73*1.5 -> 2545.6683 | R73: =P73 -> 9.9888889 | S73: =R73/31 -> 0.32222222 | T73: =S73-H73 -> 0.32222222 | U73: =Q73 -> 2545.6683 | V73: =_xlfn.XLOOKUP(B73,[1]Sheet1!$B:$B,[1]Sheet1!$P:$P) -> 1 | W73: =X73/31 -> 0.32222222 | X73: =R73*V73 -> 9.9888889 | Y73: =X73*F73*1.5 -> 2545.6683 | Z73: =_xlfn.XLOOKUP(B73,[1]Sheet1!$B:$B,[1]Sheet1!$Q:$Q) -> 0 | AA73: =AB73/31 -> 0 | AB73: =R73*Z73 -> 0 | AC73: =F73*AB73*1.5 -> 0 | AD73: 定点降解 | AE73: 保险箱送
A74: CC0938 | B74: 3C-电脑机箱T6款黑色3风扇 | C74: 马来 | D74: 3C数码 | E74: 电脑机箱 | F74: 193.62 | G74: 58 | J74: 27 | K74: 5421 | L74: =(G74-(H74*50))/50 -> 1.16 | M74: =31*(L74+H74) -> 35.96 | N74: =M74*F74 -> 6962.5752 | O74: =(G74-(H74*90))/90 -> 0.64444444 | P74: =31*(O74+H74) -> 19.977778 | Q74: =(O74+H74)*31*F74*1.5 -> 5802.146 | R74: =P74 -> 19.977778 | S74: =R74/31 -> 0.64444444 | T74: =S74-H74 -> 0.64444444 | U74: =Q74 -> 5802.146 | V74: =_xlfn.XLOOKUP(B74,[1]Sheet1!$B:$B,[1]Sheet1!$P:$P) -> 0.5 | W74: =X74/31 -> 0.32222222 | X74: =R74*V74 -> 9.9888889 | Y74: =X74*F74*1.5 -> 2901.073 | Z74: =_xlfn.XLOOKUP(B74,[1]Sheet1!$B:$B,[1]Sheet1!$Q:$Q) -> 0.5 | AA74: =AB74/31 -> 0.32222222 | AB74: =R74*Z74 -> 9.9888889 | AC74: =F74*AB74*1.5 -> 2901.073 | AD74: 成本上涨，合理降解
A75: CC0725 | B75: 3C-RGB动圈降噪桌面麦克风 | C75: 马来 | D75: 3C数码 | E75: 有线麦克风 | F75: 102.79 | G75: 36 | J75: 35 | K75: 5345 | L75: =(G75-(H75*50))/50 -> 0.72 | M75: =31*(L75+H75) -> 22.32 | N75: =M75*F75 -> 2294.2728 | O75: =(G75-(H75*90))/90 -> 0.4 | P75: =31*(O75+H75) -> 12.4 | Q75: =(O75+H75)*31*F75*1.5 -> 1911.894 | R75: =P75 -> 12.4 | S75: =R75/31 -> 0.4 | T75: =S75-H75 -> 0.4 | U75: =Q75 -> 1911.894 | V75: =_xlfn.XLOOKUP(B75,[1]Sheet1!$B:$B,[1]Sheet1!$P:$P) -> 1 | W75: =X75/31 -> 0.4 | X75: =R75*V75 -> 12.4 | Y75: =X75*F75*1.5 -> 1911.894 | Z75: =_xlfn.XLOOKUP(B75,[1]Sheet1!$B:$B,[1]Sheet1!$Q:$Q) -> 0 | AA75: =AB75/31 -> 0 | AB75: =R75*Z75 -> 0 | AC75: =F75*AB75*1.5 -> 0 | AD75: 新品长期动销不住
A76: CC0303 | B76: 3C-电脑机箱T8款白色 | C76: 马来 | D76: 3C数码 | E76: 电脑机箱 | F76: 93.2 | G76: 77 | J76: 46 | K76: 5266 | L76: =(G76-(H76*50))/50 -> 1.54 | M76: =31*(L76+H76) -> 47.74 | N76: =M76*F76 -> 4449.368 | O76: =(G76-(H76*90))/90 -> 0.85555556 | P76: =31*(O76+H76) -> 26.522222 | Q76: =(O76+H76)*31*F76*1.5 -> 3707.8067 | R76: =P76 -> 26.522222 | S76: =R76/31 -> 0.85555556 | T76: =S76-H76 -> 0.85555556 | U76: =Q76 -> 3707.8067 | V76: =_xlfn.XLOOKUP(B76,[1]Sheet1!$B:$B,[1]Sheet1!$P:$P) -> 0.88888889 | W76: =X76/31 -> 0.76049383 | X76: =R76*V76 -> 23.575309 | Y76: =X76*F76*1.5 -> 3295.8281 | Z76: =_xlfn.XLOOKUP(B76,[1]Sheet1!$B:$B,[1]Sheet1!$Q:$Q) -> 0.11111111 | AA76: =AB76/31 -> 0.095061728 | AB76: =R76*Z76 -> 2.9469136 | AC76: =F76*AB76*1.5 -> 411.97852 | AD76: 成本上涨，合理降解
A77: CC0572 | B77: 3C-原木色吉他套装包装升级款 | C77: 马来 | D77: 3C数码 | E77: 吉他套装 | F77: 99.9308 | G77: 181 | H77: 2 | I77: 90 | J77: 52 | K77: 5196 | L77: =(G77-(H77*50))/50 -> 1.62 | M77: =31*(L77+H77) -> 112.22 | N77: =M77*F77 -> 11214.234 | O77: =(G77-(H77*90))/90 -> 0.011111111 | P77: =31*(O77+H77) -> 62.344444 | Q77: =(O77+H77)*31*F77*1.5 -> 9345.1953 | R77: =P77 -> 62.344444 | S77: =R77/31 -> 2.0111111 | T77: =S77-H77 -> 0.011111111 | U77: =Q77 -> 9345.1953 | V77: =_xlfn.XLOOKUP(B77,[1]Sheet1!$B:$B,[1]Sheet1!$P:$P) -> 0.24137931 | W77: =X77/31 -> 0.48544061 | X77: =R77*V77 -> 15.048659 | Y77: =X77*F77*1.5 -> 2255.7368 | Z77: =_xlfn.XLOOKUP(B77,[1]Sheet1!$B:$B,[1]Sheet1!$Q:$Q) -> 0.75862069 | AA77: =AB77/31 -> 1.5256705 | AB77: =R77*Z77 -> 47.295785 | AC77: =F77*AB77*1.5 -> 7089.4585 | AD77: 主推产品，重点降解
A78: CC0994 | B78: 3B-断桥铝门弯舌锁体2.2*27 | C78: 马来 | D78: 办公安防 | E78: 锁体 | F78: 32.82 | G78: 112 | J78: 104 | K78: 5005 | L78: =(G78-(H78*50))/50 -> 2.24 | M78: =31*(L78+H78) -> 69.44 | N78: =M78*F78 -> 2279.0208 | O78: =(G78-(H78*90))/90 -> 1.2444444 | P78: =31*(O78+H78) -> 38.577778 | Q78: =(O78+H78)*31*F78*1.5 -> 1899.184 | R78: =P78 -> 38.577778 | S78: =R78/31 -> 1.2444444 | T78: =S78-H78 -> 1.2444444 | U78: =Q78 -> 1899.184 | V78: =_xlfn.XLOOKUP(B78,[1]Sheet1!$B:$B,[1]Sheet1!$P:$P) -> 0.66666667 | W78: =X78/31 -> 0.82962963 | X78: =R78*V78 -> 25.718519 | Y78: =X78*F78*1.5 -> 1266.1227 | Z78: =_xlfn.XLOOKUP(B78,[1]Sheet1!$B:$B,[1]Sheet1!$Q:$Q) -> 0.33333333 | AA78: =AB78/31 -> 0.41481481 | AB78: =R78*Z78 -> 12.859259 | AC78: =F78*AB78*1.5 -> 633.06133 | AD78: 新品降解 | AE78: 保险箱送
A79: CC1019 | B79: 3C-RGB蓝牙无线拉伸手机游戏手柄STK7009 | C79: 马来 | D79: 3C数码 | E79: 游戏手柄 | F79: 94.09 | G79: 138 | H79: 1 | I79: 138 | J79: 53 | K79: 4987 | L79: =(G79-(H79*50))/50 -> 1.76 | M79: =31*(L79+H79) -> 85.56 | N79: =M79*F79 -> 8050.3404 | O79: =(G79-(H79*90))/90 -> 0.53333333 | P79: =31*(O79+H79) -> 47.533333 | Q79: =(O79+H79)*31*F79*1.5 -> 6708.617 | R79: =P79 -> 47.533333 | S79: =R79/31 -> 1.5333333 | T79: =S79-H79 -> 0.53333333 | U79: =Q79 -> 6708.617 | V79: =_xlfn.XLOOKUP(B79,[1]Sheet1!$B:$B,[1]Sheet1!$P:$P) -> 0 | W79: =X79/31 -> 0 | X79: =R79*V79 -> 0 | Y79: =X79*F79*1.5 -> 0 | Z79: =_xlfn.XLOOKUP(B79,[1]Sheet1!$B:$B,[1]Sheet1!$Q:$Q) -> 1 | AA79: =AB79/31 -> 1.5333333 | AB79: =R79*Z79 -> 47.533333 | AC79: =F79*AB79*1.5 -> 6708.617 | AD79: 新品主推产品，重点降解
A80: CC0882 | B80: 3C-黑色吉他包装升级款 | C80: 马来 | D80: 3C数码 | E80: 吉他套装 | F80: 90.64 | G80: 130 | H80: 1 | I80: 130 | J80: 55 | K80: 4985 | L80: =(G80-(H80*50))/50 -> 1.6 | M80: =31*(L80+H80) -> 80.6 | N80: =M80*F80 -> 7305.584 | O80: =(G80-(H80*90))/90 -> 0.44444444 | P80: =31*(O80+H80) -> 44.777778 | Q80: =(O80+H80)*31*F80*1.5 -> 6087.9867 | R80: =P80 -> 44.777778 | S80: =R80/31 -> 1.4444444 | T80: =S80-H80 -> 0.44444444 | U80: =Q80 -> 6087.9867 | V80: =_xlfn.XLOOKUP(B80,[1]Sheet1!$B:$B,[1]Sheet1!$P:$P) -> 0.13333333 | W80: =X80/31 -> 0.19259259 | X80: =R80*V80 -> 5.9703704 | Y80: =X80*F80*1.5 -> 811.73156 | Z80: =_xlfn.XLOOKUP(B80,[1]Sheet1!$B:$B,[1]Sheet1!$Q:$Q) -> 0.86666667 | AA80: =AB80/31 -> 1.2518519 | AB80: =R80*Z80 -> 38.807407 | AC80: =F80*AB80*1.5 -> 5276.2551 | AD80: 主推产品，重点降解
A81: CC0864 | B81: 3B-导轨单相计量电能表1P机械计量款 | C81: 马来 | D81: 办公安防 | E81: 单相电子式电度表 | F81: 33.12 | G81: 100 | J81: 100 | K81: 4968 | L81: =(G81-(H81*50))/50 -> 2 | M81: =31*(L81+H81) -> 62 | N81: =M81*F81 -> 2053.44 | O81: =(G81-(H81*90))/90 -> 1.1111111 | P81: =31*(O81+H81) -> 34.444444 | Q81: =(O81+H81)*31*F81*1.5 -> 1711.2 | R81: =P81 -> 34.444444 | S81: =R81/31 -> 1.1111111 | T81: =S81-H81 -> 1.1111111 | U81: =Q81 -> 1711.2 | V81: =_xlfn.XLOOKUP(B81,[1]Sheet1!$B:$B,[1]Sheet1!$P:$P) -> 0 | W81: =X81/31 -> 0 | X81: =R81*V81 -> 0 | Y81: =X81*F81*1.5 -> 0 | Z81: =_xlfn.XLOOKUP(B81,[1]Sheet1!$B:$B,[1]Sheet1!$Q:$Q) -> 0 | AA81: =AB81/31 -> 0 | AB81: =R81*Z81 -> 0 | AC81: =F81*AB81*1.5 -> 0 | AD81: 新品降解
A82: CC1035 | B82: 3B-WIFI漏电多功能导轨表彩屏款2P100A | C82: 马来 | D82: 办公安防 | E82: 单相电子式电度表 | F82: 91.27 | G82: 36 | J82: 36 | K82: 4929 | L82: =(G82-(H82*50))/50 -> 0.72 | M82: =31*(L82+H82) -> 22.32 | N82: =M82*F82 -> 2037.1464 | O82: =(G82-(H82*90))/90 -> 0.4 | P82: =31*(O82+H82) -> 12.4 | Q82: =(O82+H82)*31*F82*1.5 -> 1697.622 | R82: =P82 -> 12.4 | S82: =R82/31 -> 0.4 | T82: =S82-H82 -> 0.4 | U82: =Q82 -> 1697.622 | V82: =_xlfn.XLOOKUP(B82,[1]Sheet1!$B:$B,[1]Sheet1!$P:$P) -> 0 | W82: =X82/31 -> 0 | X82: =R82*V82 -> 0 | Y82: =X82*F82*1.5 -> 0 | Z82: =_xlfn.XLOOKUP(B82,[1]Sheet1!$B:$B,[1]Sheet1!$Q:$Q) -> 0 | AA82: =AB82/31 -> 0 | AB82: =R82*Z82 -> 0 | AC82: =F82*AB82*1.5 -> 0 | AD82: 新品降解
A83: CC0079 | B83: 3C-显示器支架双臂铁塑款 | C83: 马来 | D83: 3C数码 | E83: 显示器支架 | F83: 84.3667 | G83: 153 | H83: 1 | I83: 153 | J83: 58 | K83: 4893 | L83: =(G83-(H83*50))/50 -> 2.06 | M83: =31*(L83+H83) -> 94.86 | N83: =M83*F83 -> 8003.0252 | O83: =(G83-(H83*90))/90 -> 0.7 | P83: =31*(O83+H83) -> 52.7 | Q83: =(O83+H83)*31*F83*1.5 -> 6669.1876 | R83: =P83 -> 52.7 | S83: =R83/31 -> 1.7 | T83: =S83-H83 -> 0.7 | U83: =Q83 -> 6669.1876 | V83: =_xlfn.XLOOKUP(B83,[1]Sheet1!$B:$B,[1]Sheet1!$P:$P) -> 0.45652174 | W83: =X83/31 -> 0.77608696 | X83: =R83*V83 -> 24.058696 | Y83: =X83*F83*1.5 -> 3044.6291 | Z83: =_xlfn.XLOOKUP(B83,[1]Sheet1!$B:$B,[1]Sheet1!$Q:$Q) -> 0.54347826 | AA83: =AB83/31 -> 0.92391304 | AB83: =R83*Z83 -> 28.641304 | AC83: =F83*AB83*1.5 -> 3624.5585 | AD83: 主推产品，重点降解
A84: CC1031 | B84: 3C-原木色吉他包装升级款 | C84: 马来 | D84: 3C数码 | E84: 吉他套装 | F84: 90.64 | G84: 157 | H84: 2 | I84: 78 | J84: 51 | K84: 4623 | L84: =(G84-(H84*50))/50 -> 1.14 | M84: =31*(L84+H84) -> 97.34 | N84: =M84*F84 -> 8822.8976 | O84: =(G84-(H84*90))/90 -> -0.25555556 | P84: =31*(O84+H84) -> 54.077778 | Q84: =(O84+H84)*31*F84*1.5 -> 7352.4147 | R84: =P84 -> 54.077778 | S84: =R84/31 -> 1.7444444 | T84: =S84-H84 -> -0.25555556 | U84: =Q84 -> 7352.4147 | V84: =_xlfn.XLOOKUP(B84,[1]Sheet1!$B:$B,[1]Sheet1!$P:$P) -> 0.032258065 | W84: =X84/31 -> 0.056272401 | X84: =R84*V84 -> 1.7444444 | Y84: =X84*F84*1.5 -> 237.17467 | Z84: =_xlfn.XLOOKUP(B84,[1]Sheet1!$B:$B,[1]Sheet1!$Q:$Q) -> 0.96774194 | AA84: =AB84/31 -> 1.688172 | AB84: =R84*Z84 -> 52.333333 | AC84: =F84*AB84*1.5 -> 7115.24 | AD84: 新品降解
A85: CC0684 | B85: 3B-迷你标签打印机白色 | C85: 马来 | D85: 办公安防 | E85: 打印机 | F85: 41.49 | G85: 107 | J85: 81 | K85: 4605 | L85: =(G85-(H85*50))/50 -> 2.14 | M85: =31*(L85+H85) -> 66.34 | N85: =M85*F85 -> 2752.4466 | O85: =(G85-(H85*90))/90 -> 1.1888889 | P85: =31*(O85+H85) -> 36.855556 | Q85: =(O85+H85)*31*F85*1.5 -> 2293.7055 | R85: =P85 -> 36.855556 | S85: =R85/31 -> 1.1888889 | T85: =S85-H85 -> 1.1888889 | U85: =Q85 -> 2293.7055 | V85: =_xlfn.XLOOKUP(B85,[1]Sheet1!$B:$B,[1]Sheet1!$P:$P) -> 1 | W85: =X85/31 -> 1.1888889 | X85: =R85*V85 -> 36.855556 | Y85: =X85*F85*1.5 -> 2293.7055 | Z85: =_xlfn.XLOOKUP(B85,[1]Sheet1!$B:$B,[1]Sheet1!$Q:$Q) -> 0 | AA85: =AB85/31 -> 0 | AB85: =R85*Z85 -> 0 | AC85: =F85*AB85*1.5 -> 0 | AD85: 长期日销偏低，系列降解
A86: CC1038 | B86: 3B-9260B标签打印机4寸黑色USB蓝牙 | C86: 马来 | D86: 办公安防 | E86: 打印机 | F86: 160.68 | G86: 29 | J86: 21 | K86: 4499 | L86: =(G86-(H86*50))/50 -> 0.58 | M86: =31*(L86+H86) -> 17.98 | N86: =M86*F86 -> 2889.0264 | O86: =(G86-(H86*90))/90 -> 0.32222222 | P86: =31*(O86+H86) -> 9.9888889 | Q86: =(O86+H86)*31*F86*1.5 -> 2407.522 | R86: =P86 -> 9.9888889 | S86: =R86/31 -> 0.32222222 | T86: =S86-H86 -> 0.32222222 | U86: =Q86 -> 2407.522 | V86: =_xlfn.XLOOKUP(B86,[1]Sheet1!$B:$B,[1]Sheet1!$P:$P) -> 0.6 | W86: =X86/31 -> 0.19333333 | X86: =R86*V86 -> 5.9933333 | Y86: =X86*F86*1.5 -> 1444.5132 | Z86: =_xlfn.XLOOKUP(B86,[1]Sheet1!$B:$B,[1]Sheet1!$Q:$Q) -> 0.4 | AA86: =AB86/31 -> 0.12888889 | AB86: =R86*Z86 -> 3.9955556 | AC86: =F86*AB86*1.5 -> 963.0088 | AD86: 长期日销偏低，系列降解
A87: CC0700 | B87: 3B-毛毡照片公告墙咖啡色80*120CM | C87: 马来 | D87: 办公安防 | E87: 毛毡照片墙 | F87: 43.51 | G87: 85 | J87: 72 | K87: 4460 | L87: =(G87-(H87*50))/50 -> 1.7 | M87: =31*(L87+H87) -> 52.7 | N87: =M87*F87 -> 2292.977 | O87: =(G87-(H87*90))/90 -> 0.94444444 | P87: =31*(O87+H87) -> 29.277778 | Q87: =(O87+H87)*31*F87*1.5 -> 1910.8142 | R87: =P87 -> 29.277778 | S87: =R87/31 -> 0.94444444 | T87: =S87-H87 -> 0.94444444 | U87: =Q87 -> 1910.8142 | V87: =_xlfn.XLOOKUP(B87,[1]Sheet1!$B:$B,[1]Sheet1!$P:$P) -> 0.5 | W87: =X87/31 -> 0.47222222 | X87: =R87*V87 -> 14.638889 | Y87: =X87*F87*1.5 -> 955.40708 | Z87: =_xlfn.XLOOKUP(B87,[1]Sheet1!$B:$B,[1]Sheet1!$Q:$Q) -> 0.5 | AA87: 50 | AB87: =R87*Z87 -> 14.638889 | AC87: =F87*AB87*1.5 -> 955.40708
A88: CC1040 | B88: 3C-电脑机箱T8款黑色 | C88: 马来 | D88: 3C数码 | E88: 电脑机箱 | F88: 86.12 | G88: 92 | J88: 46 | K88: 4349 | L88: =(G88-(H88*50))/50 -> 1.84 | M88: =31*(L88+H88) -> 57.04 | N88: =M88*F88 -> 4912.2848 | O88: =(G88-(H88*90))/90 -> 1.0222222 | P88: =31*(O88+H88) -> 31.688889 | Q88: =(O88+H88)*31*F88*1.5 -> 4093.5707 | R88: =P88 -> 31.688889 | S88: =R88/31 -> 1.0222222 | T88: =S88-H88 -> 1.0222222 | U88: =Q88 -> 4093.5707 | V88: =_xlfn.XLOOKUP(B88,[1]Sheet1!$B:$B,[1]Sheet1!$P:$P) -> 0.75 | W88: =X88/31 -> 0.76666667 | X88: =R88*V88 -> 23.766667 | Y88: =X88*F88*1.5 -> 3070.178 | Z88: =_xlfn.XLOOKUP(B88,[1]Sheet1!$B:$B,[1]Sheet1!$Q:$Q) -> 0.25 | AA88: =AB88/31 -> 0.25555556 | AB88: =R88*Z88 -> 7.9222222 | AC88: =F88*AB88*1.5 -> 1023.3927 | AD88: 成本上涨，合理降解
A89: CC1016 | B89: 3B-导轨单相多功能电能表1P液晶计量款 | C89: 马来 | D89: 办公安防 | E89: 单相电子式电度表 | F89: 28.7 | G89: 100 | J89: 100 | K89: 4305 | L89: =(G89-(H89*50))/50 -> 2 | M89: =31*(L89+H89) -> 62 | N89: =M89*F89 -> 1779.4 | O89: =(G89-(H89*90))/90 -> 1.1111111 | P89: =31*(O89+H89) -> 34.444444 | Q89: =(O89+H89)*31*F89*1.5 -> 1482.8333 | R89: =P89 -> 34.444444 | S89: =R89/31 -> 1.1111111 | T89: =S89-H89 -> 1.1111111 | U89: =Q89 -> 1482.8333 | V89: =_xlfn.XLOOKUP(B89,[1]Sheet1!$B:$B,[1]Sheet1!$P:$P) -> 0 | W89: =X89/31 -> 0 | X89: =R89*V89 -> 0 | Y89: =X89*F89*1.5 -> 0 | Z89: =_xlfn.XLOOKUP(B89,[1]Sheet1!$B:$B,[1]Sheet1!$Q:$Q) -> 0 | AA89: =AB89/31 -> 0 | AB89: =R89*Z89 -> 0 | AC89: =F89*AB89*1.5 -> 0 | AD89: 新品降解
A90: CC0940 | B90: 3C-平板旋转支架 | C90: 马来 | D90: 3C数码 | E90: 电脑支架 | F90: 16.07 | G90: 251 | H90: 1 | I90: 251 | J90: 193 | K90: 4275 | L90: =(G90-(H90*50))/50 -> 4.02 | M90: =31*(L90+H90) -> 155.62 | N90: =M90*F90 -> 2500.8134 | O90: =(G90-(H90*90))/90 -> 1.7888889 | P90: =31*(O90+H90) -> 86.455556 | Q90: =(O90+H90)*31*F90*1.5 -> 2084.0112 | R90: =P90 -> 86.455556 | S90: =R90/31 -> 2.7888889 | T90: =S90-H90 -> 1.7888889 | U90: =Q90 -> 2084.0112 | V90: =_xlfn.XLOOKUP(B90,[1]Sheet1!$B:$B,[1]Sheet1!$P:$P) -> 0 | W90: =X90/31 -> 0 | X90: =R90*V90 -> 0 | Y90: =X90*F90*1.5 -> 0 | Z90: =_xlfn.XLOOKUP(B90,[1]Sheet1!$B:$B,[1]Sheet1!$Q:$Q) -> 1 | AA90: =AB90/31 -> 2.7888889 | AB90: =R90*Z90 -> 86.455556 | AC90: =F90*AB90*1.5 -> 2084.0112 | AD90: 新品降解
A91: CC1039 | B91: 3B-广告架kt板直面3.7kg | C91: 马来 | D91: 办公安防 | E91: 广告架 | F91: 46.18 | G91: 60 | J91: 60 | K91: 4156 | L91: =(G91-(H91*50))/50 -> 1.2 | M91: =31*(L91+H91) -> 37.2 | N91: =M91*F91 -> 1717.896 | O91: =(G91-(H91*90))/90 -> 0.66666667 | P91: =31*(O91+H91) -> 20.666667 | Q91: =(O91+H91)*31*F91*1.5 -> 1431.58 | R91: =P91 -> 20.666667 | S91: =R91/31 -> 0.66666667 | T91: =S91-H91 -> 0.66666667 | U91: =Q91 -> 1431.58 | V91: =_xlfn.XLOOKUP(B91,[1]Sheet1!$B:$B,[1]Sheet1!$P:$P) -> 0 | W91: =X91/31 -> 0 | X91: =R91*V91 -> 0 | Y91: =X91*F91*1.5 -> 0 | Z91: =_xlfn.XLOOKUP(B91,[1]Sheet1!$B:$B,[1]Sheet1!$Q:$Q) -> 0 | AA91: =AB91/31 -> 0 | AB91: =R91*Z91 -> 0 | AC91: =F91*AB91*1.5 -> 0 | AD91: 新品降解
A92: CC1037 | B92: 3B-毛毡照片公告墙咖啡色120*180CM | C92: 马来 | D92: 办公安防 | E92: 毛毡照片墙 | F92: 76.97 | G92: 43 | J92: 37 | K92: 4079 | L92: =(G92-(H92*50))/50 -> 0.86 | M92: =31*(L92+H92) -> 26.66 | N92: =M92*F92 -> 2052.0202 | O92: =(G92-(H92*90))/90 -> 0.47777778 | P92: =31*(O92+H92) -> 14.811111 | Q92: =(O92+H92)*31*F92*1.5 -> 1710.0168 | R92: =P92 -> 14.811111 | S92: =R92/31 -> 0.47777778 | T92: =S92-H92 -> 0.47777778 | U92: =Q92 -> 1710.0168 | V92: =_xlfn.XLOOKUP(B92,[1]Sheet1!$B:$B,[1]Sheet1!$P:$P) -> 1 | W92: =X92/31 -> 0.47777778 | X92: =R92*V92 -> 14.811111 | Y92: =X92*F92*1.5 -> 1710.0168 | Z92: =_xlfn.XLOOKUP(B92,[1]Sheet1!$B:$B,[1]Sheet1!$Q:$Q) -> 0 | AA92: =AB92/31 -> 0 | AB92: =R92*Z92 -> 0 | AC92: =F92*AB92*1.5 -> 0 | AD92: 新品降解
A93: CC0789 | B93: 3C-带杆可升降可倒挂气弹簧双臂支架 | C93: 马来 | D93: 3C数码 | E93: 显示器支架 | F93: 123.84 | G93: 77 | J93: 32 | K93: 3963 | L93: =(G93-(H93*50))/50 -> 1.54 | M93: =31*(L93+H93) -> 47.74 | N93: =M93*F93 -> 5912.1216 | O93: =(G93-(H93*90))/90 -> 0.85555556 | P93: =31*(O93+H93) -> 26.522222 | Q93: =(O93+H93)*31*F93*1.5 -> 4926.768 | R93: =P93 -> 26.522222 | S93: =R93/31 -> 0.85555556 | T93: =S93-H93 -> 0.85555556 | U93: =Q93 -> 4926.768 | V93: =_xlfn.XLOOKUP(B93,[1]Sheet1!$B:$B,[1]Sheet1!$P:$P) -> 0.9375 | W93: =X93/31 -> 0.80208333 | X93: =R93*V93 -> 24.864583 | Y93: =X93*F93*1.5 -> 4618.845 | Z93: =_xlfn.XLOOKUP(B93,[1]Sheet1!$B:$B,[1]Sheet1!$Q:$Q) -> 0.0625 | AA93: =AB93/31 -> 0.053472222 | AB93: =R93*Z93 -> 1.6576389 | AC93: =F93*AB93*1.5 -> 307.923 | AD93: 长期日销偏低，系列降解
A94: CC0301 | B94: 3C-32至70寸电视移动支架的中托盘 | C94: 马来 | D94: 3C数码 | E94: 电视支架托盘 | F94: 14.19 | G94: 469 | H94: 4 | I94: 117 | J94: 245 | K94: 3945 | L94: =(G94-(H94*50))/50 -> 5.38 | M94: =31*(L94+H94) -> 290.78 | N94: =M94*F94 -> 4126.1682 | O94: =(G94-(H94*90))/90 -> 1.2111111 | P94: =31*(O94+H94) -> 161.54444 | Q94: =(O94+H94)*31*F94*1.5 -> 3438.4735 | R94: =P94 -> 161.54444 | S94: =R94/31 -> 5.2111111 | T94: =S94-H94 -> 1.2111111 | U94: =Q94 -> 3438.4735 | V94: =_xlfn.XLOOKUP(B94,[1]Sheet1!$B:$B,[1]Sheet1!$P:$P) -> 0.5625 | W94: =X94/31 -> 2.93125 | X94: =R94*V94 -> 90.86875 | Y94: =X94*F94*1.5 -> 1934.1413 | Z94: =_xlfn.XLOOKUP(B94,[1]Sheet1!$B:$B,[1]Sheet1!$Q:$Q) -> 0.4375 | AA94: =AB94/31 -> 2.2798611 | AB94: =R94*Z94 -> 70.675694 | AC94: =F94*AB94*1.5 -> 1504.3322 | AD94: 售后严重产品
A95: CC1033 | B95: 3B-不干胶标签打印纸单卷150*100mm | C95: 马来 | D95: 办公安防 | E95: 标签打印纸 | F95: 22.4909 | G95: 316 | H95: 3 | I95: 105 | J95: 158 | K95: 3902 | L95: =(G95-(H95*50))/50 -> 3.32 | M95: =31*(L95+H95) -> 195.92 | N95: =M95*F95 -> 4406.4171 | O95: =(G95-(H95*90))/90 -> 0.51111111 | P95: =31*(O95+H95) -> 108.84444 | Q95: =(O95+H95)*31*F95*1.5 -> 3672.0143 | R95: =P95 -> 108.84444 | S95: =R95/31 -> 3.5111111 | T95: =S95-H95 -> 0.51111111 | U95: =Q95 -> 3672.0143 | V95: =_xlfn.XLOOKUP(B95,[1]Sheet1!$B:$B,[1]Sheet1!$P:$P) -> 0.67857143 | W95: =X95/31 -> 2.3825397 | X95: =R95*V95 -> 73.85873 | Y95: =X95*F95*1.5 -> 2491.724 | Z95: =_xlfn.XLOOKUP(B95,[1]Sheet1!$B:$B,[1]Sheet1!$Q:$Q) -> 0.32142857 | AA95: =AB95/31 -> 1.1285714 | AB95: =R95*Z95 -> 34.985714 | AC95: =F95*AB95*1.5 -> 1180.2903 | AD95: 主推配套，降解打印机
A96: CC0824 | B96: 3B-8008便携式不干胶标签打印机80mm黑色 | C96: 马来 | D96: 办公安防 | E96: 打印机 | F96: 146.2 | G96: 29 | J96: 19 | K96: 3582 | L96: =(G96-(H96*50))/50 -> 0.58 | M96: =31*(L96+H96) -> 17.98 | N96: =M96*F96 -> 2628.676 | O96: =(G96-(H96*90))/90 -> 0.32222222 | P96: =31*(O96+H96) -> 9.9888889 | Q96: =(O96+H96)*31*F96*1.5 -> 2190.5633 | R96: =P96 -> 9.9888889 | S96: =R96/31 -> 0.32222222 | T96: =S96-H96 -> 0.32222222 | U96: =Q96 -> 2190.5633 | V96: =_xlfn.XLOOKUP(B96,[1]Sheet1!$B:$B,[1]Sheet1!$P:$P) -> 1 | W96: =X96/31 -> 0.32222222 | X96: =R96*V96 -> 9.9888889 | Y96: =X96*F96*1.5 -> 2190.5633 | Z96: =_xlfn.XLOOKUP(B96,[1]Sheet1!$B:$B,[1]Sheet1!$Q:$Q) -> 0 | AA96: =AB96/31 -> 0 | AB96: =R96*Z96 -> 0 | AC96: =F96*AB96*1.5 -> 0 | AD96: 长期日销偏低，系列降解
A97: CC0881 | B97: 3B-毛毡照片公告墙咖啡色60*80CM | C97: 马来 | D97: 办公安防 | E97: 毛毡照片墙 | F97: 21.36 | G97: 162 | J97: 122 | K97: 3567 | L97: =(G97-(H97*50))/50 -> 3.24 | M97: =31*(L97+H97) -> 100.44 | N97: =M97*F97 -> 2145.3984 | O97: =(G97-(H97*90))/90 -> 1.8 | P97: =31*(O97+H97) -> 55.8 | Q97: =(O97+H97)*31*F97*1.5 -> 1787.832 | R97: =P97 -> 55.8 | S97: =R97/31 -> 1.8 | T97: =S97-H97 -> 1.8 | U97: =Q97 -> 1787.832 | V97: =_xlfn.XLOOKUP(B97,[1]Sheet1!$B:$B,[1]Sheet1!$P:$P) -> 0.46153846 | W97: =X97/31 -> 0.83076923 | X97: =R97*V97 -> 25.753846 | Y97: =X97*F97*1.5 -> 825.15323 | Z97: =_xlfn.XLOOKUP(B97,[1]Sheet1!$B:$B,[1]Sheet1!$Q:$Q) -> 0.53846154 | AA97: =AB97/31 -> 0.96923077 | AB97: =R97*Z97 -> 30.046154 | AC97: =F97*AB97*1.5 -> 962.67877 | AD97: 新品降解
A98: CC0264 | B98: 3C-120英寸投影仪屏幕 | C98: 马来 | D98: 3C数码 | E98: 抗光幕布 | F98: 28.12 | G98: 474 | H98: 6 | I98: 79 | J98: 126 | K98: 3543 | L98: =(G98-(H98*50))/50 -> 3.48 | M98: =31*(L98+H98) -> 293.88 | N98: =M98*F98 -> 8263.9056 | O98: =(G98-(H98*90))/90 -> -0.73333333 | P98: =31*(O98+H98) -> 163.26667 | Q98: =(O98+H98)*31*F98*1.5 -> 6886.588 | R98: =P98 -> 163.26667 | S98: =R98/31 -> 5.2666667 | T98: =S98-H98 -> -0.73333333 | U98: =Q98 -> 6886.588 | V98: =_xlfn.XLOOKUP(B98,[1]Sheet1!$B:$B,[1]Sheet1!$P:$P) -> 0.71621622 | W98: =X98/31 -> 3.7720721 | X98: =R98*V98 -> 116.93423 | Y98: =X98*F98*1.5 -> 4932.286 | Z98: =_xlfn.XLOOKUP(B98,[1]Sheet1!$B:$B,[1]Sheet1!$Q:$Q) -> 0.28378378 | AA98: =AB98/31 -> 1.4945946 | AB98: =R98*Z98 -> 46.332432 | AC98: =F98*AB98*1.5 -> 1954.302
A99: CC1029 | B99: 3B-宽57cm不干胶标签打印纸5卷 | C99: 马来 | D99: 办公安防 | E99: 标签打印纸 | F99: 6.6874 | G99: 564 | H99: 3 | I99: 188 | J99: 383 | K99: 3357 | L99: =(G99-(H99*50))/50 -> 8.28 | M99: =31*(L99+H99) -> 349.68 | N99: =M99*F99 -> 2338.45 | O99: =(G99-(H99*90))/90 -> 3.2666667 | P99: =31*(O99+H99) -> 194.26667 | Q99: =(O99+H99)*31*F99*1.5 -> 1948.7084 | R99: =P99 -> 194.26667 | S99: =R99/31 -> 6.2666667 | T99: =S99-H99 -> 3.2666667 | U99: =Q99 -> 1948.7084 | V99: =_xlfn.XLOOKUP(B99,[1]Sheet1!$B:$B,[1]Sheet1!$P:$P) -> 1 | W99: =X99/31 -> 6.2666667 | X99: =R99*V99 -> 194.26667 | Y99: =X99*F99*1.5 -> 1948.7084 | Z99: =_xlfn.XLOOKUP(B99,[1]Sheet1!$B:$B,[1]Sheet1!$Q:$Q) -> 0 | AA99: =AB99/31 -> 0 | AB99: =R99*Z99 -> 0 | AC99: =F99*AB99*1.5 -> 0 | AD99: 主推配套，降解打印机
A100: CC0270 | B100: 3B-交换机机柜24cm | C100: 马来 | D100: 办公安防 | E100: 金属制品机柜 | F100: 81.71 | G100: 115 | H100: 1 | I100: 115 | J100: 40 | K100: 3268 | L100: =(G100-(H100*50))/50 -> 1.3 | M100: =31*(L100+H100) -> 71.3 | N100: =M100*F100 -> 5825.923 | O100: =(G100-(H100*90))/90 -> 0.27777778 | P100: =31*(O100+H100) -> 39.611111 | Q100: =(O100+H100)*31*F100*1.5 -> 4854.9358 | R100: =P100 -> 39.611111 | S100: =R100/31 -> 1.2777778 | T100: =S100-H100 -> 0.27777778 | U100: =Q100 -> 4854.9358 | V100: =_xlfn.XLOOKUP(B100,[1]Sheet1!$B:$B,[1]Sheet1!$P:$P) -> 1 | W100: =X100/31 -> 1.2777778 | X100: =R100*V100 -> 39.611111 | Y100: =X100*F100*1.5 -> 4854.9358 | Z100: =_xlfn.XLOOKUP(B100,[1]Sheet1!$B:$B,[1]Sheet1!$Q:$Q) -> 0 | AA100: =AB100/31 -> 0 | AB100: =R100*Z100 -> 0 | AC100: =F100*AB100*1.5 -> 0 | AD100: 定点降解
A101: CC1032 | B101: 3B-房间门单舌锁体2.7*6.8 | C101: 马来 | D101: 办公安防 | E101: 锁体 | F101: 13.9 | G101: 194 | J101: 164 | K101: 3253 | L101: =(G101-(H101*50))/50 -> 3.88 | M101: =31*(L101+H101) -> 120.28 | N101: =M101*F101 -> 1671.892 | O101: =(G101-(H101*90))/90 -> 2.1555556 | P101: =31*(O101+H101) -> 66.822222 | Q101: =(O101+H101)*31*F101*1.5 -> 1393.2433 | R101: =P101 -> 66.822222 | S101: =R101/31 -> 2.1555556 | T101: =S101-H101 -> 2.1555556 | U101: =Q101 -> 1393.2433 | V101: =_xlfn.XLOOKUP(B101,[1]Sheet1!$B:$B,[1]Sheet1!$P:$P) -> 0.75 | W101: =X101/31 -> 1.6166667 | X101: =R101*V101 -> 50.116667 | Y101: =X101*F101*1.5 -> 1044.9325 | Z101: =_xlfn.XLOOKUP(B101,[1]Sheet1!$B:$B,[1]Sheet1!$Q:$Q) -> 0.25 | AA101: =AB101/31 -> 0.53888889 | AB101: =R101*Z101 -> 16.705556 | AC101: =F101*AB101*1.5 -> 348.31083
...

Sheet 4月分配
R1: 90天-4月需销售量 | V1: SP | Z1: TK
A3: 主SKU | B3: 商品名称 | C3: 国家 | D3: 品类 | E3: 三级分类 | F3: 销售成本 | G3: 当前库存 | H3: 日销量 | I3: 周转天数 | J3: 月预估超期库存 | K3: 月预估超期金额 | L3: 日销差距（50天） | M3: 预计出清数量（50天） | N3: 出清金额（3月） | O3: 日销差距（90天） | P3: 预计出清数量（90天） | Q3: 出清金额(3月） | R3: 总数量 | S3: 目标日销 | T3: 日销差异 | U3: 总出清金额 | V3: 业绩占比 | W3: 目标日销 | X3: 总销量 | Y3: 出清额 | Z3: 业绩占比 | AA3: 目标日销 | AB3: 总销量 | AC3: 出清额度 | AD3: 策略方向
A4: CC0904 | B4: 3B-磁吸白板密度板夹层70cm*100cm | C4: 马来 | D4: 办公安防 | E4: 白板 | F4: 43.6 | G4: 3149 | H4: 5 | I4: 629 | J4: 2876 | K4: 183316 | L4: =(G4-(H4*50))/50 -> 57.98 | M4: =31*(L4+H4) -> 1952.38 | N4: =M4*F4 -> 85123.768 | O4: =(G4-(H4*90))/90 -> 29.988889 | P4: =31*(O4+H4) -> 1084.6556 | Q4: =(O4+H4)*31*F4*1.5 -> 70936.473 | R4: =P4 -> 1084.6556 | S4: =R4/31 -> 34.988889 | T4: =S4-H4 -> 29.988889 | U4: =Q4 -> 70936.473 | V4: 0.6 | W4: =X4/31 -> 20.993333 | X4: =R4*V4 -> 650.79333 | Y4: =X4*F4*1.5 -> 42561.884 | Z4: 0.4 | AA4: =AB4/31 -> 13.995556 | AB4: =R4*Z4 -> 433.86222 | AC4: =F4*AB4*1.5 -> 28374.589 | AD4: 重点降解
A5: CC0517 | B5: 3B-收银箱405金属黑色固定版 | C5: 马来 | D5: 办公安防 | E5: 收银箱 | F5: 93.8 | G5: 2163 | H5: 19 | I5: 113 | J5: 1208 | K5: 134134 | L5: =(G5-(H5*50))/50 -> 24.26 | M5: =31*(L5+H5) -> 1341.06 | N5: =M5*F5 -> 125791.43 | O5: =(G5-(H5*90))/90 -> 5.0333333 | P5: =31*(O5+H5) -> 745.03333 | Q5: =(O5+H5)*31*F5*1.5 -> 104826.19 | R5: =P5 -> 745.03333 | S5: =R5/31 -> 24.033333 | T5: =S5-H5 -> 5.0333333 | U5: =Q5 -> 104826.19 | V5: 0.7 | W5: =X5/31 -> 16.823333 | X5: =R5*V5 -> 521.52333 | Y5: =X5*F5*1.5 -> 73378.333 | Z5: 0.3 | AA5: =AB5/31 -> 7.21 | AB5: =R5*Z5 -> 223.51 | AC5: =F5*AB5*1.5 -> 31447.857 | AD5: 重点降解
A6: CC0903 | B6: 3B-磁吸白板密度板夹层60cm*90cm | C6: 马来 | D6: 办公安防 | E6: 白板 | F6: 34.01 | G6: 2746 | H6: 9 | I6: 305 | J6: 2288 | K6: 110481 | L6: =(G6-(H6*50))/50 -> 45.92 | M6: =31*(L6+H6) -> 1702.52 | N6: =M6*F6 -> 57902.705 | O6: =(G6-(H6*90))/90 -> 21.511111 | P6: =31*(O6+H6) -> 945.84444 | Q6: =(O6+H6)*31*F6*1.5 -> 48252.254 | R6: =P6 -> 945.84444 | S6: =R6/31 -> 30.511111 | T6: =S6-H6 -> 21.511111 | U6: =Q6 -> 48252.254 | V6: 0.6 | W6: =X6/31 -> 18.306667 | X6: =R6*V6 -> 567.50667 | Y6: =X6*F6*1.5 -> 28951.353 | Z6: 0.4 | AA6: =AB6/31 -> 12.204444 | AB6: =R6*Z6 -> 378.33778 | AC6: =F6*AB6*1.5 -> 19300.902 | AD6: 重点降解
A7: CC0711 | B7: 3B-点钞机灰色 | C7: 马来 | D7: 办公安防 | E7: 点钞机 | F7: 211.75 | G7: 1465 | H7: 20 | I7: 73 | J7: 464 | K7: 98252 | L7: =(G7-(H7*50))/50 -> 9.3 | M7: =31*(L7+H7) -> 908.3 | N7: =M7*F7 -> 192332.52 | O7: =(G7-(H7*90))/90 -> -3.7222222 | P7: =31*(O7+H7) -> 504.61111 | Q7: =(O7+H7)*31*F7*1.5 -> 160277.1 | R7: =P7 -> 504.61111 | S7: =R7/31 -> 16.277778 | T7: =S7-H7 -> -3.7222222 | U7: =Q7 -> 160277.1 | V7: 0.4 | W7: =X7/31 -> 6.5111111 | X7: =R7*V7 -> 201.84444 | Y7: =X7*F7*1.5 -> 64110.842 | Z7: 0.6 | AA7: =AB7/31 -> 9.7666667 | AB7: =R7*Z7 -> 302.76667 | AC7: =F7*AB7*1.5 -> 96166.262 | AD7: 重点降解
A8: CC0516 | B8: 3B-收银箱335金属黑色固定版 | C8: 马来 | D8: 办公安防 | E8: 收银箱 | F8: 78.76 | G8: 1563 | H8: 14 | I8: 111 | J8: 820 | K8: 73444 | L8: =(G8-(H8*50))/50 -> 17.26 | M8: =31*(L8+H8) -> 969.06 | N8: =M8*F8 -> 76323.166 | O8: =(G8-(H8*90))/90 -> 3.3666667 | P8: =31*(O8+H8) -> 538.36667 | Q8: =(O8+H8)*31*F8*1.5 -> 63602.638 | R8: =P8 -> 538.36667 | S8: =R8/31 -> 17.366667 | T8: =S8-H8 -> 3.3666667 | U8: =Q8 -> 63602.638 | V8: 0.7 | W8: =X8/31 -> 12.156667 | X8: =R8*V8 -> 376.85667 | Y8: =X8*F8*1.5 -> 44521.847 | Z8: 0.3 | AA8: =AB8/31 -> 5.21 | AB8: =R8*Z8 -> 161.51 | AC8: =F8*AB8*1.5 -> 19080.791 | AD8: 重点降解
A9: CC0706 | B9: 3C-32英寸到55英寸带中托可移动电视支架 | C9: 马来 | D9: 3C数码 | E9: 电视支架 | F9: 123.29 | G9: 842 | H9: 7 | I9: 120 | J9: 471 | K9: 68796 | L9: =(G9-(H9*50))/50 -> 9.84 | M9: =31*(L9+H9) -> 522.04 | N9: =M9*F9 -> 64362.312 | O9: =(G9-(H9*90))/90 -> 2.3555556 | P9: =31*(O9+H9) -> 290.02222 | Q9: =(O9+H9)*31*F9*1.5 -> 53635.26 | R9: =P9 -> 290.02222 | S9: =R9/31 -> 9.3555556 | T9: =S9-H9 -> 2.3555556 | U9: =Q9 -> 53635.26 | V9: 0.4 | W9: =X9/31 -> 3.7422222 | X9: =R9*V9 -> 116.00889 | Y9: =X9*F9*1.5 -> 21454.104 | Z9: 0.6 | AA9: =AB9/31 -> 5.6133333 | AB9: =R9*Z9 -> 174.01333 | AC9: =F9*AB9*1.5 -> 32181.156 | AD9: 重点降解
A10: CC0906 | B10: 3B-磁吸白板密度板夹层90cm*150cm | C10: 马来 | D10: 办公安防 | E10: 白板 | F10: 88.35 | G10: 742 | H10: 5 | I10: 148 | J10: 482 | K10: 54689 | L10: =(G10-(H10*50))/50 -> 9.84 | M10: =31*(L10+H10) -> 460.04 | N10: =M10*F10 -> 40644.534 | O10: =(G10-(H10*90))/90 -> 3.2444444 | P10: =31*(O10+H10) -> 255.57778 | Q10: =(O10+H10)*31*F10*1.5 -> 33870.445 | R10: =P10 -> 255.57778 | S10: =R10/31 -> 8.2444444 | T10: =S10-H10 -> 3.2444444 | U10: =Q10 -> 33870.445 | V10: 0.8 | W10: =X10/31 -> 6.5955556 | X10: =R10*V10 -> 204.46222 | Y10: =X10*F10*1.5 -> 27096.356 | Z10: 0.2 | AA10: =AB10/31 -> 1.6488889 | AB10: =R10*Z10 -> 51.115556 | AC10: =F10*AB10*1.5 -> 6774.089 | AD10: 重点降解
A11: CC0228 | B11: 3C-黑色吉他套装 | C11: 马来 | D11: 3C数码 | E11: 吉他套装 | F11: 76.15 | G11: 875 | H11: 6 | I11: 145 | J11: 550 | K11: 52924 | L11: =(G11-(H11*50))/50 -> 11.5 | M11: =31*(L11+H11) -> 542.5 | N11: =M11*F11 -> 41311.375 | O11: =(G11-(H11*90))/90 -> 3.7222222 | P11: =31*(O11+H11) -> 301.38889 | Q11: =(O11+H11)*31*F11*1.5 -> 34426.146 | R11: =P11 -> 301.38889 | S11: =R11/31 -> 9.7222222 | T11: =S11-H11 -> 3.7222222 | U11: =Q11 -> 34426.146 | V11: 0.5 | W11: =X11/31 -> 4.8611111 | X11: =R11*V11 -> 150.69444 | Y11: =X11*F11*1.5 -> 17213.073 | Z11: 0.5 | AA11: =AB11/31 -> 4.8611111 | AB11: =R11*Z11 -> 150.69444 | AC11: =F11*AB11*1.5 -> 17213.073 | AD11: 重点降解
A12: CC0764 | B12: 3C-无弦吉他 | C12: 马来 | D12: 3C数码 | E12: 未来吉他 | F12: 712.84 | G12: 211 | H12: 2 | I12: 105 | J12: 74 | K12: 52750 | L12: =(G12-(H12*50))/50 -> 2.22 | M12: =31*(L12+H12) -> 130.82 | N12: =M12*F12 -> 93253.729 | O12: =(G12-(H12*90))/90 -> 0.34444444 | P12: =31*(O12+H12) -> 72.677778 | Q12: =(O12+H12)*31*F12*1.5 -> 77711.441 | R12: =P12 -> 72.677778 | S12: =R12/31 -> 2.3444444 | T12: =S12-H12 -> 0.34444444 | U12: =Q12 -> 77711.441 | V12: 0.3 | W12: =X12/31 -> 0.70333333 | X12: =R12*V12 -> 21.803333 | Y12: =X12*F12*1.5 -> 23313.432 | Z12: 0.7 | AA12: =AB12/31 -> 1.6411111 | AB12: =R12*Z12 -> 50.874444 | AC12: =F12*AB12*1.5 -> 54398.008 | AD12: 重点降解
A13: CC0278 | B13: 3B-智能指纹门锁X7 | C13: 马来 | D13: 办公安防 | E13: 指纹锁 | F13: 94.05 | G13: 1342 | H13: 15 | I13: 89 | J13: 552 | K13: 51916 | L13: =(G13-(H13*50))/50 -> 11.84 | M13: =31*(L13+H13) -> 832.04 | N13: z | O13: =(G13-(H13*90))/90 -> -0.088888889 | P13: =31*(O13+H13) -> 462.24444 | Q13: =(O13+H13)*31*F13*1.5 -> 65211.135 | R13: =P13 -> 462.24444 | S13: =R13/31 -> 14.911111 | T13: =S13-H13 -> -0.088888889 | U13: =Q13 -> 65211.135 | V13: 0.5 | W13: =X13/31 -> 7.4555556 | X13: =R13*V13 -> 231.12222 | Y13: =X13*F13*1.5 -> 32605.568 | Z13: 0.5 | AA13: =AB13/31 -> 7.4555556 | AB13: =R13*Z13 -> 231.12222 | AC13: =F13*AB13*1.5 -> 32605.568 | AD13: 重点降解
A14: CC0634 | B14: 3C-电子琴61健黑色 | C14: 马来 | D14: 3C数码 | E14: 电子琴 | F14: 37.88 | G14: 1221 | H14: 5 | I14: 244 | J14: 968 | K14: 51157 | L14: =(G14-(H14*50))/50 -> 19.42 | M14: =31*(L14+H14) -> 757.02 | N14: =M14*F14 -> 28675.918 | O14: =(G14-(H14*90))/90 -> 8.5666667 | P14: =31*(O14+H14) -> 420.56667 | Q14: =(O14+H14)*31*F14*1.5 -> 23896.598 | R14: =P14 -> 420.56667 | S14: =R14/31 -> 13.566667 | T14: =S14-H14 -> 8.5666667 | U14: =Q14 -> 23896.598 | V14: 0.5 | W14: =X14/31 -> 6.7833333 | X14: =R14*V14 -> 210.28333 | Y14: =X14*F14*1.5 -> 11948.299 | Z14: 0.5 | AA14: =AB14/31 -> 6.7833333 | AB14: =R14*Z14 -> 210.28333 | AC14: =F14*AB14*1.5 -> 11948.299 | AD14: 重点降解
A15: CC0342 | B15: 3B-保险柜100cm*51cm*45cm | C15: 马来 | D15: 办公安防 | E15: 保险箱 | F15: 823.74 | G15: 53 | J15: 42 | K15: 48189 | L15: =(G15-(H15*50))/50 -> 1.06 | M15: =31*(L15+H15) -> 32.86 | N15: =M15*F15 -> 27068.096 | O15: =(G15-(H15*90))/90 -> 0.58888889 | P15: =31*(O15+H15) -> 18.255556 | Q15: =(O15+H15)*31*F15*1.5 -> 22556.747 | R15: =P15 -> 18.255556 | S15: =R15/31 -> 0.58888889 | T15: =S15-H15 -> 0.58888889 | U15: =Q15 -> 22556.747 | V15: 0.5 | W15: =X15/31 -> 0.29444444 | X15: =R15*V15 -> 9.1277778 | Y15: =X15*F15*1.5 -> 11278.373 | Z15: 0.5 | AA15: =AB15/31 -> 0.29444444 | AB15: =R15*Z15 -> 9.1277778 | AC15: =F15*AB15*1.5 -> 11278.373 | AD15: 定点降解
A16: CC0686 | B16: 3B-白板通用支架60cm*100cm | C16: 马来 | D16: 办公安防 | E16: 支架 | F16: 22.27 | G16: 2095 | H16: 10 | I16: 209 | J16: 1549 | K16: 46878 | L16: =(G16-(H16*50))/50 -> 31.9 | M16: =31*(L16+H16) -> 1298.9 | N16: =M16*F16 -> 28926.503 | O16: =(G16-(H16*90))/90 -> 13.277778 | P16: =31*(O16+H16) -> 721.61111 | Q16: =(O16+H16)*31*F16*1.5 -> 24105.419 | R16: =P16 -> 721.61111 | S16: =R16/31 -> 23.277778 | T16: =S16-H16 -> 13.277778 | U16: =Q16 -> 24105.419 | V16: 0.6 | W16: =X16/31 -> 13.966667 | X16: =R16*V16 -> 432.96667 | Y16: =X16*F16*1.5 -> 14463.252 | Z16: 0.4 | AA16: =AB16/31 -> 9.3111111 | AB16: =R16*Z16 -> 288.64444 | AC16: =F16*AB16*1.5 -> 9642.1677
A17: CC0907 | B17: 3B-磁吸白板密度板夹层90cm*180cm | C17: 马来 | D17: 办公安防 | E17: 白板 | F17: 100.98 | G17: 646 | H17: 5 | I17: 129 | J17: 380 | K17: 46855 | L17: =(G17-(H17*50))/50 -> 7.92 | M17: =31*(L17+H17) -> 400.52 | N17: =M17*F17 -> 40444.51 | O17: =(G17-(H17*90))/90 -> 2.1777778 | P17: =31*(O17+H17) -> 222.51111 | Q17: =(O17+H17)*31*F17*1.5 -> 33703.758 | R17: =P17 -> 222.51111 | S17: =R17/31 -> 7.1777778 | T17: =S17-H17 -> 2.1777778 | U17: =Q17 -> 33703.758 | V17: 0.8 | W17: =X17/31 -> 5.7422222 | X17: =R17*V17 -> 178.00889 | Y17: =X17*F17*1.5 -> 26963.006 | Z17: 0.2 | AA17: =AB17/31 -> 1.4355556 | AB17: =R17*Z17 -> 44.502222 | AC17: =F17*AB17*1.5 -> 6740.7516 | AD17: 重点降解
A18: CC0514 | B18: 3B-路由器P6000白色 | C18: 马来 | D18: 办公安防 | E18: 路由器 | F18: 93.44 | G18: 401 | H18: 1 | I18: 401 | J18: 334 | K18: 44337 | L18: =(G18-(H18*50))/50 -> 7.02 | M18: =31*(L18+H18) -> 248.62 | N18: =M18*F18 -> 23231.053 | O18: =(G18-(H18*90))/90 -> 3.4555556 | P18: =31*(O18+H18) -> 138.12222 | Q18: =(O18+H18)*31*F18*1.5 -> 19359.211 | R18: =P18 -> 138.12222 | S18: =R18/31 -> 4.4555556 | T18: =S18-H18 -> 3.4555556 | U18: =Q18 -> 19359.211 | V18: 0 | W18: =X18/31 -> 0 | X18: =R18*V18 -> 0 | Y18: =X18*F18*1.5 -> 0 | Z18: 0 | AA18: =AB18/31 -> 0 | AB18: =R18*Z18 -> 0 | AC18: =F18*AB18*1.5 -> 0
A19: CC0688 | B19: 3C-原木色吉他套装 | C19: 马来 | D19: 3C数码 | E19: 吉他套装 | F19: 76.15 | G19: 830 | H19: 7 | I19: 118 | J19: 469 | K19: 42606 | L19: =(G19-(H19*50))/50 -> 9.6 | M19: =31*(L19+H19) -> 514.6 | N19: =M19*F19 -> 39186.79 | O19: =(G19-(H19*90))/90 -> 2.2222222 | P19: =31*(O19+H19) -> 285.88889 | Q19: =(O19+H19)*31*F19*1.5 -> 32655.658 | R19: =P19 -> 285.88889 | S19: =R19/31 -> 9.2222222 | T19: =S19-H19 -> 2.2222222 | U19: =Q19 -> 32655.658 | V19: 0.5 | W19: =X19/31 -> 4.6111111 | X19: =R19*V19 -> 142.94444 | Y19: =X19*F19*1.5 -> 16327.829 | Z19: 0.5 | AA19: =AB19/31 -> 4.6111111 | AB19: =R19*Z19 -> 142.94444 | AC19: =F19*AB19*1.5 -> 16327.829
A20: CC0732 | B20: 3B-橡胶磁白板背胶90cm*180cm | C20: 马来 | D20: 办公安防 | E20: 白板 | F20: 67.4 | G20: 471 | H20: 1 | I20: 471 | J20: 396 | K20: 38014 | L20: =(G20-(H20*50))/50 -> 8.42 | M20: =31*(L20+H20) -> 292.02 | N20: =M20*F20 -> 19682.148 | O20: =(G20-(H20*90))/90 -> 4.2333333 | P20: =31*(O20+H20) -> 162.23333 | Q20: =(O20+H20)*31*F20*1.5 -> 16401.79 | R20: =P20 -> 162.23333 | S20: =R20/31 -> 5.2333333 | T20: =S20-H20 -> 4.2333333 | U20: =Q20 -> 16401.79 | V20: 0.5 | W20: =X20/31 -> 2.6166667 | X20: =R20*V20 -> 81.116667 | Y20: =X20*F20*1.5 -> 8200.895 | Z20: 0.5 | AA20: =AB20/31 -> 2.6166667 | AB20: =R20*Z20 -> 81.116667 | AC20: =F20*AB20*1.5 -> 8200.895 | AD20: 重点降解
A21: CC0315 | B21: 3B-密码保险箱黑 | C21: 马来 | D21: 办公安防 | E21: 保险箱 | F21: 123.29 | G21: 752 | H21: 9 | I21: 83 | J21: 287 | K21: 35384 | L21: =(G21-(H21*50))/50 -> 6.04 | M21: =31*(L21+H21) -> 466.24 | N21: =M21*F21 -> 57482.73 | O21: =(G21-(H21*90))/90 -> -0.64444444 | P21: =31*(O21+H21) -> 259.02222 | Q21: =(O21+H21)*31*F21*1.5 -> 47902.275 | R21: =P21 -> 259.02222 | S21: =R21/31 -> 8.3555556 | T21: =S21-H21 -> -0.64444444 | U21: =Q21 -> 47902.275 | V21: 0.4 | W21: =X21/31 -> 3.3422222 | X21: =R21*V21 -> 103.60889 | Y21: 60 | Z21: 0.74358974 | AA21: =AB21/31 -> 6.2131054 | AB21: =R21*Z21 -> 192.60627 | AC21: =F21*AB21*1.5 -> 35619.64
A22: CC0277 | B22: 3B-智能指纹门锁M20 | C22: 马来 | D22: 办公安防 | E22: 指纹锁 | F22: 74.88 | G22: 505 | H22: 3 | I22: 168 | J22: 347 | K22: 34220 | L22: =(G22-(H22*50))/50 -> 7.1 | M22: =31*(L22+H22) -> 313.1 | N22: =M22*F22 -> 23444.928 | O22: =(G22-(H22*90))/90 -> 2.6111111 | P22: =31*(O22+H22) -> 173.94444 | Q22: =(O22+H22)*31*F22*1.5 -> 19537.44 | R22: =P22 -> 173.94444 | S22: =R22/31 -> 5.6111111 | T22: =S22-H22 -> 2.6111111 | U22: =Q22 -> 19537.44 | V22: 0.6 | W22: =X22/31 -> 3.3666667 | X22: =R22*V22 -> 104.36667 | Y22: =X22*F22*1.5 -> 11722.464 | Z22: 0.4 | AA22: =AB22/31 -> 2.2444444 | AB22: =R22*Z22 -> 69.577778 | AC22: =F22*AB22*1.5 -> 7814.976 | AD22: 重点降解
A23: CC0377 | B23: 3B-宽57cm热敏打印纸5卷 | C23: 马来 | D23: 办公安防 | E23: 标签打印纸 | F23: 4.1901 | G23: 10112 | H23: 81 | I23: 124 | J23: 6024 | K23: 31009 | L23: =(G23-(H23*50))/50 -> 121.24 | M23: =31*(L23+H23) -> 6269.44 | N23: =M23*F23 -> 26269.581 | O23: =(G23-(H23*90))/90 -> 31.355556 | P23: =31*(O23+H23) -> 3483.0222 | Q23: =(O23+H23)*31*F23*1.5 -> 21891.317 | R23: =P23 -> 3483.0222 | S23: =R23/31 -> 112.35556 | T23: =S23-H23 -> 31.355556 | U23: =Q23 -> 21891.317 | V23: 0.65 | W23: =X23/31 -> 73.031111 | X23: =R23*V23 -> 2263.9644 | Y23: =X23*F23*1.5 -> 14229.356 | Z23: 0.35 | AA23: =AB23/31 -> 39.324444 | AB23: =R23*Z23 -> 1219.0578 | AC23: =F23*AB23*1.5 -> 7661.961
A24: CC0768 | B24: 3B-可翻转白板50*70 | C24: 马来 | D24: 办公安防 | E24: 教具白板 | F24: 77.78 | G24: 388 | H24: 2 | I24: 194 | J24: 285 | K24: 30023 | L24: =(G24-(H24*50))/50 -> 5.76 | M24: =31*(L24+H24) -> 240.56 | N24: =M24*F24 -> 18710.757 | O24: =(G24-(H24*90))/90 -> 2.3111111 | P24: =31*(O24+H24) -> 133.64444 | Q24: =(O24+H24)*31*F24*1.5 -> 15592.297 | R24: =P24 -> 133.64444 | S24: =R24/31 -> 4.3111111 | T24: =S24-H24 -> 2.3111111 | U24: =Q24 -> 15592.297 | V24: 0.5 | W24: =X24/31 -> 2.1555556 | X24: =R24*V24 -> 66.822222 | Y24: =X24*F24*1.5 -> 7796.1487 | Z24: 0.5 | AA24: =AB24/31 -> 2.1555556 | AB24: =R24*Z24 -> 66.822222 | AC24: =F24*AB24*1.5 -> 7796.1487 | AD24: 重点降解
A25: CC0181 | B25: 3B-碎纸机10L | C25: 马来 | D25: 办公安防 | E25: 碎纸机 | F25: 83.69 | G25: 816 | H25: 9 | I25: 90 | J25: 358 | K25: 29961 | L25: =(G25-(H25*50))/50 -> 7.32 | M25: =31*(L25+H25) -> 505.92 | N25: =M25*F25 -> 42340.445 | O25: =(G25-(H25*90))/90 -> 0.066666667 | P25: =31*(O25+H25) -> 281.06667 | Q25: =(O25+H25)*31*F25*1.5 -> 35283.704 | R25: =P25 -> 281.06667 | S25: =R25/31 -> 9.0666667 | T25: =S25-H25 -> 0.066666667 | U25: =Q25 -> 35283.704 | V25: 0.6 | W25: =X25/31 -> 5.44 | X25: =R25*V25 -> 168.64 | Y25: =X25*F25*1.5 -> 21170.222 | Z25: 0.4 | AA25: =AB25/31 -> 3.6266667 | AB25: =R25*Z25 -> 112.42667 | AC25: =F25*AB25*1.5 -> 14113.482 | AD25: 重点降解
A26: CC0876 | B26: 3B-B1A五功能断桥铝锁带APP | C26: 马来 | D26: 办公安防 | E26: 密码锁 | F26: 176.53 | G26: 122 | J26: 106 | K26: 26921 | L26: =(G26-(H26*50))/50 -> 2.44 | M26: =31*(L26+H26) -> 75.64 | N26: =M26*F26 -> 13352.729 | O26: =(G26-(H26*90))/90 -> 1.3555556 | P26: =31*(O26+H26) -> 42.022222 | Q26: =(O26+H26)*31*F26*1.5 -> 11127.274 | R26: =P26 -> 42.022222 | S26: =R26/31 -> 1.3555556 | T26: =S26-H26 -> 1.3555556 | U26: =Q26 -> 11127.274 | V26: 0.5 | W26: =X26/31 -> 0.67777778 | X26: =R26*V26 -> 21.011111 | Y26: =X26*F26*1.5 -> 5563.6372 | Z26: 0.5 | AA26: =AB26/31 -> 0.67777778 | AB26: =R26*Z26 -> 21.011111 | AC26: =F26*AB26*1.5 -> 5563.6372 | AD26: 重点降解
A27: CC0678 | B27: 3C-11.6寸60Hz直面1K便携式显示器无触摸黑色 | C27: 马来 | D27: 3C数码 | E27: 显示器 | F27: 160.23 | G27: 1219 | H27: 21 | I27: 58 | J27: 161 | K27: 25797 | L27: =(G27-(H27*50))/50 -> 3.38 | M27: =31*(L27+H27) -> 755.78 | N27: =M27*F27 -> 121098.63 | O27: =(G27-(H27*90))/90 -> -7.4555556 | P27: =31*(O27+H27) -> 419.87778 | Q27: =(O27+H27)*31*F27*1.5 -> 100915.52 | R27: =P27 -> 419.87778 | S27: =R27/31 -> 13.544444 | T27: =S27-H27 -> -7.4555556 | U27: =Q27 -> 100915.52 | V27: 0.5 | W27: =X27/31 -> 6.7722222 | X27: =R27*V27 -> 209.93889 | Y27: =X27*F27*1.5 -> 50457.762 | Z27: 0.5 | AA27: =AB27/31 -> 6.7722222 | AB27: =R27*Z27 -> 209.93889 | AC27: =F27*AB27*1.5 -> 50457.762
A28: CC0177 | B28: 3B-300CWiFi路由器 | C28: 马来 | D28: 办公安防 | E28: 路由器 | F28: 127.34 | G28: 135 | J28: 132 | K28: 25022 | L28: =(G28-(H28*50))/50 -> 2.7 | M28: =31*(L28+H28) -> 83.7 | N28: =M28*F28 -> 10658.358 | O28: =(G28-(H28*90))/90 -> 1.5 | P28: =31*(O28+H28) -> 46.5 | Q28: =(O28+H28)*31*F28*1.5 -> 8881.965 | R28: =P28 -> 46.5 | S28: =R28/31 -> 1.5 | T28: =S28-H28 -> 1.5 | U28: =Q28 -> 8881.965 | V28: 0.85 | W28: =X28/31 -> 1.275 | X28: =R28*V28 -> 39.525 | Y28: =X28*F28*1.5 -> 7549.6703 | Z28: 0.14090909 | AA28: =AB28/31 -> 0.21136364 | AB28: =R28*Z28 -> 6.5522727 | AC28: =F28*AB28*1.5 -> 1251.5496
A29: CC0860 | B29: 3C-辉光管 | C29: 马来 | D29: 3C数码 | E29: 辉光管 | F29: 203.25 | G29: 83 | J29: 78 | K29: 23374 | L29: =(G29-(H29*50))/50 -> 1.66 | M29: =31*(L29+H29) -> 51.46 | N29: =M29*F29 -> 10459.245 | O29: =(G29-(H29*90))/90 -> 0.92222222 | P29: =31*(O29+H29) -> 28.588889 | Q29: =(O29+H29)*31*F29*1.5 -> 8716.0375 | R29: =P29 -> 28.588889 | S29: =R29/31 -> 0.92222222 | T29: =S29-H29 -> 0.92222222 | U29: =Q29 -> 8716.0375 | V29: 0.3 | W29: =X29/31 -> 0.27666667 | X29: =R29*V29 -> 8.5766667 | Y29: =X29*F29*1.5 -> 2614.8113 | Z29: 0.7 | AA29: =AB29/31 -> 0.64555556 | AB29: =R29*Z29 -> 20.012222 | AC29: =F29*AB29*1.5 -> 6101.2262 | AD29: 定点降解
A30: CC0850 | B30: 3C-RGB蓝牙无线拉伸手机游戏手柄STK7009 | C30: 马来 | D30: 3C数码 | E30: 游戏手柄 | F30: 94.09 | G30: 189 | J30: 163 | K30: 22017 | L30: =(G30-(H30*50))/50 -> 3.78 | M30: =31*(L30+H30) -> 117.18 | N30: =M30*F30 -> 11025.466 | O30: =(G30-(H30*90))/90 -> 2.1 | P30: =31*(O30+H30) -> 65.1 | Q30: =(O30+H30)*31*F30*1.5 -> 9187.8885 | R30: =P30 -> 65.1 | S30: =R30/31 -> 2.1 | T30: =S30-H30 -> 2.1 | U30: =Q30 -> 9187.8885 | V30: 0.2 | W30: =X30/31 -> 0.42 | X30: =R30*V30 -> 13.02 | Y30: =X30*F30*1.5 -> 1837.5777 | Z30: 0.8 | AA30: =AB30/31 -> 1.68 | AB30: =R30*Z30 -> 52.08 | AC30: =F30*AB30*1.5 -> 7350.3108
A31: CC0807 | B31: 3C-显示器桌面支架3屏 | C31: 马来 | D31: 3C数码 | E31: 显示器支架 | F31: 89.55 | G31: 170 | J31: 164 | K31: 21805 | L31: =(G31-(H31*50))/50 -> 3.4 | M31: =31*(L31+H31) -> 105.4 | N31: =M31*F31 -> 9438.57 | O31: =(G31-(H31*90))/90 -> 1.8888889 | P31: =31*(O31+H31) -> 58.555556 | Q31: =(O31+H31)*31*F31*1.5 -> 7865.475 | R31: =P31 -> 58.555556 | S31: =R31/31 -> 1.8888889 | T31: =S31-H31 -> 1.8888889 | U31: =Q31 -> 7865.475 | V31: 0.7 | W31: =X31/31 -> 1.3222222 | X31: =R31*V31 -> 40.988889 | Y31: =X31*F31*1.5 -> 5505.8325 | Z31: 0.3 | AA31: =AB31/31 -> 0.56666667 | AB31: =R31*Z31 -> 17.566667 | AC31: =F31*AB31*1.5 -> 2359.6425 | AD31: 重点降解
A32: CC0905 | B32: 3B-磁吸白板密度板夹层90cm*120cm | C32: 马来 | D32: 办公安防 | E32: 白板 | F32: 79.26 | G32: 957 | H32: 13 | I32: 73 | J32: 266 | K32: 21083 | L32: =(G32-(H32*50))/50 -> 6.14 | M32: =31*(L32+H32) -> 593.34 | N32: =M32*F32 -> 47028.128 | O32: =(G32-(H32*90))/90 -> -2.3666667 | P32: =31*(O32+H32) -> 329.63333 | Q32: =(O32+H32)*31*F32*1.5 -> 39190.107 | R32: =P32 -> 329.63333 | S32: =R32/31 -> 10.633333 | T32: =S32-H32 -> -2.3666667 | U32: =Q32 -> 39190.107 | V32: 0.5 | W32: =X32/31 -> 5.3166667 | X32: =R32*V32 -> 164.81667 | Y32: =X32*F32*1.5 -> 19595.054 | Z32: 0.5 | AA32: =AB32/31 -> 5.3166667 | AB32: =R32*Z32 -> 164.81667 | AC32: =F32*AB32*1.5 -> 19595.054 | AD32: 重点降解
A33: CC0763 | B33: 3B-打孔机 | C33: 马来 | D33: 办公安防 | E33: 装订机 | F33: 116.93 | G33: 200 | H33: 1 | I33: 200 | J33: 127 | K33: 18826 | L33: =(G33-(H33*50))/50 -> 3 | M33: =31*(L33+H33) -> 124 | N33: =M33*F33 -> 14499.32 | O33: =(G33-(H33*90))/90 -> 1.2222222 | P33: =31*(O33+H33) -> 68.888889 | Q33: =(O33+H33)*31*F33*1.5 -> 12082.767 | R33: =P33 -> 68.888889 | S33: =R33/31 -> 2.2222222 | T33: =S33-H33 -> 1.2222222 | U33: =Q33 -> 12082.767 | V33: 0.6 | W33: =X33/31 -> 1.3333333 | X33: =R33*V33 -> 41.333333 | Y33: =X33*F33*1.5 -> 7249.66 | Z33: 0.4 | AA33: =AB33/31 -> 0.88888889 | AB33: =R33*Z33 -> 27.555556 | AC33: =F33*AB33*1.5 -> 4833.1067
A34: CC0339 | B34: 3B-保险柜80cm*44cm*40cm | C34: 马来 | D34: 办公安防 | E34: 保险箱 | F34: 616.96 | G34: 33 | J34: 23 | K34: 18817 | L34: =(G34-(H34*50))/50 -> 0.66 | M34: =31*(L34+H34) -> 20.46 | N34: =M34*F34 -> 12623.002 | O34: =(G34-(H34*90))/90 -> 0.36666667 | P34: =31*(O34+H34) -> 11.366667 | Q34: =(O34+H34)*31*F34*1.5 -> 10519.168 | R34: =P34 -> 11.366667 | S34: =R34/31 -> 0.36666667 | T34: =S34-H34 -> 0.36666667 | U34: =Q34 -> 10519.168 | V34: 0.5 | W34: =X34/31 -> 0.18333333 | X34: =R34*V34 -> 5.6833333 | Y34: =X34*F34*1.5 -> 5259.584 | Z34: 0.5 | AA34: =AB34/31 -> 0.18333333 | AB34: =R34*Z34 -> 5.6833333 | AC34: =F34*AB34*1.5 -> 5259.584 | AD34: 定点降解
A35: CC0730 | B35: 3B-橡胶磁白板背胶60cm*90cm | C35: 马来 | D35: 办公安防 | E35: 白板 | F35: 27.45 | G35: 717 | H35: 4 | I35: 179 | J35: 502 | K35: 18309 | L35: =(G35-(H35*50))/50 -> 10.34 | M35: =31*(L35+H35) -> 444.54 | N35: =M35*F35 -> 12202.623 | O35: =(G35-(H35*90))/90 -> 3.9666667 | P35: =31*(O35+H35) -> 246.96667 | Q35: =(O35+H35)*31*F35*1.5 -> 10168.853 | R35: =P35 -> 246.96667 | S35: =R35/31 -> 7.9666667 | T35: =S35-H35 -> 3.9666667 | U35: =Q35 -> 10168.853 | V35: 0.5 | W35: =X35/31 -> 3.9833333 | X35: =R35*V35 -> 123.48333 | Y35: =X35*F35*1.5 -> 5084.4263 | Z35: 0.5 | AA35: =AB35/31 -> 3.9833333 | AB35: =R35*Z35 -> 123.48333 | AC35: =F35*AB35*1.5 -> 5084.4263 | AD35: 重点降解
A36: CC0733 | B36: 3B-橡胶磁白板背胶120cm*150cm | C36: 马来 | D36: 办公安防 | E36: 白板 | F36: 77.79 | G36: 308 | H36: 2 | I36: 154 | J36: 182 | K36: 17308 | L36: =(G36-(H36*50))/50 -> 4.16 | M36: =31*(L36+H36) -> 190.96 | N36: =M36*F36 -> 14854.778 | O36: =(G36-(H36*90))/90 -> 1.4222222 | P36: =31*(O36+H36) -> 106.08889 | Q36: =(O36+H36)*31*F36*1.5 -> 12378.982 | R36: =P36 -> 106.08889 | S36: =R36/31 -> 3.4222222 | T36: =S36-H36 -> 1.4222222 | U36: =Q36 -> 12378.982 | V36: 0.5 | W36: =X36/31 -> 1.7111111 | X36: =R36*V36 -> 53.044444 | Y36: =X36*F36*1.5 -> 6189.491 | Z36: 0.5 | AA36: =AB36/31 -> 1.7111111 | AB36: =R36*Z36 -> 53.044444 | AC36: =F36*AB36*1.5 -> 6189.491 | AD36: 重点降解
A37: CC0731 | B37: 3B-橡胶磁白板背胶90cm*120cm | C37: 马来 | D37: 办公安防 | E37: 白板 | F37: 48.74 | G37: 505 | H37: 4 | I37: 126 | J37: 293 | K37: 17303 | L37: =(G37-(H37*50))/50 -> 6.1 | M37: =31*(L37+H37) -> 313.1 | N37: =M37*F37 -> 15260.494 | O37: =(G37-(H37*90))/90 -> 1.6111111 | P37: =31*(O37+H37) -> 173.94444 | Q37: =(O37+H37)*31*F37*1.5 -> 12717.078 | R37: =P37 -> 173.94444 | S37: =R37/31 -> 5.6111111 | T37: =S37-H37 -> 1.6111111 | U37: =Q37 -> 12717.078 | V37: 0.5 | W37: =X37/31 -> 2.8055556 | X37: =R37*V37 -> 86.972222 | Y37: =X37*F37*1.5 -> 6358.5392 | Z37: 0.5 | AA37: =AB37/31 -> 2.8055556 | AB37: =R37*Z37 -> 86.972222 | AC37: =F37*AB37*1.5 -> 6358.5392 | AD37: 重点降解
A38: CC0433 | B38: 3B-四功能智能门锁 | C38: 马来 | D38: 办公安防 | E38: 智能锁 | F38: 95.2 | G38: 801 | H38: 12 | I38: 66 | J38: 179 | K38: 17041 | L38: =(G38-(H38*50))/50 -> 4.02 | M38: =31*(L38+H38) -> 496.62 | N38: =M38*F38 -> 47278.224 | O38: =(G38-(H38*90))/90 -> -3.1 | P38: =31*(O38+H38) -> 275.9 | Q38: =(O38+H38)*31*F38*1.5 -> 39398.52 | R38: =P38 -> 275.9 | S38: =R38/31 -> 8.9 | T38: =S38-H38 -> -3.1 | U38: =Q38 -> 39398.52 | V38: 0.5 | W38: =X38/31 -> 4.45 | X38: =R38*V38 -> 137.95 | Y38: =X38*F38*1.5 -> 19699.26 | Z38: 0.5 | AA38: =AB38/31 -> 4.45 | AB38: =R38*Z38 -> 137.95 | AC38: =F38*AB38*1.5 -> 19699.26
A39: CC0727 | B39: 3C-led智能互动屏59.5cm*12cm | C39: 马来 | D39: 3C数码 | E39: LED像素屏 | F39: 157.1 | G39: 96 | J39: 76 | K39: 16653 | L39: =(G39-(H39*50))/50 -> 1.92 | M39: =31*(L39+H39) -> 59.52 | N39: =M39*F39 -> 9350.592 | O39: =(G39-(H39*90))/90 -> 1.0666667 | P39: =31*(O39+H39) -> 33.066667 | Q39: =(O39+H39)*31*F39*1.5 -> 7792.16 | R39: =P39 -> 33.066667 | S39: =R39/31 -> 1.0666667 | T39: =S39-H39 -> 1.0666667 | U39: =Q39 -> 7792.16 | V39: 0.4 | W39: =X39/31 -> 0.42666667 | X39: =R39*V39 -> 13.226667 | Y39: =X39*F39*1.5 -> 3116.864 | Z39: 0.6 | AA39: =AB39/31 -> 0.64 | AB39: =R39*Z39 -> 19.84 | AC39: =F39*AB39*1.5 -> 4675.296
A40: CC0101 | B40: 3C-插电式分体电动旋转盘白色20cm | C40: 马来 | D40: 3C数码 | E40: 展示台 | F40: 25.54 | G40: 933 | H40: 8 | I40: 116 | J40: 532 | K40: 16282 | L40: =(G40-(H40*50))/50 -> 10.66 | M40: =31*(L40+H40) -> 578.46 | N40: =M40*F40 -> 14773.868 | O40: =(G40-(H40*90))/90 -> 2.3666667 | P40: =31*(O40+H40) -> 321.36667 | Q40: =(O40+H40)*31*F40*1.5 -> 12311.557 | R40: =P40 -> 321.36667 | S40: =R40/31 -> 10.366667 | T40: =S40-H40 -> 2.3666667 | U40: =Q40 -> 12311.557 | V40: 0.6 | W40: =X40/31 -> 6.22 | X40: =R40*V40 -> 192.82 | Y40: =X40*F40*1.5 -> 7386.9342 | Z40: 0.4 | AA40: =AB40/31 -> 4.1466667 | AB40: =R40*Z40 -> 128.54667 | AC40: =F40*AB40*1.5 -> 4924.6228
A41: CC0695 | B41: 3B-白板双杠可伸缩通用支架 | C41: 马来 | D41: 办公安防 | E41: 白板通用支架 | F41: 30.64 | G41: 1198 | H41: 13 | I41: 92 | J41: 506 | K41: 15504 | L41: =(G41-(H41*50))/50 -> 10.96 | M41: =31*(L41+H41) -> 742.76 | N41: =M41*F41 -> 22758.166 | O41: =(G41-(H41*90))/90 -> 0.31111111 | P41: =31*(O41+H41) -> 412.64444 | Q41: =(O41+H41)*31*F41*1.5 -> 18965.139 | R41: =P41 -> 412.64444 | S41: =R41/31 -> 13.311111 | T41: =S41-H41 -> 0.31111111 | U41: =Q41 -> 18965.139 | V41: 0.65 | W41: =X41/31 -> 8.6522222 | X41: =R41*V41 -> 268.21889 | Y41: =X41*F41*1.5 -> 12327.34 | Z41: 0.35 | AA41: =AB41/31 -> 4.6588889 | AB41: =R41*Z41 -> 144.42556 | AC41: =F41*AB41*1.5 -> 6637.7985
A42: CC0996 | B42: 3C-专业播客动圈麦克风 | C42: 马来 | D42: 3C数码 | E42: 有线麦克风 | F42: 152.93 | G42: 74 | J42: 68 | K42: 15217 | L42: =(G42-(H42*50))/50 -> 1.48 | M42: =31*(L42+H42) -> 45.88 | N42: =M42*F42 -> 7016.4284 | O42: =(G42-(H42*90))/90 -> 0.82222222 | P42: =31*(O42+H42) -> 25.488889 | Q42: =(O42+H42)*31*F42*1.5 -> 5847.0237 | R42: =P42 -> 25.488889 | S42: =R42/31 -> 0.82222222 | T42: =S42-H42 -> 0.82222222 | U42: =Q42 -> 5847.0237 | V42: 0.5 | W42: =X42/31 -> 0.41111111 | X42: =R42*V42 -> 12.744444 | Y42: =X42*F42*1.5 -> 2923.5118 | Z42: 0.5 | AA42: =AB42/31 -> 0.41111111 | AB42: =R42*Z42 -> 12.744444 | AC42: =F42*AB42*1.5 -> 2923.5118 | AD42: 新品降解
A43: CC0477 | B43: 3B-快递面单打印机白色 | C43: 马来 | D43: 办公安防 | E43: 打印机 | F43: 184.47 | G43: 238 | H43: 3 | I43: 79 | J43: 82 | K43: 15127 | L43: =(G43-(H43*50))/50 -> 1.76 | M43: =31*(L43+H43) -> 147.56 | N43: =M43*F43 -> 27220.393 | O43: =(G43-(H43*90))/90 -> -0.35555556 | P43: =31*(O43+H43) -> 81.977778 | Q43: =(O43+H43)*31*F43*1.5 -> 22683.661 | R43: =P43 -> 81.977778 | S43: =R43/31 -> 2.6444444 | T43: =S43-H43 -> -0.35555556 | U43: =Q43 -> 22683.661 | V43: 0.7 | W43: =X43/31 -> 1.8511111 | X43: =R43*V43 -> 57.384444 | Y43: =X43*F43*1.5 -> 15878.563 | Z43: 0.3 | AA43: =AB43/31 -> 0.79333333 | AB43: =R43*Z43 -> 24.593333 | AC43: =F43*AB43*1.5 -> 6805.0983
A44: CC0823 | B44: 3B-指纹挂锁 | C44: 马来 | D44: 办公安防 | E44: 智能锁 | F44: 37.32 | G44: 291 | J44: 273 | K44: 15003 | L44: =(G44-(H44*50))/50 -> 5.82 | M44: =31*(L44+H44) -> 180.42 | N44: =M44*F44 -> 6733.2744 | O44: =(G44-(H44*90))/90 -> 3.2333333 | P44: =31*(O44+H44) -> 100.23333 | Q44: =(O44+H44)*31*F44*1.5 -> 5611.062 | R44: =P44 -> 100.23333 | S44: =R44/31 -> 3.2333333 | T44: =S44-H44 -> 3.2333333 | U44: =Q44 -> 5611.062 | V44: 0.5 | W44: =X44/31 -> 1.6166667 | X44: =R44*V44 -> 50.116667 | Y44: =X44*F44*1.5 -> 2805.531 | Z44: 0.5 | AA44: =AB44/31 -> 1.6166667 | AB44: =R44*Z44 -> 50.116667 | AC44: =F44*AB44*1.5 -> 2805.531 | AD44: 重点降解
A45: CC0728 | B45: 3B-橡胶磁白板背胶45cm*75cm | C45: 马来 | D45: 办公安防 | E45: 白板 | F45: 18.48 | G45: 764 | H45: 4 | I45: 191 | J45: 549 | K45: 13629 | L45: =(G45-(H45*50))/50 -> 11.28 | M45: =31*(L45+H45) -> 473.68 | N45: =M45*F45 -> 8753.6064 | O45: =(G45-(H45*90))/90 -> 4.4888889 | P45: =31*(O45+H45) -> 263.15556 | Q45: =(O45+H45)*31*F45*1.5 -> 7294.672 | R45: =P45 -> 263.15556 | S45: =R45/31 -> 8.4888889 | T45: =S45-H45 -> 4.4888889 | U45: =Q45 -> 7294.672 | V45: 0.5 | W45: =X45/31 -> 4.2444444 | X45: =R45*V45 -> 131.57778 | Y45: =X45*F45*1.5 -> 3647.336 | Z45: 0.5 | AA45: =AB45/31 -> 4.2444444 | AB45: =R45*Z45 -> 131.57778 | AC45: =F45*AB45*1.5 -> 3647.336 | AD45: 重点降解
A46: CC0102 | B46: 3C-插电式分体电动旋转盘黑色13cm | C46: 马来 | D46: 3C数码 | E46: 展示台 | F46: 16.51 | G46: 716 | H46: 3 | I46: 238 | J46: 551 | K46: 12556 | L46: =(G46-(H46*50))/50 -> 11.32 | M46: =31*(L46+H46) -> 443.92 | N46: =M46*F46 -> 7329.1192 | O46: =(G46-(H46*90))/90 -> 4.9555556 | P46: =31*(O46+H46) -> 246.62222 | Q46: =(O46+H46)*31*F46*1.5 -> 6107.5993 | R46: =P46 -> 246.62222 | S46: =R46/31 -> 7.9555556 | T46: =S46-H46 -> 4.9555556 | U46: =Q46 -> 6107.5993 | V46: 0.5 | W46: =X46/31 -> 3.9777778 | X46: =R46*V46 -> 123.31111 | Y46: =X46*F46*1.5 -> 3053.7997 | Z46: 0.5 | AA46: =AB46/31 -> 3.9777778 | AB46: =R46*Z46 -> 123.31111 | AC46: =F46*AB46*1.5 -> 3053.7997
A47: CC0611 | B47: 3C-投影仪支架1.2米 | C47: 马来 | D47: 3C数码 | E47: 投影仪支架 | F47: 17.1 | G47: 577 | H47: 1 | I47: 577 | J47: 506 | K47: 12492 | L47: =(G47-(H47*50))/50 -> 10.54 | M47: =31*(L47+H47) -> 357.74 | N47: =M47*F47 -> 6117.354 | O47: =(G47-(H47*90))/90 -> 5.4111111 | P47: =31*(O47+H47) -> 198.74444 | Q47: =(O47+H47)*31*F47*1.5 -> 5097.795 | R47: =P47 -> 198.74444 | S47: =R47/31 -> 6.4111111 | T47: =S47-H47 -> 5.4111111 | U47: =Q47 -> 5097.795 | V47: 0.6 | W47: =X47/31 -> 3.8466667 | X47: =R47*V47 -> 119.24667 | Y47: =X47*F47*1.5 -> 3058.677 | Z47: 0.4 | AA47: =AB47/31 -> 2.5644444 | AB47: =R47*Z47 -> 79.497778 | AC47: =F47*AB47*1.5 -> 2039.118
A48: CC0386 | B48: 3B-钥匙款保险箱黑小23*17*17cm | C48: 马来 | D48: 办公安防 | E48: 保险箱 | F48: 53.84 | G48: 381 | H48: 3 | I48: 127 | J48: 201 | K48: 12356 | L48: =(G48-(H48*50))/50 -> 4.62 | M48: =31*(L48+H48) -> 236.22 | N48: =M48*F48 -> 12718.085 | O48: =(G48-(H48*90))/90 -> 1.2333333 | P48: =31*(O48+H48) -> 131.23333 | Q48: =(O48+H48)*31*F48*1.5 -> 10598.404 | R48: =P48 -> 131.23333 | S48: =R48/31 -> 4.2333333 | T48: =S48-H48 -> 1.2333333 | U48: =Q48 -> 10598.404 | V48: 0.4 | W48: =X48/31 -> 1.6933333 | X48: =R48*V48 -> 52.493333 | Y48: =X48*F48*1.5 -> 4239.3616 | Z48: 0.6 | AA48: =AB48/31 -> 2.54 | AB48: =R48*Z48 -> 78.74 | AC48: =F48*AB48*1.5 -> 6359.0424
A49: CC0633 | B49: 3C-电子琴37健黑色 | C49: 马来 | D49: 3C数码 | E49: 电子琴 | F49: 18.76 | G49: 928 | H49: 7 | I49: 132 | J49: 538 | K49: 12213 | L49: =(G49-(H49*50))/50 -> 11.56 | M49: =31*(L49+H49) -> 575.36 | N49: =M49*F49 -> 10793.754 | O49: =(G49-(H49*90))/90 -> 3.3111111 | P49: =31*(O49+H49) -> 319.64444 | Q49: =(O49+H49)*31*F49*1.5 -> 8994.7947 | R49: =P49 -> 319.64444 | S49: =R49/31 -> 10.311111 | T49: =S49-H49 -> 3.3111111 | U49: =Q49 -> 8994.7947 | V49: 0.5 | W49: =X49/31 -> 5.1555556 | X49: =R49*V49 -> 159.82222 | Y49: =X49*F49*1.5 -> 4497.3973 | Z49: 0.5 | AA49: =AB49/31 -> 5.1555556 | AB49: =R49*Z49 -> 159.82222 | AC49: =F49*AB49*1.5 -> 4497.3973 | AD49: 重点降解
A50: CC1008 | B50: 3C-电脑机箱T6款黑色3风扇 | C50: 马来 | D50: 3C数码 | E50: 电脑机箱 | F50: 193.62 | G50: 74 | J50: 48 | K50: 12004 | L50: =(G50-(H50*50))/50 -> 1.48 | M50: =31*(L50+H50) -> 45.88 | N50: =M50*F50 -> 8883.2856 | O50: =(G50-(H50*90))/90 -> 0.82222222 | P50: =31*(O50+H50) -> 25.488889 | Q50: =(O50+H50)*31*F50*1.5 -> 7402.738 | R50: =P50 -> 25.488889 | S50: =R50/31 -> 0.82222222 | T50: =S50-H50 -> 0.82222222 | U50: =Q50 -> 7402.738 | V50: 0.5 | W50: =X50/31 -> 0.41111111 | X50: =R50*V50 -> 12.744444 | Y50: =X50*F50*1.5 -> 3701.369 | Z50: 0.5 | AA50: =AB50/31 -> 0.41111111 | AB50: =R50*Z50 -> 12.744444 | AC50: =F50*AB50*1.5 -> 3701.369 | AD50: 重点降解
A51: CC0769 | B51: 3B-可翻转白板60*90 | C51: 马来 | D51: 办公安防 | E51: 教具白板 | F51: 96.65 | G51: 92 | J51: 79 | K51: 10921 | L51: =(G51-(H51*50))/50 -> 1.84 | M51: =31*(L51+H51) -> 57.04 | N51: =M51*F51 -> 5512.916 | O51: =(G51-(H51*90))/90 -> 1.0222222 | P51: =31*(O51+H51) -> 31.688889 | Q51: =(O51+H51)*31*F51*1.5 -> 4594.0967 | R51: =P51 -> 31.688889 | S51: =R51/31 -> 1.0222222 | T51: =S51-H51 -> 1.0222222 | U51: =Q51 -> 4594.0967 | V51: 0.5 | W51: =X51/31 -> 0.51111111 | X51: =R51*V51 -> 15.844444 | Y51: =X51*F51*1.5 -> 2297.0483 | Z51: 0.5 | AA51: =AB51/31 -> 0.51111111 | AB51: =R51*Z51 -> 15.844444 | AC51: =F51*AB51*1.5 -> 2297.0483
A52: CC0741 | B52: 3B-道路广角镜60cm | C52: 马来 | D52: 办公安防 | E52: 道路反光镜 | F52: 40.62 | G52: 188 | J52: 175 | K52: 10439 | L52: =(G52-(H52*50))/50 -> 3.76 | M52: =31*(L52+H52) -> 116.56 | N52: =M52*F52 -> 4734.6672 | O52: =(G52-(H52*90))/90 -> 2.0888889 | P52: =31*(O52+H52) -> 64.755556 | Q52: =(O52+H52)*31*F52*1.5 -> 3945.556 | R52: =P52 -> 64.755556 | S52: =R52/31 -> 2.0888889 | T52: =S52-H52 -> 2.0888889 | U52: =Q52 -> 3945.556 | V52: 0.6 | W52: =X52/31 -> 1.2533333 | X52: =R52*V52 -> 38.853333 | Y52: =X52*F52*1.5 -> 2367.3336 | Z52: 0.4 | AA52: =AB52/31 -> 0.83555556 | AB52: =R52*Z52 -> 25.902222 | AC52: =F52*AB52*1.5 -> 1578.2224 | AD52: 定点降解
A53: CC0878 | B53: 3B-R5A房间门锁单锁舌四功能不带APP | C53: 马来 | D53: 办公安防 | E53: 密码锁 | F53: 127.26 | G53: 74 | J53: 56 | K53: 9735 | L53: =(G53-(H53*50))/50 -> 1.48 | M53: =31*(L53+H53) -> 45.88 | N53: =M53*F53 -> 5838.6888 | O53: =(G53-(H53*90))/90 -> 0.82222222 | P53: =31*(O53+H53) -> 25.488889 | Q53: =(O53+H53)*31*F53*1.5 -> 4865.574 | R53: =P53 -> 25.488889 | S53: =R53/31 -> 0.82222222 | T53: =S53-H53 -> 0.82222222 | U53: =Q53 -> 4865.574 | V53: 0.5 | W53: =X53/31 -> 0.41111111 | X53: =R53*V53 -> 12.744444 | Y53: =X53*F53*1.5 -> 2432.787 | Z53: 0.5 | AA53: =AB53/31 -> 0.41111111 | AB53: =R53*Z53 -> 12.744444 | AC53: =F53*AB53*1.5 -> 2432.787 | AD53: 重点降解
A54: CC0605 | B54: 3C-32至70寸电视移动支架的单支架 | C54: 马来 | D54: 3C数码 | E54: 电视支架 | F54: 96.31 | G54: 645 | H54: 10 | I54: 64 | J54: 99 | K54: 9535 | L54: =(G54-(H54*50))/50 -> 2.9 | M54: =31*(L54+H54) -> 399.9 | N54: =M54*F54 -> 38514.369 | O54: =(G54-(H54*90))/90 -> -2.8333333 | P54: =31*(O54+H54) -> 222.16667 | Q54: =(O54+H54)*31*F54*1.5 -> 32095.307 | R54: =P54 -> 222.16667 | S54: =R54/31 -> 7.1666667 | T54: =S54-H54 -> -2.8333333 | U54: =Q54 -> 32095.307 | V54: 0.5 | W54: =X54/31 -> 3.5833333 | X54: =R54*V54 -> 111.08333 | Y54: =X54*F54*1.5 -> 16047.654 | Z54: 0.5 | AA54: =AB54/31 -> 3.5833333 | AB54: =R54*Z54 -> 111.08333 | AC54: =F54*AB54*1.5 -> 16047.654
A55: CC0297 | B55: 3C-翻页笔 | C55: 马来 | D55: 3C数码 | E55: 翻页笔 | F55: 19.49 | G55: 399 | H55: 1 | I55: 399 | J55: 339 | K55: 9443 | L55: =(G55-(H55*50))/50 -> 6.98 | M55: =31*(L55+H55) -> 247.38 | N55: =M55*F55 -> 4821.4362 | O55: =(G55-(H55*90))/90 -> 3.4333333 | P55: =31*(O55+H55) -> 137.43333 | Q55: =(O55+H55)*31*F55*1.5 -> 4017.8635 | R55: =P55 -> 137.43333 | S55: =R55/31 -> 4.4333333 | T55: =S55-H55 -> 3.4333333 | U55: =Q55 -> 4017.8635 | V55: 1 | W55: =X55/31 -> 4.4333333 | X55: =R55*V55 -> 137.43333 | Y55: =X55*F55*1.5 -> 4017.8635 | Z55: 0 | AA55: =AB55/31 -> 0 | AB55: =R55*Z55 -> 0 | AC55: =F55*AB55*1.5 -> 0 | AD55: 定点降解
A56: CC0830 | B56: 3C-显示器桌面支架4屏 | C56: 马来 | D56: 3C数码 | E56: 电视支架 | F56: 123.31 | G56: 58 | J56: 52 | K56: 9310 | L56: =(G56-(H56*50))/50 -> 1.16 | M56: =31*(L56+H56) -> 35.96 | N56: =M56*F56 -> 4434.2276 | O56: =(G56-(H56*90))/90 -> 0.64444444 | P56: =31*(O56+H56) -> 19.977778 | Q56: =(O56+H56)*31*F56*1.5 -> 3695.1897 | R56: =P56 -> 19.977778 | S56: =R56/31 -> 0.64444444 | T56: =S56-H56 -> 0.64444444 | U56: =Q56 -> 3695.1897 | V56: 1 | W56: =X56/31 -> 0.64444444 | X56: =R56*V56 -> 19.977778 | Y56: =X56*F56*1.5 -> 3695.1897 | Z56: 0 | AA56: =AB56/31 -> 0 | AB56: =R56*Z56 -> 0 | AC56: =F56*AB56*1.5 -> 0 | AD56: 重点降解
A57: CC0780 | B57: 3C-折叠带蓝牙带琴谱架电子琴61键 | C57: 马来 | D57: 3C数码 | E57: 电子琴 | F57: 175.48 | G57: 190 | H57: 2 | I57: 95 | J57: 52 | K57: 9125 | L57: =(G57-(H57*50))/50 -> 1.8 | M57: =31*(L57+H57) -> 117.8 | N57: =M57*F57 -> 20671.544 | O57: =(G57-(H57*90))/90 -> 0.11111111 | P57: =31*(O57+H57) -> 65.444444 | Q57: =(O57+H57)*31*F57*1.5 -> 17226.287 | R57: =P57 -> 65.444444 | S57: =R57/31 -> 2.1111111 | T57: =S57-H57 -> 0.11111111 | U57: =Q57 -> 17226.287 | V57: 0.5 | W57: =X57/31 -> 1.0555556 | X57: =R57*V57 -> 32.722222 | Y57: =X57*F57*1.5 -> 8613.1433 | Z57: 0.5 | AA57: =AB57/31 -> 1.0555556 | AB57: =R57*Z57 -> 32.722222 | AC57: =F57*AB57*1.5 -> 8613.1433 | AD57: 重点降解
A58: CC0490 | B58: 3B-不干胶标签打印纸单卷150*100mm | C58: 马来 | D58: 办公安防 | E58: 标签打印纸 | F58: 22.4909 | G58: 407 | H58: 2 | I58: 203 | J58: 297 | K58: 9030 | L58: =(G58-(H58*50))/50 -> 6.14 | M58: =31*(L58+H58) -> 252.34 | N58: =M58*F58 -> 5675.3537 | O58: =(G58-(H58*90))/90 -> 2.5222222 | P58: =31*(O58+H58) -> 140.18889 | Q58: =(O58+H58)*31*F58*1.5 -> 4729.4614 | R58: =P58 -> 140.18889 | S58: =R58/31 -> 4.5222222 | T58: =S58-H58 -> 2.5222222 | U58: =Q58 -> 4729.4614 | V58: 0.8 | W58: =X58/31 -> 3.6177778 | X58: =R58*V58 -> 112.15111 | Y58: =X58*F58*1.5 -> 3783.5691 | Z58: 0.2 | AA58: =AB58/31 -> 0.90444444 | AB58: =R58*Z58 -> 28.037778 | AC58: =F58*AB58*1.5 -> 945.89228
A59: CC0430 | B59: 3C-插电电池两用电动旋转盘12cm | C59: 马来 | D59: 3C数码 | E59: 展示台 | F59: 23.42 | G59: 363 | H59: 1 | I59: 363 | J59: 270 | K59: 8607 | L59: =(G59-(H59*50))/50 -> 6.26 | M59: =31*(L59+H59) -> 225.06 | N59: =M59*F59 -> 5270.9052 | O59: =(G59-(H59*90))/90 -> 3.0333333 | P59: =31*(O59+H59) -> 125.03333 | Q59: =(O59+H59)*31*F59*1.5 -> 4392.421 | R59: =P59 -> 125.03333 | S59: =R59/31 -> 4.0333333 | T59: =S59-H59 -> 3.0333333 | U59: =Q59 -> 4392.421 | V59: 0.6 | W59: =X59/31 -> 2.42 | X59: =R59*V59 -> 75.02 | Y59: =X59*F59*1.5 -> 2635.4526 | Z59: 0.4 | AA59: =AB59/31 -> 1.6133333 | AB59: =R59*Z59 -> 50.013333 | AC59: =F59*AB59*1.5 -> 1756.9684
A60: CC0887 | B60: 3B-U9五功能玻璃门智能锁带TUYAAPP | C60: 马来 | D60: 办公安防 | E60: 智能锁 | F60: 94.25 | G60: 62 | J60: 61 | K60: 8577 | L60: =(G60-(H60*50))/50 -> 1.24 | M60: =31*(L60+H60) -> 38.44 | N60: =M60*F60 -> 3622.97 | O60: =(G60-(H60*90))/90 -> 0.68888889 | P60: =31*(O60+H60) -> 21.355556 | Q60: =(O60+H60)*31*F60*1.5 -> 3019.1417 | R60: =P60 -> 21.355556 | S60: =R60/31 -> 0.68888889 | T60: =S60-H60 -> 0.68888889 | U60: =Q60 -> 3019.1417 | V60: 0.7 | W60: =X60/31 -> 0.48222222 | X60: =R60*V60 -> 14.948889 | Y60: =X60*F60*1.5 -> 2113.3992 | Z60: 0.3 | AA60: =AB60/31 -> 0.20666667 | AB60: =R60*Z60 -> 6.4066667 | AC60: =F60*AB60*1.5 -> 905.7425 | AD60: 新品降解
A61: CC0942 | B61: 3B-9260B标签打印机4寸黑色USB蓝牙 | C61: 马来 | D61: 办公安防 | E61: 打印机 | F61: 160.68 | G61: 35 | J61: 35 | K61: 8436 | L61: =(G61-(H61*50))/50 -> 0.7 | M61: =31*(L61+H61) -> 21.7 | N61: =M61*F61 -> 3486.756 | O61: =(G61-(H61*90))/90 -> 0.38888889 | P61: =31*(O61+H61) -> 12.055556 | Q61: =(O61+H61)*31*F61*1.5 -> 2905.63 | R61: =P61 -> 12.055556 | S61: =R61/31 -> 0.38888889 | T61: =S61-H61 -> 0.38888889 | U61: =Q61 -> 2905.63 | V61: 0.5 | W61: =X61/31 -> 0.19444444 | X61: =R61*V61 -> 6.0277778 | Y61: =X61*F61*1.5 -> 1452.815 | Z61: 0.5 | AA61: =AB61/31 -> 0.19444444 | AB61: =R61*Z61 -> 6.0277778 | AC61: =F61*AB61*1.5 -> 1452.815 | AD61: 新品降解
A62: CC0998 | B62: 3C-RGB全透明动圈降噪桌面麦克风 | C62: 马来 | D62: 3C数码 | E62: 有线麦克风 | F62: 80.47 | G62: 71 | J62: 70 | K62: 8409 | L62: =(G62-(H62*50))/50 -> 1.42 | M62: =31*(L62+H62) -> 44.02 | N62: =M62*F62 -> 3542.2894 | O62: =(G62-(H62*90))/90 -> 0.78888889 | P62: =31*(O62+H62) -> 24.455556 | Q62: =(O62+H62)*31*F62*1.5 -> 2951.9078 | R62: =P62 -> 24.455556 | S62: =R62/31 -> 0.78888889 | T62: =S62-H62 -> 0.78888889 | U62: =Q62 -> 2951.9078 | V62: 0.5 | W62: =X62/31 -> 0.39444444 | X62: =R62*V62 -> 12.227778 | Y62: =X62*F62*1.5 -> 1475.9539 | Z62: 0.5 | AA62: =AB62/31 -> 0.39444444 | AB62: =R62*Z62 -> 12.227778 | AC62: =F62*AB62*1.5 -> 1475.9539 | AD62: 新品降解
A63: CC0138 | B63: 3C-投影仪支架 | C63: 马来 | D63: 3C数码 | E63: 投影仪支架-2 | F63: 37.42 | G63: 515 | H63: 5 | I63: 103 | J63: 220 | K63: 8232 | L63: =(G63-(H63*50))/50 -> 5.3 | M63: =31*(L63+H63) -> 319.3 | N63: =M63*F63 -> 11948.206 | O63: =(G63-(H63*90))/90 -> 0.72222222 | P63: =31*(O63+H63) -> 177.38889 | Q63: =(O63+H63)*31*F63*1.5 -> 9956.8383 | R63: =P63 -> 177.38889 | S63: =R63/31 -> 5.7222222 | T63: =S63-H63 -> 0.72222222 | U63: =Q63 -> 9956.8383 | V63: 0.5 | W63: =X63/31 -> 2.8611111 | X63: =R63*V63 -> 88.694444 | Y63: =X63*F63*1.5 -> 4978.4192 | Z63: 0.5 | AA63: =AB63/31 -> 2.8611111 | AB63: =R63*Z63 -> 88.694444 | AC63: =F63*AB63*1.5 -> 4978.4192
A64: CC0235 | B64: 3B-306CWiFi路由器 | C64: 马来 | D64: 办公安防 | E64: 路由器 | F64: 109.41 | G64: 50 | J64: 50 | K64: 8206 | L64: =(G64-(H64*50))/50 -> 1 | M64: =31*(L64+H64) -> 31 | N64: =M64*F64 -> 3391.71 | O64: =(G64-(H64*90))/90 -> 0.55555556 | P64: =31*(O64+H64) -> 17.222222 | Q64: =(O64+H64)*31*F64*1.5 -> 2826.425 | R64: =P64 -> 17.222222 | S64: =R64/31 -> 0.55555556 | T64: =S64-H64 -> 0.55555556 | U64: =Q64 -> 2826.425 | V64: 0.05 | W64: =X64/31 -> 0.027777778 | X64: =R64*V64 -> 0.86111111 | Y64: =X64*F64*1.5 -> 141.32125 | Z64: 0.95 | AA64: =AB64/31 -> 0.52777778 | AB64: =R64*Z64 -> 16.361111 | AC64: =F64*AB64*1.5 -> 2685.1038
A65: CC0280 | B65: 3C-黑色民谣吉他 | C65: 马来 | D65: 3C数码 | E65: 吉他套装 | F65: 79.47 | G65: 372 | H65: 5 | I65: 74 | J65: 102 | K65: 8106 | L65: =(G65-(H65*50))/50 -> 2.44 | M65: =31*(L65+H65) -> 230.64 | N65: =M65*F65 -> 18328.961 | O65: =(G65-(H65*90))/90 -> -0.86666667 | P65: =31*(O65+H65) -> 128.13333 | Q65: =(O65+H65)*31*F65*1.5 -> 15274.134 | R65: =P65 -> 128.13333 | S65: =R65/31 -> 4.1333333 | T65: =S65-H65 -> -0.86666667 | U65: =Q65 -> 15274.134 | V65: 0.5 | W65: =X65/31 -> 2.0666667 | X65: =R65*V65 -> 64.066667 | Y65: =X65*F65*1.5 -> 7637.067 | Z65: 0.5 | AA65: =AB65/31 -> 2.0666667 | AB65: =R65*Z65 -> 64.066667 | AC65: =F65*AB65*1.5 -> 7637.067
A66: CC0036 | B66: 3C-H型32至70寸电视壁架 | C66: 马来 | D66: 3C数码 | E66: 电视支架 | F66: 55.52 | G66: 1628 | H66: 29 | I66: 56 | J66: 141 | K66: 7828 | L66: =(G66-(H66*50))/50 -> 3.56 | M66: =31*(L66+H66) -> 1009.36 | N66: =M66*F66 -> 56039.667 | O66: =(G66-(H66*90))/90 -> -10.911111 | P66: =31*(O66+H66) -> 560.75556 | Q66: =(O66+H66)*31*F66*1.5 -> 46699.723 | R66: =P66 -> 560.75556 | S66: =R66/31 -> 18.088889 | T66: =S66-H66 -> -10.911111 | U66: =Q66 -> 46699.723 | V66: 0.4 | W66: =X66/31 -> 7.2355556 | X66: =R66*V66 -> 224.30222 | Y66: =X66*F66*1.5 -> 18679.889 | Z66: 0.6 | AA66: =AB66/31 -> 10.853333 | AB66: =R66*Z66 -> 336.45333 | AC66: =F66*AB66*1.5 -> 28019.834
A67: CC0790 | B67: 3C-相机三脚架160cm | C67: 马来 | D67: 3C数码 | E67: 三脚架 | F67: 44.15 | G67: 114 | J67: 113 | K67: 7461 | L67: =(G67-(H67*50))/50 -> 2.28 | M67: =31*(L67+H67) -> 70.68 | N67: =M67*F67 -> 3120.522 | O67: =(G67-(H67*90))/90 -> 1.2666667 | P67: =31*(O67+H67) -> 39.266667 | Q67: =(O67+H67)*31*F67*1.5 -> 2600.435 | R67: =P67 -> 39.266667 | S67: =R67/31 -> 1.2666667 | T67: =S67-H67 -> 1.2666667 | U67: =Q67 -> 2600.435 | V67: 0.5 | W67: =X67/31 -> 0.63333333 | X67: =R67*V67 -> 19.633333 | Y67: =X67*F67*1.5 -> 1300.2175 | Z67: 0.5 | AA67: =AB67/31 -> 0.63333333 | AB67: =R67*Z67 -> 19.633333 | AC67: =F67*AB67*1.5 -> 1300.2175 | AD67: 定点降解
A68: CC0976 | B68: 3B-捆钞机8011A型 | C68: 马来 | D68: 办公安防 | E68: 捆钞机 | F68: 351.07 | G68: 18 | J68: 15 | K68: 7372 | L68: =(G68-(H68*50))/50 -> 0.36 | M68: =31*(L68+H68) -> 11.16 | N68: =M68*F68 -> 3917.9412 | O68: =(G68-(H68*90))/90 -> 0.2 | P68: =31*(O68+H68) -> 6.2 | Q68: =(O68+H68)*31*F68*1.5 -> 3264.951 | R68: =P68 -> 6.2 | S68: =R68/31 -> 0.2 | T68: =S68-H68 -> 0.2 | U68: =Q68 -> 3264.951 | V68: 0.5 | W68: =X68/31 -> 0.1 | X68: =R68*V68 -> 3.1 | Y68: =X68*F68*1.5 -> 1632.4755 | Z68: 0.5 | AA68: =AB68/31 -> 0.1 | AB68: =R68*Z68 -> 3.1 | AC68: =F68*AB68*1.5 -> 1632.4755
A69: CC0729 | B69: 3B-橡胶磁白板背胶45cm*100cm | C69: 马来 | D69: 办公安防 | E69: 白板 | F69: 21.13 | G69: 442 | H69: 3 | I69: 147 | J69: 269 | K69: 7057 | L69: =(G69-(H69*50))/50 -> 5.84 | M69: =31*(L69+H69) -> 274.04 | N69: =M69*F69 -> 5790.4652 | O69: =(G69-(H69*90))/90 -> 1.9111111 | P69: =31*(O69+H69) -> 152.24444 | Q69: =(O69+H69)*31*F69*1.5 -> 4825.3877 | R69: =P69 -> 152.24444 | S69: =R69/31 -> 4.9111111 | T69: =S69-H69 -> 1.9111111 | U69: =Q69 -> 4825.3877 | V69: 0.5 | W69: =X69/31 -> 2.4555556 | X69: =R69*V69 -> 76.122222 | Y69: =X69*F69*1.5 -> 2412.6938 | Z69: 0.5 | AA69: =AB69/31 -> 2.4555556 | AB69: =R69*Z69 -> 76.122222 | AC69: =F69*AB69*1.5 -> 2412.6938 | AD69: 重点降解
A70: CC0814 | B70: 3C-带杆可升降可倒挂气弹簧双臂支架 | C70: 马来 | D70: 3C数码 | E70: 显示器支架 | F70: 123.84 | G70: 107 | H70: 1 | I70: 107 | J70: 52 | K70: 6935 | L70: =(G70-(H70*50))/50 -> 1.14 | M70: =31*(L70+H70) -> 66.34 | N70: =M70*F70 -> 8215.5456 | O70: =(G70-(H70*90))/90 -> 0.18888889 | P70: =31*(O70+H70) -> 36.855556 | Q70: =(O70+H70)*31*F70*1.5 -> 6846.288 | R70: =P70 -> 36.855556 | S70: =R70/31 -> 1.1888889 | T70: =S70-H70 -> 0.18888889 | U70: =Q70 -> 6846.288 | V70: 0.6 | W70: =X70/31 -> 0.71333333 | X70: =R70*V70 -> 22.113333 | Y70: =X70*F70*1.5 -> 4107.7728 | Z70: 0.4 | AA70: =AB70/31 -> 0.47555556 | AB70: =R70*Z70 -> 14.742222 | AC70: =F70*AB70*1.5 -> 2738.5152
A71: CC0801 | B71: 3C-电脑机箱T8款白色 | C71: 马来 | D71: 3C数码 | E71: 电脑机箱 | F71: 93.2 | G71: 97 | J71: 59 | K71: 6804 | L71: =(G71-(H71*50))/50 -> 1.94 | M71: =31*(L71+H71) -> 60.14 | N71: =M71*F71 -> 5605.048 | O71: =(G71-(H71*90))/90 -> 1.0777778 | P71: =31*(O71+H71) -> 33.411111 | Q71: =(O71+H71)*31*F71*1.5 -> 4670.8733 | R71: =P71 -> 33.411111 | S71: =R71/31 -> 1.0777778 | T71: =S71-H71 -> 1.0777778 | U71: =Q71 -> 4670.8733 | V71: 0.5 | W71: =X71/31 -> 0.53888889 | X71: =R71*V71 -> 16.705556 | Y71: =X71*F71*1.5 -> 2335.4367 | Z71: 0.5 | AA71: =AB71/31 -> 0.53888889 | AB71: =R71*Z71 -> 16.705556 | AC71: =F71*AB71*1.5 -> 2335.4367 | AD71: 新品降解
